Workbook

Sheet Start
B2: StratOS Workbook
B3: Strategy analysis worksheets
B4: Blank template.
B6: How to use | C6: Each sheet is one StratOS framework. Type only in the cream cells (blue text). Grey cells are formulas: they score, rank and flag automatically. Every finding should name its evidence in the Source column, the same rule StratOS follows.
B7: Colour key | C7: Blue on cream = input · black on grey = formula · green / amber / red = status.
B8: PESTEL | C8: Macro findings with impact × certainty priority and the P&L line each one hits.
B9: Five Forces | C9: Sub-factor scores roll up to each force and to an industry attractiveness score.
B10: KSF Scorecard | C10: Weighted KSFs, every competitor scored, totals and rank; weights must sum to 100%.
B11: VRIO | C11: Yes / No / ? for each test; the verdict and the KSF reality check are calculated.
B12: SWOT-TOWS | C12: Four traced lists and the TOWS options that pair them.
B13: Decision Matrix | C13: Criteria weights × option scores, with a weighted total and rank; do nothing included.
B14: Expected Value | C14: Scenario probabilities × NPVs, expected NPV, worst case, maximin, value of information, and a Bayes' rule pilot check (EVSI).
B15: Business Case | C15: Driver-based cash flows, NPV, IRR and cumulative cash.
B16: Risk Analysis | C16: Exhibit Q-3: a tornado chart (which driver moves NPV most) and a 1,000-run Monte Carlo simulation (median, P10-P90, chance NPV is below zero) over your low / likely / high ranges.
B17: Balanced Scorecard | C17: Objectives and measures in four perspectives, leading vs lagging, status vs target, balance check.
... B23: Your work stays yours | C23: In graded work, the inputs, choices and every Impact Summary are the student's. The workbook calculates; it never decides.
B25: © 2026 Brad Scheller · StratOS Strategy Lab · Apache-2.0

Sheet PESTEL
A1: PESTEL Analysis
A2: Macro findings, each tied to a P&L line. Priority = impact × certainty (1-25).
A3: Blue text on cream = your inputs. Black on grey = formulas (do not type over them).
A5: ID | B5: Dimension | C5: Finding | D5: Direction (+ / - / ±) | E5: Impact 1-5 | F5: Certainty 1-5 | G5: Priority | H5: P&L line | I5: Source / evidence
G6: =IF(AND(ISNUMBER(E6),ISNUMBER(F6)),E6*F6,"")
G7: =IF(AND(ISNUMBER(E7),ISNUMBER(F7)),E7*F7,"")
G8: =IF(AND(ISNUMBER(E8),ISNUMBER(F8)),E8*F8,"")
G9: =IF(AND(ISNUMBER(E9),ISNUMBER(F9)),E9*F9,"")
G10: =IF(AND(ISNUMBER(E10),ISNUMBER(F10)),E10*F10,"")
G11: =IF(AND(ISNUMBER(E11),ISNUMBER(F11)),E11*F11,"")
G12: =IF(AND(ISNUMBER(E12),ISNUMBER(F12)),E12*F12,"")
G13: =IF(AND(ISNUMBER(E13),ISNUMBER(F13)),E13*F13,"")
G14: =IF(AND(ISNUMBER(E14),ISNUMBER(F14)),E14*F14,"")
G15: =IF(AND(ISNUMBER(E15),ISNUMBER(F15)),E15*F15,"")
G16: =IF(AND(ISNUMBER(E16),ISNUMBER(F16)),E16*F16,"")
G17: =IF(AND(ISNUMBER(E17),ISNUMBER(F17)),E17*F17,"")
... G30: =IF(AND(ISNUMBER(E30),ISNUMBER(F30)),E30*F30,"")
B32: Findings | C32: =COUNTA(C6:C30) -> 0
B33: High priority (≥16) | C33: =COUNTIF(G6:G30,">=16") -> 0
B34: Missing a source | C34: =SUMPRODUCT((C6:C30<>"")*(I6:I30="")) -> 0

Sheet Five Forces
A1: Porter's Five Forces
A2: Score each sub-factor 1 (weak force, good for profit) to 5 (strong force). A force score you enter overrides the sub-factor average.
A3: Blue text on cream = your inputs. Black on grey = formulas (do not type over them).
A5: Force | B5: Sub-factor | C5: Score 1-5 | D5: Evidence / source
A6: Competitive rivalry | B6: Current competition
A7: Competitive rivalry | B7: Market growth
A8: Competitive rivalry | B8: Exit barriers
A9: Competitive rivalry | B9: Differentiation
A10: Supplier power | B10: Supplier concentration
A11: Supplier power | B11: Switching costs
A12: Supplier power | B12: Forward integration
A13: Supplier power | B13: Input uniqueness
A14: Buyer power | B14: Buyer concentration
A15: Buyer power | B15: Purchase volume
A16: Buyer power | B16: Switching costs
A17: Buyer power | B17: Price sensitivity
... A25: Threat of substitutes | B25: Buyer propensity
A27: Force | B27: Sub-factor average | C27: Your force score (optional) | D27: Score used | E27: Strength | F27: Horizon score (optional)
A28: Competitive rivalry | B28: =IFERROR(AVERAGEIF($A$6:$A$25,A28,$C$6:$C$25),"") | D28: =IF(ISNUMBER(C28),C28,B28) | E28: =IF(D28="","",IF(D28>=4,"Strong",IF(D28>=2.5,"Moderate","Weak")))
A29: Supplier power | B29: =IFERROR(AVERAGEIF($A$6:$A$25,A29,$C$6:$C$25),"") | D29: =IF(ISNUMBER(C29),C29,B29) | E29: =IF(D29="","",IF(D29>=4,"Strong",IF(D29>=2.5,"Moderate","Weak")))
A30: Buyer power | B30: =IFERROR(AVERAGEIF($A$6:$A$25,A30,$C$6:$C$25),"") | D30: =IF(ISNUMBER(C30),C30,B30) | E30: =IF(D30="","",IF(D30>=4,"Strong",IF(D30>=2.5,"Moderate","Weak")))
A31: Threat of new entrants | B31: =IFERROR(AVERAGEIF($A$6:$A$25,A31,$C$6:$C$25),"") | D31: =IF(ISNUMBER(C31),C31,B31) | E31: =IF(D31="","",IF(D31>=4,"Strong",IF(D31>=2.5,"Moderate","Weak")))
A32: Threat of substitutes | B32: =IFERROR(AVERAGEIF($A$6:$A$25,A32,$C$6:$C$25),"") | D32: =IF(ISNUMBER(C32),C32,B32) | E32: =IF(D32="","",IF(D32>=4,"Strong",IF(D32>=2.5,"Moderate","Weak")))
A34: Industry attractiveness (1-5) | B34: =IFERROR(6-AVERAGE(D28:D32),"")
A35: At the horizon | B35: =IF(COUNT(F28:F32)=5,6-AVERAGE(F28:F32),"")
A37: Attractiveness = 6 minus the average force score (1-5; higher is more attractive).
A38: The horizon score appears once all five horizon scores are entered.

Sheet KSF Scorecard
A1: Key Success Factors Scorecard
A2: Weights are fractions that must sum to 100%. Score each competitor 1 (weak) to 5 (strong) on each KSF.
A3: Blue text on cream = your inputs. Black on grey = formulas (do not type over them).
A5: ID | B5: Key success factor | C5: Weight | D5: Traces to (force / driver) | E5: Competitor 1 | F5: Competitor 2 | G5: Competitor 3 | H5: Competitor 4 | I5: Competitor 5 | J5: Competitor 6
B16: Weight check (must be 100%) | C16: =SUM(C6:C15) -> 0 | D16: =IF(ABS(C16-1)<0.001,"OK","Weights must sum to 100%") -> Weights must sum to 100%
B17: Weighted score (out of 5) | E17: =IF(COUNT(E6:E15)=0,"",SUMPRODUCT($C$6:$C$15,E6:E15)) | F17: =IF(COUNT(F6:F15)=0,"",SUMPRODUCT($C$6:$C$15,F6:F15)) | G17: =IF(COUNT(G6:G15)=0,"",SUMPRODUCT($C$6:$C$15,G6:G15)) | H17: =IF(COUNT(H6:H15)=0,"",SUMPRODUCT($C$6:$C$15,H6:H15)) | I17: =IF(COUNT(I6:I15)=0,"",SUMPRODUCT($C$6:$C$15,I6:I15)) | J17: =IF(COUNT(J6:J15)=0,"",SUMPRODUCT($C$6:$C$15,J6:J15))
B18: Rank | E18: =IF(E17="","",RANK(E17,$E$17:$J$17)) | F18: =IF(F17="","",RANK(F17,$E$17:$J$17)) | G18: =IF(G17="","",RANK(G17,$E$17:$J$17)) | H18: =IF(H17="","",RANK(H17,$E$17:$J$17)) | I18: =IF(I17="","",RANK(I17,$E$17:$J$17)) | J18: =IF(J17="","",RANK(J17,$E$17:$J$17))

Sheet VRIO
A1: VRIO Analysis
A2: Answer the four tests in order with Yes / No / ?. The verdict stops at the first No or ?. KSF weight (a fraction) drives the reality check.
A3: Blue text on cream = your inputs. Black on grey = formulas (do not type over them).
A5: Resource or capability | B5: Type | C5: Valuable? | D5: Rare? | E5: Inimitable? | F5: Organized? | G5: Verdict | H5: KSF it delivers | I5: KSF weight | J5: Reality check | K5: Evidence
G6: =IF(A6="","",IF(C6<>"Yes",IF(C6="No","Competitive disadvantage","Undetermined"),IF(D6<>"Yes",IF(D6="No","Competitive parity","Undetermined beyond valuable"),IF(E6<>"Yes",IF(E6="No","Temporary advantage","Undetermined beyond rare"),IF(F6="Yes","Sustained advantage",IF(F6="No","Unexploited advantage","Undetermined beyond inimitable")))))) | J6: =IF(A6="","",IF(AND(C6="Yes",D6="Yes",E6="Yes",N(I6)<0.1),"Competence trap",IF(AND(OR(G6="Temporary advantage",G6="Unexploited advantage",G6="Sustained advantage"),N(I6)>=0.1),"Supported",IF(AND(G6="Competitive parity",N(I6)>=0.1),"Table stakes",""))))
G7: =IF(A7="","",IF(C7<>"Yes",IF(C7="No","Competitive disadvantage","Undetermined"),IF(D7<>"Yes",IF(D7="No","Competitive parity","Undetermined beyond valuable"),IF(E7<>"Yes",IF(E7="No","Temporary advantage","Undetermined beyond rare"),IF(F7="Yes","Sustained advantage",IF(F7="No","Unexploited advantage","Undetermined beyond inimitable")))))) | J7: =IF(A7="","",IF(AND(C7="Yes",D7="Yes",E7="Yes",N(I7)<0.1),"Competence trap",IF(AND(OR(G7="Temporary advantage",G7="Unexploited advantage",G7="Sustained advantage"),N(I7)>=0.1),"Supported",IF(AND(G7="Competitive parity",N(I7)>=0.1),"Table stakes",""))))
G8: =IF(A8="","",IF(C8<>"Yes",IF(C8="No","Competitive disadvantage","Undetermined"),IF(D8<>"Yes",IF(D8="No","Competitive parity","Undetermined beyond valuable"),IF(E8<>"Yes",IF(E8="No","Temporary advantage","Undetermined beyond rare"),IF(F8="Yes","Sustained advantage",IF(F8="No","Unexploited advantage","Undetermined beyond inimitable")))))) | J8: =IF(A8="","",IF(AND(C8="Yes",D8="Yes",E8="Yes",N(I8)<0.1),"Competence trap",IF(AND(OR(G8="Temporary advantage",G8="Unexploited advantage",G8="Sustained advantage"),N(I8)>=0.1),"Supported",IF(AND(G8="Competitive parity",N(I8)>=0.1),"Table stakes",""))))
G9: =IF(A9="","",IF(C9<>"Yes",IF(C9="No","Competitive disadvantage","Undetermined"),IF(D9<>"Yes",IF(D9="No","Competitive parity","Undetermined beyond valuable"),IF(E9<>"Yes",IF(E9="No","Temporary advantage","Undetermined beyond rare"),IF(F9="Yes","Sustained advantage",IF(F9="No","Unexploited advantage","Undetermined beyond inimitable")))))) | J9: =IF(A9="","",IF(AND(C9="Yes",D9="Yes",E9="Yes",N(I9)<0.1),"Competence trap",IF(AND(OR(G9="Temporary advantage",G9="Unexploited advantage",G9="Sustained advantage"),N(I9)>=0.1),"Supported",IF(AND(G9="Competitive parity",N(I9)>=0.1),"Table stakes",""))))
G10: =IF(A10="","",IF(C10<>"Yes",IF(C10="No","Competitive disadvantage","Undetermined"),IF(D10<>"Yes",IF(D10="No","Competitive parity","Undetermined beyond valuable"),IF(E10<>"Yes",IF(E10="No","Temporary advantage","Undetermined beyond rare"),IF(F10="Yes","Sustained advantage",IF(F10="No","Unexploited advantage","Undetermined beyond inimitable")))))) | J10: =IF(A10="","",IF(AND(C10="Yes",D10="Yes",E10="Yes",N(I10)<0.1),"Competence trap",IF(AND(OR(G10="Temporary advantage",G10="Unexploited advantage",G10="Sustained advantage"),N(I10)>=0.1),"Supported",IF(AND(G10="Competitive parity",N(I10)>=0.1),"Table stakes",""))))
G11: =IF(A11="","",IF(C11<>"Yes",IF(C11="No","Competitive disadvantage","Undetermined"),IF(D11<>"Yes",IF(D11="No","Competitive parity","Undetermined beyond valuable"),IF(E11<>"Yes",IF(E11="No","Temporary advantage","Undetermined beyond rare"),IF(F11="Yes","Sustained advantage",IF(F11="No","Unexploited advantage","Undetermined beyond inimitable")))))) | J11: =IF(A11="","",IF(AND(C11="Yes",D11="Yes",E11="Yes",N(I11)<0.1),"Competence trap",IF(AND(OR(G11="Temporary advantage",G11="Unexploited advantage",G11="Sustained advantage"),N(I11)>=0.1),"Supported",IF(AND(G11="Competitive parity",N(I11)>=0.1),"Table stakes",""))))
G12: =IF(A12="","",IF(C12<>"Yes",IF(C12="No","Competitive disadvantage","Undetermined"),IF(D12<>"Yes",IF(D12="No","Competitive parity","Undetermined beyond valuable"),IF(E12<>"Yes",IF(E12="No","Temporary advantage","Undetermined beyond rare"),IF(F12="Yes","Sustained advantage",IF(F12="No","Unexploited advantage","Undetermined beyond inimitable")))))) | J12: =IF(A12="","",IF(AND(C12="Yes",D12="Yes",E12="Yes",N(I12)<0.1),"Competence trap",IF(AND(OR(G12="Temporary advantage",G12="Unexploited advantage",G12="Sustained advantage"),N(I12)>=0.1),"Supported",IF(AND(G12="Competitive parity",N(I12)>=0.1),"Table stakes",""))))
G13: =IF(A13="","",IF(C13<>"Yes",IF(C13="No","Competitive disadvantage","Undetermined"),IF(D13<>"Yes",IF(D13="No","Competitive parity","Undetermined beyond valuable"),IF(E13<>"Yes",IF(E13="No","Temporary advantage","Undetermined beyond rare"),IF(F13="Yes","Sustained advantage",IF(F13="No","Unexploited advantage","Undetermined beyond inimitable")))))) | J13: =IF(A13="","",IF(AND(C13="Yes",D13="Yes",E13="Yes",N(I13)<0.1),"Competence trap",IF(AND(OR(G13="Temporary advantage",G13="Unexploited advantage",G13="Sustained advantage"),N(I13)>=0.1),"Supported",IF(AND(G13="Competitive parity",N(I13)>=0.1),"Table stakes",""))))
G14: =IF(A14="","",IF(C14<>"Yes",IF(C14="No","Competitive disadvantage","Undetermined"),IF(D14<>"Yes",IF(D14="No","Competitive parity","Undetermined beyond valuable"),IF(E14<>"Yes",IF(E14="No","Temporary advantage","Undetermined beyond rare"),IF(F14="Yes","Sustained advantage",IF(F14="No","Unexploited advantage","Undetermined beyond inimitable")))))) | J14: =IF(A14="","",IF(AND(C14="Yes",D14="Yes",E14="Yes",N(I14)<0.1),"Competence trap",IF(AND(OR(G14="Temporary advantage",G14="Unexploited advantage",G14="Sustained advantage"),N(I14)>=0.1),"Supported",IF(AND(G14="Competitive parity",N(I14)>=0.1),"Table stakes",""))))
G15: =IF(A15="","",IF(C15<>"Yes",IF(C15="No","Competitive disadvantage","Undetermined"),IF(D15<>"Yes",IF(D15="No","Competitive parity","Undetermined beyond valuable"),IF(E15<>"Yes",IF(E15="No","Temporary advantage","Undetermined beyond rare"),IF(F15="Yes","Sustained advantage",IF(F15="No","Unexploited advantage","Undetermined beyond inimitable")))))) | J15: =IF(A15="","",IF(AND(C15="Yes",D15="Yes",E15="Yes",N(I15)<0.1),"Competence trap",IF(AND(OR(G15="Temporary advantage",G15="Unexploited advantage",G15="Sustained advantage"),N(I15)>=0.1),"Supported",IF(AND(G15="Competitive parity",N(I15)>=0.1),"Table stakes",""))))
G16: =IF(A16="","",IF(C16<>"Yes",IF(C16="No","Competitive disadvantage","Undetermined"),IF(D16<>"Yes",IF(D16="No","Competitive parity","Undetermined beyond valuable"),IF(E16<>"Yes",IF(E16="No","Temporary advantage","Undetermined beyond rare"),IF(F16="Yes","Sustained advantage",IF(F16="No","Unexploited advantage","Undetermined beyond inimitable")))))) | J16: =IF(A16="","",IF(AND(C16="Yes",D16="Yes",E16="Yes",N(I16)<0.1),"Competence trap",IF(AND(OR(G16="Temporary advantage",G16="Unexploited advantage",G16="Sustained advantage"),N(I16)>=0.1),"Supported",IF(AND(G16="Competitive parity",N(I16)>=0.1),"Table stakes",""))))
G17: =IF(A17="","",IF(C17<>"Yes",IF(C17="No","Competitive disadvantage","Undetermined"),IF(D17<>"Yes",IF(D17="No","Competitive parity","Undetermined beyond valuable"),IF(E17<>"Yes",IF(E17="No","Temporary advantage","Undetermined beyond rare"),IF(F17="Yes","Sustained advantage",IF(F17="No","Unexploited advantage","Undetermined beyond inimitable")))))) | J17: =IF(A17="","",IF(AND(C17="Yes",D17="Yes",E17="Yes",N(I17)<0.1),"Competence trap",IF(AND(OR(G17="Temporary advantage",G17="Unexploited advantage",G17="Sustained advantage"),N(I17)>=0.1),"Supported",IF(AND(G17="Competitive parity",N(I17)>=0.1),"Table stakes",""))))
... G20: =IF(A20="","",IF(C20<>"Yes",IF(C20="No","Competitive disadvantage","Undetermined"),IF(D20<>"Yes",IF(D20="No","Competitive parity","Undetermined beyond valuable"),IF(E20<>"Yes",IF(E20="No","Temporary advantage","Undetermined beyond rare"),IF(F20="Yes","Sustained advantage",IF(F20="No","Unexploited advantage","Undetermined beyond inimitable")))))) | J20: =IF(A20="","",IF(AND(C20="Yes",D20="Yes",E20="Yes",N(I20)<0.1),"Competence trap",IF(AND(OR(G20="Temporary advantage",G20="Unexploited advantage",G20="Sustained advantage"),N(I20)>=0.1),"Supported",IF(AND(G20="Competitive parity",N(I20)>=0.1),"Table stakes",""))))

Sheet SWOT-TOWS
A1: SWOT and TOWS
A2: Every item names the finding it came from. TOWS options pair the items by ID.
A3: Blue text on cream = your inputs. Black on grey = formulas (do not type over them).
A5: ID | B5: Strengths (internal, helpful) | C5: Source | E5: ID | F5: Weaknesses (internal, harmful) | G5: Source
A6: S1 | E6: W1
A7: S2 | E7: W2
A8: S3 | E8: W3
A9: S4 | E9: W4
A10: S5 | E10: W5
A11: S6 | E11: W6
A14: ID | B14: Opportunities (external, helpful) | C14: Source | E14: ID | F14: Threats (external, harmful) | G14: Source
A15: O1 | E15: T1
A16: O2 | E16: T2
A17: O3 | E17: T3
A18: O4 | E18: T4
A19: O5 | E19: T5
A20: O6 | E20: T6
A23: Cell | B23: TOWS strategic option | C23: Pairs (e.g. S1 × O1)

Sheet Decision Matrix
A1: Decision Matrix
A2: Weight each criterion 1-5 and score each option 1-5. Include do nothing.
A3: Blue text on cream = your inputs. Black on grey = formulas (do not type over them).
A5: Criterion | B5: Weight 1-5 | C5: Tied to goal | D5: Option 1 | E5: Option 2 | F5: Option 3 | G5: Option 4 | H5: Option 5
A14: Weighted score (out of 5) | D14: =IF(COUNT(D6:D13)=0,"",SUMPRODUCT($B$6:$B$13,D6:D13)/SUMPRODUCT($B$6:$B$13*(D6:D13<>""))) | E14: =IF(COUNT(E6:E13)=0,"",SUMPRODUCT($B$6:$B$13,E6:E13)/SUMPRODUCT($B$6:$B$13*(E6:E13<>""))) | F14: =IF(COUNT(F6:F13)=0,"",SUMPRODUCT($B$6:$B$13,F6:F13)/SUMPRODUCT($B$6:$B$13*(F6:F13<>""))) | G14: =IF(COUNT(G6:G13)=0,"",SUMPRODUCT($B$6:$B$13,G6:G13)/SUMPRODUCT($B$6:$B$13*(G6:G13<>""))) | H14: =IF(COUNT(H6:H13)=0,"",SUMPRODUCT($B$6:$B$13,H6:H13)/SUMPRODUCT($B$6:$B$13*(H6:H13<>"")))
A15: Rank | D15: =IF(D14="","",RANK(D14,$D$14:$H$14)) | E15: =IF(E14="","",RANK(E14,$D$14:$H$14)) | F15: =IF(F14="","",RANK(F14,$D$14:$H$14)) | G15: =IF(G14="","",RANK(G14,$D$14:$H$14)) | H15: =IF(H14="","",RANK(H14,$D$14:$H$14))
A17: The matrix ranks; it does not choose. The recommendation is yours.

Sheet Expected Value
A1: Expected Value
A2: Probabilities as percentages that sum to 100% per option; NPV in $M. Follows the course handout 'Choosing Among Strategic Alternatives'.
A3: Blue text on cream = your inputs. Black on grey = formulas (do not type over them).
A5: Option | B5: P strong | C5: NPV strong ($M) | D5: P moderate | E5: NPV moderate ($M) | F5: P weak | G5: NPV weak ($M) | H5: Probability check | I5: Expected NPV ($M) | J5: Worst case | K5: Best case
H6: =IF(A6="","",IF(ABS(B6+D6+F6-1)<0.001,"OK","Must sum to 100%")) | I6: =IF(A6="","",B6*C6+D6*E6+F6*G6) | J6: =IF(A6="","",MIN(C6,E6,G6)) | K6: =IF(A6="","",MAX(C6,E6,G6))
H7: =IF(A7="","",IF(ABS(B7+D7+F7-1)<0.001,"OK","Must sum to 100%")) | I7: =IF(A7="","",B7*C7+D7*E7+F7*G7) | J7: =IF(A7="","",MIN(C7,E7,G7)) | K7: =IF(A7="","",MAX(C7,E7,G7))
H8: =IF(A8="","",IF(ABS(B8+D8+F8-1)<0.001,"OK","Must sum to 100%")) | I8: =IF(A8="","",B8*C8+D8*E8+F8*G8) | J8: =IF(A8="","",MIN(C8,E8,G8)) | K8: =IF(A8="","",MAX(C8,E8,G8))
H9: =IF(A9="","",IF(ABS(B9+D9+F9-1)<0.001,"OK","Must sum to 100%")) | I9: =IF(A9="","",B9*C9+D9*E9+F9*G9) | J9: =IF(A9="","",MIN(C9,E9,G9)) | K9: =IF(A9="","",MAX(C9,E9,G9))
H10: =IF(A10="","",IF(ABS(B10+D10+F10-1)<0.001,"OK","Must sum to 100%")) | I10: =IF(A10="","",B10*C10+D10*E10+F10*G10) | J10: =IF(A10="","",MIN(C10,E10,G10)) | K10: =IF(A10="","",MAX(C10,E10,G10))
H11: =IF(A11="","",IF(ABS(B11+D11+F11-1)<0.001,"OK","Must sum to 100%")) | I11: =IF(A11="","",B11*C11+D11*E11+F11*G11) | J11: =IF(A11="","",MIN(C11,E11,G11)) | K11: =IF(A11="","",MAX(C11,E11,G11))
A13: Leader on expected value | B13: =IFERROR(INDEX(A6:A11,MATCH(MAX(I6:I11),I6:I11,0)),"")
A14: Maximin choice (best worst case) | B14: =IFERROR(INDEX(A6:A11,MATCH(MAX(J6:J11),J6:J11,0)),"")
A15: Value of perfect information ($M) | B15: =IFERROR(INDEX(B6:B11,MATCH(MAX(I6:I11),I6:I11,0))*MAX(C6:C11)+INDEX(D6:D11,MATCH(MAX(I6:I11),I6:I11,0))*MAX(E6:E11)+INDEX(F6:F11,MATCH(MAX(I6:I11),I6:I11,0))*MAX(G6:G11)-MAX(I6:I11),"") | C15: The most worth paying for a pilot that reveals the scenario first (leader's probabilities).
A18: Is a pilot worth it? (Bayes' rule) | B18: How likely the pilot shows each result IF that scenario is real. Each row sums to 100%. Uses the first option's scenario probabilities as the prior.
A19: Scenario | B19: Prior | C19: P(positive | scenario) | D19: P(negative | scenario) | E19: Row check | F19: Posterior if positive | G19: Posterior if negative
A20: Strong | B20: =IF(B6="","",B6) | E20: =IF(C20="","",IF(ABS(C20+D20-1)<0.001,"OK","Must sum to 100%")) | F20: =IFERROR(B20*C20/SUMPRODUCT($B$20:$B$22,$C$20:$C$22),"") | G20: =IFERROR(B20*D20/SUMPRODUCT($B$20:$B$22,$D$20:$D$22),"")
A21: Moderate | B21: =IF(D6="","",D6) | E21: =IF(C21="","",IF(ABS(C21+D21-1)<0.001,"OK","Must sum to 100%")) | F21: =IFERROR(B21*C21/SUMPRODUCT($B$20:$B$22,$C$20:$C$22),"") | G21: =IFERROR(B21*D21/SUMPRODUCT($B$20:$B$22,$D$20:$D$22),"")
A22: Weak | B22: =IF(F6="","",F6) | E22: =IF(C22="","",IF(ABS(C22+D22-1)<0.001,"OK","Must sum to 100%")) | F22: =IFERROR(B22*C22/SUMPRODUCT($B$20:$B$22,$C$20:$C$22),"") | G22: =IFERROR(B22*D22/SUMPRODUCT($B$20:$B$22,$D$20:$D$22),"")
A23: P(result) | F23: =IFERROR(SUMPRODUCT(B20:B22,C20:C22),"") -> 0 | G23: =IFERROR(SUMPRODUCT(B20:B22,D20:D22),"") -> 0
A25: Option | B25: Expected NPV now | C25: If positive | D25: If negative
A26: =IF(A6="","",A6) | B26: =IF(A6="","",I6) | C26: =IF(OR(A6="",F20=""),"",C6*F20+E6*F21+G6*F22) | D26: =IF(OR(A6="",G20=""),"",C6*G20+E6*G21+G6*G22)
A27: =IF(A7="","",A7) | B27: =IF(A7="","",I7) | C27: =IF(OR(A7="",F20=""),"",C7*F20+E7*F21+G7*F22) | D27: =IF(OR(A7="",G20=""),"",C7*G20+E7*G21+G7*G22)
A28: =IF(A8="","",A8) | B28: =IF(A8="","",I8) | C28: =IF(OR(A8="",F20=""),"",C8*F20+E8*F21+G8*F22) | D28: =IF(OR(A8="",G20=""),"",C8*G20+E8*G21+G8*G22)
A29: =IF(A9="","",A9) | B29: =IF(A9="","",I9) | C29: =IF(OR(A9="",F20=""),"",C9*F20+E9*F21+G9*F22) | D29: =IF(OR(A9="",G20=""),"",C9*G20+E9*G21+G9*G22)
A30: =IF(A10="","",A10) | B30: =IF(A10="","",I10) | C30: =IF(OR(A10="",F20=""),"",C10*F20+E10*F21+G10*F22) | D30: =IF(OR(A10="",G20=""),"",C10*G20+E10*G21+G10*G22)
A31: =IF(A11="","",A11) | B31: =IF(A11="","",I11) | C31: =IF(OR(A11="",F20=""),"",C11*F20+E11*F21+G11*F22) | D31: =IF(OR(A11="",G20=""),"",C11*G20+E11*G21+G11*G22)
A33: Best option if the pilot is positive | B33: =IFERROR(INDEX(A26:A31,MATCH(MAX(C26:C31),C26:C31,0)),"") | C33: If both results point to the same option, the pilot cannot change the choice and is worth nothing for this decision.
A34: Best option if the pilot is negative | B34: =IFERROR(INDEX(A26:A31,MATCH(MAX(D26:D31),D26:D31,0)),"")
A35: Expected NPV with the pilot ($M) | B35: =IFERROR(F23*MAX(C26:C31)+G23*MAX(D26:D31),"") -> 0
A36: Value of the pilot, EVSI ($M) | B36: =IFERROR(B35-MAX(I6:I11),"") -> 0
A37: Pilot cost ($M)
A38: Net value of running the pilot ($M) | B38: =IFERROR(IF(B37="","",B36-B37),"")
A39: Share of perfect information | B39: =IFERROR(B36/B15,"")

Sheet Business Case
A1: Business Case
A2: One option. Year 0 is the investment year. Working capital is released in the final year. Money in $.
A3: Blue text on cream = your inputs. Black on grey = formulas (do not type over them).
A5: Assumptions
A6: Discount rate
A7: Tax rate
A8: Working capital (% of revenue)
A10: $ | B10: Year 0 | C10: Year 1 | D10: Year 2 | E10: Year 3 | F10: Year 4 | G10: Year 5
A11: Units
A12: Price per unit
A13: Variable cost per unit
A14: Fixed costs
A15: Capex
A16: Revenue | B16: =B11*B12 -> 0 | C16: =C11*C12 -> 0 | D16: =D11*D12 -> 0 | E16: =E11*E12 -> 0 | F16: =F11*F12 -> 0 | G16: =G11*G12 -> 0
A17: Contribution | B17: =B11*(B12-B13) -> 0 | C17: =C11*(C12-C13) -> 0 | D17: =D11*(D12-D13) -> 0 | E17: =E11*(E12-E13) -> 0 | F17: =F11*(F12-F13) -> 0 | G17: =G11*(G12-G13) -> 0
A18: Operating profit (EBIT) | B18: =B17-B14 -> 0 | C18: =C17-C14 -> 0 | D18: =D17-D14 -> 0 | E18: =E17-E14 -> 0 | F18: =F17-F14 -> 0 | G18: =G17-G14 -> 0
A19: Tax | B19: =MAX(0,B18)*$B$7 -> 0 | C19: =MAX(0,C18)*$B$7 -> 0 | D19: =MAX(0,D18)*$B$7 -> 0 | E19: =MAX(0,E18)*$B$7 -> 0 | F19: =MAX(0,F18)*$B$7 -> 0 | G19: =MAX(0,G18)*$B$7 -> 0
A20: Working capital | B20: =B16*$B$8 -> 0 | C20: =C16*$B$8 -> 0 | D20: =D16*$B$8 -> 0 | E20: =E16*$B$8 -> 0 | F20: =F16*$B$8 -> 0 | G20: =G16*$B$8 -> 0
A21: Change in working capital | B21: =B20 -> 0 | C21: =C20-B20 -> 0 | D21: =D20-C20 -> 0 | E21: =E20-D20 -> 0 | F21: =F20-E20 -> 0 | G21: =G20-F20 -> 0
A22: Cash flow | B22: =B18-B19-B21-B15 -> 0 | C22: =C18-C19-C21-C15 -> 0 | D22: =D18-D19-D21-D15 -> 0 | E22: =E18-E19-E21-E15 -> 0 | F22: =F18-F19-F21-F15 -> 0 | G22: =G18-G19-G21-G15+G20 -> 0
A23: Cumulative cash flow | B23: =B22 -> 0 | C23: =B23+C22 -> 0 | D23: =C23+D22 -> 0 | E23: =D23+E22 -> 0 | F23: =E23+F22 -> 0 | G23: =F23+G22 -> 0
A25: NPV | B25: =IF(COUNT(B11:G11)=0,"",B22+NPV($B$6,C22:G22))
A26: IRR | B26: =IFERROR(IRR(B22:G22),"n/a") -> n/a
A27: Clears the hurdle? | B27: =IF(ISNUMBER(B26),IF(B26>=$B$6,"Yes","No"),"")
A29: State the break-even in words in your exhibit (the Business Case skill computes it).

Sheet Risk Analysis
A1: Risk Analysis (Exhibit Q-3)
A2: Works on the Business Case sheet. Set a low / likely / high for each driver: % change from plan, except the discount rate (an absolute rate). Blank = no uncertainty.
A3: Blue text on cream = your inputs. Black on grey = formulas (do not type over them).
A5: Driver | B5: Low | C5: Likely | D5: High | E5: Eff. low | F5: Eff. likely | G5: Eff. high
A6: Price per unit | E6: =IF(B6="",F6,B6) -> 0 | F6: =IF(C6="",0,C6) -> 0 | G6: =IF(D6="",F6,D6) -> 0
A7: Units | E7: =IF(B7="",F7,B7) -> 0 | F7: =IF(C7="",0,C7) -> 0 | G7: =IF(D7="",F7,D7) -> 0
A8: Variable cost per unit | E8: =IF(B8="",F8,B8) -> 0 | F8: =IF(C8="",0,C8) -> 0 | G8: =IF(D8="",F8,D8) -> 0
A9: Fixed costs | E9: =IF(B9="",F9,B9) -> 0 | F9: =IF(C9="",0,C9) -> 0 | G9: =IF(D9="",F9,D9) -> 0
A10: Capex | E10: =IF(B10="",F10,B10) -> 0 | F10: =IF(C10="",0,C10) -> 0 | G10: =IF(D10="",F10,D10) -> 0
A11: Discount rate (absolute) | E11: =IF(B11="",F11,B11) -> 0 | F11: =IF(C11="",'Business Case'!$B$6,C11) -> 0 | G11: =IF(D11="",F11,D11) -> 0
A12: Range check | B12: =IF(SUMPRODUCT((E6:E11>F6:F11)+(F6:F11>G6:G11))=0,"OK","Need low <= likely <= high") -> OK
A14: Tornado: NPV with one driver at its low or high, the others at plan
A15: Scenario | B15: Price × | C15: Units × | D15: Var. cost × | E15: Fixed × | F15: Capex × | G15: Rate | H15: CF Y0 | I15: CF Y1 | J15: CF Y2 | K15: CF Y3 | L15: CF Y4 | M15: CF Y5 | N15: NPV
A16: Plan | B16: =1 -> 1 | C16: =1 -> 1 | D16: =1 -> 1 | E16: =1 -> 1 | F16: =1 -> 1 | G16: ='Business Case'!$B$6 -> 0 | H16: =(('Business Case'!B11*$C16*'Business Case'!B12*$B16)-'Business Case'!B11*$C16*'Business Case'!B13*$D16-'Business Case'!B14*$E16)-MAX(0,(('Business Case'!B11*$C16*'Business Case'!B12*$B16)-'Business Case'!B11*$C16*'Business Case'!B13*$D16-'Business Case'!B14*$E16))*'Business Case'!$B$7-'Business Case'!$B$8*('Business Case'!B11*$C16*'Business Case'!B12*$B16)-'Business Case'!B15*$F16 -> 0 | I16: =(('Business Case'!C11*$C16*'Business Case'!C12*$B16)-'Business Case'!C11*$C16*'Business Case'!C13*$D16-'Business Case'!C14*$E16)-MAX(0,(('Business Case'!C11*$C16*'Business Case'!C12*$B16)-'Business Case'!C11*$C16*'Business Case'!C13*$D16-'Business Case'!C14*$E16))*'Business Case'!$B$7-'Business Case'!$B$8*(('Business Case'!C11*$C16*'Business Case'!C12*$B16)-('Business Case'!B11*$C16*'Business Case'!B12*$B16))-'Business Case'!C15*$F16 -> 0 | J16: =(('Business Case'!D11*$C16*'Business Case'!D12*$B16)-'Business Case'!D11*$C16*'Business Case'!D13*$D16-'Business Case'!D14*$E16)-MAX(0,(('Business Case'!D11*$C16*'Business Case'!D12*$B16)-'Business Case'!D11*$C16*'Business Case'!D13*$D16-'Business Case'!D14*$E16))*'Business Case'!$B$7-'Business Case'!$B$8*(('Business Case'!D11*$C16*'Business Case'!D12*$B16)-('Business Case'!C11*$C16*'Business Case'!C12*$B16))-'Business Case'!D15*$F16 -> 0 | K16: =(('Business Case'!E11*$C16*'Business Case'!E12*$B16)-'Business Case'!E11*$C16*'Business Case'!E13*$D16-'Business Case'!E14*$E16)-MAX(0,(('Business Case'!E11*$C16*'Business Case'!E12*$B16)-'Business Case'!E11*$C16*'Business Case'!E13*$D16-'Business Case'!E14*$E16))*'Business Case'!$B$7-'Business Case'!$B$8*(('Business Case'!E11*$C16*'Business Case'!E12*$B16)-('Business Case'!D11*$C16*'Business Case'!D12*$B16))-'Business Case'!E15*$F16 -> 0 | L16: =(('Business Case'!F11*$C16*'Business Case'!F12*$B16)-'Business Case'!F11*$C16*'Business Case'!F13*$D16-'Business Case'!F14*$E16)-MAX(0,(('Business Case'!F11*$C16*'Business Case'!F12*$B16)-'Business Case'!F11*$C16*'Business Case'!F13*$D16-'Business Case'!F14*$E16))*'Business Case'!$B$7-'Business Case'!$B$8*(('Business Case'!F11*$C16*'Business Case'!F12*$B16)-('Business Case'!E11*$C16*'Business Case'!E12*$B16))-'Business Case'!F15*$F16 -> 0 | M16: =(('Business Case'!G11*$C16*'Business Case'!G12*$B16)-'Business Case'!G11*$C16*'Business Case'!G13*$D16-'Business Case'!G14*$E16)-MAX(0,(('Business Case'!G11*$C16*'Business Case'!G12*$B16)-'Business Case'!G11*$C16*'Business Case'!G13*$D16-'Business Case'!G14*$E16))*'Business Case'!$B$7-'Business Case'!$B$8*(('Business Case'!G11*$C16*'Business Case'!G12*$B16)-('Business Case'!F11*$C16*'Business Case'!F12*$B16))-'Business Case'!G15*$F16+'Business Case'!$B$8*('Business Case'!G11*$C16*'Business Case'!G12*$B16) -> 0 | N16: =IF(COUNT('Business Case'!B11:G11)=0,"",H16+NPV(G16,I16:M16))
A17: Price per unit low | B17: =1+E6 -> 1 | C17: =1 -> 1 | D17: =1 -> 1 | E17: =1 -> 1 | F17: =1 -> 1 | G17: ='Business Case'!$B$6 -> 0 | H17: =(('Business Case'!B11*$C17*'Business Case'!B12*$B17)-'Business Case'!B11*$C17*'Business Case'!B13*$D17-'Business Case'!B14*$E17)-MAX(0,(('Business Case'!B11*$C17*'Business Case'!B12*$B17)-'Business Case'!B11*$C17*'Business Case'!B13*$D17-'Business Case'!B14*$E17))*'Business Case'!$B$7-'Business Case'!$B$8*('Business Case'!B11*$C17*'Business Case'!B12*$B17)-'Business Case'!B15*$F17 -> 0 | I17: =(('Business Case'!C11*$C17*'Business Case'!C12*$B17)-'Business Case'!C11*$C17*'Business Case'!C13*$D17-'Business Case'!C14*$E17)-MAX(0,(('Business Case'!C11*$C17*'Business Case'!C12*$B17)-'Business Case'!C11*$C17*'Business Case'!C13*$D17-'Business Case'!C14*$E17))*'Business Case'!$B$7-'Business Case'!$B$8*(('Business Case'!C11*$C17*'Business Case'!C12*$B17)-('Business Case'!B11*$C17*'Business Case'!B12*$B17))-'Business Case'!C15*$F17 -> 0 | J17: =(('Business Case'!D11*$C17*'Business Case'!D12*$B17)-'Business Case'!D11*$C17*'Business Case'!D13*$D17-'Business Case'!D14*$E17)-MAX(0,(('Business Case'!D11*$C17*'Business Case'!D12*$B17)-'Business Case'!D11*$C17*'Business Case'!D13*$D17-'Business Case'!D14*$E17))*'Business Case'!$B$7-'Business Case'!$B$8*(('Business Case'!D11*$C17*'Business Case'!D12*$B17)-('Business Case'!C11*$C17*'Business Case'!C12*$B17))-'Business Case'!D15*$F17 -> 0 | K17: =(('Business Case'!E11*$C17*'Business Case'!E12*$B17)-'Business Case'!E11*$C17*'Business Case'!E13*$D17-'Business Case'!E14*$E17)-MAX(0,(('Business Case'!E11*$C17*'Business Case'!E12*$B17)-'Business Case'!E11*$C17*'Business Case'!E13*$D17-'Business Case'!E14*$E17))*'Business Case'!$B$7-'Business Case'!$B$8*(('Business Case'!E11*$C17*'Business Case'!E12*$B17)-('Business Case'!D11*$C17*'Business Case'!D12*$B17))-'Business Case'!E15*$F17 -> 0 | L17: =(('Business Case'!F11*$C17*'Business Case'!F12*$B17)-'Business Case'!F11*$C17*'Business Case'!F13*$D17-'Business Case'!F14*$E17)-MAX(0,(('Business Case'!F11*$C17*'Business Case'!F12*$B17)-'Business Case'!F11*$C17*'Business Case'!F13*$D17-'Business Case'!F14*$E17))*'Business Case'!$B$7-'Business Case'!$B$8*(('Business Case'!F11*$C17*'Business Case'!F12*$B17)-('Business Case'!E11*$C17*'Business Case'!E12*$B17))-'Business Case'!F15*$F17 -> 0 | M17: =(('Business Case'!G11*$C17*'Business Case'!G12*$B17)-'Business Case'!G11*$C17*'Business Case'!G13*$D17-'Business Case'!G14*$E17)-MAX(0,(('Business Case'!G11*$C17*'Business Case'!G12*$B17)-'Business Case'!G11*$C17*'Business Case'!G13*$D17-'Business Case'!G14*$E17))*'Business Case'!$B$7-'Business Case'!$B$8*(('Business Case'!G11*$C17*'Business Case'!G12*$B17)-('Business Case'!F11*$C17*'Business Case'!F12*$B17))-'Business Case'!G15*$F17+'Business Case'!$B$8*('Business Case'!G11*$C17*'Business Case'!G12*$B17) -> 0 | N17: =IF(COUNT('Business Case'!B11:G11)=0,"",H17+NPV(G17,I17:M17))
A18: Price per unit high | B18: =1+G6 -> 1 | C18: =1 -> 1 | D18: =1 -> 1 | E18: =1 -> 1 | F18: =1 -> 1 | G18: ='Business Case'!$B$6 -> 0 | H18: =(('Business Case'!B11*$C18*'Business Case'!B12*$B18)-'Business Case'!B11*$C18*'Business Case'!B13*$D18-'Business Case'!B14*$E18)-MAX(0,(('Business Case'!B11*$C18*'Business Case'!B12*$B18)-'Business Case'!B11*$C18*'Business Case'!B13*$D18-'Business Case'!B14*$E18))*'Business Case'!$B$7-'Business Case'!$B$8*('Business Case'!B11*$C18*'Business Case'!B12*$B18)-'Business Case'!B15*$F18 -> 0 | I18: =(('Business Case'!C11*$C18*'Business Case'!C12*$B18)-'Business Case'!C11*$C18*'Business Case'!C13*$D18-'Business Case'!C14*$E18)-MAX(0,(('Business Case'!C11*$C18*'Business Case'!C12*$B18)-'Business Case'!C11*$C18*'Business Case'!C13*$D18-'Business Case'!C14*$E18))*'Business Case'!$B$7-'Business Case'!$B$8*(('Business Case'!C11*$C18*'Business Case'!C12*$B18)-('Business Case'!B11*$C18*'Business Case'!B12*$B18))-'Business Case'!C15*$F18 -> 0 | J18: =(('Business Case'!D11*$C18*'Business Case'!D12*$B18)-'Business Case'!D11*$C18*'Business Case'!D13*$D18-'Business Case'!D14*$E18)-MAX(0,(('Business Case'!D11*$C18*'Business Case'!D12*$B18)-'Business Case'!D11*$C18*'Business Case'!D13*$D18-'Business Case'!D14*$E18))*'Business Case'!$B$7-'Business Case'!$B$8*(('Business Case'!D11*$C18*'Business Case'!D12*$B18)-('Business Case'!C11*$C18*'Business Case'!C12*$B18))-'Business Case'!D15*$F18 -> 0 | K18: =(('Business Case'!E11*$C18*'Business Case'!E12*$B18)-'Business Case'!E11*$C18*'Business Case'!E13*$D18-'Business Case'!E14*$E18)-MAX(0,(('Business Case'!E11*$C18*'Business Case'!E12*$B18)-'Business Case'!E11*$C18*'Business Case'!E13*$D18-'Business Case'!E14*$E18))*'Business Case'!$B$7-'Business Case'!$B$8*(('Business Case'!E11*$C18*'Business Case'!E12*$B18)-('Business Case'!D11*$C18*'Business Case'!D12*$B18))-'Business Case'!E15*$F18 -> 0 | L18: =(('Business Case'!F11*$C18*'Business Case'!F12*$B18)-'Business Case'!F11*$C18*'Business Case'!F13*$D18-'Business Case'!F14*$E18)-MAX(0,(('Business Case'!F11*$C18*'Business Case'!F12*$B18)-'Business Case'!F11*$C18*'Business Case'!F13*$D18-'Business Case'!F14*$E18))*'Business Case'!$B$7-'Business Case'!$B$8*(('Business Case'!F11*$C18*'Business Case'!F12*$B18)-('Business Case'!E11*$C18*'Business Case'!E12*$B18))-'Business Case'!F15*$F18 -> 0 | M18: =(('Business Case'!G11*$C18*'Business Case'!G12*$B18)-'Business Case'!G11*$C18*'Business Case'!G13*$D18-'Business Case'!G14*$E18)-MAX(0,(('Business Case'!G11*$C18*'Business Case'!G12*$B18)-'Business Case'!G11*$C18*'Business Case'!G13*$D18-'Business Case'!G14*$E18))*'Business Case'!$B$7-'Business Case'!$B$8*(('Business Case'!G11*$C18*'Business Case'!G12*$B18)-('Business Case'!F11*$C18*'Business Case'!F12*$B18))-'Business Case'!G15*$F18+'Business Case'!$B$8*('Business Case'!G11*$C18*'Business Case'!G12*$B18) -> 0 | N18: =IF(COUNT('Business Case'!B11:G11)=0,"",H18+NPV(G18,I18:M18))
A19: Units low | B19: =1 -> 1 | C19: =1+E7 -> 1 | D19: =1 -> 1 | E19: =1 -> 1 | F19: =1 -> 1 | G19: ='Business Case'!$B$6 -> 0 | H19: =(('Business Case'!B11*$C19*'Business Case'!B12*$B19)-'Business Case'!B11*$C19*'Business Case'!B13*$D19-'Business Case'!B14*$E19)-MAX(0,(('Business Case'!B11*$C19*'Business Case'!B12*$B19)-'Business Case'!B11*$C19*'Business Case'!B13*$D19-'Business Case'!B14*$E19))*'Business Case'!$B$7-'Business Case'!$B$8*('Business Case'!B11*$C19*'Business Case'!B12*$B19)-'Business Case'!B15*$F19 -> 0 | I19: =(('Business Case'!C11*$C19*'Business Case'!C12*$B19)-'Business Case'!C11*$C19*'Business Case'!C13*$D19-'Business Case'!C14*$E19)-MAX(0,(('Business Case'!C11*$C19*'Business Case'!C12*$B19)-'Business Case'!C11*$C19*'Business Case'!C13*$D19-'Business Case'!C14*$E19))*'Business Case'!$B$7-'Business Case'!$B$8*(('Business Case'!C11*$C19*'Business Case'!C12*$B19)-('Business Case'!B11*$C19*'Business Case'!B12*$B19))-'Business Case'!C15*$F19 -> 0 | J19: =(('Business Case'!D11*$C19*'Business Case'!D12*$B19)-'Business Case'!D11*$C19*'Business Case'!D13*$D19-'Business Case'!D14*$E19)-MAX(0,(('Business Case'!D11*$C19*'Business Case'!D12*$B19)-'Business Case'!D11*$C19*'Business Case'!D13*$D19-'Business Case'!D14*$E19))*'Business Case'!$B$7-'Business Case'!$B$8*(('Business Case'!D11*$C19*'Business Case'!D12*$B19)-('Business Case'!C11*$C19*'Business Case'!C12*$B19))-'Business Case'!D15*$F19 -> 0 | K19: =(('Business Case'!E11*$C19*'Business Case'!E12*$B19)-'Business Case'!E11*$C19*'Business Case'!E13*$D19-'Business Case'!E14*$E19)-MAX(0,(('Business Case'!E11*$C19*'Business Case'!E12*$B19)-'Business Case'!E11*$C19*'Business Case'!E13*$D19-'Business Case'!E14*$E19))*'Business Case'!$B$7-'Business Case'!$B$8*(('Business Case'!E11*$C19*'Business Case'!E12*$B19)-('Business Case'!D11*$C19*'Business Case'!D12*$B19))-'Business Case'!E15*$F19 -> 0 | L19: =(('Business Case'!F11*$C19*'Business Case'!F12*$B19)-'Business Case'!F11*$C19*'Business Case'!F13*$D19-'Business Case'!F14*$E19)-MAX(0,(('Business Case'!F11*$C19*'Business Case'!F12*$B19)-'Business Case'!F11*$C19*'Business Case'!F13*$D19-'Business Case'!F14*$E19))*'Business Case'!$B$7-'Business Case'!$B$8*(('Business Case'!F11*$C19*'Business Case'!F12*$B19)-('Business Case'!E11*$C19*'Business Case'!E12*$B19))-'Business Case'!F15*$F19 -> 0 | M19: =(('Business Case'!G11*$C19*'Business Case'!G12*$B19)-'Business Case'!G11*$C19*'Business Case'!G13*$D19-'Business Case'!G14*$E19)-MAX(0,(('Business Case'!G11*$C19*'Business Case'!G12*$B19)-'Business Case'!G11*$C19*'Business Case'!G13*$D19-'Business Case'!G14*$E19))*'Business Case'!$B$7-'Business Case'!$B$8*(('Business Case'!G11*$C19*'Business Case'!G12*$B19)-('Business Case'!F11*$C19*'Business Case'!F12*$B19))-'Business Case'!G15*$F19+'Business Case'!$B$8*('Business Case'!G11*$C19*'Business Case'!G12*$B19) -> 0 | N19: =IF(COUNT('Business Case'!B11:G11)=0,"",H19+NPV(G19,I19:M19))
A20: Units high | B20: =1 -> 1 | C20: =1+G7 -> 1 | D20: =1 -> 1 | E20: =1 -> 1 | F20: =1 -> 1 | G20: ='Business Case'!$B$6 -> 0 | H20: =(('Business Case'!B11*$C20*'Business Case'!B12*$B20)-'Business Case'!B11*$C20*'Business Case'!B13*$D20-'Business Case'!B14*$E20)-MAX(0,(('Business Case'!B11*$C20*'Business Case'!B12*$B20)-'Business Case'!B11*$C20*'Business Case'!B13*$D20-'Business Case'!B14*$E20))*'Business Case'!$B$7-'Business Case'!$B$8*('Business Case'!B11*$C20*'Business Case'!B12*$B20)-'Business Case'!B15*$F20 -> 0 | I20: =(('Business Case'!C11*$C20*'Business Case'!C12*$B20)-'Business Case'!C11*$C20*'Business Case'!C13*$D20-'Business Case'!C14*$E20)-MAX(0,(('Business Case'!C11*$C20*'Business Case'!C12*$B20)-'Business Case'!C11*$C20*'Business Case'!C13*$D20-'Business Case'!C14*$E20))*'Business Case'!$B$7-'Business Case'!$B$8*(('Business Case'!C11*$C20*'Business Case'!C12*$B20)-('Business Case'!B11*$C20*'Business Case'!B12*$B20))-'Business Case'!C15*$F20 -> 0 | J20: =(('Business Case'!D11*$C20*'Business Case'!D12*$B20)-'Business Case'!D11*$C20*'Business Case'!D13*$D20-'Business Case'!D14*$E20)-MAX(0,(('Business Case'!D11*$C20*'Business Case'!D12*$B20)-'Business Case'!D11*$C20*'Business Case'!D13*$D20-'Business Case'!D14*$E20))*'Business Case'!$B$7-'Business Case'!$B$8*(('Business Case'!D11*$C20*'Business Case'!D12*$B20)-('Business Case'!C11*$C20*'Business Case'!C12*$B20))-'Business Case'!D15*$F20 -> 0 | K20: =(('Business Case'!E11*$C20*'Business Case'!E12*$B20)-'Business Case'!E11*$C20*'Business Case'!E13*$D20-'Business Case'!E14*$E20)-MAX(0,(('Business Case'!E11*$C20*'Business Case'!E12*$B20)-'Business Case'!E11*$C20*'Business Case'!E13*$D20-'Business Case'!E14*$E20))*'Business Case'!$B$7-'Business Case'!$B$8*(('Business Case'!E11*$C20*'Business Case'!E12*$B20)-('Business Case'!D11*$C20*'Business Case'!D12*$B20))-'Business Case'!E15*$F20 -> 0 | L20: =(('Business Case'!F11*$C20*'Business Case'!F12*$B20)-'Business Case'!F11*$C20*'Business Case'!F13*$D20-'Business Case'!F14*$E20)-MAX(0,(('Business Case'!F11*$C20*'Business Case'!F12*$B20)-'Business Case'!F11*$C20*'Business Case'!F13*$D20-'Business Case'!F14*$E20))*'Business Case'!$B$7-'Business Case'!$B$8*(('Business Case'!F11*$C20*'Business Case'!F12*$B20)-('Business Case'!E11*$C20*'Business Case'!E12*$B20))-'Business Case'!F15*$F20 -> 0 | M20: =(('Business Case'!G11*$C20*'Business Case'!G12*$B20)-'Business Case'!G11*$C20*'Business Case'!G13*$D20-'Business Case'!G14*$E20)-MAX(0,(('Business Case'!G11*$C20*'Business Case'!G12*$B20)-'Business Case'!G11*$C20*'Business Case'!G13*$D20-'Business Case'!G14*$E20))*'Business Case'!$B$7-'Business Case'!$B$8*(('Business Case'!G11*$C20*'Business Case'!G12*$B20)-('Business Case'!F11*$C20*'Business Case'!F12*$B20))-'Business Case'!G15*$F20+'Business Case'!$B$8*('Business Case'!G11*$C20*'Business Case'!G12*$B20) -> 0 | N20: =IF(COUNT('Business Case'!B11:G11)=0,"",H20+NPV(G20,I20:M20))
A21: Variable cost per unit low | B21: =1 -> 1 | C21: =1 -> 1 | D21: =1+E8 -> 1 | E21: =1 -> 1 | F21: =1 -> 1 | G21: ='Business Case'!$B$6 -> 0 | H21: =(('Business Case'!B11*$C21*'Business Case'!B12*$B21)-'Business Case'!B11*$C21*'Business Case'!B13*$D21-'Business Case'!B14*$E21)-MAX(0,(('Business Case'!B11*$C21*'Business Case'!B12*$B21)-'Business Case'!B11*$C21*'Business Case'!B13*$D21-'Business Case'!B14*$E21))*'Business Case'!$B$7-'Business Case'!$B$8*('Business Case'!B11*$C21*'Business Case'!B12*$B21)-'Business Case'!B15*$F21 -> 0 | I21: =(('Business Case'!C11*$C21*'Business Case'!C12*$B21)-'Business Case'!C11*$C21*'Business Case'!C13*$D21-'Business Case'!C14*$E21)-MAX(0,(('Business Case'!C11*$C21*'Business Case'!C12*$B21)-'Business Case'!C11*$C21*'Business Case'!C13*$D21-'Business Case'!C14*$E21))*'Business Case'!$B$7-'Business Case'!$B$8*(('Business Case'!C11*$C21*'Business Case'!C12*$B21)-('Business Case'!B11*$C21*'Business Case'!B12*$B21))-'Business Case'!C15*$F21 -> 0 | J21: =(('Business Case'!D11*$C21*'Business Case'!D12*$B21)-'Business Case'!D11*$C21*'Business Case'!D13*$D21-'Business Case'!D14*$E21)-MAX(0,(('Business Case'!D11*$C21*'Business Case'!D12*$B21)-'Business Case'!D11*$C21*'Business Case'!D13*$D21-'Business Case'!D14*$E21))*'Business Case'!$B$7-'Business Case'!$B$8*(('Business Case'!D11*$C21*'Business Case'!D12*$B21)-('Business Case'!C11*$C21*'Business Case'!C12*$B21))-'Business Case'!D15*$F21 -> 0 | K21: =(('Business Case'!E11*$C21*'Business Case'!E12*$B21)-'Business Case'!E11*$C21*'Business Case'!E13*$D21-'Business Case'!E14*$E21)-MAX(0,(('Business Case'!E11*$C21*'Business Case'!E12*$B21)-'Business Case'!E11*$C21*'Business Case'!E13*$D21-'Business Case'!E14*$E21))*'Business Case'!$B$7-'Business Case'!$B$8*(('Business Case'!E11*$C21*'Business Case'!E12*$B21)-('Business Case'!D11*$C21*'Business Case'!D12*$B21))-'Business Case'!E15*$F21 -> 0 | L21: =(('Business Case'!F11*$C21*'Business Case'!F12*$B21)-'Business Case'!F11*$C21*'Business Case'!F13*$D21-'Business Case'!F14*$E21)-MAX(0,(('Business Case'!F11*$C21*'Business Case'!F12*$B21)-'Business Case'!F11*$C21*'Business Case'!F13*$D21-'Business Case'!F14*$E21))*'Business Case'!$B$7-'Business Case'!$B$8*(('Business Case'!F11*$C21*'Business Case'!F12*$B21)-('Business Case'!E11*$C21*'Business Case'!E12*$B21))-'Business Case'!F15*$F21 -> 0 | M21: =(('Business Case'!G11*$C21*'Business Case'!G12*$B21)-'Business Case'!G11*$C21*'Business Case'!G13*$D21-'Business Case'!G14*$E21)-MAX(0,(('Business Case'!G11*$C21*'Business Case'!G12*$B21)-'Business Case'!G11*$C21*'Business Case'!G13*$D21-'Business Case'!G14*$E21))*'Business Case'!$B$7-'Business Case'!$B$8*(('Business Case'!G11*$C21*'Business Case'!G12*$B21)-('Business Case'!F11*$C21*'Business Case'!F12*$B21))-'Business Case'!G15*$F21+'Business Case'!$B$8*('Business Case'!G11*$C21*'Business Case'!G12*$B21) -> 0 | N21: =IF(COUNT('Business Case'!B11:G11)=0,"",H21+NPV(G21,I21:M21))
A22: Variable cost per unit high | B22: =1 -> 1 | C22: =1 -> 1 | D22: =1+G8 -> 1 | E22: =1 -> 1 | F22: =1 -> 1 | G22: ='Business Case'!$B$6 -> 0 | H22: =(('Business Case'!B11*$C22*'Business Case'!B12*$B22)-'Business Case'!B11*$C22*'Business Case'!B13*$D22-'Business Case'!B14*$E22)-MAX(0,(('Business Case'!B11*$C22*'Business Case'!B12*$B22)-'Business Case'!B11*$C22*'Business Case'!B13*$D22-'Business Case'!B14*$E22))*'Business Case'!$B$7-'Business Case'!$B$8*('Business Case'!B11*$C22*'Business Case'!B12*$B22)-'Business Case'!B15*$F22 -> 0 | I22: =(('Business Case'!C11*$C22*'Business Case'!C12*$B22)-'Business Case'!C11*$C22*'Business Case'!C13*$D22-'Business Case'!C14*$E22)-MAX(0,(('Business Case'!C11*$C22*'Business Case'!C12*$B22)-'Business Case'!C11*$C22*'Business Case'!C13*$D22-'Business Case'!C14*$E22))*'Business Case'!$B$7-'Business Case'!$B$8*(('Business Case'!C11*$C22*'Business Case'!C12*$B22)-('Business Case'!B11*$C22*'Business Case'!B12*$B22))-'Business Case'!C15*$F22 -> 0 | J22: =(('Business Case'!D11*$C22*'Business Case'!D12*$B22)-'Business Case'!D11*$C22*'Business Case'!D13*$D22-'Business Case'!D14*$E22)-MAX(0,(('Business Case'!D11*$C22*'Business Case'!D12*$B22)-'Business Case'!D11*$C22*'Business Case'!D13*$D22-'Business Case'!D14*$E22))*'Business Case'!$B$7-'Business Case'!$B$8*(('Business Case'!D11*$C22*'Business Case'!D12*$B22)-('Business Case'!C11*$C22*'Business Case'!C12*$B22))-'Business Case'!D15*$F22 -> 0 | K22: =(('Business Case'!E11*$C22*'Business Case'!E12*$B22)-'Business Case'!E11*$C22*'Business Case'!E13*$D22-'Business Case'!E14*$E22)-MAX(0,(('Business Case'!E11*$C22*'Business Case'!E12*$B22)-'Business Case'!E11*$C22*'Business Case'!E13*$D22-'Business Case'!E14*$E22))*'Business Case'!$B$7-'Business Case'!$B$8*(('Business Case'!E11*$C22*'Business Case'!E12*$B22)-('Business Case'!D11*$C22*'Business Case'!D12*$B22))-'Business Case'!E15*$F22 -> 0 | L22: =(('Business Case'!F11*$C22*'Business Case'!F12*$B22)-'Business Case'!F11*$C22*'Business Case'!F13*$D22-'Business Case'!F14*$E22)-MAX(0,(('Business Case'!F11*$C22*'Business Case'!F12*$B22)-'Business Case'!F11*$C22*'Business Case'!F13*$D22-'Business Case'!F14*$E22))*'Business Case'!$B$7-'Business Case'!$B$8*(('Business Case'!F11*$C22*'Business Case'!F12*$B22)-('Business Case'!E11*$C22*'Business Case'!E12*$B22))-'Business Case'!F15*$F22 -> 0 | M22: =(('Business Case'!G11*$C22*'Business Case'!G12*$B22)-'Business Case'!G11*$C22*'Business Case'!G13*$D22-'Business Case'!G14*$E22)-MAX(0,(('Business Case'!G11*$C22*'Business Case'!G12*$B22)-'Business Case'!G11*$C22*'Business Case'!G13*$D22-'Business Case'!G14*$E22))*'Business Case'!$B$7-'Business Case'!$B$8*(('Business Case'!G11*$C22*'Business Case'!G12*$B22)-('Business Case'!F11*$C22*'Business Case'!F12*$B22))-'Business Case'!G15*$F22+'Business Case'!$B$8*('Business Case'!G11*$C22*'Business Case'!G12*$B22) -> 0 | N22: =IF(COUNT('Business Case'!B11:G11)=0,"",H22+NPV(G22,I22:M22))
A23: Fixed costs low | B23: =1 -> 1 | C23: =1 -> 1 | D23: =1 -> 1 | E23: =1+E9 -> 1 | F23: =1 -> 1 | G23: ='Business Case'!$B$6 -> 0 | H23: =(('Business Case'!B11*$C23*'Business Case'!B12*$B23)-'Business Case'!B11*$C23*'Business Case'!B13*$D23-'Business Case'!B14*$E23)-MAX(0,(('Business Case'!B11*$C23*'Business Case'!B12*$B23)-'Business Case'!B11*$C23*'Business Case'!B13*$D23-'Business Case'!B14*$E23))*'Business Case'!$B$7-'Business Case'!$B$8*('Business Case'!B11*$C23*'Business Case'!B12*$B23)-'Business Case'!B15*$F23 -> 0 | I23: =(('Business Case'!C11*$C23*'Business Case'!C12*$B23)-'Business Case'!C11*$C23*'Business Case'!C13*$D23-'Business Case'!C14*$E23)-MAX(0,(('Business Case'!C11*$C23*'Business Case'!C12*$B23)-'Business Case'!C11*$C23*'Business Case'!C13*$D23-'Business Case'!C14*$E23))*'Business Case'!$B$7-'Business Case'!$B$8*(('Business Case'!C11*$C23*'Business Case'!C12*$B23)-('Business Case'!B11*$C23*'Business Case'!B12*$B23))-'Business Case'!C15*$F23 -> 0 | J23: =(('Business Case'!D11*$C23*'Business Case'!D12*$B23)-'Business Case'!D11*$C23*'Business Case'!D13*$D23-'Business Case'!D14*$E23)-MAX(0,(('Business Case'!D11*$C23*'Business Case'!D12*$B23)-'Business Case'!D11*$C23*'Business Case'!D13*$D23-'Business Case'!D14*$E23))*'Business Case'!$B$7-'Business Case'!$B$8*(('Business Case'!D11*$C23*'Business Case'!D12*$B23)-('Business Case'!C11*$C23*'Business Case'!C12*$B23))-'Business Case'!D15*$F23 -> 0 | K23: =(('Business Case'!E11*$C23*'Business Case'!E12*$B23)-'Business Case'!E11*$C23*'Business Case'!E13*$D23-'Business Case'!E14*$E23)-MAX(0,(('Business Case'!E11*$C23*'Business Case'!E12*$B23)-'Business Case'!E11*$C23*'Business Case'!E13*$D23-'Business Case'!E14*$E23))*'Business Case'!$B$7-'Business Case'!$B$8*(('Business Case'!E11*$C23*'Business Case'!E12*$B23)-('Business Case'!D11*$C23*'Business Case'!D12*$B23))-'Business Case'!E15*$F23 -> 0 | L23: =(('Business Case'!F11*$C23*'Business Case'!F12*$B23)-'Business Case'!F11*$C23*'Business Case'!F13*$D23-'Business Case'!F14*$E23)-MAX(0,(('Business Case'!F11*$C23*'Business Case'!F12*$B23)-'Business Case'!F11*$C23*'Business Case'!F13*$D23-'Business Case'!F14*$E23))*'Business Case'!$B$7-'Business Case'!$B$8*(('Business Case'!F11*$C23*'Business Case'!F12*$B23)-('Business Case'!E11*$C23*'Business Case'!E12*$B23))-'Business Case'!F15*$F23 -> 0 | M23: =(('Business Case'!G11*$C23*'Business Case'!G12*$B23)-'Business Case'!G11*$C23*'Business Case'!G13*$D23-'Business Case'!G14*$E23)-MAX(0,(('Business Case'!G11*$C23*'Business Case'!G12*$B23)-'Business Case'!G11*$C23*'Business Case'!G13*$D23-'Business Case'!G14*$E23))*'Business Case'!$B$7-'Business Case'!$B$8*(('Business Case'!G11*$C23*'Business Case'!G12*$B23)-('Business Case'!F11*$C23*'Business Case'!F12*$B23))-'Business Case'!G15*$F23+'Business Case'!$B$8*('Business Case'!G11*$C23*'Business Case'!G12*$B23) -> 0 | N23: =IF(COUNT('Business Case'!B11:G11)=0,"",H23+NPV(G23,I23:M23))
A24: Fixed costs high | B24: =1 -> 1 | C24: =1 -> 1 | D24: =1 -> 1 | E24: =1+G9 -> 1 | F24: =1 -> 1 | G24: ='Business Case'!$B$6 -> 0 | H24: =(('Business Case'!B11*$C24*'Business Case'!B12*$B24)-'Business Case'!B11*$C24*'Business Case'!B13*$D24-'Business Case'!B14*$E24)-MAX(0,(('Business Case'!B11*$C24*'Business Case'!B12*$B24)-'Business Case'!B11*$C24*'Business Case'!B13*$D24-'Business Case'!B14*$E24))*'Business Case'!$B$7-'Business Case'!$B$8*('Business Case'!B11*$C24*'Business Case'!B12*$B24)-'Business Case'!B15*$F24 -> 0 | I24: =(('Business Case'!C11*$C24*'Business Case'!C12*$B24)-'Business Case'!C11*$C24*'Business Case'!C13*$D24-'Business Case'!C14*$E24)-MAX(0,(('Business Case'!C11*$C24*'Business Case'!C12*$B24)-'Business Case'!C11*$C24*'Business Case'!C13*$D24-'Business Case'!C14*$E24))*'Business Case'!$B$7-'Business Case'!$B$8*(('Business Case'!C11*$C24*'Business Case'!C12*$B24)-('Business Case'!B11*$C24*'Business Case'!B12*$B24))-'Business Case'!C15*$F24 -> 0 | J24: =(('Business Case'!D11*$C24*'Business Case'!D12*$B24)-'Business Case'!D11*$C24*'Business Case'!D13*$D24-'Business Case'!D14*$E24)-MAX(0,(('Business Case'!D11*$C24*'Business Case'!D12*$B24)-'Business Case'!D11*$C24*'Business Case'!D13*$D24-'Business Case'!D14*$E24))*'Business Case'!$B$7-'Business Case'!$B$8*(('Business Case'!D11*$C24*'Business Case'!D12*$B24)-('Business Case'!C11*$C24*'Business Case'!C12*$B24))-'Business Case'!D15*$F24 -> 0 | K24: =(('Business Case'!E11*$C24*'Business Case'!E12*$B24)-'Business Case'!E11*$C24*'Business Case'!E13*$D24-'Business Case'!E14*$E24)-MAX(0,(('Business Case'!E11*$C24*'Business Case'!E12*$B24)-'Business Case'!E11*$C24*'Business Case'!E13*$D24-'Business Case'!E14*$E24))*'Business Case'!$B$7-'Business Case'!$B$8*(('Business Case'!E11*$C24*'Business Case'!E12*$B24)-('Business Case'!D11*$C24*'Business Case'!D12*$B24))-'Business Case'!E15*$F24 -> 0 | L24: =(('Business Case'!F11*$C24*'Business Case'!F12*$B24)-'Business Case'!F11*$C24*'Business Case'!F13*$D24-'Business Case'!F14*$E24)-MAX(0,(('Business Case'!F11*$C24*'Business Case'!F12*$B24)-'Business Case'!F11*$C24*'Business Case'!F13*$D24-'Business Case'!F14*$E24))*'Business Case'!$B$7-'Business Case'!$B$8*(('Business Case'!F11*$C24*'Business Case'!F12*$B24)-('Business Case'!E11*$C24*'Business Case'!E12*$B24))-'Business Case'!F15*$F24 -> 0 | M24: =(('Business Case'!G11*$C24*'Business Case'!G12*$B24)-'Business Case'!G11*$C24*'Business Case'!G13*$D24-'Business Case'!G14*$E24)-MAX(0,(('Business Case'!G11*$C24*'Business Case'!G12*$B24)-'Business Case'!G11*$C24*'Business Case'!G13*$D24-'Business Case'!G14*$E24))*'Business Case'!$B$7-'Business Case'!$B$8*(('Business Case'!G11*$C24*'Business Case'!G12*$B24)-('Business Case'!F11*$C24*'Business Case'!F12*$B24))-'Business Case'!G15*$F24+'Business Case'!$B$8*('Business Case'!G11*$C24*'Business Case'!G12*$B24) -> 0 | N24: =IF(COUNT('Business Case'!B11:G11)=0,"",H24+NPV(G24,I24:M24))
A25: Capex low | B25: =1 -> 1 | C25: =1 -> 1 | D25: =1 -> 1 | E25: =1 -> 1 | F25: =1+E10 -> 1 | G25: ='Business Case'!$B$6 -> 0 | H25: =(('Business Case'!B11*$C25*'Business Case'!B12*$B25)-'Business Case'!B11*$C25*'Business Case'!B13*$D25-'Business Case'!B14*$E25)-MAX(0,(('Business Case'!B11*$C25*'Business Case'!B12*$B25)-'Business Case'!B11*$C25*'Business Case'!B13*$D25-'Business Case'!B14*$E25))*'Business Case'!$B$7-'Business Case'!$B$8*('Business Case'!B11*$C25*'Business Case'!B12*$B25)-'Business Case'!B15*$F25 -> 0 | I25: =(('Business Case'!C11*$C25*'Business Case'!C12*$B25)-'Business Case'!C11*$C25*'Business Case'!C13*$D25-'Business Case'!C14*$E25)-MAX(0,(('Business Case'!C11*$C25*'Business Case'!C12*$B25)-'Business Case'!C11*$C25*'Business Case'!C13*$D25-'Business Case'!C14*$E25))*'Business Case'!$B$7-'Business Case'!$B$8*(('Business Case'!C11*$C25*'Business Case'!C12*$B25)-('Business Case'!B11*$C25*'Business Case'!B12*$B25))-'Business Case'!C15*$F25 -> 0 | J25: =(('Business Case'!D11*$C25*'Business Case'!D12*$B25)-'Business Case'!D11*$C25*'Business Case'!D13*$D25-'Business Case'!D14*$E25)-MAX(0,(('Business Case'!D11*$C25*'Business Case'!D12*$B25)-'Business Case'!D11*$C25*'Business Case'!D13*$D25-'Business Case'!D14*$E25))*'Business Case'!$B$7-'Business Case'!$B$8*(('Business Case'!D11*$C25*'Business Case'!D12*$B25)-('Business Case'!C11*$C25*'Business Case'!C12*$B25))-'Business Case'!D15*$F25 -> 0 | K25: =(('Business Case'!E11*$C25*'Business Case'!E12*$B25)-'Business Case'!E11*$C25*'Business Case'!E13*$D25-'Business Case'!E14*$E25)-MAX(0,(('Business Case'!E11*$C25*'Business Case'!E12*$B25)-'Business Case'!E11*$C25*'Business Case'!E13*$D25-'Business Case'!E14*$E25))*'Business Case'!$B$7-'Business Case'!$B$8*(('Business Case'!E11*$C25*'Business Case'!E12*$B25)-('Business Case'!D11*$C25*'Business Case'!D12*$B25))-'Business Case'!E15*$F25 -> 0 | L25: =(('Business Case'!F11*$C25*'Business Case'!F12*$B25)-'Business Case'!F11*$C25*'Business Case'!F13*$D25-'Business Case'!F14*$E25)-MAX(0,(('Business Case'!F11*$C25*'Business Case'!F12*$B25)-'Business Case'!F11*$C25*'Business Case'!F13*$D25-'Business Case'!F14*$E25))*'Business Case'!$B$7-'Business Case'!$B$8*(('Business Case'!F11*$C25*'Business Case'!F12*$B25)-('Business Case'!E11*$C25*'Business Case'!E12*$B25))-'Business Case'!F15*$F25 -> 0 | M25: =(('Business Case'!G11*$C25*'Business Case'!G12*$B25)-'Business Case'!G11*$C25*'Business Case'!G13*$D25-'Business Case'!G14*$E25)-MAX(0,(('Business Case'!G11*$C25*'Business Case'!G12*$B25)-'Business Case'!G11*$C25*'Business Case'!G13*$D25-'Business Case'!G14*$E25))*'Business Case'!$B$7-'Business Case'!$B$8*(('Business Case'!G11*$C25*'Business Case'!G12*$B25)-('Business Case'!F11*$C25*'Business Case'!F12*$B25))-'Business Case'!G15*$F25+'Business Case'!$B$8*('Business Case'!G11*$C25*'Business Case'!G12*$B25) -> 0 | N25: =IF(COUNT('Business Case'!B11:G11)=0,"",H25+NPV(G25,I25:M25))
A26: Capex high | B26: =1 -> 1 | C26: =1 -> 1 | D26: =1 -> 1 | E26: =1 -> 1 | F26: =1+G10 -> 1 | G26: ='Business Case'!$B$6 -> 0 | H26: =(('Business Case'!B11*$C26*'Business Case'!B12*$B26)-'Business Case'!B11*$C26*'Business Case'!B13*$D26-'Business Case'!B14*$E26)-MAX(0,(('Business Case'!B11*$C26*'Business Case'!B12*$B26)-'Business Case'!B11*$C26*'Business Case'!B13*$D26-'Business Case'!B14*$E26))*'Business Case'!$B$7-'Business Case'!$B$8*('Business Case'!B11*$C26*'Business Case'!B12*$B26)-'Business Case'!B15*$F26 -> 0 | I26: =(('Business Case'!C11*$C26*'Business Case'!C12*$B26)-'Business Case'!C11*$C26*'Business Case'!C13*$D26-'Business Case'!C14*$E26)-MAX(0,(('Business Case'!C11*$C26*'Business Case'!C12*$B26)-'Business Case'!C11*$C26*'Business Case'!C13*$D26-'Business Case'!C14*$E26))*'Business Case'!$B$7-'Business Case'!$B$8*(('Business Case'!C11*$C26*'Business Case'!C12*$B26)-('Business Case'!B11*$C26*'Business Case'!B12*$B26))-'Business Case'!C15*$F26 -> 0 | J26: =(('Business Case'!D11*$C26*'Business Case'!D12*$B26)-'Business Case'!D11*$C26*'Business Case'!D13*$D26-'Business Case'!D14*$E26)-MAX(0,(('Business Case'!D11*$C26*'Business Case'!D12*$B26)-'Business Case'!D11*$C26*'Business Case'!D13*$D26-'Business Case'!D14*$E26))*'Business Case'!$B$7-'Business Case'!$B$8*(('Business Case'!D11*$C26*'Business Case'!D12*$B26)-('Business Case'!C11*$C26*'Business Case'!C12*$B26))-'Business Case'!D15*$F26 -> 0 | K26: =(('Business Case'!E11*$C26*'Business Case'!E12*$B26)-'Business Case'!E11*$C26*'Business Case'!E13*$D26-'Business Case'!E14*$E26)-MAX(0,(('Business Case'!E11*$C26*'Business Case'!E12*$B26)-'Business Case'!E11*$C26*'Business Case'!E13*$D26-'Business Case'!E14*$E26))*'Business Case'!$B$7-'Business Case'!$B$8*(('Business Case'!E11*$C26*'Business Case'!E12*$B26)-('Business Case'!D11*$C26*'Business Case'!D12*$B26))-'Business Case'!E15*$F26 -> 0 | L26: =(('Business Case'!F11*$C26*'Business Case'!F12*$B26)-'Business Case'!F11*$C26*'Business Case'!F13*$D26-'Business Case'!F14*$E26)-MAX(0,(('Business Case'!F11*$C26*'Business Case'!F12*$B26)-'Business Case'!F11*$C26*'Business Case'!F13*$D26-'Business Case'!F14*$E26))*'Business Case'!$B$7-'Business Case'!$B$8*(('Business Case'!F11*$C26*'Business Case'!F12*$B26)-('Business Case'!E11*$C26*'Business Case'!E12*$B26))-'Business Case'!F15*$F26 -> 0 | M26: =(('Business Case'!G11*$C26*'Business Case'!G12*$B26)-'Business Case'!G11*$C26*'Business Case'!G13*$D26-'Business Case'!G14*$E26)-MAX(0,(('Business Case'!G11*$C26*'Business Case'!G12*$B26)-'Business Case'!G11*$C26*'Business Case'!G13*$D26-'Business Case'!G14*$E26))*'Business Case'!$B$7-'Business Case'!$B$8*(('Business Case'!G11*$C26*'Business Case'!G12*$B26)-('Business Case'!F11*$C26*'Business Case'!F12*$B26))-'Business Case'!G15*$F26+'Business Case'!$B$8*('Business Case'!G11*$C26*'Business Case'!G12*$B26) -> 0 | N26: =IF(COUNT('Business Case'!B11:G11)=0,"",H26+NPV(G26,I26:M26))
A27: Discount rate (absolute) low | B27: =1 -> 1 | C27: =1 -> 1 | D27: =1 -> 1 | E27: =1 -> 1 | F27: =1 -> 1 | G27: =E11 -> 0 | H27: =(('Business Case'!B11*$C27*'Business Case'!B12*$B27)-'Business Case'!B11*$C27*'Business Case'!B13*$D27-'Business Case'!B14*$E27)-MAX(0,(('Business Case'!B11*$C27*'Business Case'!B12*$B27)-'Business Case'!B11*$C27*'Business Case'!B13*$D27-'Business Case'!B14*$E27))*'Business Case'!$B$7-'Business Case'!$B$8*('Business Case'!B11*$C27*'Business Case'!B12*$B27)-'Business Case'!B15*$F27 -> 0 | I27: =(('Business Case'!C11*$C27*'Business Case'!C12*$B27)-'Business Case'!C11*$C27*'Business Case'!C13*$D27-'Business Case'!C14*$E27)-MAX(0,(('Business Case'!C11*$C27*'Business Case'!C12*$B27)-'Business Case'!C11*$C27*'Business Case'!C13*$D27-'Business Case'!C14*$E27))*'Business Case'!$B$7-'Business Case'!$B$8*(('Business Case'!C11*$C27*'Business Case'!C12*$B27)-('Business Case'!B11*$C27*'Business Case'!B12*$B27))-'Business Case'!C15*$F27 -> 0 | J27: =(('Business Case'!D11*$C27*'Business Case'!D12*$B27)-'Business Case'!D11*$C27*'Business Case'!D13*$D27-'Business Case'!D14*$E27)-MAX(0,(('Business Case'!D11*$C27*'Business Case'!D12*$B27)-'Business Case'!D11*$C27*'Business Case'!D13*$D27-'Business Case'!D14*$E27))*'Business Case'!$B$7-'Business Case'!$B$8*(('Business Case'!D11*$C27*'Business Case'!D12*$B27)-('Business Case'!C11*$C27*'Business Case'!C12*$B27))-'Business Case'!D15*$F27 -> 0 | K27: =(('Business Case'!E11*$C27*'Business Case'!E12*$B27)-'Business Case'!E11*$C27*'Business Case'!E13*$D27-'Business Case'!E14*$E27)-MAX(0,(('Business Case'!E11*$C27*'Business Case'!E12*$B27)-'Business Case'!E11*$C27*'Business Case'!E13*$D27-'Business Case'!E14*$E27))*'Business Case'!$B$7-'Business Case'!$B$8*(('Business Case'!E11*$C27*'Business Case'!E12*$B27)-('Business Case'!D11*$C27*'Business Case'!D12*$B27))-'Business Case'!E15*$F27 -> 0 | L27: =(('Business Case'!F11*$C27*'Business Case'!F12*$B27)-'Business Case'!F11*$C27*'Business Case'!F13*$D27-'Business Case'!F14*$E27)-MAX(0,(('Business Case'!F11*$C27*'Business Case'!F12*$B27)-'Business Case'!F11*$C27*'Business Case'!F13*$D27-'Business Case'!F14*$E27))*'Business Case'!$B$7-'Business Case'!$B$8*(('Business Case'!F11*$C27*'Business Case'!F12*$B27)-('Business Case'!E11*$C27*'Business Case'!E12*$B27))-'Business Case'!F15*$F27 -> 0 | M27: =(('Business Case'!G11*$C27*'Business Case'!G12*$B27)-'Business Case'!G11*$C27*'Business Case'!G13*$D27-'Business Case'!G14*$E27)-MAX(0,(('Business Case'!G11*$C27*'Business Case'!G12*$B27)-'Business Case'!G11*$C27*'Business Case'!G13*$D27-'Business Case'!G14*$E27))*'Business Case'!$B$7-'Business Case'!$B$8*(('Business Case'!G11*$C27*'Business Case'!G12*$B27)-('Business Case'!F11*$C27*'Business Case'!F12*$B27))-'Business Case'!G15*$F27+'Business Case'!$B$8*('Business Case'!G11*$C27*'Business Case'!G12*$B27) -> 0 | N27: =IF(COUNT('Business Case'!B11:G11)=0,"",H27+NPV(G27,I27:M27))
A28: Discount rate (absolute) high | B28: =1 -> 1 | C28: =1 -> 1 | D28: =1 -> 1 | E28: =1 -> 1 | F28: =1 -> 1 | G28: =G11 -> 0 | H28: =(('Business Case'!B11*$C28*'Business Case'!B12*$B28)-'Business Case'!B11*$C28*'Business Case'!B13*$D28-'Business Case'!B14*$E28)-MAX(0,(('Business Case'!B11*$C28*'Business Case'!B12*$B28)-'Business Case'!B11*$C28*'Business Case'!B13*$D28-'Business Case'!B14*$E28))*'Business Case'!$B$7-'Business Case'!$B$8*('Business Case'!B11*$C28*'Business Case'!B12*$B28)-'Business Case'!B15*$F28 -> 0 | I28: =(('Business Case'!C11*$C28*'Business Case'!C12*$B28)-'Business Case'!C11*$C28*'Business Case'!C13*$D28-'Business Case'!C14*$E28)-MAX(0,(('Business Case'!C11*$C28*'Business Case'!C12*$B28)-'Business Case'!C11*$C28*'Business Case'!C13*$D28-'Business Case'!C14*$E28))*'Business Case'!$B$7-'Business Case'!$B$8*(('Business Case'!C11*$C28*'Business Case'!C12*$B28)-('Business Case'!B11*$C28*'Business Case'!B12*$B28))-'Business Case'!C15*$F28 -> 0 | J28: =(('Business Case'!D11*$C28*'Business Case'!D12*$B28)-'Business Case'!D11*$C28*'Business Case'!D13*$D28-'Business Case'!D14*$E28)-MAX(0,(('Business Case'!D11*$C28*'Business Case'!D12*$B28)-'Business Case'!D11*$C28*'Business Case'!D13*$D28-'Business Case'!D14*$E28))*'Business Case'!$B$7-'Business Case'!$B$8*(('Business Case'!D11*$C28*'Business Case'!D12*$B28)-('Business Case'!C11*$C28*'Business Case'!C12*$B28))-'Business Case'!D15*$F28 -> 0 | K28: =(('Business Case'!E11*$C28*'Business Case'!E12*$B28)-'Business Case'!E11*$C28*'Business Case'!E13*$D28-'Business Case'!E14*$E28)-MAX(0,(('Business Case'!E11*$C28*'Business Case'!E12*$B28)-'Business Case'!E11*$C28*'Business Case'!E13*$D28-'Business Case'!E14*$E28))*'Business Case'!$B$7-'Business Case'!$B$8*(('Business Case'!E11*$C28*'Business Case'!E12*$B28)-('Business Case'!D11*$C28*'Business Case'!D12*$B28))-'Business Case'!E15*$F28 -> 0 | L28: =(('Business Case'!F11*$C28*'Business Case'!F12*$B28)-'Business Case'!F11*$C28*'Business Case'!F13*$D28-'Business Case'!F14*$E28)-MAX(0,(('Business Case'!F11*$C28*'Business Case'!F12*$B28)-'Business Case'!F11*$C28*'Business Case'!F13*$D28-'Business Case'!F14*$E28))*'Business Case'!$B$7-'Business Case'!$B$8*(('Business Case'!F11*$C28*'Business Case'!F12*$B28)-('Business Case'!E11*$C28*'Business Case'!E12*$B28))-'Business Case'!F15*$F28 -> 0 | M28: =(('Business Case'!G11*$C28*'Business Case'!G12*$B28)-'Business Case'!G11*$C28*'Business Case'!G13*$D28-'Business Case'!G14*$E28)-MAX(0,(('Business Case'!G11*$C28*'Business Case'!G12*$B28)-'Business Case'!G11*$C28*'Business Case'!G13*$D28-'Business Case'!G14*$E28))*'Business Case'!$B$7-'Business Case'!$B$8*(('Business Case'!G11*$C28*'Business Case'!G12*$B28)-('Business Case'!F11*$C28*'Business Case'!F12*$B28))-'Business Case'!G15*$F28+'Business Case'!$B$8*('Business Case'!G11*$C28*'Business Case'!G12*$B28) -> 0 | N28: =IF(COUNT('Business Case'!B11:G11)=0,"",H28+NPV(G28,I28:M28))
A30: Tornado table (sorted by swing; the chart reads this)
A31: Driver | B31: NPV at low | C31: NPV at high | D31: Swing | E31: Low − plan | F31: High − plan | G31: Crosses zero? | H31: Rank key
A32: =INDEX($A$40:$A$45,MATCH(LARGE($D$40:$D$45,1),$D$40:$D$45,0)) -> Price per unit | B32: =INDEX($B$40:$B$45,MATCH(LARGE($D$40:$D$45,1),$D$40:$D$45,0)) | C32: =INDEX($C$40:$C$45,MATCH(LARGE($D$40:$D$45,1),$D$40:$D$45,0)) | D32: =IFERROR(ABS(C32-B32),"") | E32: =IFERROR(B32-$N$16,"") | F32: =IFERROR(C32-$N$16,"") | G32: =IF(B32="","",IF(MIN(B32,C32)<0,IF(MAX(B32,C32)>0,"Yes","Below zero"),"No")) | H32: =1 -> 1
A33: =INDEX($A$40:$A$45,MATCH(LARGE($D$40:$D$45,2),$D$40:$D$45,0)) -> Price per unit | B33: =INDEX($B$40:$B$45,MATCH(LARGE($D$40:$D$45,2),$D$40:$D$45,0)) | C33: =INDEX($C$40:$C$45,MATCH(LARGE($D$40:$D$45,2),$D$40:$D$45,0)) | D33: =IFERROR(ABS(C33-B33),"") | E33: =IFERROR(B33-$N$16,"") | F33: =IFERROR(C33-$N$16,"") | G33: =IF(B33="","",IF(MIN(B33,C33)<0,IF(MAX(B33,C33)>0,"Yes","Below zero"),"No")) | H33: =2 -> 2
A34: =INDEX($A$40:$A$45,MATCH(LARGE($D$40:$D$45,3),$D$40:$D$45,0)) -> Price per unit | B34: =INDEX($B$40:$B$45,MATCH(LARGE($D$40:$D$45,3),$D$40:$D$45,0)) | C34: =INDEX($C$40:$C$45,MATCH(LARGE($D$40:$D$45,3),$D$40:$D$45,0)) | D34: =IFERROR(ABS(C34-B34),"") | E34: =IFERROR(B34-$N$16,"") | F34: =IFERROR(C34-$N$16,"") | G34: =IF(B34="","",IF(MIN(B34,C34)<0,IF(MAX(B34,C34)>0,"Yes","Below zero"),"No")) | H34: =3 -> 3
A35: =INDEX($A$40:$A$45,MATCH(LARGE($D$40:$D$45,4),$D$40:$D$45,0)) -> Price per unit | B35: =INDEX($B$40:$B$45,MATCH(LARGE($D$40:$D$45,4),$D$40:$D$45,0)) | C35: =INDEX($C$40:$C$45,MATCH(LARGE($D$40:$D$45,4),$D$40:$D$45,0)) | D35: =IFERROR(ABS(C35-B35),"") | E35: =IFERROR(B35-$N$16,"") | F35: =IFERROR(C35-$N$16,"") | G35: =IF(B35="","",IF(MIN(B35,C35)<0,IF(MAX(B35,C35)>0,"Yes","Below zero"),"No")) | H35: =4 -> 4
A36: =INDEX($A$40:$A$45,MATCH(LARGE($D$40:$D$45,5),$D$40:$D$45,0)) -> Price per unit | B36: =INDEX($B$40:$B$45,MATCH(LARGE($D$40:$D$45,5),$D$40:$D$45,0)) | C36: =INDEX($C$40:$C$45,MATCH(LARGE($D$40:$D$45,5),$D$40:$D$45,0)) | D36: =IFERROR(ABS(C36-B36),"") | E36: =IFERROR(B36-$N$16,"") | F36: =IFERROR(C36-$N$16,"") | G36: =IF(B36="","",IF(MIN(B36,C36)<0,IF(MAX(B36,C36)>0,"Yes","Below zero"),"No")) | H36: =5 -> 5
A37: =INDEX($A$40:$A$45,MATCH(LARGE($D$40:$D$45,6),$D$40:$D$45,0)) -> Price per unit | B37: =INDEX($B$40:$B$45,MATCH(LARGE($D$40:$D$45,6),$D$40:$D$45,0)) | C37: =INDEX($C$40:$C$45,MATCH(LARGE($D$40:$D$45,6),$D$40:$D$45,0)) | D37: =IFERROR(ABS(C37-B37),"") | E37: =IFERROR(B37-$N$16,"") | F37: =IFERROR(C37-$N$16,"") | G37: =IF(B37="","",IF(MIN(B37,C37)<0,IF(MAX(B37,C37)>0,"Yes","Below zero"),"No")) | H37: =6 -> 6
A39: Helper (unsorted)
A40: Price per unit | B40: =N17 | C40: =N18 | D40: =IFERROR(ABS(C40-B40)+ROW()/1000000000,0) -> 0
A41: Units | B41: =N19 | C41: =N20 | D41: =IFERROR(ABS(C41-B41)+ROW()/1000000000,0) -> 0
A42: Variable cost per unit | B42: =N21 | C42: =N22 | D42: =IFERROR(ABS(C42-B42)+ROW()/1000000000,0) -> 0
A43: Fixed costs | B43: =N23 | C43: =N24 | D43: =IFERROR(ABS(C43-B43)+ROW()/1000000000,0) -> 0
A44: Capex | B44: =N25 | C44: =N26 | D44: =IFERROR(ABS(C44-B44)+ROW()/1000000000,0) -> 0
A45: Discount rate (absolute) | B45: =N27 | C45: =N28 | D45: =IFERROR(ABS(C45-B45)+ROW()/1000000000,0) -> 0
A48: Monte Carlo simulation: 1,000 futures, each driver drawn from a triangular (low, likely, high) distribution. Press F9 to draw again; results move slightly each time.
A49: Mean NPV | B49: =IFERROR(AVERAGE($N$81:$N$1080),"")
A50: Median NPV | B50: =IFERROR(MEDIAN($N$81:$N$1080),"")
A51: P10 (1 in 10 worse than this) | B51: =IFERROR(PERCENTILE($N$81:$N$1080,0.1),"")
A52: P90 (1 in 10 better than this) | B52: =IFERROR(PERCENTILE($N$81:$N$1080,0.9),"")
A53: Standard deviation | B53: =IFERROR(STDEV($N$81:$N$1080),"")
A54: Probability NPV < 0 | B54: =IFERROR(COUNTIF($N$81:$N$1080,"<0")/COUNT($N$81:$N$1080),"")
A55: NPV at plan (for comparison) | B55: =IFERROR(N16,"")
A56: Drivers are drawn independently. If two move together (e.g. a price cut that lifts volume), the real spread differs. For exact, repeatable figures use the Business Case skill's risk_analysis.py.
A58: Bin from | B58: Bin to | C58: Count
A59: =MIN($N$81:$N$1080)+(MAX($N$81:$N$1080)-MIN($N$81:$N$1080))*0/20 -> 0 | B59: =MIN($N$81:$N$1080)+(MAX($N$81:$N$1080)-MIN($N$81:$N$1080))*1/20 -> 0 | C59: =COUNTIFS($N$81:$N$1080,">="&A59,$N$81:$N$1080,"<"&B59) -> 0
A60: =MIN($N$81:$N$1080)+(MAX($N$81:$N$1080)-MIN($N$81:$N$1080))*1/20 -> 0 | B60: =MIN($N$81:$N$1080)+(MAX($N$81:$N$1080)-MIN($N$81:$N$1080))*2/20 -> 0 | C60: =COUNTIFS($N$81:$N$1080,">="&A60,$N$81:$N$1080,"<"&B60) -> 0
A61: =MIN($N$81:$N$1080)+(MAX($N$81:$N$1080)-MIN($N$81:$N$1080))*2/20 -> 0 | B61: =MIN($N$81:$N$1080)+(MAX($N$81:$N$1080)-MIN($N$81:$N$1080))*3/20 -> 0 | C61: =COUNTIFS($N$81:$N$1080,">="&A61,$N$81:$N$1080,"<"&B61) -> 0
A62: =MIN($N$81:$N$1080)+(MAX($N$81:$N$1080)-MIN($N$81:$N$1080))*3/20 -> 0 | B62: =MIN($N$81:$N$1080)+(MAX($N$81:$N$1080)-MIN($N$81:$N$1080))*4/20 -> 0 | C62: =COUNTIFS($N$81:$N$1080,">="&A62,$N$81:$N$1080,"<"&B62) -> 0
A63: =MIN($N$81:$N$1080)+(MAX($N$81:$N$1080)-MIN($N$81:$N$1080))*4/20 -> 0 | B63: =MIN($N$81:$N$1080)+(MAX($N$81:$N$1080)-MIN($N$81:$N$1080))*5/20 -> 0 | C63: =COUNTIFS($N$81:$N$1080,">="&A63,$N$81:$N$1080,"<"&B63) -> 0
A64: =MIN($N$81:$N$1080)+(MAX($N$81:$N$1080)-MIN($N$81:$N$1080))*5/20 -> 0 | B64: =MIN($N$81:$N$1080)+(MAX($N$81:$N$1080)-MIN($N$81:$N$1080))*6/20 -> 0 | C64: =COUNTIFS($N$81:$N$1080,">="&A64,$N$81:$N$1080,"<"&B64) -> 0
A65: =MIN($N$81:$N$1080)+(MAX($N$81:$N$1080)-MIN($N$81:$N$1080))*6/20 -> 0 | B65: =MIN($N$81:$N$1080)+(MAX($N$81:$N$1080)-MIN($N$81:$N$1080))*7/20 -> 0 | C65: =COUNTIFS($N$81:$N$1080,">="&A65,$N$81:$N$1080,"<"&B65) -> 0
A66: =MIN($N$81:$N$1080)+(MAX($N$81:$N$1080)-MIN($N$81:$N$1080))*7/20 -> 0 | B66: =MIN($N$81:$N$1080)+(MAX($N$81:$N$1080)-MIN($N$81:$N$1080))*8/20 -> 0 | C66: =COUNTIFS($N$81:$N$1080,">="&A66,$N$81:$N$1080,"<"&B66) -> 0
A67: =MIN($N$81:$N$1080)+(MAX($N$81:$N$1080)-MIN($N$81:$N$1080))*8/20 -> 0 | B67: =MIN($N$81:$N$1080)+(MAX($N$81:$N$1080)-MIN($N$81:$N$1080))*9/20 -> 0 | C67: =COUNTIFS($N$81:$N$1080,">="&A67,$N$81:$N$1080,"<"&B67) -> 0
A68: =MIN($N$81:$N$1080)+(MAX($N$81:$N$1080)-MIN($N$81:$N$1080))*9/20 -> 0 | B68: =MIN($N$81:$N$1080)+(MAX($N$81:$N$1080)-MIN($N$81:$N$1080))*10/20 -> 0 | C68: =COUNTIFS($N$81:$N$1080,">="&A68,$N$81:$N$1080,"<"&B68) -> 0
A69: =MIN($N$81:$N$1080)+(MAX($N$81:$N$1080)-MIN($N$81:$N$1080))*10/20 -> 0 | B69: =MIN($N$81:$N$1080)+(MAX($N$81:$N$1080)-MIN($N$81:$N$1080))*11/20 -> 0 | C69: =COUNTIFS($N$81:$N$1080,">="&A69,$N$81:$N$1080,"<"&B69) -> 0
A70: =MIN($N$81:$N$1080)+(MAX($N$81:$N$1080)-MIN($N$81:$N$1080))*11/20 -> 0 | B70: =MIN($N$81:$N$1080)+(MAX($N$81:$N$1080)-MIN($N$81:$N$1080))*12/20 -> 0 | C70: =COUNTIFS($N$81:$N$1080,">="&A70,$N$81:$N$1080,"<"&B70) -> 0
A71: =MIN($N$81:$N$1080)+(MAX($N$81:$N$1080)-MIN($N$81:$N$1080))*12/20 -> 0 | B71: =MIN($N$81:$N$1080)+(MAX($N$81:$N$1080)-MIN($N$81:$N$1080))*13/20 -> 0 | C71: =COUNTIFS($N$81:$N$1080,">="&A71,$N$81:$N$1080,"<"&B71) -> 0
A72: =MIN($N$81:$N$1080)+(MAX($N$81:$N$1080)-MIN($N$81:$N$1080))*13/20 -> 0 | B72: =MIN($N$81:$N$1080)+(MAX($N$81:$N$1080)-MIN($N$81:$N$1080))*14/20 -> 0 | C72: =COUNTIFS($N$81:$N$1080,">="&A72,$N$81:$N$1080,"<"&B72) -> 0
A73: =MIN($N$81:$N$1080)+(MAX($N$81:$N$1080)-MIN($N$81:$N$1080))*14/20 -> 0 | B73: =MIN($N$81:$N$1080)+(MAX($N$81:$N$1080)-MIN($N$81:$N$1080))*15/20 -> 0 | C73: =COUNTIFS($N$81:$N$1080,">="&A73,$N$81:$N$1080,"<"&B73) -> 0
A74: =MIN($N$81:$N$1080)+(MAX($N$81:$N$1080)-MIN($N$81:$N$1080))*15/20 -> 0 | B74: =MIN($N$81:$N$1080)+(MAX($N$81:$N$1080)-MIN($N$81:$N$1080))*16/20 -> 0 | C74: =COUNTIFS($N$81:$N$1080,">="&A74,$N$81:$N$1080,"<"&B74) -> 0
A75: =MIN($N$81:$N$1080)+(MAX($N$81:$N$1080)-MIN($N$81:$N$1080))*16/20 -> 0 | B75: =MIN($N$81:$N$1080)+(MAX($N$81:$N$1080)-MIN($N$81:$N$1080))*17/20 -> 0 | C75: =COUNTIFS($N$81:$N$1080,">="&A75,$N$81:$N$1080,"<"&B75) -> 0
A76: =MIN($N$81:$N$1080)+(MAX($N$81:$N$1080)-MIN($N$81:$N$1080))*17/20 -> 0 | B76: =MIN($N$81:$N$1080)+(MAX($N$81:$N$1080)-MIN($N$81:$N$1080))*18/20 -> 0 | C76: =COUNTIFS($N$81:$N$1080,">="&A76,$N$81:$N$1080,"<"&B76) -> 0
A77: =MIN($N$81:$N$1080)+(MAX($N$81:$N$1080)-MIN($N$81:$N$1080))*18/20 -> 0 | B77: =MIN($N$81:$N$1080)+(MAX($N$81:$N$1080)-MIN($N$81:$N$1080))*19/20 -> 0 | C77: =COUNTIFS($N$81:$N$1080,">="&A77,$N$81:$N$1080,"<"&B77) -> 0
A78: =MIN($N$81:$N$1080)+(MAX($N$81:$N$1080)-MIN($N$81:$N$1080))*19/20 -> 0 | B78: =MIN($N$81:$N$1080)+(MAX($N$81:$N$1080)-MIN($N$81:$N$1080))*20/20 -> 0 | C78: =COUNTIFS($N$81:$N$1080,">="&A78,$N$81:$N$1080,"<="&B78) -> 0
A80: Run | B80: Price × | C80: Units × | D80: Var. cost × | E80: Fixed × | F80: Capex × | G80: Rate | H80: CF Y0 | I80: CF Y1 | J80: CF Y2 | K80: CF Y3 | L80: CF Y4 | M80: CF Y5 | N80: NPV | P80: Random 1 | Q80: Random 2 | R80: Random 3 | S80: Random 4 | T80: Random 5 | U80: Random 6
A81: 1 | B81: =1+IF($G$6=$E$6,$F$6,IF(P81<($F$6-$E$6)/($G$6-$E$6),$E$6+SQRT(P81*($G$6-$E$6)*($F$6-$E$6)),$G$6-SQRT((1-P81)*($G$6-$E$6)*($G$6-$F$6)))) -> 1 | C81: =1+IF($G$7=$E$7,$F$7,IF(Q81<($F$7-$E$7)/($G$7-$E$7),$E$7+SQRT(Q81*($G$7-$E$7)*($F$7-$E$7)),$G$7-SQRT((1-Q81)*($G$7-$E$7)*($G$7-$F$7)))) -> 1 | D81: =1+IF($G$8=$E$8,$F$8,IF(R81<($F$8-$E$8)/($G$8-$E$8),$E$8+SQRT(R81*($G$8-$E$8)*($F$8-$E$8)),$G$8-SQRT((1-R81)*($G$8-$E$8)*($G$8-$F$8)))) -> 1 | E81: =1+IF($G$9=$E$9,$F$9,IF(S81<($F$9-$E$9)/($G$9-$E$9),$E$9+SQRT(S81*($G$9-$E$9)*($F$9-$E$9)),$G$9-SQRT((1-S81)*($G$9-$E$9)*($G$9-$F$9)))) -> 1 | F81: =1+IF($G$10=$E$10,$F$10,IF(T81<($F$10-$E$10)/($G$10-$E$10),$E$10+SQRT(T81*($G$10-$E$10)*($F$10-$E$10)),$G$10-SQRT((1-T81)*($G$10-$E$10)*($G$10-$F$10)))) -> 1 | G81: =IF($G$11=$E$11,$F$11,IF(U81<($F$11-$E$11)/($G$11-$E$11),$E$11+SQRT(U81*($G$11-$E$11)*($F$11-$E$11)),$G$11-SQRT((1-U81)*($G$11-$E$11)*($G$11-$F$11)))) -> 0 | H81: =(('Business Case'!B11*$C81*'Business Case'!B12*$B81)-'Business Case'!B11*$C81*'Business Case'!B13*$D81-'Business Case'!B14*$E81)-MAX(0,(('Business Case'!B11*$C81*'Business Case'!B12*$B81)-'Business Case'!B11*$C81*'Business Case'!B13*$D81-'Business Case'!B14*$E81))*'Business Case'!$B$7-'Business Case'!$B$8*('Business Case'!B11*$C81*'Business Case'!B12*$B81)-'Business Case'!B15*$F81 -> 0 | I81: =(('Business Case'!C11*$C81*'Business Case'!C12*$B81)-'Business Case'!C11*$C81*'Business Case'!C13*$D81-'Business Case'!C14*$E81)-MAX(0,(('Business Case'!C11*$C81*'Business Case'!C12*$B81)-'Business Case'!C11*$C81*'Business Case'!C13*$D81-'Business Case'!C14*$E81))*'Business Case'!$B$7-'Business Case'!$B$8*(('Business Case'!C11*$C81*'Business Case'!C12*$B81)-('Business Case'!B11*$C81*'Business Case'!B12*$B81))-'Business Case'!C15*$F81 -> 0 | J81: =(('Business Case'!D11*$C81*'Business Case'!D12*$B81)-'Business Case'!D11*$C81*'Business Case'!D13*$D81-'Business Case'!D14*$E81)-MAX(0,(('Business Case'!D11*$C81*'Business Case'!D12*$B81)-'Business Case'!D11*$C81*'Business Case'!D13*$D81-'Business Case'!D14*$E81))*'Business Case'!$B$7-'Business Case'!$B$8*(('Business Case'!D11*$C81*'Business Case'!D12*$B81)-('Business Case'!C11*$C81*'Business Case'!C12*$B81))-'Business Case'!D15*$F81 -> 0 | K81: =(('Business Case'!E11*$C81*'Business Case'!E12*$B81)-'Business Case'!E11*$C81*'Business Case'!E13*$D81-'Business Case'!E14*$E81)-MAX(0,(('Business Case'!E11*$C81*'Business Case'!E12*$B81)-'Business Case'!E11*$C81*'Business Case'!E13*$D81-'Business Case'!E14*$E81))*'Business Case'!$B$7-'Business Case'!$B$8*(('Business Case'!E11*$C81*'Business Case'!E12*$B81)-('Business Case'!D11*$C81*'Business Case'!D12*$B81))-'Business Case'!E15*$F81 -> 0 | L81: =(('Business Case'!F11*$C81*'Business Case'!F12*$B81)-'Business Case'!F11*$C81*'Business Case'!F13*$D81-'Business Case'!F14*$E81)-MAX(0,(('Business Case'!F11*$C81*'Business Case'!F12*$B81)-'Business Case'!F11*$C81*'Business Case'!F13*$D81-'Business Case'!F14*$E81))*'Business Case'!$B$7-'Business Case'!$B$8*(('Business Case'!F11*$C81*'Business Case'!F12*$B81)-('Business Case'!E11*$C81*'Business Case'!E12*$B81))-'Business Case'!F15*$F81 -> 0 | M81: =(('Business Case'!G11*$C81*'Business Case'!G12*$B81)-'Business Case'!G11*$C81*'Business Case'!G13*$D81-'Business Case'!G14*$E81)-MAX(0,(('Business Case'!G11*$C81*'Business Case'!G12*$B81)-'Business Case'!G11*$C81*'Business Case'!G13*$D81-'Business Case'!G14*$E81))*'Business Case'!$B$7-'Business Case'!$B$8*(('Business Case'!G11*$C81*'Business Case'!G12*$B81)-('Business Case'!F11*$C81*'Business Case'!F12*$B81))-'Business Case'!G15*$F81+'Business Case'!$B$8*('Business Case'!G11*$C81*'Business Case'!G12*$B81) -> 0 | N81: =IF(COUNT('Business Case'!B11:G11)=0,"",H81+NPV(G81,I81:M81)) | P81: =RAND() -> 0.8043573 | Q81: =RAND() -> 0.26377284 | R81: =RAND() -> 0.73860863 | S81: =RAND() -> 0.081320126 | T81: =RAND() -> 0.20868018 | U81: =RAND() -> 0.20335399
A82: 2 | B82: =1+IF($G$6=$E$6,$F$6,IF(P82<($F$6-$E$6)/($G$6-$E$6),$E$6+SQRT(P82*($G$6-$E$6)*($F$6-$E$6)),$G$6-SQRT((1-P82)*($G$6-$E$6)*($G$6-$F$6)))) -> 1 | C82: =1+IF($G$7=$E$7,$F$7,IF(Q82<($F$7-$E$7)/($G$7-$E$7),$E$7+SQRT(Q82*($G$7-$E$7)*($F$7-$E$7)),$G$7-SQRT((1-Q82)*($G$7-$E$7)*($G$7-$F$7)))) -> 1 | D82: =1+IF($G$8=$E$8,$F$8,IF(R82<($F$8-$E$8)/($G$8-$E$8),$E$8+SQRT(R82*($G$8-$E$8)*($F$8-$E$8)),$G$8-SQRT((1-R82)*($G$8-$E$8)*($G$8-$F$8)))) -> 1 | E82: =1+IF($G$9=$E$9,$F$9,IF(S82<($F$9-$E$9)/($G$9-$E$9),$E$9+SQRT(S82*($G$9-$E$9)*($F$9-$E$9)),$G$9-SQRT((1-S82)*($G$9-$E$9)*($G$9-$F$9)))) -> 1 | F82: =1+IF($G$10=$E$10,$F$10,IF(T82<($F$10-$E$10)/($G$10-$E$10),$E$10+SQRT(T82*($G$10-$E$10)*($F$10-$E$10)),$G$10-SQRT((1-T82)*($G$10-$E$10)*($G$10-$F$10)))) -> 1 | G82: =IF($G$11=$E$11,$F$11,IF(U82<($F$11-$E$11)/($G$11-$E$11),$E$11+SQRT(U82*($G$11-$E$11)*($F$11-$E$11)),$G$11-SQRT((1-U82)*($G$11-$E$11)*($G$11-$F$11)))) -> 0 | H82: =(('Business Case'!B11*$C82*'Business Case'!B12*$B82)-'Business Case'!B11*$C82*'Business Case'!B13*$D82-'Business Case'!B14*$E82)-MAX(0,(('Business Case'!B11*$C82*'Business Case'!B12*$B82)-'Business Case'!B11*$C82*'Business Case'!B13*$D82-'Business Case'!B14*$E82))*'Business Case'!$B$7-'Business Case'!$B$8*('Business Case'!B11*$C82*'Business Case'!B12*$B82)-'Business Case'!B15*$F82 -> 0 | I82: =(('Business Case'!C11*$C82*'Business Case'!C12*$B82)-'Business Case'!C11*$C82*'Business Case'!C13*$D82-'Business Case'!C14*$E82)-MAX(0,(('Business Case'!C11*$C82*'Business Case'!C12*$B82)-'Business Case'!C11*$C82*'Business Case'!C13*$D82-'Business Case'!C14*$E82))*'Business Case'!$B$7-'Business Case'!$B$8*(('Business Case'!C11*$C82*'Business Case'!C12*$B82)-('Business Case'!B11*$C82*'Business Case'!B12*$B82))-'Business Case'!C15*$F82 -> 0 | J82: =(('Business Case'!D11*$C82*'Business Case'!D12*$B82)-'Business Case'!D11*$C82*'Business Case'!D13*$D82-'Business Case'!D14*$E82)-MAX(0,(('Business Case'!D11*$C82*'Business Case'!D12*$B82)-'Business Case'!D11*$C82*'Business Case'!D13*$D82-'Business Case'!D14*$E82))*'Business Case'!$B$7-'Business Case'!$B$8*(('Business Case'!D11*$C82*'Business Case'!D12*$B82)-('Business Case'!C11*$C82*'Business Case'!C12*$B82))-'Business Case'!D15*$F82 -> 0 | K82: =(('Business Case'!E11*$C82*'Business Case'!E12*$B82)-'Business Case'!E11*$C82*'Business Case'!E13*$D82-'Business Case'!E14*$E82)-MAX(0,(('Business Case'!E11*$C82*'Business Case'!E12*$B82)-'Business Case'!E11*$C82*'Business Case'!E13*$D82-'Business Case'!E14*$E82))*'Business Case'!$B$7-'Business Case'!$B$8*(('Business Case'!E11*$C82*'Business Case'!E12*$B82)-('Business Case'!D11*$C82*'Business Case'!D12*$B82))-'Business Case'!E15*$F82 -> 0 | L82: =(('Business Case'!F11*$C82*'Business Case'!F12*$B82)-'Business Case'!F11*$C82*'Business Case'!F13*$D82-'Business Case'!F14*$E82)-MAX(0,(('Business Case'!F11*$C82*'Business Case'!F12*$B82)-'Business Case'!F11*$C82*'Business Case'!F13*$D82-'Business Case'!F14*$E82))*'Business Case'!$B$7-'Business Case'!$B$8*(('Business Case'!F11*$C82*'Business Case'!F12*$B82)-('Business Case'!E11*$C82*'Business Case'!E12*$B82))-'Business Case'!F15*$F82 -> 0 | M82: =(('Business Case'!G11*$C82*'Business Case'!G12*$B82)-'Business Case'!G11*$C82*'Business Case'!G13*$D82-'Business Case'!G14*$E82)-MAX(0,(('Business Case'!G11*$C82*'Business Case'!G12*$B82)-'Business Case'!G11*$C82*'Business Case'!G13*$D82-'Business Case'!G14*$E82))*'Business Case'!$B$7-'Business Case'!$B$8*(('Business Case'!G11*$C82*'Business Case'!G12*$B82)-('Business Case'!F11*$C82*'Business Case'!F12*$B82))-'Business Case'!G15*$F82+'Business Case'!$B$8*('Business Case'!G11*$C82*'Business Case'!G12*$B82) -> 0 | N82: =IF(COUNT('Business Case'!B11:G11)=0,"",H82+NPV(G82,I82:M82)) | P82: =RAND() -> 0.6210618 | Q82: =RAND() -> 0.95128266 | R82: =RAND() -> 0.60515833 | S82: =RAND() -> 0.51140018 | T82: =RAND() -> 0.21274996 | U82: =RAND() -> 0.37731698
A83: 3 | B83: =1+IF($G$6=$E$6,$F$6,IF(P83<($F$6-$E$6)/($G$6-$E$6),$E$6+SQRT(P83*($G$6-$E$6)*($F$6-$E$6)),$G$6-SQRT((1-P83)*($G$6-$E$6)*($G$6-$F$6)))) -> 1 | C83: =1+IF($G$7=$E$7,$F$7,IF(Q83<($F$7-$E$7)/($G$7-$E$7),$E$7+SQRT(Q83*($G$7-$E$7)*($F$7-$E$7)),$G$7-SQRT((1-Q83)*($G$7-$E$7)*($G$7-$F$7)))) -> 1 | D83: =1+IF($G$8=$E$8,$F$8,IF(R83<($F$8-$E$8)/($G$8-$E$8),$E$8+SQRT(R83*($G$8-$E$8)*($F$8-$E$8)),$G$8-SQRT((1-R83)*($G$8-$E$8)*($G$8-$F$8)))) -> 1 | E83: =1+IF($G$9=$E$9,$F$9,IF(S83<($F$9-$E$9)/($G$9-$E$9),$E$9+SQRT(S83*($G$9-$E$9)*($F$9-$E$9)),$G$9-SQRT((1-S83)*($G$9-$E$9)*($G$9-$F$9)))) -> 1 | F83: =1+IF($G$10=$E$10,$F$10,IF(T83<($F$10-$E$10)/($G$10-$E$10),$E$10+SQRT(T83*($G$10-$E$10)*($F$10-$E$10)),$G$10-SQRT((1-T83)*($G$10-$E$10)*($G$10-$F$10)))) -> 1 | G83: =IF($G$11=$E$11,$F$11,IF(U83<($F$11-$E$11)/($G$11-$E$11),$E$11+SQRT(U83*($G$11-$E$11)*($F$11-$E$11)),$G$11-SQRT((1-U83)*($G$11-$E$11)*($G$11-$F$11)))) -> 0 | H83: =(('Business Case'!B11*$C83*'Business Case'!B12*$B83)-'Business Case'!B11*$C83*'Business Case'!B13*$D83-'Business Case'!B14*$E83)-MAX(0,(('Business Case'!B11*$C83*'Business Case'!B12*$B83)-'Business Case'!B11*$C83*'Business Case'!B13*$D83-'Business Case'!B14*$E83))*'Business Case'!$B$7-'Business Case'!$B$8*('Business Case'!B11*$C83*'Business Case'!B12*$B83)-'Business Case'!B15*$F83 -> 0 | I83: =(('Business Case'!C11*$C83*'Business Case'!C12*$B83)-'Business Case'!C11*$C83*'Business Case'!C13*$D83-'Business Case'!C14*$E83)-MAX(0,(('Business Case'!C11*$C83*'Business Case'!C12*$B83)-'Business Case'!C11*$C83*'Business Case'!C13*$D83-'Business Case'!C14*$E83))*'Business Case'!$B$7-'Business Case'!$B$8*(('Business Case'!C11*$C83*'Business Case'!C12*$B83)-('Business Case'!B11*$C83*'Business Case'!B12*$B83))-'Business Case'!C15*$F83 -> 0 | J83: =(('Business Case'!D11*$C83*'Business Case'!D12*$B83)-'Business Case'!D11*$C83*'Business Case'!D13*$D83-'Business Case'!D14*$E83)-MAX(0,(('Business Case'!D11*$C83*'Business Case'!D12*$B83)-'Business Case'!D11*$C83*'Business Case'!D13*$D83-'Business Case'!D14*$E83))*'Business Case'!$B$7-'Business Case'!$B$8*(('Business Case'!D11*$C83*'Business Case'!D12*$B83)-('Business Case'!C11*$C83*'Business Case'!C12*$B83))-'Business Case'!D15*$F83 -> 0 | K83: =(('Business Case'!E11*$C83*'Business Case'!E12*$B83)-'Business Case'!E11*$C83*'Business Case'!E13*$D83-'Business Case'!E14*$E83)-MAX(0,(('Business Case'!E11*$C83*'Business Case'!E12*$B83)-'Business Case'!E11*$C83*'Business Case'!E13*$D83-'Business Case'!E14*$E83))*'Business Case'!$B$7-'Business Case'!$B$8*(('Business Case'!E11*$C83*'Business Case'!E12*$B83)-('Business Case'!D11*$C83*'Business Case'!D12*$B83))-'Business Case'!E15*$F83 -> 0 | L83: =(('Business Case'!F11*$C83*'Business Case'!F12*$B83)-'Business Case'!F11*$C83*'Business Case'!F13*$D83-'Business Case'!F14*$E83)-MAX(0,(('Business Case'!F11*$C83*'Business Case'!F12*$B83)-'Business Case'!F11*$C83*'Business Case'!F13*$D83-'Business Case'!F14*$E83))*'Business Case'!$B$7-'Business Case'!$B$8*(('Business Case'!F11*$C83*'Business Case'!F12*$B83)-('Business Case'!E11*$C83*'Business Case'!E12*$B83))-'Business Case'!F15*$F83 -> 0 | M83: =(('Business Case'!G11*$C83*'Business Case'!G12*$B83)-'Business Case'!G11*$C83*'Business Case'!G13*$D83-'Business Case'!G14*$E83)-MAX(0,(('Business Case'!G11*$C83*'Business Case'!G12*$B83)-'Business Case'!G11*$C83*'Business Case'!G13*$D83-'Business Case'!G14*$E83))*'Business Case'!$B$7-'Business Case'!$B$8*(('Business Case'!G11*$C83*'Business Case'!G12*$B83)-('Business Case'!F11*$C83*'Business Case'!F12*$B83))-'Business Case'!G15*$F83+'Business Case'!$B$8*('Business Case'!G11*$C83*'Business Case'!G12*$B83) -> 0 | N83: =IF(COUNT('Business Case'!B11:G11)=0,"",H83+NPV(G83,I83:M83)) | P83: =RAND() -> 0.24475038 | Q83: =RAND() -> 0.77094167 | R83: =RAND() -> 0.058683922 | S83: =RAND() -> 0.64675157 | T83: =RAND() -> 0.27147938 | U83: =RAND() -> 0.0014479868
A84: 4 | B84: =1+IF($G$6=$E$6,$F$6,IF(P84<($F$6-$E$6)/($G$6-$E$6),$E$6+SQRT(P84*($G$6-$E$6)*($F$6-$E$6)),$G$6-SQRT((1-P84)*($G$6-$E$6)*($G$6-$F$6)))) -> 1 | C84: =1+IF($G$7=$E$7,$F$7,IF(Q84<($F$7-$E$7)/($G$7-$E$7),$E$7+SQRT(Q84*($G$7-$E$7)*($F$7-$E$7)),$G$7-SQRT((1-Q84)*($G$7-$E$7)*($G$7-$F$7)))) -> 1 | D84: =1+IF($G$8=$E$8,$F$8,IF(R84<($F$8-$E$8)/($G$8-$E$8),$E$8+SQRT(R84*($G$8-$E$8)*($F$8-$E$8)),$G$8-SQRT((1-R84)*($G$8-$E$8)*($G$8-$F$8)))) -> 1 | E84: =1+IF($G$9=$E$9,$F$9,IF(S84<($F$9-$E$9)/($G$9-$E$9),$E$9+SQRT(S84*($G$9-$E$9)*($F$9-$E$9)),$G$9-SQRT((1-S84)*($G$9-$E$9)*($G$9-$F$9)))) -> 1 | F84: =1+IF($G$10=$E$10,$F$10,IF(T84<($F$10-$E$10)/($G$10-$E$10),$E$10+SQRT(T84*($G$10-$E$10)*($F$10-$E$10)),$G$10-SQRT((1-T84)*($G$10-$E$10)*($G$10-$F$10)))) -> 1 | G84: =IF($G$11=$E$11,$F$11,IF(U84<($F$11-$E$11)/($G$11-$E$11),$E$11+SQRT(U84*($G$11-$E$11)*($F$11-$E$11)),$G$11-SQRT((1-U84)*($G$11-$E$11)*($G$11-$F$11)))) -> 0 | H84: =(('Business Case'!B11*$C84*'Business Case'!B12*$B84)-'Business Case'!B11*$C84*'Business Case'!B13*$D84-'Business Case'!B14*$E84)-MAX(0,(('Business Case'!B11*$C84*'Business Case'!B12*$B84)-'Business Case'!B11*$C84*'Business Case'!B13*$D84-'Business Case'!B14*$E84))*'Business Case'!$B$7-'Business Case'!$B$8*('Business Case'!B11*$C84*'Business Case'!B12*$B84)-'Business Case'!B15*$F84 -> 0 | I84: =(('Business Case'!C11*$C84*'Business Case'!C12*$B84)-'Business Case'!C11*$C84*'Business Case'!C13*$D84-'Business Case'!C14*$E84)-MAX(0,(('Business Case'!C11*$C84*'Business Case'!C12*$B84)-'Business Case'!C11*$C84*'Business Case'!C13*$D84-'Business Case'!C14*$E84))*'Business Case'!$B$7-'Business Case'!$B$8*(('Business Case'!C11*$C84*'Business Case'!C12*$B84)-('Business Case'!B11*$C84*'Business Case'!B12*$B84))-'Business Case'!C15*$F84 -> 0 | J84: =(('Business Case'!D11*$C84*'Business Case'!D12*$B84)-'Business Case'!D11*$C84*'Business Case'!D13*$D84-'Business Case'!D14*$E84)-MAX(0,(('Business Case'!D11*$C84*'Business Case'!D12*$B84)-'Business Case'!D11*$C84*'Business Case'!D13*$D84-'Business Case'!D14*$E84))*'Business Case'!$B$7-'Business Case'!$B$8*(('Business Case'!D11*$C84*'Business Case'!D12*$B84)-('Business Case'!C11*$C84*'Business Case'!C12*$B84))-'Business Case'!D15*$F84 -> 0 | K84: =(('Business Case'!E11*$C84*'Business Case'!E12*$B84)-'Business Case'!E11*$C84*'Business Case'!E13*$D84-'Business Case'!E14*$E84)-MAX(0,(('Business Case'!E11*$C84*'Business Case'!E12*$B84)-'Business Case'!E11*$C84*'Business Case'!E13*$D84-'Business Case'!E14*$E84))*'Business Case'!$B$7-'Business Case'!$B$8*(('Business Case'!E11*$C84*'Business Case'!E12*$B84)-('Business Case'!D11*$C84*'Business Case'!D12*$B84))-'Business Case'!E15*$F84 -> 0 | L84: =(('Business Case'!F11*$C84*'Business Case'!F12*$B84)-'Business Case'!F11*$C84*'Business Case'!F13*$D84-'Business Case'!F14*$E84)-MAX(0,(('Business Case'!F11*$C84*'Business Case'!F12*$B84)-'Business Case'!F11*$C84*'Business Case'!F13*$D84-'Business Case'!F14*$E84))*'Business Case'!$B$7-'Business Case'!$B$8*(('Business Case'!F11*$C84*'Business Case'!F12*$B84)-('Business Case'!E11*$C84*'Business Case'!E12*$B84))-'Business Case'!F15*$F84 -> 0 | M84: =(('Business Case'!G11*$C84*'Business Case'!G12*$B84)-'Business Case'!G11*$C84*'Business Case'!G13*$D84-'Business Case'!G14*$E84)-MAX(0,(('Business Case'!G11*$C84*'Business Case'!G12*$B84)-'Business Case'!G11*$C84*'Business Case'!G13*$D84-'Business Case'!G14*$E84))*'Business Case'!$B$7-'Business Case'!$B$8*(('Business Case'!G11*$C84*'Business Case'!G12*$B84)-('Business Case'!F11*$C84*'Business Case'!F12*$B84))-'Business Case'!G15*$F84+'Business Case'!$B$8*('Business Case'!G11*$C84*'Business Case'!G12*$B84) -> 0 | N84: =IF(COUNT('Business Case'!B11:G11)=0,"",H84+NPV(G84,I84:M84)) | P84: =RAND() -> 0.44887165 | Q84: =RAND() -> 0.49929896 | R84: =RAND() -> 0.60383949 | S84: =RAND() -> 0.73476441 | T84: =RAND() -> 0.52318929 | U84: =RAND() -> 0.73328095
A85: 5 | B85: =1+IF($G$6=$E$6,$F$6,IF(P85<($F$6-$E$6)/($G$6-$E$6),$E$6+SQRT(P85*($G$6-$E$6)*($F$6-$E$6)),$G$6-SQRT((1-P85)*($G$6-$E$6)*($G$6-$F$6)))) -> 1 | C85: =1+IF($G$7=$E$7,$F$7,IF(Q85<($F$7-$E$7)/($G$7-$E$7),$E$7+SQRT(Q85*($G$7-$E$7)*($F$7-$E$7)),$G$7-SQRT((1-Q85)*($G$7-$E$7)*($G$7-$F$7)))) -> 1 | D85: =1+IF($G$8=$E$8,$F$8,IF(R85<($F$8-$E$8)/($G$8-$E$8),$E$8+SQRT(R85*($G$8-$E$8)*($F$8-$E$8)),$G$8-SQRT((1-R85)*($G$8-$E$8)*($G$8-$F$8)))) -> 1 | E85: =1+IF($G$9=$E$9,$F$9,IF(S85<($F$9-$E$9)/($G$9-$E$9),$E$9+SQRT(S85*($G$9-$E$9)*($F$9-$E$9)),$G$9-SQRT((1-S85)*($G$9-$E$9)*($G$9-$F$9)))) -> 1 | F85: =1+IF($G$10=$E$10,$F$10,IF(T85<($F$10-$E$10)/($G$10-$E$10),$E$10+SQRT(T85*($G$10-$E$10)*($F$10-$E$10)),$G$10-SQRT((1-T85)*($G$10-$E$10)*($G$10-$F$10)))) -> 1 | G85: =IF($G$11=$E$11,$F$11,IF(U85<($F$11-$E$11)/($G$11-$E$11),$E$11+SQRT(U85*($G$11-$E$11)*($F$11-$E$11)),$G$11-SQRT((1-U85)*($G$11-$E$11)*($G$11-$F$11)))) -> 0 | H85: =(('Business Case'!B11*$C85*'Business Case'!B12*$B85)-'Business Case'!B11*$C85*'Business Case'!B13*$D85-'Business Case'!B14*$E85)-MAX(0,(('Business Case'!B11*$C85*'Business Case'!B12*$B85)-'Business Case'!B11*$C85*'Business Case'!B13*$D85-'Business Case'!B14*$E85))*'Business Case'!$B$7-'Business Case'!$B$8*('Business Case'!B11*$C85*'Business Case'!B12*$B85)-'Business Case'!B15*$F85 -> 0 | I85: =(('Business Case'!C11*$C85*'Business Case'!C12*$B85)-'Business Case'!C11*$C85*'Business Case'!C13*$D85-'Business Case'!C14*$E85)-MAX(0,(('Business Case'!C11*$C85*'Business Case'!C12*$B85)-'Business Case'!C11*$C85*'Business Case'!C13*$D85-'Business Case'!C14*$E85))*'Business Case'!$B$7-'Business Case'!$B$8*(('Business Case'!C11*$C85*'Business Case'!C12*$B85)-('Business Case'!B11*$C85*'Business Case'!B12*$B85))-'Business Case'!C15*$F85 -> 0 | J85: =(('Business Case'!D11*$C85*'Business Case'!D12*$B85)-'Business Case'!D11*$C85*'Business Case'!D13*$D85-'Business Case'!D14*$E85)-MAX(0,(('Business Case'!D11*$C85*'Business Case'!D12*$B85)-'Business Case'!D11*$C85*'Business Case'!D13*$D85-'Business Case'!D14*$E85))*'Business Case'!$B$7-'Business Case'!$B$8*(('Business Case'!D11*$C85*'Business Case'!D12*$B85)-('Business Case'!C11*$C85*'Business Case'!C12*$B85))-'Business Case'!D15*$F85 -> 0 | K85: =(('Business Case'!E11*$C85*'Business Case'!E12*$B85)-'Business Case'!E11*$C85*'Business Case'!E13*$D85-'Business Case'!E14*$E85)-MAX(0,(('Business Case'!E11*$C85*'Business Case'!E12*$B85)-'Business Case'!E11*$C85*'Business Case'!E13*$D85-'Business Case'!E14*$E85))*'Business Case'!$B$7-'Business Case'!$B$8*(('Business Case'!E11*$C85*'Business Case'!E12*$B85)-('Business Case'!D11*$C85*'Business Case'!D12*$B85))-'Business Case'!E15*$F85 -> 0 | L85: =(('Business Case'!F11*$C85*'Business Case'!F12*$B85)-'Business Case'!F11*$C85*'Business Case'!F13*$D85-'Business Case'!F14*$E85)-MAX(0,(('Business Case'!F11*$C85*'Business Case'!F12*$B85)-'Business Case'!F11*$C85*'Business Case'!F13*$D85-'Business Case'!F14*$E85))*'Business Case'!$B$7-'Business Case'!$B$8*(('Business Case'!F11*$C85*'Business Case'!F12*$B85)-('Business Case'!E11*$C85*'Business Case'!E12*$B85))-'Business Case'!F15*$F85 -> 0 | M85: =(('Business Case'!G11*$C85*'Business Case'!G12*$B85)-'Business Case'!G11*$C85*'Business Case'!G13*$D85-'Business Case'!G14*$E85)-MAX(0,(('Business Case'!G11*$C85*'Business Case'!G12*$B85)-'Business Case'!G11*$C85*'Business Case'!G13*$D85-'Business Case'!G14*$E85))*'Business Case'!$B$7-'Business Case'!$B$8*(('Business Case'!G11*$C85*'Business Case'!G12*$B85)-('Business Case'!F11*$C85*'Business Case'!F12*$B85))-'Business Case'!G15*$F85+'Business Case'!$B$8*('Business Case'!G11*$C85*'Business Case'!G12*$B85) -> 0 | N85: =IF(COUNT('Business Case'!B11:G11)=0,"",H85+NPV(G85,I85:M85)) | P85: =RAND() -> 0.45563057 | Q85: =RAND() -> 0.65970989 | R85: =RAND() -> 0.23487331 | S85: =RAND() -> 0.45798151 | T85: =RAND() -> 0.90535176 | U85: =RAND() -> 0.53426117
A86: 6 | B86: =1+IF($G$6=$E$6,$F$6,IF(P86<($F$6-$E$6)/($G$6-$E$6),$E$6+SQRT(P86*($G$6-$E$6)*($F$6-$E$6)),$G$6-SQRT((1-P86)*($G$6-$E$6)*($G$6-$F$6)))) -> 1 | C86: =1+IF($G$7=$E$7,$F$7,IF(Q86<($F$7-$E$7)/($G$7-$E$7),$E$7+SQRT(Q86*($G$7-$E$7)*($F$7-$E$7)),$G$7-SQRT((1-Q86)*($G$7-$E$7)*($G$7-$F$7)))) -> 1 | D86: =1+IF($G$8=$E$8,$F$8,IF(R86<($F$8-$E$8)/($G$8-$E$8),$E$8+SQRT(R86*($G$8-$E$8)*($F$8-$E$8)),$G$8-SQRT((1-R86)*($G$8-$E$8)*($G$8-$F$8)))) -> 1 | E86: =1+IF($G$9=$E$9,$F$9,IF(S86<($F$9-$E$9)/($G$9-$E$9),$E$9+SQRT(S86*($G$9-$E$9)*($F$9-$E$9)),$G$9-SQRT((1-S86)*($G$9-$E$9)*($G$9-$F$9)))) -> 1 | F86: =1+IF($G$10=$E$10,$F$10,IF(T86<($F$10-$E$10)/($G$10-$E$10),$E$10+SQRT(T86*($G$10-$E$10)*($F$10-$E$10)),$G$10-SQRT((1-T86)*($G$10-$E$10)*($G$10-$F$10)))) -> 1 | G86: =IF($G$11=$E$11,$F$11,IF(U86<($F$11-$E$11)/($G$11-$E$11),$E$11+SQRT(U86*($G$11-$E$11)*($F$11-$E$11)),$G$11-SQRT((1-U86)*($G$11-$E$11)*($G$11-$F$11)))) -> 0 | H86: =(('Business Case'!B11*$C86*'Business Case'!B12*$B86)-'Business Case'!B11*$C86*'Business Case'!B13*$D86-'Business Case'!B14*$E86)-MAX(0,(('Business Case'!B11*$C86*'Business Case'!B12*$B86)-'Business Case'!B11*$C86*'Business Case'!B13*$D86-'Business Case'!B14*$E86))*'Business Case'!$B$7-'Business Case'!$B$8*('Business Case'!B11*$C86*'Business Case'!B12*$B86)-'Business Case'!B15*$F86 -> 0 | I86: =(('Business Case'!C11*$C86*'Business Case'!C12*$B86)-'Business Case'!C11*$C86*'Business Case'!C13*$D86-'Business Case'!C14*$E86)-MAX(0,(('Business Case'!C11*$C86*'Business Case'!C12*$B86)-'Business Case'!C11*$C86*'Business Case'!C13*$D86-'Business Case'!C14*$E86))*'Business Case'!$B$7-'Business Case'!$B$8*(('Business Case'!C11*$C86*'Business Case'!C12*$B86)-('Business Case'!B11*$C86*'Business Case'!B12*$B86))-'Business Case'!C15*$F86 -> 0 | J86: =(('Business Case'!D11*$C86*'Business Case'!D12*$B86)-'Business Case'!D11*$C86*'Business Case'!D13*$D86-'Business Case'!D14*$E86)-MAX(0,(('Business Case'!D11*$C86*'Business Case'!D12*$B86)-'Business Case'!D11*$C86*'Business Case'!D13*$D86-'Business Case'!D14*$E86))*'Business Case'!$B$7-'Business Case'!$B$8*(('Business Case'!D11*$C86*'Business Case'!D12*$B86)-('Business Case'!C11*$C86*'Business Case'!C12*$B86))-'Business Case'!D15*$F86 -> 0 | K86: =(('Business Case'!E11*$C86*'Business Case'!E12*$B86)-'Business Case'!E11*$C86*'Business Case'!E13*$D86-'Business Case'!E14*$E86)-MAX(0,(('Business Case'!E11*$C86*'Business Case'!E12*$B86)-'Business Case'!E11*$C86*'Business Case'!E13*$D86-'Business Case'!E14*$E86))*'Business Case'!$B$7-'Business Case'!$B$8*(('Business Case'!E11*$C86*'Business Case'!E12*$B86)-('Business Case'!D11*$C86*'Business Case'!D12*$B86))-'Business Case'!E15*$F86 -> 0 | L86: =(('Business Case'!F11*$C86*'Business Case'!F12*$B86)-'Business Case'!F11*$C86*'Business Case'!F13*$D86-'Business Case'!F14*$E86)-MAX(0,(('Business Case'!F11*$C86*'Business Case'!F12*$B86)-'Business Case'!F11*$C86*'Business Case'!F13*$D86-'Business Case'!F14*$E86))*'Business Case'!$B$7-'Business Case'!$B$8*(('Business Case'!F11*$C86*'Business Case'!F12*$B86)-('Business Case'!E11*$C86*'Business Case'!E12*$B86))-'Business Case'!F15*$F86 -> 0 | M86: =(('Business Case'!G11*$C86*'Business Case'!G12*$B86)-'Business Case'!G11*$C86*'Business Case'!G13*$D86-'Business Case'!G14*$E86)-MAX(0,(('Business Case'!G11*$C86*'Business Case'!G12*$B86)-'Business Case'!G11*$C86*'Business Case'!G13*$D86-'Business Case'!G14*$E86))*'Business Case'!$B$7-'Business Case'!$B$8*(('Business Case'!G11*$C86*'Business Case'!G12*$B86)-('Business Case'!F11*$C86*'Business Case'!F12*$B86))-'Business Case'!G15*$F86+'Business Case'!$B$8*('Business Case'!G11*$C86*'Business Case'!G12*$B86) -> 0 | N86: =IF(COUNT('Business Case'!B11:G11)=0,"",H86+NPV(G86,I86:M86)) | P86: =RAND() -> 0.8665511 | Q86: =RAND() -> 0.92360681 | R86: =RAND() -> 0.9837105 | S86: =RAND() -> 0.3467748 | T86: =RAND() -> 0.68311094 | U86: =RAND() -> 0.81153605
A87: 7 | B87: =1+IF($G$6=$E$6,$F$6,IF(P87<($F$6-$E$6)/($G$6-$E$6),$E$6+SQRT(P87*($G$6-$E$6)*($F$6-$E$6)),$G$6-SQRT((1-P87)*($G$6-$E$6)*($G$6-$F$6)))) -> 1 | C87: =1+IF($G$7=$E$7,$F$7,IF(Q87<($F$7-$E$7)/($G$7-$E$7),$E$7+SQRT(Q87*($G$7-$E$7)*($F$7-$E$7)),$G$7-SQRT((1-Q87)*($G$7-$E$7)*($G$7-$F$7)))) -> 1 | D87: =1+IF($G$8=$E$8,$F$8,IF(R87<($F$8-$E$8)/($G$8-$E$8),$E$8+SQRT(R87*($G$8-$E$8)*($F$8-$E$8)),$G$8-SQRT((1-R87)*($G$8-$E$8)*($G$8-$F$8)))) -> 1 | E87: =1+IF($G$9=$E$9,$F$9,IF(S87<($F$9-$E$9)/($G$9-$E$9),$E$9+SQRT(S87*($G$9-$E$9)*($F$9-$E$9)),$G$9-SQRT((1-S87)*($G$9-$E$9)*($G$9-$F$9)))) -> 1 | F87: =1+IF($G$10=$E$10,$F$10,IF(T87<($F$10-$E$10)/($G$10-$E$10),$E$10+SQRT(T87*($G$10-$E$10)*($F$10-$E$10)),$G$10-SQRT((1-T87)*($G$10-$E$10)*($G$10-$F$10)))) -> 1 | G87: =IF($G$11=$E$11,$F$11,IF(U87<($F$11-$E$11)/($G$11-$E$11),$E$11+SQRT(U87*($G$11-$E$11)*($F$11-$E$11)),$G$11-SQRT((1-U87)*($G$11-$E$11)*($G$11-$F$11)))) -> 0 | H87: =(('Business Case'!B11*$C87*'Business Case'!B12*$B87)-'Business Case'!B11*$C87*'Business Case'!B13*$D87-'Business Case'!B14*$E87)-MAX(0,(('Business Case'!B11*$C87*'Business Case'!B12*$B87)-'Business Case'!B11*$C87*'Business Case'!B13*$D87-'Business Case'!B14*$E87))*'Business Case'!$B$7-'Business Case'!$B$8*('Business Case'!B11*$C87*'Business Case'!B12*$B87)-'Business Case'!B15*$F87 -> 0 | I87: =(('Business Case'!C11*$C87*'Business Case'!C12*$B87)-'Business Case'!C11*$C87*'Business Case'!C13*$D87-'Business Case'!C14*$E87)-MAX(0,(('Business Case'!C11*$C87*'Business Case'!C12*$B87)-'Business Case'!C11*$C87*'Business Case'!C13*$D87-'Business Case'!C14*$E87))*'Business Case'!$B$7-'Business Case'!$B$8*(('Business Case'!C11*$C87*'Business Case'!C12*$B87)-('Business Case'!B11*$C87*'Business Case'!B12*$B87))-'Business Case'!C15*$F87 -> 0 | J87: =(('Business Case'!D11*$C87*'Business Case'!D12*$B87)-'Business Case'!D11*$C87*'Business Case'!D13*$D87-'Business Case'!D14*$E87)-MAX(0,(('Business Case'!D11*$C87*'Business Case'!D12*$B87)-'Business Case'!D11*$C87*'Business Case'!D13*$D87-'Business Case'!D14*$E87))*'Business Case'!$B$7-'Business Case'!$B$8*(('Business Case'!D11*$C87*'Business Case'!D12*$B87)-('Business Case'!C11*$C87*'Business Case'!C12*$B87))-'Business Case'!D15*$F87 -> 0 | K87: =(('Business Case'!E11*$C87*'Business Case'!E12*$B87)-'Business Case'!E11*$C87*'Business Case'!E13*$D87-'Business Case'!E14*$E87)-MAX(0,(('Business Case'!E11*$C87*'Business Case'!E12*$B87)-'Business Case'!E11*$C87*'Business Case'!E13*$D87-'Business Case'!E14*$E87))*'Business Case'!$B$7-'Business Case'!$B$8*(('Business Case'!E11*$C87*'Business Case'!E12*$B87)-('Business Case'!D11*$C87*'Business Case'!D12*$B87))-'Business Case'!E15*$F87 -> 0 | L87: =(('Business Case'!F11*$C87*'Business Case'!F12*$B87)-'Business Case'!F11*$C87*'Business Case'!F13*$D87-'Business Case'!F14*$E87)-MAX(0,(('Business Case'!F11*$C87*'Business Case'!F12*$B87)-'Business Case'!F11*$C87*'Business Case'!F13*$D87-'Business Case'!F14*$E87))*'Business Case'!$B$7-'Business Case'!$B$8*(('Business Case'!F11*$C87*'Business Case'!F12*$B87)-('Business Case'!E11*$C87*'Business Case'!E12*$B87))-'Business Case'!F15*$F87 -> 0 | M87: =(('Business Case'!G11*$C87*'Business Case'!G12*$B87)-'Business Case'!G11*$C87*'Business Case'!G13*$D87-'Business Case'!G14*$E87)-MAX(0,(('Business Case'!G11*$C87*'Business Case'!G12*$B87)-'Business Case'!G11*$C87*'Business Case'!G13*$D87-'Business Case'!G14*$E87))*'Business Case'!$B$7-'Business Case'!$B$8*(('Business Case'!G11*$C87*'Business Case'!G12*$B87)-('Business Case'!F11*$C87*'Business Case'!F12*$B87))-'Business Case'!G15*$F87+'Business Case'!$B$8*('Business Case'!G11*$C87*'Business Case'!G12*$B87) -> 0 | N87: =IF(COUNT('Business Case'!B11:G11)=0,"",H87+NPV(G87,I87:M87)) | P87: =RAND() -> 0.98604796 | Q87: =RAND() -> 0.35935731 | R87: =RAND() -> 0.71915757 | S87: =RAND() -> 0.33118665 | T87: =RAND() -> 0.86090253 | U87: =RAND() -> 0.88905015
A88: 8 | B88: =1+IF($G$6=$E$6,$F$6,IF(P88<($F$6-$E$6)/($G$6-$E$6),$E$6+SQRT(P88*($G$6-$E$6)*($F$6-$E$6)),$G$6-SQRT((1-P88)*($G$6-$E$6)*($G$6-$F$6)))) -> 1 | C88: =1+IF($G$7=$E$7,$F$7,IF(Q88<($F$7-$E$7)/($G$7-$E$7),$E$7+SQRT(Q88*($G$7-$E$7)*($F$7-$E$7)),$G$7-SQRT((1-Q88)*($G$7-$E$7)*($G$7-$F$7)))) -> 1 | D88: =1+IF($G$8=$E$8,$F$8,IF(R88<($F$8-$E$8)/($G$8-$E$8),$E$8+SQRT(R88*($G$8-$E$8)*($F$8-$E$8)),$G$8-SQRT((1-R88)*($G$8-$E$8)*($G$8-$F$8)))) -> 1 | E88: =1+IF($G$9=$E$9,$F$9,IF(S88<($F$9-$E$9)/($G$9-$E$9),$E$9+SQRT(S88*($G$9-$E$9)*($F$9-$E$9)),$G$9-SQRT((1-S88)*($G$9-$E$9)*($G$9-$F$9)))) -> 1 | F88: =1+IF($G$10=$E$10,$F$10,IF(T88<($F$10-$E$10)/($G$10-$E$10),$E$10+SQRT(T88*($G$10-$E$10)*($F$10-$E$10)),$G$10-SQRT((1-T88)*($G$10-$E$10)*($G$10-$F$10)))) -> 1 | G88: =IF($G$11=$E$11,$F$11,IF(U88<($F$11-$E$11)/($G$11-$E$11),$E$11+SQRT(U88*($G$11-$E$11)*($F$11-$E$11)),$G$11-SQRT((1-U88)*($G$11-$E$11)*($G$11-$F$11)))) -> 0 | H88: =(('Business Case'!B11*$C88*'Business Case'!B12*$B88)-'Business Case'!B11*$C88*'Business Case'!B13*$D88-'Business Case'!B14*$E88)-MAX(0,(('Business Case'!B11*$C88*'Business Case'!B12*$B88)-'Business Case'!B11*$C88*'Business Case'!B13*$D88-'Business Case'!B14*$E88))*'Business Case'!$B$7-'Business Case'!$B$8*('Business Case'!B11*$C88*'Business Case'!B12*$B88)-'Business Case'!B15*$F88 -> 0 | I88: =(('Business Case'!C11*$C88*'Business Case'!C12*$B88)-'Business Case'!C11*$C88*'Business Case'!C13*$D88-'Business Case'!C14*$E88)-MAX(0,(('Business Case'!C11*$C88*'Business Case'!C12*$B88)-'Business Case'!C11*$C88*'Business Case'!C13*$D88-'Business Case'!C14*$E88))*'Business Case'!$B$7-'Business Case'!$B$8*(('Business Case'!C11*$C88*'Business Case'!C12*$B88)-('Business Case'!B11*$C88*'Business Case'!B12*$B88))-'Business Case'!C15*$F88 -> 0 | J88: =(('Business Case'!D11*$C88*'Business Case'!D12*$B88)-'Business Case'!D11*$C88*'Business Case'!D13*$D88-'Business Case'!D14*$E88)-MAX(0,(('Business Case'!D11*$C88*'Business Case'!D12*$B88)-'Business Case'!D11*$C88*'Business Case'!D13*$D88-'Business Case'!D14*$E88))*'Business Case'!$B$7-'Business Case'!$B$8*(('Business Case'!D11*$C88*'Business Case'!D12*$B88)-('Business Case'!C11*$C88*'Business Case'!C12*$B88))-'Business Case'!D15*$F88 -> 0 | K88: =(('Business Case'!E11*$C88*'Business Case'!E12*$B88)-'Business Case'!E11*$C88*'Business Case'!E13*$D88-'Business Case'!E14*$E88)-MAX(0,(('Business Case'!E11*$C88*'Business Case'!E12*$B88)-'Business Case'!E11*$C88*'Business Case'!E13*$D88-'Business Case'!E14*$E88))*'Business Case'!$B$7-'Business Case'!$B$8*(('Business Case'!E11*$C88*'Business Case'!E12*$B88)-('Business Case'!D11*$C88*'Business Case'!D12*$B88))-'Business Case'!E15*$F88 -> 0 | L88: =(('Business Case'!F11*$C88*'Business Case'!F12*$B88)-'Business Case'!F11*$C88*'Business Case'!F13*$D88-'Business Case'!F14*$E88)-MAX(0,(('Business Case'!F11*$C88*'Business Case'!F12*$B88)-'Business Case'!F11*$C88*'Business Case'!F13*$D88-'Business Case'!F14*$E88))*'Business Case'!$B$7-'Business Case'!$B$8*(('Business Case'!F11*$C88*'Business Case'!F12*$B88)-('Business Case'!E11*$C88*'Business Case'!E12*$B88))-'Business Case'!F15*$F88 -> 0 | M88: =(('Business Case'!G11*$C88*'Business Case'!G12*$B88)-'Business Case'!G11*$C88*'Business Case'!G13*$D88-'Business Case'!G14*$E88)-MAX(0,(('Business Case'!G11*$C88*'Business Case'!G12*$B88)-'Business Case'!G11*$C88*'Business Case'!G13*$D88-'Business Case'!G14*$E88))*'Business Case'!$B$7-'Business Case'!$B$8*(('Business Case'!G11*$C88*'Business Case'!G12*$B88)-('Business Case'!F11*$C88*'Business Case'!F12*$B88))-'Business Case'!G15*$F88+'Business Case'!$B$8*('Business Case'!G11*$C88*'Business Case'!G12*$B88) -> 0 | N88: =IF(COUNT('Business Case'!B11:G11)=0,"",H88+NPV(G88,I88:M88)) | P88: =RAND() -> 0.26926359 | Q88: =RAND() -> 0.76136518 | R88: =RAND() -> 0.6744619 | S88: =RAND() -> 0.94264778 | T88: =RAND() -> 0.59459286 | U88: =RAND() -> 0.11968013
A89: 9 | B89: =1+IF($G$6=$E$6,$F$6,IF(P89<($F$6-$E$6)/($G$6-$E$6),$E$6+SQRT(P89*($G$6-$E$6)*($F$6-$E$6)),$G$6-SQRT((1-P89)*($G$6-$E$6)*($G$6-$F$6)))) -> 1 | C89: =1+IF($G$7=$E$7,$F$7,IF(Q89<($F$7-$E$7)/($G$7-$E$7),$E$7+SQRT(Q89*($G$7-$E$7)*($F$7-$E$7)),$G$7-SQRT((1-Q89)*($G$7-$E$7)*($G$7-$F$7)))) -> 1 | D89: =1+IF($G$8=$E$8,$F$8,IF(R89<($F$8-$E$8)/($G$8-$E$8),$E$8+SQRT(R89*($G$8-$E$8)*($F$8-$E$8)),$G$8-SQRT((1-R89)*($G$8-$E$8)*($G$8-$F$8)))) -> 1 | E89: =1+IF($G$9=$E$9,$F$9,IF(S89<($F$9-$E$9)/($G$9-$E$9),$E$9+SQRT(S89*($G$9-$E$9)*($F$9-$E$9)),$G$9-SQRT((1-S89)*($G$9-$E$9)*($G$9-$F$9)))) -> 1 | F89: =1+IF($G$10=$E$10,$F$10,IF(T89<($F$10-$E$10)/($G$10-$E$10),$E$10+SQRT(T89*($G$10-$E$10)*($F$10-$E$10)),$G$10-SQRT((1-T89)*($G$10-$E$10)*($G$10-$F$10)))) -> 1 | G89: =IF($G$11=$E$11,$F$11,IF(U89<($F$11-$E$11)/($G$11-$E$11),$E$11+SQRT(U89*($G$11-$E$11)*($F$11-$E$11)),$G$11-SQRT((1-U89)*($G$11-$E$11)*($G$11-$F$11)))) -> 0 | H89: =(('Business Case'!B11*$C89*'Business Case'!B12*$B89)-'Business Case'!B11*$C89*'Business Case'!B13*$D89-'Business Case'!B14*$E89)-MAX(0,(('Business Case'!B11*$C89*'Business Case'!B12*$B89)-'Business Case'!B11*$C89*'Business Case'!B13*$D89-'Business Case'!B14*$E89))*'Business Case'!$B$7-'Business Case'!$B$8*('Business Case'!B11*$C89*'Business Case'!B12*$B89)-'Business Case'!B15*$F89 -> 0 | I89: =(('Business Case'!C11*$C89*'Business Case'!C12*$B89)-'Business Case'!C11*$C89*'Business Case'!C13*$D89-'Business Case'!C14*$E89)-MAX(0,(('Business Case'!C11*$C89*'Business Case'!C12*$B89)-'Business Case'!C11*$C89*'Business Case'!C13*$D89-'Business Case'!C14*$E89))*'Business Case'!$B$7-'Business Case'!$B$8*(('Business Case'!C11*$C89*'Business Case'!C12*$B89)-('Business Case'!B11*$C89*'Business Case'!B12*$B89))-'Business Case'!C15*$F89 -> 0 | J89: =(('Business Case'!D11*$C89*'Business Case'!D12*$B89)-'Business Case'!D11*$C89*'Business Case'!D13*$D89-'Business Case'!D14*$E89)-MAX(0,(('Business Case'!D11*$C89*'Business Case'!D12*$B89)-'Business Case'!D11*$C89*'Business Case'!D13*$D89-'Business Case'!D14*$E89))*'Business Case'!$B$7-'Business Case'!$B$8*(('Business Case'!D11*$C89*'Business Case'!D12*$B89)-('Business Case'!C11*$C89*'Business Case'!C12*$B89))-'Business Case'!D15*$F89 -> 0 | K89: =(('Business Case'!E11*$C89*'Business Case'!E12*$B89)-'Business Case'!E11*$C89*'Business Case'!E13*$D89-'Business Case'!E14*$E89)-MAX(0,(('Business Case'!E11*$C89*'Business Case'!E12*$B89)-'Business Case'!E11*$C89*'Business Case'!E13*$D89-'Business Case'!E14*$E89))*'Business Case'!$B$7-'Business Case'!$B$8*(('Business Case'!E11*$C89*'Business Case'!E12*$B89)-('Business Case'!D11*$C89*'Business Case'!D12*$B89))-'Business Case'!E15*$F89 -> 0 | L89: =(('Business Case'!F11*$C89*'Business Case'!F12*$B89)-'Business Case'!F11*$C89*'Business Case'!F13*$D89-'Business Case'!F14*$E89)-MAX(0,(('Business Case'!F11*$C89*'Business Case'!F12*$B89)-'Business Case'!F11*$C89*'Business Case'!F13*$D89-'Business Case'!F14*$E89))*'Business Case'!$B$7-'Business Case'!$B$8*(('Business Case'!F11*$C89*'Business Case'!F12*$B89)-('Business Case'!E11*$C89*'Business Case'!E12*$B89))-'Business Case'!F15*$F89 -> 0 | M89: =(('Business Case'!G11*$C89*'Business Case'!G12*$B89)-'Business Case'!G11*$C89*'Business Case'!G13*$D89-'Business Case'!G14*$E89)-MAX(0,(('Business Case'!G11*$C89*'Business Case'!G12*$B89)-'Business Case'!G11*$C89*'Business Case'!G13*$D89-'Business Case'!G14*$E89))*'Business Case'!$B$7-'Business Case'!$B$8*(('Business Case'!G11*$C89*'Business Case'!G12*$B89)-('Business Case'!F11*$C89*'Business Case'!F12*$B89))-'Business Case'!G15*$F89+'Business Case'!$B$8*('Business Case'!G11*$C89*'Business Case'!G12*$B89) -> 0 | N89: =IF(COUNT('Business Case'!B11:G11)=0,"",H89+NPV(G89,I89:M89)) | P89: =RAND() -> 0.92954742 | Q89: =RAND() -> 0.15515961 | R89: =RAND() -> 0.80924878 | S89: =RAND() -> 0.92060524 | T89: =RAND() -> 0.058595013 | U89: =RAND() -> 0.58376995
A90: 10 | B90: =1+IF($G$6=$E$6,$F$6,IF(P90<($F$6-$E$6)/($G$6-$E$6),$E$6+SQRT(P90*($G$6-$E$6)*($F$6-$E$6)),$G$6-SQRT((1-P90)*($G$6-$E$6)*($G$6-$F$6)))) -> 1 | C90: =1+IF($G$7=$E$7,$F$7,IF(Q90<($F$7-$E$7)/($G$7-$E$7),$E$7+SQRT(Q90*($G$7-$E$7)*($F$7-$E$7)),$G$7-SQRT((1-Q90)*($G$7-$E$7)*($G$7-$F$7)))) -> 1 | D90: =1+IF($G$8=$E$8,$F$8,IF(R90<($F$8-$E$8)/($G$8-$E$8),$E$8+SQRT(R90*($G$8-$E$8)*($F$8-$E$8)),$G$8-SQRT((1-R90)*($G$8-$E$8)*($G$8-$F$8)))) -> 1 | E90: =1+IF($G$9=$E$9,$F$9,IF(S90<($F$9-$E$9)/($G$9-$E$9),$E$9+SQRT(S90*($G$9-$E$9)*($F$9-$E$9)),$G$9-SQRT((1-S90)*($G$9-$E$9)*($G$9-$F$9)))) -> 1 | F90: =1+IF($G$10=$E$10,$F$10,IF(T90<($F$10-$E$10)/($G$10-$E$10),$E$10+SQRT(T90*($G$10-$E$10)*($F$10-$E$10)),$G$10-SQRT((1-T90)*($G$10-$E$10)*($G$10-$F$10)))) -> 1 | G90: =IF($G$11=$E$11,$F$11,IF(U90<($F$11-$E$11)/($G$11-$E$11),$E$11+SQRT(U90*($G$11-$E$11)*($F$11-$E$11)),$G$11-SQRT((1-U90)*($G$11-$E$11)*($G$11-$F$11)))) -> 0 | H90: =(('Business Case'!B11*$C90*'Business Case'!B12*$B90)-'Business Case'!B11*$C90*'Business Case'!B13*$D90-'Business Case'!B14*$E90)-MAX(0,(('Business Case'!B11*$C90*'Business Case'!B12*$B90)-'Business Case'!B11*$C90*'Business Case'!B13*$D90-'Business Case'!B14*$E90))*'Business Case'!$B$7-'Business Case'!$B$8*('Business Case'!B11*$C90*'Business Case'!B12*$B90)-'Business Case'!B15*$F90 -> 0 | I90: =(('Business Case'!C11*$C90*'Business Case'!C12*$B90)-'Business Case'!C11*$C90*'Business Case'!C13*$D90-'Business Case'!C14*$E90)-MAX(0,(('Business Case'!C11*$C90*'Business Case'!C12*$B90)-'Business Case'!C11*$C90*'Business Case'!C13*$D90-'Business Case'!C14*$E90))*'Business Case'!$B$7-'Business Case'!$B$8*(('Business Case'!C11*$C90*'Business Case'!C12*$B90)-('Business Case'!B11*$C90*'Business Case'!B12*$B90))-'Business Case'!C15*$F90 -> 0 | J90: =(('Business Case'!D11*$C90*'Business Case'!D12*$B90)-'Business Case'!D11*$C90*'Business Case'!D13*$D90-'Business Case'!D14*$E90)-MAX(0,(('Business Case'!D11*$C90*'Business Case'!D12*$B90)-'Business Case'!D11*$C90*'Business Case'!D13*$D90-'Business Case'!D14*$E90))*'Business Case'!$B$7-'Business Case'!$B$8*(('Business Case'!D11*$C90*'Business Case'!D12*$B90)-('Business Case'!C11*$C90*'Business Case'!C12*$B90))-'Business Case'!D15*$F90 -> 0 | K90: =(('Business Case'!E11*$C90*'Business Case'!E12*$B90)-'Business Case'!E11*$C90*'Business Case'!E13*$D90-'Business Case'!E14*$E90)-MAX(0,(('Business Case'!E11*$C90*'Business Case'!E12*$B90)-'Business Case'!E11*$C90*'Business Case'!E13*$D90-'Business Case'!E14*$E90))*'Business Case'!$B$7-'Business Case'!$B$8*(('Business Case'!E11*$C90*'Business Case'!E12*$B90)-('Business Case'!D11*$C90*'Business Case'!D12*$B90))-'Business Case'!E15*$F90 -> 0 | L90: =(('Business Case'!F11*$C90*'Business Case'!F12*$B90)-'Business Case'!F11*$C90*'Business Case'!F13*$D90-'Business Case'!F14*$E90)-MAX(0,(('Business Case'!F11*$C90*'Business Case'!F12*$B90)-'Business Case'!F11*$C90*'Business Case'!F13*$D90-'Business Case'!F14*$E90))*'Business Case'!$B$7-'Business Case'!$B$8*(('Business Case'!F11*$C90*'Business Case'!F12*$B90)-('Business Case'!E11*$C90*'Business Case'!E12*$B90))-'Business Case'!F15*$F90 -> 0 | M90: =(('Business Case'!G11*$C90*'Business Case'!G12*$B90)-'Business Case'!G11*$C90*'Business Case'!G13*$D90-'Business Case'!G14*$E90)-MAX(0,(('Business Case'!G11*$C90*'Business Case'!G12*$B90)-'Business Case'!G11*$C90*'Business Case'!G13*$D90-'Business Case'!G14*$E90))*'Business Case'!$B$7-'Business Case'!$B$8*(('Business Case'!G11*$C90*'Business Case'!G12*$B90)-('Business Case'!F11*$C90*'Business Case'!F12*$B90))-'Business Case'!G15*$F90+'Business Case'!$B$8*('Business Case'!G11*$C90*'Business Case'!G12*$B90) -> 0 | N90: =IF(COUNT('Business Case'!B11:G11)=0,"",H90+NPV(G90,I90:M90)) | P90: =RAND() -> 0.61611306 | Q90: =RAND() -> 0.41874822 | R90: =RAND() -> 0.83695804 | S90: =RAND() -> 0.47116327 | T90: =RAND() -> 0.80135202 | U90: =RAND() -> 0.12883143
A91: 11 | B91: =1+IF($G$6=$E$6,$F$6,IF(P91<($F$6-$E$6)/($G$6-$E$6),$E$6+SQRT(P91*($G$6-$E$6)*($F$6-$E$6)),$G$6-SQRT((1-P91)*($G$6-$E$6)*($G$6-$F$6)))) -> 1 | C91: =1+IF($G$7=$E$7,$F$7,IF(Q91<($F$7-$E$7)/($G$7-$E$7),$E$7+SQRT(Q91*($G$7-$E$7)*($F$7-$E$7)),$G$7-SQRT((1-Q91)*($G$7-$E$7)*($G$7-$F$7)))) -> 1 | D91: =1+IF($G$8=$E$8,$F$8,IF(R91<($F$8-$E$8)/($G$8-$E$8),$E$8+SQRT(R91*($G$8-$E$8)*($F$8-$E$8)),$G$8-SQRT((1-R91)*($G$8-$E$8)*($G$8-$F$8)))) -> 1 | E91: =1+IF($G$9=$E$9,$F$9,IF(S91<($F$9-$E$9)/($G$9-$E$9),$E$9+SQRT(S91*($G$9-$E$9)*($F$9-$E$9)),$G$9-SQRT((1-S91)*($G$9-$E$9)*($G$9-$F$9)))) -> 1 | F91: =1+IF($G$10=$E$10,$F$10,IF(T91<($F$10-$E$10)/($G$10-$E$10),$E$10+SQRT(T91*($G$10-$E$10)*($F$10-$E$10)),$G$10-SQRT((1-T91)*($G$10-$E$10)*($G$10-$F$10)))) -> 1 | G91: =IF($G$11=$E$11,$F$11,IF(U91<($F$11-$E$11)/($G$11-$E$11),$E$11+SQRT(U91*($G$11-$E$11)*($F$11-$E$11)),$G$11-SQRT((1-U91)*($G$11-$E$11)*($G$11-$F$11)))) -> 0 | H91: =(('Business Case'!B11*$C91*'Business Case'!B12*$B91)-'Business Case'!B11*$C91*'Business Case'!B13*$D91-'Business Case'!B14*$E91)-MAX(0,(('Business Case'!B11*$C91*'Business Case'!B12*$B91)-'Business Case'!B11*$C91*'Business Case'!B13*$D91-'Business Case'!B14*$E91))*'Business Case'!$B$7-'Business Case'!$B$8*('Business Case'!B11*$C91*'Business Case'!B12*$B91)-'Business Case'!B15*$F91 -> 0 | I91: =(('Business Case'!C11*$C91*'Business Case'!C12*$B91)-'Business Case'!C11*$C91*'Business Case'!C13*$D91-'Business Case'!C14*$E91)-MAX(0,(('Business Case'!C11*$C91*'Business Case'!C12*$B91)-'Business Case'!C11*$C91*'Business Case'!C13*$D91-'Business Case'!C14*$E91))*'Business Case'!$B$7-'Business Case'!$B$8*(('Business Case'!C11*$C91*'Business Case'!C12*$B91)-('Business Case'!B11*$C91*'Business Case'!B12*$B91))-'Business Case'!C15*$F91 -> 0 | J91: =(('Business Case'!D11*$C91*'Business Case'!D12*$B91)-'Business Case'!D11*$C91*'Business Case'!D13*$D91-'Business Case'!D14*$E91)-MAX(0,(('Business Case'!D11*$C91*'Business Case'!D12*$B91)-'Business Case'!D11*$C91*'Business Case'!D13*$D91-'Business Case'!D14*$E91))*'Business Case'!$B$7-'Business Case'!$B$8*(('Business Case'!D11*$C91*'Business Case'!D12*$B91)-('Business Case'!C11*$C91*'Business Case'!C12*$B91))-'Business Case'!D15*$F91 -> 0 | K91: =(('Business Case'!E11*$C91*'Business Case'!E12*$B91)-'Business Case'!E11*$C91*'Business Case'!E13*$D91-'Business Case'!E14*$E91)-MAX(0,(('Business Case'!E11*$C91*'Business Case'!E12*$B91)-'Business Case'!E11*$C91*'Business Case'!E13*$D91-'Business Case'!E14*$E91))*'Business Case'!$B$7-'Business Case'!$B$8*(('Business Case'!E11*$C91*'Business Case'!E12*$B91)-('Business Case'!D11*$C91*'Business Case'!D12*$B91))-'Business Case'!E15*$F91 -> 0 | L91: =(('Business Case'!F11*$C91*'Business Case'!F12*$B91)-'Business Case'!F11*$C91*'Business Case'!F13*$D91-'Business Case'!F14*$E91)-MAX(0,(('Business Case'!F11*$C91*'Business Case'!F12*$B91)-'Business Case'!F11*$C91*'Business Case'!F13*$D91-'Business Case'!F14*$E91))*'Business Case'!$B$7-'Business Case'!$B$8*(('Business Case'!F11*$C91*'Business Case'!F12*$B91)-('Business Case'!E11*$C91*'Business Case'!E12*$B91))-'Business Case'!F15*$F91 -> 0 | M91: =(('Business Case'!G11*$C91*'Business Case'!G12*$B91)-'Business Case'!G11*$C91*'Business Case'!G13*$D91-'Business Case'!G14*$E91)-MAX(0,(('Business Case'!G11*$C91*'Business Case'!G12*$B91)-'Business Case'!G11*$C91*'Business Case'!G13*$D91-'Business Case'!G14*$E91))*'Business Case'!$B$7-'Business Case'!$B$8*(('Business Case'!G11*$C91*'Business Case'!G12*$B91)-('Business Case'!F11*$C91*'Business Case'!F12*$B91))-'Business Case'!G15*$F91+'Business Case'!$B$8*('Business Case'!G11*$C91*'Business Case'!G12*$B91) -> 0 | N91: =IF(COUNT('Business Case'!B11:G11)=0,"",H91+NPV(G91,I91:M91)) | P91: =RAND() -> 0.082418646 | Q91: =RAND() -> 0.85759602 | R91: =RAND() -> 0.91255543 | S91: =RAND() -> 0.15797165 | T91: =RAND() -> 0.14549635 | U91: =RAND() -> 0.75598973
A92: 12 | B92: =1+IF($G$6=$E$6,$F$6,IF(P92<($F$6-$E$6)/($G$6-$E$6),$E$6+SQRT(P92*($G$6-$E$6)*($F$6-$E$6)),$G$6-SQRT((1-P92)*($G$6-$E$6)*($G$6-$F$6)))) -> 1 | C92: =1+IF($G$7=$E$7,$F$7,IF(Q92<($F$7-$E$7)/($G$7-$E$7),$E$7+SQRT(Q92*($G$7-$E$7)*($F$7-$E$7)),$G$7-SQRT((1-Q92)*($G$7-$E$7)*($G$7-$F$7)))) -> 1 | D92: =1+IF($G$8=$E$8,$F$8,IF(R92<($F$8-$E$8)/($G$8-$E$8),$E$8+SQRT(R92*($G$8-$E$8)*($F$8-$E$8)),$G$8-SQRT((1-R92)*($G$8-$E$8)*($G$8-$F$8)))) -> 1 | E92: =1+IF($G$9=$E$9,$F$9,IF(S92<($F$9-$E$9)/($G$9-$E$9),$E$9+SQRT(S92*($G$9-$E$9)*($F$9-$E$9)),$G$9-SQRT((1-S92)*($G$9-$E$9)*($G$9-$F$9)))) -> 1 | F92: =1+IF($G$10=$E$10,$F$10,IF(T92<($F$10-$E$10)/($G$10-$E$10),$E$10+SQRT(T92*($G$10-$E$10)*($F$10-$E$10)),$G$10-SQRT((1-T92)*($G$10-$E$10)*($G$10-$F$10)))) -> 1 | G92: =IF($G$11=$E$11,$F$11,IF(U92<($F$11-$E$11)/($G$11-$E$11),$E$11+SQRT(U92*($G$11-$E$11)*($F$11-$E$11)),$G$11-SQRT((1-U92)*($G$11-$E$11)*($G$11-$F$11)))) -> 0 | H92: =(('Business Case'!B11*$C92*'Business Case'!B12*$B92)-'Business Case'!B11*$C92*'Business Case'!B13*$D92-'Business Case'!B14*$E92)-MAX(0,(('Business Case'!B11*$C92*'Business Case'!B12*$B92)-'Business Case'!B11*$C92*'Business Case'!B13*$D92-'Business Case'!B14*$E92))*'Business Case'!$B$7-'Business Case'!$B$8*('Business Case'!B11*$C92*'Business Case'!B12*$B92)-'Business Case'!B15*$F92 -> 0 | I92: =(('Business Case'!C11*$C92*'Business Case'!C12*$B92)-'Business Case'!C11*$C92*'Business Case'!C13*$D92-'Business Case'!C14*$E92)-MAX(0,(('Business Case'!C11*$C92*'Business Case'!C12*$B92)-'Business Case'!C11*$C92*'Business Case'!C13*$D92-'Business Case'!C14*$E92))*'Business Case'!$B$7-'Business Case'!$B$8*(('Business Case'!C11*$C92*'Business Case'!C12*$B92)-('Business Case'!B11*$C92*'Business Case'!B12*$B92))-'Business Case'!C15*$F92 -> 0 | J92: =(('Business Case'!D11*$C92*'Business Case'!D12*$B92)-'Business Case'!D11*$C92*'Business Case'!D13*$D92-'Business Case'!D14*$E92)-MAX(0,(('Business Case'!D11*$C92*'Business Case'!D12*$B92)-'Business Case'!D11*$C92*'Business Case'!D13*$D92-'Business Case'!D14*$E92))*'Business Case'!$B$7-'Business Case'!$B$8*(('Business Case'!D11*$C92*'Business Case'!D12*$B92)-('Business Case'!C11*$C92*'Business Case'!C12*$B92))-'Business Case'!D15*$F92 -> 0 | K92: =(('Business Case'!E11*$C92*'Business Case'!E12*$B92)-'Business Case'!E11*$C92*'Business Case'!E13*$D92-'Business Case'!E14*$E92)-MAX(0,(('Business Case'!E11*$C92*'Business Case'!E12*$B92)-'Business Case'!E11*$C92*'Business Case'!E13*$D92-'Business Case'!E14*$E92))*'Business Case'!$B$7-'Business Case'!$B$8*(('Business Case'!E11*$C92*'Business Case'!E12*$B92)-('Business Case'!D11*$C92*'Business Case'!D12*$B92))-'Business Case'!E15*$F92 -> 0 | L92: =(('Business Case'!F11*$C92*'Business Case'!F12*$B92)-'Business Case'!F11*$C92*'Business Case'!F13*$D92-'Business Case'!F14*$E92)-MAX(0,(('Business Case'!F11*$C92*'Business Case'!F12*$B92)-'Business Case'!F11*$C92*'Business Case'!F13*$D92-'Business Case'!F14*$E92))*'Business Case'!$B$7-'Business Case'!$B$8*(('Business Case'!F11*$C92*'Business Case'!F12*$B92)-('Business Case'!E11*$C92*'Business Case'!E12*$B92))-'Business Case'!F15*$F92 -> 0 | M92: =(('Business Case'!G11*$C92*'Business Case'!G12*$B92)-'Business Case'!G11*$C92*'Business Case'!G13*$D92-'Business Case'!G14*$E92)-MAX(0,(('Business Case'!G11*$C92*'Business Case'!G12*$B92)-'Business Case'!G11*$C92*'Business Case'!G13*$D92-'Business Case'!G14*$E92))*'Business Case'!$B$7-'Business Case'!$B$8*(('Business Case'!G11*$C92*'Business Case'!G12*$B92)-('Business Case'!F11*$C92*'Business Case'!F12*$B92))-'Business Case'!G15*$F92+'Business Case'!$B$8*('Business Case'!G11*$C92*'Business Case'!G12*$B92) -> 0 | N92: =IF(COUNT('Business Case'!B11:G11)=0,"",H92+NPV(G92,I92:M92)) | P92: =RAND() -> 0.27027189 | Q92: =RAND() -> 0.66750681 | R92: =RAND() -> 0.56050807 | S92: =RAND() -> 0.58365053 | T92: =RAND() -> 0.90199526 | U92: =RAND() -> 0.35420109
A93: 13 | B93: =1+IF($G$6=$E$6,$F$6,IF(P93<($F$6-$E$6)/($G$6-$E$6),$E$6+SQRT(P93*($G$6-$E$6)*($F$6-$E$6)),$G$6-SQRT((1-P93)*($G$6-$E$6)*($G$6-$F$6)))) -> 1 | C93: =1+IF($G$7=$E$7,$F$7,IF(Q93<($F$7-$E$7)/($G$7-$E$7),$E$7+SQRT(Q93*($G$7-$E$7)*($F$7-$E$7)),$G$7-SQRT((1-Q93)*($G$7-$E$7)*($G$7-$F$7)))) -> 1 | D93: =1+IF($G$8=$E$8,$F$8,IF(R93<($F$8-$E$8)/($G$8-$E$8),$E$8+SQRT(R93*($G$8-$E$8)*($F$8-$E$8)),$G$8-SQRT((1-R93)*($G$8-$E$8)*($G$8-$F$8)))) -> 1 | E93: =1+IF($G$9=$E$9,$F$9,IF(S93<($F$9-$E$9)/($G$9-$E$9),$E$9+SQRT(S93*($G$9-$E$9)*($F$9-$E$9)),$G$9-SQRT((1-S93)*($G$9-$E$9)*($G$9-$F$9)))) -> 1 | F93: =1+IF($G$10=$E$10,$F$10,IF(T93<($F$10-$E$10)/($G$10-$E$10),$E$10+SQRT(T93*($G$10-$E$10)*($F$10-$E$10)),$G$10-SQRT((1-T93)*($G$10-$E$10)*($G$10-$F$10)))) -> 1 | G93: =IF($G$11=$E$11,$F$11,IF(U93<($F$11-$E$11)/($G$11-$E$11),$E$11+SQRT(U93*($G$11-$E$11)*($F$11-$E$11)),$G$11-SQRT((1-U93)*($G$11-$E$11)*($G$11-$F$11)))) -> 0 | H93: =(('Business Case'!B11*$C93*'Business Case'!B12*$B93)-'Business Case'!B11*$C93*'Business Case'!B13*$D93-'Business Case'!B14*$E93)-MAX(0,(('Business Case'!B11*$C93*'Business Case'!B12*$B93)-'Business Case'!B11*$C93*'Business Case'!B13*$D93-'Business Case'!B14*$E93))*'Business Case'!$B$7-'Business Case'!$B$8*('Business Case'!B11*$C93*'Business Case'!B12*$B93)-'Business Case'!B15*$F93 -> 0 | I93: =(('Business Case'!C11*$C93*'Business Case'!C12*$B93)-'Business Case'!C11*$C93*'Business Case'!C13*$D93-'Business Case'!C14*$E93)-MAX(0,(('Business Case'!C11*$C93*'Business Case'!C12*$B93)-'Business Case'!C11*$C93*'Business Case'!C13*$D93-'Business Case'!C14*$E93))*'Business Case'!$B$7-'Business Case'!$B$8*(('Business Case'!C11*$C93*'Business Case'!C12*$B93)-('Business Case'!B11*$C93*'Business Case'!B12*$B93))-'Business Case'!C15*$F93 -> 0 | J93: =(('Business Case'!D11*$C93*'Business Case'!D12*$B93)-'Business Case'!D11*$C93*'Business Case'!D13*$D93-'Business Case'!D14*$E93)-MAX(0,(('Business Case'!D11*$C93*'Business Case'!D12*$B93)-'Business Case'!D11*$C93*'Business Case'!D13*$D93-'Business Case'!D14*$E93))*'Business Case'!$B$7-'Business Case'!$B$8*(('Business Case'!D11*$C93*'Business Case'!D12*$B93)-('Business Case'!C11*$C93*'Business Case'!C12*$B93))-'Business Case'!D15*$F93 -> 0 | K93: =(('Business Case'!E11*$C93*'Business Case'!E12*$B93)-'Business Case'!E11*$C93*'Business Case'!E13*$D93-'Business Case'!E14*$E93)-MAX(0,(('Business Case'!E11*$C93*'Business Case'!E12*$B93)-'Business Case'!E11*$C93*'Business Case'!E13*$D93-'Business Case'!E14*$E93))*'Business Case'!$B$7-'Business Case'!$B$8*(('Business Case'!E11*$C93*'Business Case'!E12*$B93)-('Business Case'!D11*$C93*'Business Case'!D12*$B93))-'Business Case'!E15*$F93 -> 0 | L93: =(('Business Case'!F11*$C93*'Business Case'!F12*$B93)-'Business Case'!F11*$C93*'Business Case'!F13*$D93-'Business Case'!F14*$E93)-MAX(0,(('Business Case'!F11*$C93*'Business Case'!F12*$B93)-'Business Case'!F11*$C93*'Business Case'!F13*$D93-'Business Case'!F14*$E93))*'Business Case'!$B$7-'Business Case'!$B$8*(('Business Case'!F11*$C93*'Business Case'!F12*$B93)-('Business Case'!E11*$C93*'Business Case'!E12*$B93))-'Business Case'!F15*$F93 -> 0 | M93: =(('Business Case'!G11*$C93*'Business Case'!G12*$B93)-'Business Case'!G11*$C93*'Business Case'!G13*$D93-'Business Case'!G14*$E93)-MAX(0,(('Business Case'!G11*$C93*'Business Case'!G12*$B93)-'Business Case'!G11*$C93*'Business Case'!G13*$D93-'Business Case'!G14*$E93))*'Business Case'!$B$7-'Business Case'!$B$8*(('Business Case'!G11*$C93*'Business Case'!G12*$B93)-('Business Case'!F11*$C93*'Business Case'!F12*$B93))-'Business Case'!G15*$F93+'Business Case'!$B$8*('Business Case'!G11*$C93*'Business Case'!G12*$B93) -> 0 | N93: =IF(COUNT('Business Case'!B11:G11)=0,"",H93+NPV(G93,I93:M93)) | P93: =RAND() -> 0.75109768 | Q93: =RAND() -> 0.16316709 | R93: =RAND() -> 0.049410369 | S93: =RAND() -> 0.59661179 | T93: =RAND() -> 0.37201864 | U93: =RAND() -> 0.92063082
A94: 14 | B94: =1+IF($G$6=$E$6,$F$6,IF(P94<($F$6-$E$6)/($G$6-$E$6),$E$6+SQRT(P94*($G$6-$E$6)*($F$6-$E$6)),$G$6-SQRT((1-P94)*($G$6-$E$6)*($G$6-$F$6)))) -> 1 | C94: =1+IF($G$7=$E$7,$F$7,IF(Q94<($F$7-$E$7)/($G$7-$E$7),$E$7+SQRT(Q94*($G$7-$E$7)*($F$7-$E$7)),$G$7-SQRT((1-Q94)*($G$7-$E$7)*($G$7-$F$7)))) -> 1 | D94: =1+IF($G$8=$E$8,$F$8,IF(R94<($F$8-$E$8)/($G$8-$E$8),$E$8+SQRT(R94*($G$8-$E$8)*($F$8-$E$8)),$G$8-SQRT((1-R94)*($G$8-$E$8)*($G$8-$F$8)))) -> 1 | E94: =1+IF($G$9=$E$9,$F$9,IF(S94<($F$9-$E$9)/($G$9-$E$9),$E$9+SQRT(S94*($G$9-$E$9)*($F$9-$E$9)),$G$9-SQRT((1-S94)*($G$9-$E$9)*($G$9-$F$9)))) -> 1 | F94: =1+IF($G$10=$E$10,$F$10,IF(T94<($F$10-$E$10)/($G$10-$E$10),$E$10+SQRT(T94*($G$10-$E$10)*($F$10-$E$10)),$G$10-SQRT((1-T94)*($G$10-$E$10)*($G$10-$F$10)))) -> 1 | G94: =IF($G$11=$E$11,$F$11,IF(U94<($F$11-$E$11)/($G$11-$E$11),$E$11+SQRT(U94*($G$11-$E$11)*($F$11-$E$11)),$G$11-SQRT((1-U94)*($G$11-$E$11)*($G$11-$F$11)))) -> 0 | H94: =(('Business Case'!B11*$C94*'Business Case'!B12*$B94)-'Business Case'!B11*$C94*'Business Case'!B13*$D94-'Business Case'!B14*$E94)-MAX(0,(('Business Case'!B11*$C94*'Business Case'!B12*$B94)-'Business Case'!B11*$C94*'Business Case'!B13*$D94-'Business Case'!B14*$E94))*'Business Case'!$B$7-'Business Case'!$B$8*('Business Case'!B11*$C94*'Business Case'!B12*$B94)-'Business Case'!B15*$F94 -> 0 | I94: =(('Business Case'!C11*$C94*'Business Case'!C12*$B94)-'Business Case'!C11*$C94*'Business Case'!C13*$D94-'Business Case'!C14*$E94)-MAX(0,(('Business Case'!C11*$C94*'Business Case'!C12*$B94)-'Business Case'!C11*$C94*'Business Case'!C13*$D94-'Business Case'!C14*$E94))*'Business Case'!$B$7-'Business Case'!$B$8*(('Business Case'!C11*$C94*'Business Case'!C12*$B94)-('Business Case'!B11*$C94*'Business Case'!B12*$B94))-'Business Case'!C15*$F94 -> 0 | J94: =(('Business Case'!D11*$C94*'Business Case'!D12*$B94)-'Business Case'!D11*$C94*'Business Case'!D13*$D94-'Business Case'!D14*$E94)-MAX(0,(('Business Case'!D11*$C94*'Business Case'!D12*$B94)-'Business Case'!D11*$C94*'Business Case'!D13*$D94-'Business Case'!D14*$E94))*'Business Case'!$B$7-'Business Case'!$B$8*(('Business Case'!D11*$C94*'Business Case'!D12*$B94)-('Business Case'!C11*$C94*'Business Case'!C12*$B94))-'Business Case'!D15*$F94 -> 0 | K94: =(('Business Case'!E11*$C94*'Business Case'!E12*$B94)-'Business Case'!E11*$C94*'Business Case'!E13*$D94-'Business Case'!E14*$E94)-MAX(0,(('Business Case'!E11*$C94*'Business Case'!E12*$B94)-'Business Case'!E11*$C94*'Business Case'!E13*$D94-'Business Case'!E14*$E94))*'Business Case'!$B$7-'Business Case'!$B$8*(('Business Case'!E11*$C94*'Business Case'!E12*$B94)-('Business Case'!D11*$C94*'Business Case'!D12*$B94))-'Business Case'!E15*$F94 -> 0 | L94: =(('Business Case'!F11*$C94*'Business Case'!F12*$B94)-'Business Case'!F11*$C94*'Business Case'!F13*$D94-'Business Case'!F14*$E94)-MAX(0,(('Business Case'!F11*$C94*'Business Case'!F12*$B94)-'Business Case'!F11*$C94*'Business Case'!F13*$D94-'Business Case'!F14*$E94))*'Business Case'!$B$7-'Business Case'!$B$8*(('Business Case'!F11*$C94*'Business Case'!F12*$B94)-('Business Case'!E11*$C94*'Business Case'!E12*$B94))-'Business Case'!F15*$F94 -> 0 | M94: =(('Business Case'!G11*$C94*'Business Case'!G12*$B94)-'Business Case'!G11*$C94*'Business Case'!G13*$D94-'Business Case'!G14*$E94)-MAX(0,(('Business Case'!G11*$C94*'Business Case'!G12*$B94)-'Business Case'!G11*$C94*'Business Case'!G13*$D94-'Business Case'!G14*$E94))*'Business Case'!$B$7-'Business Case'!$B$8*(('Business Case'!G11*$C94*'Business Case'!G12*$B94)-('Business Case'!F11*$C94*'Business Case'!F12*$B94))-'Business Case'!G15*$F94+'Business Case'!$B$8*('Business Case'!G11*$C94*'Business Case'!G12*$B94) -> 0 | N94: =IF(COUNT('Business Case'!B11:G11)=0,"",H94+NPV(G94,I94:M94)) | P94: =RAND() -> 0.90410264 | Q94: =RAND() -> 0.82962859 | R94: =RAND() -> 0.82045775 | S94: =RAND() -> 0.039064206 | T94: =RAND() -> 0.67026462 | U94: =RAND() -> 0.92319274
A95: 15 | B95: =1+IF($G$6=$E$6,$F$6,IF(P95<($F$6-$E$6)/($G$6-$E$6),$E$6+SQRT(P95*($G$6-$E$6)*($F$6-$E$6)),$G$6-SQRT((1-P95)*($G$6-$E$6)*($G$6-$F$6)))) -> 1 | C95: =1+IF($G$7=$E$7,$F$7,IF(Q95<($F$7-$E$7)/($G$7-$E$7),$E$7+SQRT(Q95*($G$7-$E$7)*($F$7-$E$7)),$G$7-SQRT((1-Q95)*($G$7-$E$7)*($G$7-$F$7)))) -> 1 | D95: =1+IF($G$8=$E$8,$F$8,IF(R95<($F$8-$E$8)/($G$8-$E$8),$E$8+SQRT(R95*($G$8-$E$8)*($F$8-$E$8)),$G$8-SQRT((1-R95)*($G$8-$E$8)*($G$8-$F$8)))) -> 1 | E95: =1+IF($G$9=$E$9,$F$9,IF(S95<($F$9-$E$9)/($G$9-$E$9),$E$9+SQRT(S95*($G$9-$E$9)*($F$9-$E$9)),$G$9-SQRT((1-S95)*($G$9-$E$9)*($G$9-$F$9)))) -> 1 | F95: =1+IF($G$10=$E$10,$F$10,IF(T95<($F$10-$E$10)/($G$10-$E$10),$E$10+SQRT(T95*($G$10-$E$10)*($F$10-$E$10)),$G$10-SQRT((1-T95)*($G$10-$E$10)*($G$10-$F$10)))) -> 1 | G95: =IF($G$11=$E$11,$F$11,IF(U95<($F$11-$E$11)/($G$11-$E$11),$E$11+SQRT(U95*($G$11-$E$11)*($F$11-$E$11)),$G$11-SQRT((1-U95)*($G$11-$E$11)*($G$11-$F$11)))) -> 0 | H95: =(('Business Case'!B11*$C95*'Business Case'!B12*$B95)-'Business Case'!B11*$C95*'Business Case'!B13*$D95-'Business Case'!B14*$E95)-MAX(0,(('Business Case'!B11*$C95*'Business Case'!B12*$B95)-'Business Case'!B11*$C95*'Business Case'!B13*$D95-'Business Case'!B14*$E95))*'Business Case'!$B$7-'Business Case'!$B$8*('Business Case'!B11*$C95*'Business Case'!B12*$B95)-'Business Case'!B15*$F95 -> 0 | I95: =(('Business Case'!C11*$C95*'Business Case'!C12*$B95)-'Business Case'!C11*$C95*'Business Case'!C13*$D95-'Business Case'!C14*$E95)-MAX(0,(('Business Case'!C11*$C95*'Business Case'!C12*$B95)-'Business Case'!C11*$C95*'Business Case'!C13*$D95-'Business Case'!C14*$E95))*'Business Case'!$B$7-'Business Case'!$B$8*(('Business Case'!C11*$C95*'Business Case'!C12*$B95)-('Business Case'!B11*$C95*'Business Case'!B12*$B95))-'Business Case'!C15*$F95 -> 0 | J95: =(('Business Case'!D11*$C95*'Business Case'!D12*$B95)-'Business Case'!D11*$C95*'Business Case'!D13*$D95-'Business Case'!D14*$E95)-MAX(0,(('Business Case'!D11*$C95*'Business Case'!D12*$B95)-'Business Case'!D11*$C95*'Business Case'!D13*$D95-'Business Case'!D14*$E95))*'Business Case'!$B$7-'Business Case'!$B$8*(('Business Case'!D11*$C95*'Business Case'!D12*$B95)-('Business Case'!C11*$C95*'Business Case'!C12*$B95))-'Business Case'!D15*$F95 -> 0 | K95: =(('Business Case'!E11*$C95*'Business Case'!E12*$B95)-'Business Case'!E11*$C95*'Business Case'!E13*$D95-'Business Case'!E14*$E95)-MAX(0,(('Business Case'!E11*$C95*'Business Case'!E12*$B95)-'Business Case'!E11*$C95*'Business Case'!E13*$D95-'Business Case'!E14*$E95))*'Business Case'!$B$7-'Business Case'!$B$8*(('Business Case'!E11*$C95*'Business Case'!E12*$B95)-('Business Case'!D11*$C95*'Business Case'!D12*$B95))-'Business Case'!E15*$F95 -> 0 | L95: =(('Business Case'!F11*$C95*'Business Case'!F12*$B95)-'Business Case'!F11*$C95*'Business Case'!F13*$D95-'Business Case'!F14*$E95)-MAX(0,(('Business Case'!F11*$C95*'Business Case'!F12*$B95)-'Business Case'!F11*$C95*'Business Case'!F13*$D95-'Business Case'!F14*$E95))*'Business Case'!$B$7-'Business Case'!$B$8*(('Business Case'!F11*$C95*'Business Case'!F12*$B95)-('Business Case'!E11*$C95*'Business Case'!E12*$B95))-'Business Case'!F15*$F95 -> 0 | M95: =(('Business Case'!G11*$C95*'Business Case'!G12*$B95)-'Business Case'!G11*$C95*'Business Case'!G13*$D95-'Business Case'!G14*$E95)-MAX(0,(('Business Case'!G11*$C95*'Business Case'!G12*$B95)-'Business Case'!G11*$C95*'Business Case'!G13*$D95-'Business Case'!G14*$E95))*'Business Case'!$B$7-'Business Case'!$B$8*(('Business Case'!G11*$C95*'Business Case'!G12*$B95)-('Business Case'!F11*$C95*'Business Case'!F12*$B95))-'Business Case'!G15*$F95+'Business Case'!$B$8*('Business Case'!G11*$C95*'Business Case'!G12*$B95) -> 0 | N95: =IF(COUNT('Business Case'!B11:G11)=0,"",H95+NPV(G95,I95:M95)) | P95: =RAND() -> 0.32329068 | Q95: =RAND() -> 0.27932004 | R95: =RAND() -> 0.76691261 | S95: =RAND() -> 0.8543202 | T95: =RAND() -> 0.13099015 | U95: =RAND() -> 0.34247441
A96: 16 | B96: =1+IF($G$6=$E$6,$F$6,IF(P96<($F$6-$E$6)/($G$6-$E$6),$E$6+SQRT(P96*($G$6-$E$6)*($F$6-$E$6)),$G$6-SQRT((1-P96)*($G$6-$E$6)*($G$6-$F$6)))) -> 1 | C96: =1+IF($G$7=$E$7,$F$7,IF(Q96<($F$7-$E$7)/($G$7-$E$7),$E$7+SQRT(Q96*($G$7-$E$7)*($F$7-$E$7)),$G$7-SQRT((1-Q96)*($G$7-$E$7)*($G$7-$F$7)))) -> 1 | D96: =1+IF($G$8=$E$8,$F$8,IF(R96<($F$8-$E$8)/($G$8-$E$8),$E$8+SQRT(R96*($G$8-$E$8)*($F$8-$E$8)),$G$8-SQRT((1-R96)*($G$8-$E$8)*($G$8-$F$8)))) -> 1 | E96: =1+IF($G$9=$E$9,$F$9,IF(S96<($F$9-$E$9)/($G$9-$E$9),$E$9+SQRT(S96*($G$9-$E$9)*($F$9-$E$9)),$G$9-SQRT((1-S96)*($G$9-$E$9)*($G$9-$F$9)))) -> 1 | F96: =1+IF($G$10=$E$10,$F$10,IF(T96<($F$10-$E$10)/($G$10-$E$10),$E$10+SQRT(T96*($G$10-$E$10)*($F$10-$E$10)),$G$10-SQRT((1-T96)*($G$10-$E$10)*($G$10-$F$10)))) -> 1 | G96: =IF($G$11=$E$11,$F$11,IF(U96<($F$11-$E$11)/($G$11-$E$11),$E$11+SQRT(U96*($G$11-$E$11)*($F$11-$E$11)),$G$11-SQRT((1-U96)*($G$11-$E$11)*($G$11-$F$11)))) -> 0 | H96: =(('Business Case'!B11*$C96*'Business Case'!B12*$B96)-'Business Case'!B11*$C96*'Business Case'!B13*$D96-'Business Case'!B14*$E96)-MAX(0,(('Business Case'!B11*$C96*'Business Case'!B12*$B96)-'Business Case'!B11*$C96*'Business Case'!B13*$D96-'Business Case'!B14*$E96))*'Business Case'!$B$7-'Business Case'!$B$8*('Business Case'!B11*$C96*'Business Case'!B12*$B96)-'Business Case'!B15*$F96 -> 0 | I96: =(('Business Case'!C11*$C96*'Business Case'!C12*$B96)-'Business Case'!C11*$C96*'Business Case'!C13*$D96-'Business Case'!C14*$E96)-MAX(0,(('Business Case'!C11*$C96*'Business Case'!C12*$B96)-'Business Case'!C11*$C96*'Business Case'!C13*$D96-'Business Case'!C14*$E96))*'Business Case'!$B$7-'Business Case'!$B$8*(('Business Case'!C11*$C96*'Business Case'!C12*$B96)-('Business Case'!B11*$C96*'Business Case'!B12*$B96))-'Business Case'!C15*$F96 -> 0 | J96: =(('Business Case'!D11*$C96*'Business Case'!D12*$B96)-'Business Case'!D11*$C96*'Business Case'!D13*$D96-'Business Case'!D14*$E96)-MAX(0,(('Business Case'!D11*$C96*'Business Case'!D12*$B96)-'Business Case'!D11*$C96*'Business Case'!D13*$D96-'Business Case'!D14*$E96))*'Business Case'!$B$7-'Business Case'!$B$8*(('Business Case'!D11*$C96*'Business Case'!D12*$B96)-('Business Case'!C11*$C96*'Business Case'!C12*$B96))-'Business Case'!D15*$F96 -> 0 | K96: =(('Business Case'!E11*$C96*'Business Case'!E12*$B96)-'Business Case'!E11*$C96*'Business Case'!E13*$D96-'Business Case'!E14*$E96)-MAX(0,(('Business Case'!E11*$C96*'Business Case'!E12*$B96)-'Business Case'!E11*$C96*'Business Case'!E13*$D96-'Business Case'!E14*$E96))*'Business Case'!$B$7-'Business Case'!$B$8*(('Business Case'!E11*$C96*'Business Case'!E12*$B96)-('Business Case'!D11*$C96*'Business Case'!D12*$B96))-'Business Case'!E15*$F96 -> 0 | L96: =(('Business Case'!F11*$C96*'Business Case'!F12*$B96)-'Business Case'!F11*$C96*'Business Case'!F13*$D96-'Business Case'!F14*$E96)-MAX(0,(('Business Case'!F11*$C96*'Business Case'!F12*$B96)-'Business Case'!F11*$C96*'Business Case'!F13*$D96-'Business Case'!F14*$E96))*'Business Case'!$B$7-'Business Case'!$B$8*(('Business Case'!F11*$C96*'Business Case'!F12*$B96)-('Business Case'!E11*$C96*'Business Case'!E12*$B96))-'Business Case'!F15*$F96 -> 0 | M96: =(('Business Case'!G11*$C96*'Business Case'!G12*$B96)-'Business Case'!G11*$C96*'Business Case'!G13*$D96-'Business Case'!G14*$E96)-MAX(0,(('Business Case'!G11*$C96*'Business Case'!G12*$B96)-'Business Case'!G11*$C96*'Business Case'!G13*$D96-'Business Case'!G14*$E96))*'Business Case'!$B$7-'Business Case'!$B$8*(('Business Case'!G11*$C96*'Business Case'!G12*$B96)-('Business Case'!F11*$C96*'Business Case'!F12*$B96))-'Business Case'!G15*$F96+'Business Case'!$B$8*('Business Case'!G11*$C96*'Business Case'!G12*$B96) -> 0 | N96: =IF(COUNT('Business Case'!B11:G11)=0,"",H96+NPV(G96,I96:M96)) | P96: =RAND() -> 0.72332942 | Q96: =RAND() -> 0.78697021 | R96: =RAND() -> 0.58541409 | S96: =RAND() -> 0.9121441 | T96: =RAND() -> 0.36525638 | U96: =RAND() -> 0.38486318
A97: 17 | B97: =1+IF($G$6=$E$6,$F$6,IF(P97<($F$6-$E$6)/($G$6-$E$6),$E$6+SQRT(P97*($G$6-$E$6)*($F$6-$E$6)),$G$6-SQRT((1-P97)*($G$6-$E$6)*($G$6-$F$6)))) -> 1 | C97: =1+IF($G$7=$E$7,$F$7,IF(Q97<($F$7-$E$7)/($G$7-$E$7),$E$7+SQRT(Q97*($G$7-$E$7)*($F$7-$E$7)),$G$7-SQRT((1-Q97)*($G$7-$E$7)*($G$7-$F$7)))) -> 1 | D97: =1+IF($G$8=$E$8,$F$8,IF(R97<($F$8-$E$8)/($G$8-$E$8),$E$8+SQRT(R97*($G$8-$E$8)*($F$8-$E$8)),$G$8-SQRT((1-R97)*($G$8-$E$8)*($G$8-$F$8)))) -> 1 | E97: =1+IF($G$9=$E$9,$F$9,IF(S97<($F$9-$E$9)/($G$9-$E$9),$E$9+SQRT(S97*($G$9-$E$9)*($F$9-$E$9)),$G$9-SQRT((1-S97)*($G$9-$E$9)*($G$9-$F$9)))) -> 1 | F97: =1+IF($G$10=$E$10,$F$10,IF(T97<($F$10-$E$10)/($G$10-$E$10),$E$10+SQRT(T97*($G$10-$E$10)*($F$10-$E$10)),$G$10-SQRT((1-T97)*($G$10-$E$10)*($G$10-$F$10)))) -> 1 | G97: =IF($G$11=$E$11,$F$11,IF(U97<($F$11-$E$11)/($G$11-$E$11),$E$11+SQRT(U97*($G$11-$E$11)*($F$11-$E$11)),$G$11-SQRT((1-U97)*($G$11-$E$11)*($G$11-$F$11)))) -> 0 | H97: =(('Business Case'!B11*$C97*'Business Case'!B12*$B97)-'Business Case'!B11*$C97*'Business Case'!B13*$D97-'Business Case'!B14*$E97)-MAX(0,(('Business Case'!B11*$C97*'Business Case'!B12*$B97)-'Business Case'!B11*$C97*'Business Case'!B13*$D97-'Business Case'!B14*$E97))*'Business Case'!$B$7-'Business Case'!$B$8*('Business Case'!B11*$C97*'Business Case'!B12*$B97)-'Business Case'!B15*$F97 -> 0 | I97: =(('Business Case'!C11*$C97*'Business Case'!C12*$B97)-'Business Case'!C11*$C97*'Business Case'!C13*$D97-'Business Case'!C14*$E97)-MAX(0,(('Business Case'!C11*$C97*'Business Case'!C12*$B97)-'Business Case'!C11*$C97*'Business Case'!C13*$D97-'Business Case'!C14*$E97))*'Business Case'!$B$7-'Business Case'!$B$8*(('Business Case'!C11*$C97*'Business Case'!C12*$B97)-('Business Case'!B11*$C97*'Business Case'!B12*$B97))-'Business Case'!C15*$F97 -> 0 | J97: =(('Business Case'!D11*$C97*'Business Case'!D12*$B97)-'Business Case'!D11*$C97*'Business Case'!D13*$D97-'Business Case'!D14*$E97)-MAX(0,(('Business Case'!D11*$C97*'Business Case'!D12*$B97)-'Business Case'!D11*$C97*'Business Case'!D13*$D97-'Business Case'!D14*$E97))*'Business Case'!$B$7-'Business Case'!$B$8*(('Business Case'!D11*$C97*'Business Case'!D12*$B97)-('Business Case'!C11*$C97*'Business Case'!C12*$B97))-'Business Case'!D15*$F97 -> 0 | K97: =(('Business Case'!E11*$C97*'Business Case'!E12*$B97)-'Business Case'!E11*$C97*'Business Case'!E13*$D97-'Business Case'!E14*$E97)-MAX(0,(('Business Case'!E11*$C97*'Business Case'!E12*$B97)-'Business Case'!E11*$C97*'Business Case'!E13*$D97-'Business Case'!E14*$E97))*'Business Case'!$B$7-'Business Case'!$B$8*(('Business Case'!E11*$C97*'Business Case'!E12*$B97)-('Business Case'!D11*$C97*'Business Case'!D12*$B97))-'Business Case'!E15*$F97 -> 0 | L97: =(('Business Case'!F11*$C97*'Business Case'!F12*$B97)-'Business Case'!F11*$C97*'Business Case'!F13*$D97-'Business Case'!F14*$E97)-MAX(0,(('Business Case'!F11*$C97*'Business Case'!F12*$B97)-'Business Case'!F11*$C97*'Business Case'!F13*$D97-'Business Case'!F14*$E97))*'Business Case'!$B$7-'Business Case'!$B$8*(('Business Case'!F11*$C97*'Business Case'!F12*$B97)-('Business Case'!E11*$C97*'Business Case'!E12*$B97))-'Business Case'!F15*$F97 -> 0 | M97: =(('Business Case'!G11*$C97*'Business Case'!G12*$B97)-'Business Case'!G11*$C97*'Business Case'!G13*$D97-'Business Case'!G14*$E97)-MAX(0,(('Business Case'!G11*$C97*'Business Case'!G12*$B97)-'Business Case'!G11*$C97*'Business Case'!G13*$D97-'Business Case'!G14*$E97))*'Business Case'!$B$7-'Business Case'!$B$8*(('Business Case'!G11*$C97*'Business Case'!G12*$B97)-('Business Case'!F11*$C97*'Business Case'!F12*$B97))-'Business Case'!G15*$F97+'Business Case'!$B$8*('Business Case'!G11*$C97*'Business Case'!G12*$B97) -> 0 | N97: =IF(COUNT('Business Case'!B11:G11)=0,"",H97+NPV(G97,I97:M97)) | P97: =RAND() -> 0.15425415 | Q97: =RAND() -> 0.68481771 | R97: =RAND() -> 0.96803195 | S97: =RAND() -> 0.23130265 | T97: =RAND() -> 0.91194568 | U97: =RAND() -> 0.51930282
A98: 18 | B98: =1+IF($G$6=$E$6,$F$6,IF(P98<($F$6-$E$6)/($G$6-$E$6),$E$6+SQRT(P98*($G$6-$E$6)*($F$6-$E$6)),$G$6-SQRT((1-P98)*($G$6-$E$6)*($G$6-$F$6)))) -> 1 | C98: =1+IF($G$7=$E$7,$F$7,IF(Q98<($F$7-$E$7)/($G$7-$E$7),$E$7+SQRT(Q98*($G$7-$E$7)*($F$7-$E$7)),$G$7-SQRT((1-Q98)*($G$7-$E$7)*($G$7-$F$7)))) -> 1 | D98: =1+IF($G$8=$E$8,$F$8,IF(R98<($F$8-$E$8)/($G$8-$E$8),$E$8+SQRT(R98*($G$8-$E$8)*($F$8-$E$8)),$G$8-SQRT((1-R98)*($G$8-$E$8)*($G$8-$F$8)))) -> 1 | E98: =1+IF($G$9=$E$9,$F$9,IF(S98<($F$9-$E$9)/($G$9-$E$9),$E$9+SQRT(S98*($G$9-$E$9)*($F$9-$E$9)),$G$9-SQRT((1-S98)*($G$9-$E$9)*($G$9-$F$9)))) -> 1 | F98: =1+IF($G$10=$E$10,$F$10,IF(T98<($F$10-$E$10)/($G$10-$E$10),$E$10+SQRT(T98*($G$10-$E$10)*($F$10-$E$10)),$G$10-SQRT((1-T98)*($G$10-$E$10)*($G$10-$F$10)))) -> 1 | G98: =IF($G$11=$E$11,$F$11,IF(U98<($F$11-$E$11)/($G$11-$E$11),$E$11+SQRT(U98*($G$11-$E$11)*($F$11-$E$11)),$G$11-SQRT((1-U98)*($G$11-$E$11)*($G$11-$F$11)))) -> 0 | H98: =(('Business Case'!B11*$C98*'Business Case'!B12*$B98)-'Business Case'!B11*$C98*'Business Case'!B13*$D98-'Business Case'!B14*$E98)-MAX(0,(('Business Case'!B11*$C98*'Business Case'!B12*$B98)-'Business Case'!B11*$C98*'Business Case'!B13*$D98-'Business Case'!B14*$E98))*'Business Case'!$B$7-'Business Case'!$B$8*('Business Case'!B11*$C98*'Business Case'!B12*$B98)-'Business Case'!B15*$F98 -> 0 | I98: =(('Business Case'!C11*$C98*'Business Case'!C12*$B98)-'Business Case'!C11*$C98*'Business Case'!C13*$D98-'Business Case'!C14*$E98)-MAX(0,(('Business Case'!C11*$C98*'Business Case'!C12*$B98)-'Business Case'!C11*$C98*'Business Case'!C13*$D98-'Business Case'!C14*$E98))*'Business Case'!$B$7-'Business Case'!$B$8*(('Business Case'!C11*$C98*'Business Case'!C12*$B98)-('Business Case'!B11*$C98*'Business Case'!B12*$B98))-'Business Case'!C15*$F98 -> 0 | J98: =(('Business Case'!D11*$C98*'Business Case'!D12*$B98)-'Business Case'!D11*$C98*'Business Case'!D13*$D98-'Business Case'!D14*$E98)-MAX(0,(('Business Case'!D11*$C98*'Business Case'!D12*$B98)-'Business Case'!D11*$C98*'Business Case'!D13*$D98-'Business Case'!D14*$E98))*'Business Case'!$B$7-'Business Case'!$B$8*(('Business Case'!D11*$C98*'Business Case'!D12*$B98)-('Business Case'!C11*$C98*'Business Case'!C12*$B98))-'Business Case'!D15*$F98 -> 0 | K98: =(('Business Case'!E11*$C98*'Business Case'!E12*$B98)-'Business Case'!E11*$C98*'Business Case'!E13*$D98-'Business Case'!E14*$E98)-MAX(0,(('Business Case'!E11*$C98*'Business Case'!E12*$B98)-'Business Case'!E11*$C98*'Business Case'!E13*$D98-'Business Case'!E14*$E98))*'Business Case'!$B$7-'Business Case'!$B$8*(('Business Case'!E11*$C98*'Business Case'!E12*$B98)-('Business Case'!D11*$C98*'Business Case'!D12*$B98))-'Business Case'!E15*$F98 -> 0 | L98: =(('Business Case'!F11*$C98*'Business Case'!F12*$B98)-'Business Case'!F11*$C98*'Business Case'!F13*$D98-'Business Case'!F14*$E98)-MAX(0,(('Business Case'!F11*$C98*'Business Case'!F12*$B98)-'Business Case'!F11*$C98*'Business Case'!F13*$D98-'Business Case'!F14*$E98))*'Business Case'!$B$7-'Business Case'!$B$8*(('Business Case'!F11*$C98*'Business Case'!F12*$B98)-('Business Case'!E11*$C98*'Business Case'!E12*$B98))-'Business Case'!F15*$F98 -> 0 | M98: =(('Business Case'!G11*$C98*'Business Case'!G12*$B98)-'Business Case'!G11*$C98*'Business Case'!G13*$D98-'Business Case'!G14*$E98)-MAX(0,(('Business Case'!G11*$C98*'Business Case'!G12*$B98)-'Business Case'!G11*$C98*'Business Case'!G13*$D98-'Business Case'!G14*$E98))*'Business Case'!$B$7-'Business Case'!$B$8*(('Business Case'!G11*$C98*'Business Case'!G12*$B98)-('Business Case'!F11*$C98*'Business Case'!F12*$B98))-'Business Case'!G15*$F98+'Business Case'!$B$8*('Business Case'!G11*$C98*'Business Case'!G12*$B98) -> 0 | N98: =IF(COUNT('Business Case'!B11:G11)=0,"",H98+NPV(G98,I98:M98)) | P98: =RAND() -> 0.9411991 | Q98: =RAND() -> 0.43221812 | R98: =RAND() -> 0.51993724 | S98: =RAND() -> 0.76079154 | T98: =RAND() -> 0.6924526 | U98: =RAND() -> 0.14515733
A99: 19 | B99: =1+IF($G$6=$E$6,$F$6,IF(P99<($F$6-$E$6)/($G$6-$E$6),$E$6+SQRT(P99*($G$6-$E$6)*($F$6-$E$6)),$G$6-SQRT((1-P99)*($G$6-$E$6)*($G$6-$F$6)))) -> 1 | C99: =1+IF($G$7=$E$7,$F$7,IF(Q99<($F$7-$E$7)/($G$7-$E$7),$E$7+SQRT(Q99*($G$7-$E$7)*($F$7-$E$7)),$G$7-SQRT((1-Q99)*($G$7-$E$7)*($G$7-$F$7)))) -> 1 | D99: =1+IF($G$8=$E$8,$F$8,IF(R99<($F$8-$E$8)/($G$8-$E$8),$E$8+SQRT(R99*($G$8-$E$8)*($F$8-$E$8)),$G$8-SQRT((1-R99)*($G$8-$E$8)*($G$8-$F$8)))) -> 1 | E99: =1+IF($G$9=$E$9,$F$9,IF(S99<($F$9-$E$9)/($G$9-$E$9),$E$9+SQRT(S99*($G$9-$E$9)*($F$9-$E$9)),$G$9-SQRT((1-S99)*($G$9-$E$9)*($G$9-$F$9)))) -> 1 | F99: =1+IF($G$10=$E$10,$F$10,IF(T99<($F$10-$E$10)/($G$10-$E$10),$E$10+SQRT(T99*($G$10-$E$10)*($F$10-$E$10)),$G$10-SQRT((1-T99)*($G$10-$E$10)*($G$10-$F$10)))) -> 1 | G99: =IF($G$11=$E$11,$F$11,IF(U99<($F$11-$E$11)/($G$11-$E$11),$E$11+SQRT(U99*($G$11-$E$11)*($F$11-$E$11)),$G$11-SQRT((1-U99)*($G$11-$E$11)*($G$11-$F$11)))) -> 0 | H99: =(('Business Case'!B11*$C99*'Business Case'!B12*$B99)-'Business Case'!B11*$C99*'Business Case'!B13*$D99-'Business Case'!B14*$E99)-MAX(0,(('Business Case'!B11*$C99*'Business Case'!B12*$B99)-'Business Case'!B11*$C99*'Business Case'!B13*$D99-'Business Case'!B14*$E99))*'Business Case'!$B$7-'Business Case'!$B$8*('Business Case'!B11*$C99*'Business Case'!B12*$B99)-'Business Case'!B15*$F99 -> 0 | I99: =(('Business Case'!C11*$C99*'Business Case'!C12*$B99)-'Business Case'!C11*$C99*'Business Case'!C13*$D99-'Business Case'!C14*$E99)-MAX(0,(('Business Case'!C11*$C99*'Business Case'!C12*$B99)-'Business Case'!C11*$C99*'Business Case'!C13*$D99-'Business Case'!C14*$E99))*'Business Case'!$B$7-'Business Case'!$B$8*(('Business Case'!C11*$C99*'Business Case'!C12*$B99)-('Business Case'!B11*$C99*'Business Case'!B12*$B99))-'Business Case'!C15*$F99 -> 0 | J99: =(('Business Case'!D11*$C99*'Business Case'!D12*$B99)-'Business Case'!D11*$C99*'Business Case'!D13*$D99-'Business Case'!D14*$E99)-MAX(0,(('Business Case'!D11*$C99*'Business Case'!D12*$B99)-'Business Case'!D11*$C99*'Business Case'!D13*$D99-'Business Case'!D14*$E99))*'Business Case'!$B$7-'Business Case'!$B$8*(('Business Case'!D11*$C99*'Business Case'!D12*$B99)-('Business Case'!C11*$C99*'Business Case'!C12*$B99))-'Business Case'!D15*$F99 -> 0 | K99: =(('Business Case'!E11*$C99*'Business Case'!E12*$B99)-'Business Case'!E11*$C99*'Business Case'!E13*$D99-'Business Case'!E14*$E99)-MAX(0,(('Business Case'!E11*$C99*'Business Case'!E12*$B99)-'Business Case'!E11*$C99*'Business Case'!E13*$D99-'Business Case'!E14*$E99))*'Business Case'!$B$7-'Business Case'!$B$8*(('Business Case'!E11*$C99*'Business Case'!E12*$B99)-('Business Case'!D11*$C99*'Business Case'!D12*$B99))-'Business Case'!E15*$F99 -> 0 | L99: =(('Business Case'!F11*$C99*'Business Case'!F12*$B99)-'Business Case'!F11*$C99*'Business Case'!F13*$D99-'Business Case'!F14*$E99)-MAX(0,(('Business Case'!F11*$C99*'Business Case'!F12*$B99)-'Business Case'!F11*$C99*'Business Case'!F13*$D99-'Business Case'!F14*$E99))*'Business Case'!$B$7-'Business Case'!$B$8*(('Business Case'!F11*$C99*'Business Case'!F12*$B99)-('Business Case'!E11*$C99*'Business Case'!E12*$B99))-'Business Case'!F15*$F99 -> 0 | M99: =(('Business Case'!G11*$C99*'Business Case'!G12*$B99)-'Business Case'!G11*$C99*'Business Case'!G13*$D99-'Business Case'!G14*$E99)-MAX(0,(('Business Case'!G11*$C99*'Business Case'!G12*$B99)-'Business Case'!G11*$C99*'Business Case'!G13*$D99-'Business Case'!G14*$E99))*'Business Case'!$B$7-'Business Case'!$B$8*(('Business Case'!G11*$C99*'Business Case'!G12*$B99)-('Business Case'!F11*$C99*'Business Case'!F12*$B99))-'Business Case'!G15*$F99+'Business Case'!$B$8*('Business Case'!G11*$C99*'Business Case'!G12*$B99) -> 0 | N99: =IF(COUNT('Business Case'!B11:G11)=0,"",H99+NPV(G99,I99:M99)) | P99: =RAND() -> 0.90822434 | Q99: =RAND() -> 0.4877343 | R99: =RAND() -> 0.7393357 | S99: =RAND() -> 0.43040039 | T99: =RAND() -> 0.19991842 | U99: =RAND() -> 0.88034223
A100: 20 | B100: =1+IF($G$6=$E$6,$F$6,IF(P100<($F$6-$E$6)/($G$6-$E$6),$E$6+SQRT(P100*($G$6-$E$6)*($F$6-$E$6)),$G$6-SQRT((1-P100)*($G$6-$E$6)*($G$6-$F$6)))) -> 1 | C100: =1+IF($G$7=$E$7,$F$7,IF(Q100<($F$7-$E$7)/($G$7-$E$7),$E$7+SQRT(Q100*($G$7-$E$7)*($F$7-$E$7)),$G$7-SQRT((1-Q100)*($G$7-$E$7)*($G$7-$F$7)))) -> 1 | D100: =1+IF($G$8=$E$8,$F$8,IF(R100<($F$8-$E$8)/($G$8-$E$8),$E$8+SQRT(R100*($G$8-$E$8)*($F$8-$E$8)),$G$8-SQRT((1-R100)*($G$8-$E$8)*($G$8-$F$8)))) -> 1 | E100: =1+IF($G$9=$E$9,$F$9,IF(S100<($F$9-$E$9)/($G$9-$E$9),$E$9+SQRT(S100*($G$9-$E$9)*($F$9-$E$9)),$G$9-SQRT((1-S100)*($G$9-$E$9)*($G$9-$F$9)))) -> 1 | F100: =1+IF($G$10=$E$10,$F$10,IF(T100<($F$10-$E$10)/($G$10-$E$10),$E$10+SQRT(T100*($G$10-$E$10)*($F$10-$E$10)),$G$10-SQRT((1-T100)*($G$10-$E$10)*($G$10-$F$10)))) -> 1 | G100: =IF($G$11=$E$11,$F$11,IF(U100<($F$11-$E$11)/($G$11-$E$11),$E$11+SQRT(U100*($G$11-$E$11)*($F$11-$E$11)),$G$11-SQRT((1-U100)*($G$11-$E$11)*($G$11-$F$11)))) -> 0 | H100: =(('Business Case'!B11*$C100*'Business Case'!B12*$B100)-'Business Case'!B11*$C100*'Business Case'!B13*$D100-'Business Case'!B14*$E100)-MAX(0,(('Business Case'!B11*$C100*'Business Case'!B12*$B100)-'Business Case'!B11*$C100*'Business Case'!B13*$D100-'Business Case'!B14*$E100))*'Business Case'!$B$7-'Business Case'!$B$8*('Business Case'!B11*$C100*'Business Case'!B12*$B100)-'Business Case'!B15*$F100 -> 0 | I100: =(('Business Case'!C11*$C100*'Business Case'!C12*$B100)-'Business Case'!C11*$C100*'Business Case'!C13*$D100-'Business Case'!C14*$E100)-MAX(0,(('Business Case'!C11*$C100*'Business Case'!C12*$B100)-'Business Case'!C11*$C100*'Business Case'!C13*$D100-'Business Case'!C14*$E100))*'Business Case'!$B$7-'Business Case'!$B$8*(('Business Case'!C11*$C100*'Business Case'!C12*$B100)-('Business Case'!B11*$C100*'Business Case'!B12*$B100))-'Business Case'!C15*$F100 -> 0 | J100: =(('Business Case'!D11*$C100*'Business Case'!D12*$B100)-'Business Case'!D11*$C100*'Business Case'!D13*$D100-'Business Case'!D14*$E100)-MAX(0,(('Business Case'!D11*$C100*'Business Case'!D12*$B100)-'Business Case'!D11*$C100*'Business Case'!D13*$D100-'Business Case'!D14*$E100))*'Business Case'!$B$7-'Business Case'!$B$8*(('Business Case'!D11*$C100*'Business Case'!D12*$B100)-('Business Case'!C11*$C100*'Business Case'!C12*$B100))-'Business Case'!D15*$F100 -> 0 | K100: =(('Business Case'!E11*$C100*'Business Case'!E12*$B100)-'Business Case'!E11*$C100*'Business Case'!E13*$D100-'Business Case'!E14*$E100)-MAX(0,(('Business Case'!E11*$C100*'Business Case'!E12*$B100)-'Business Case'!E11*$C100*'Business Case'!E13*$D100-'Business Case'!E14*$E100))*'Business Case'!$B$7-'Business Case'!$B$8*(('Business Case'!E11*$C100*'Business Case'!E12*$B100)-('Business Case'!D11*$C100*'Business Case'!D12*$B100))-'Business Case'!E15*$F100 -> 0 | L100: =(('Business Case'!F11*$C100*'Business Case'!F12*$B100)-'Business Case'!F11*$C100*'Business Case'!F13*$D100-'Business Case'!F14*$E100)-MAX(0,(('Business Case'!F11*$C100*'Business Case'!F12*$B100)-'Business Case'!F11*$C100*'Business Case'!F13*$D100-'Business Case'!F14*$E100))*'Business Case'!$B$7-'Business Case'!$B$8*(('Business Case'!F11*$C100*'Business Case'!F12*$B100)-('Business Case'!E11*$C100*'Business Case'!E12*$B100))-'Business Case'!F15*$F100 -> 0 | M100: =(('Business Case'!G11*$C100*'Business Case'!G12*$B100)-'Business Case'!G11*$C100*'Business Case'!G13*$D100-'Business Case'!G14*$E100)-MAX(0,(('Business Case'!G11*$C100*'Business Case'!G12*$B100)-'Business Case'!G11*$C100*'Business Case'!G13*$D100-'Business Case'!G14*$E100))*'Business Case'!$B$7-'Business Case'!$B$8*(('Business Case'!G11*$C100*'Business Case'!G12*$B100)-('Business Case'!F11*$C100*'Business Case'!F12*$B100))-'Business Case'!G15*$F100+'Business Case'!$B$8*('Business Case'!G11*$C100*'Business Case'!G12*$B100) -> 0 | N100: =IF(COUNT('Business Case'!B11:G11)=0,"",H100+NPV(G100,I100:M100)) | P100: =RAND() -> 0.19695972 | Q100: =RAND() -> 0.70025761 | R100: =RAND() -> 0.95232954 | S100: =RAND() -> 0.77083378 | T100: =RAND() -> 0.62949656 | U100: =RAND() -> 0.55456667
A101: 21 | B101: =1+IF($G$6=$E$6,$F$6,IF(P101<($F$6-$E$6)/($G$6-$E$6),$E$6+SQRT(P101*($G$6-$E$6)*($F$6-$E$6)),$G$6-SQRT((1-P101)*($G$6-$E$6)*($G$6-$F$6)))) -> 1 | C101: =1+IF($G$7=$E$7,$F$7,IF(Q101<($F$7-$E$7)/($G$7-$E$7),$E$7+SQRT(Q101*($G$7-$E$7)*($F$7-$E$7)),$G$7-SQRT((1-Q101)*($G$7-$E$7)*($G$7-$F$7)))) -> 1 | D101: =1+IF($G$8=$E$8,$F$8,IF(R101<($F$8-$E$8)/($G$8-$E$8),$E$8+SQRT(R101*($G$8-$E$8)*($F$8-$E$8)),$G$8-SQRT((1-R101)*($G$8-$E$8)*($G$8-$F$8)))) -> 1 | E101: =1+IF($G$9=$E$9,$F$9,IF(S101<($F$9-$E$9)/($G$9-$E$9),$E$9+SQRT(S101*($G$9-$E$9)*($F$9-$E$9)),$G$9-SQRT((1-S101)*($G$9-$E$9)*($G$9-$F$9)))) -> 1 | F101: =1+IF($G$10=$E$10,$F$10,IF(T101<($F$10-$E$10)/($G$10-$E$10),$E$10+SQRT(T101*($G$10-$E$10)*($F$10-$E$10)),$G$10-SQRT((1-T101)*($G$10-$E$10)*($G$10-$F$10)))) -> 1 | G101: =IF($G$11=$E$11,$F$11,IF(U101<($F$11-$E$11)/($G$11-$E$11),$E$11+SQRT(U101*($G$11-$E$11)*($F$11-$E$11)),$G$11-SQRT((1-U101)*($G$11-$E$11)*($G$11-$F$11)))) -> 0 | H101: =(('Business Case'!B11*$C101*'Business Case'!B12*$B101)-'Business Case'!B11*$C101*'Business Case'!B13*$D101-'Business Case'!B14*$E101)-MAX(0,(('Business Case'!B11*$C101*'Business Case'!B12*$B101)-'Business Case'!B11*$C101*'Business Case'!B13*$D101-'Business Case'!B14*$E101))*'Business Case'!$B$7-'Business Case'!$B$8*('Business Case'!B11*$C101*'Business Case'!B12*$B101)-'Business Case'!B15*$F101 -> 0 | I101: =(('Business Case'!C11*$C101*'Business Case'!C12*$B101)-'Business Case'!C11*$C101*'Business Case'!C13*$D101-'Business Case'!C14*$E101)-MAX(0,(('Business Case'!C11*$C101*'Business Case'!C12*$B101)-'Business Case'!C11*$C101*'Business Case'!C13*$D101-'Business Case'!C14*$E101))*'Business Case'!$B$7-'Business Case'!$B$8*(('Business Case'!C11*$C101*'Business Case'!C12*$B101)-('Business Case'!B11*$C101*'Business Case'!B12*$B101))-'Business Case'!C15*$F101 -> 0 | J101: =(('Business Case'!D11*$C101*'Business Case'!D12*$B101)-'Business Case'!D11*$C101*'Business Case'!D13*$D101-'Business Case'!D14*$E101)-MAX(0,(('Business Case'!D11*$C101*'Business Case'!D12*$B101)-'Business Case'!D11*$C101*'Business Case'!D13*$D101-'Business Case'!D14*$E101))*'Business Case'!$B$7-'Business Case'!$B$8*(('Business Case'!D11*$C101*'Business Case'!D12*$B101)-('Business Case'!C11*$C101*'Business Case'!C12*$B101))-'Business Case'!D15*$F101 -> 0 | K101: =(('Business Case'!E11*$C101*'Business Case'!E12*$B101)-'Business Case'!E11*$C101*'Business Case'!E13*$D101-'Business Case'!E14*$E101)-MAX(0,(('Business Case'!E11*$C101*'Business Case'!E12*$B101)-'Business Case'!E11*$C101*'Business Case'!E13*$D101-'Business Case'!E14*$E101))*'Business Case'!$B$7-'Business Case'!$B$8*(('Business Case'!E11*$C101*'Business Case'!E12*$B101)-('Business Case'!D11*$C101*'Business Case'!D12*$B101))-'Business Case'!E15*$F101 -> 0 | L101: =(('Business Case'!F11*$C101*'Business Case'!F12*$B101)-'Business Case'!F11*$C101*'Business Case'!F13*$D101-'Business Case'!F14*$E101)-MAX(0,(('Business Case'!F11*$C101*'Business Case'!F12*$B101)-'Business Case'!F11*$C101*'Business Case'!F13*$D101-'Business Case'!F14*$E101))*'Business Case'!$B$7-'Business Case'!$B$8*(('Business Case'!F11*$C101*'Business Case'!F12*$B101)-('Business Case'!E11*$C101*'Business Case'!E12*$B101))-'Business Case'!F15*$F101 -> 0 | M101: =(('Business Case'!G11*$C101*'Business Case'!G12*$B101)-'Business Case'!G11*$C101*'Business Case'!G13*$D101-'Business Case'!G14*$E101)-MAX(0,(('Business Case'!G11*$C101*'Business Case'!G12*$B101)-'Business Case'!G11*$C101*'Business Case'!G13*$D101-'Business Case'!G14*$E101))*'Business Case'!$B$7-'Business Case'!$B$8*(('Business Case'!G11*$C101*'Business Case'!G12*$B101)-('Business Case'!F11*$C101*'Business Case'!F12*$B101))-'Business Case'!G15*$F101+'Business Case'!$B$8*('Business Case'!G11*$C101*'Business Case'!G12*$B101) -> 0 | N101: =IF(COUNT('Business Case'!B11:G11)=0,"",H101+NPV(G101,I101:M101)) | P101: =RAND() -> 0.14550135 | Q101: =RAND() -> 0.62036777 | R101: =RAND() -> 0.16875926 | S101: =RAND() -> 0.28388178 | T101: =RAND() -> 0.0044753417 | U101: =RAND() -> 0.87240386
A102: 22 | B102: =1+IF($G$6=$E$6,$F$6,IF(P102<($F$6-$E$6)/($G$6-$E$6),$E$6+SQRT(P102*($G$6-$E$6)*($F$6-$E$6)),$G$6-SQRT((1-P102)*($G$6-$E$6)*($G$6-$F$6)))) -> 1 | C102: =1+IF($G$7=$E$7,$F$7,IF(Q102<($F$7-$E$7)/($G$7-$E$7),$E$7+SQRT(Q102*($G$7-$E$7)*($F$7-$E$7)),$G$7-SQRT((1-Q102)*($G$7-$E$7)*($G$7-$F$7)))) -> 1 | D102: =1+IF($G$8=$E$8,$F$8,IF(R102<($F$8-$E$8)/($G$8-$E$8),$E$8+SQRT(R102*($G$8-$E$8)*($F$8-$E$8)),$G$8-SQRT((1-R102)*($G$8-$E$8)*($G$8-$F$8)))) -> 1 | E102: =1+IF($G$9=$E$9,$F$9,IF(S102<($F$9-$E$9)/($G$9-$E$9),$E$9+SQRT(S102*($G$9-$E$9)*($F$9-$E$9)),$G$9-SQRT((1-S102)*($G$9-$E$9)*($G$9-$F$9)))) -> 1 | F102: =1+IF($G$10=$E$10,$F$10,IF(T102<($F$10-$E$10)/($G$10-$E$10),$E$10+SQRT(T102*($G$10-$E$10)*($F$10-$E$10)),$G$10-SQRT((1-T102)*($G$10-$E$10)*($G$10-$F$10)))) -> 1 | G102: =IF($G$11=$E$11,$F$11,IF(U102<($F$11-$E$11)/($G$11-$E$11),$E$11+SQRT(U102*($G$11-$E$11)*($F$11-$E$11)),$G$11-SQRT((1-U102)*($G$11-$E$11)*($G$11-$F$11)))) -> 0 | H102: =(('Business Case'!B11*$C102*'Business Case'!B12*$B102)-'Business Case'!B11*$C102*'Business Case'!B13*$D102-'Business Case'!B14*$E102)-MAX(0,(('Business Case'!B11*$C102*'Business Case'!B12*$B102)-'Business Case'!B11*$C102*'Business Case'!B13*$D102-'Business Case'!B14*$E102))*'Business Case'!$B$7-'Business Case'!$B$8*('Business Case'!B11*$C102*'Business Case'!B12*$B102)-'Business Case'!B15*$F102 -> 0 | I102: =(('Business Case'!C11*$C102*'Business Case'!C12*$B102)-'Business Case'!C11*$C102*'Business Case'!C13*$D102-'Business Case'!C14*$E102)-MAX(0,(('Business Case'!C11*$C102*'Business Case'!C12*$B102)-'Business Case'!C11*$C102*'Business Case'!C13*$D102-'Business Case'!C14*$E102))*'Business Case'!$B$7-'Business Case'!$B$8*(('Business Case'!C11*$C102*'Business Case'!C12*$B102)-('Business Case'!B11*$C102*'Business Case'!B12*$B102))-'Business Case'!C15*$F102 -> 0 | J102: =(('Business Case'!D11*$C102*'Business Case'!D12*$B102)-'Business Case'!D11*$C102*'Business Case'!D13*$D102-'Business Case'!D14*$E102)-MAX(0,(('Business Case'!D11*$C102*'Business Case'!D12*$B102)-'Business Case'!D11*$C102*'Business Case'!D13*$D102-'Business Case'!D14*$E102))*'Business Case'!$B$7-'Business Case'!$B$8*(('Business Case'!D11*$C102*'Business Case'!D12*$B102)-('Business Case'!C11*$C102*'Business Case'!C12*$B102))-'Business Case'!D15*$F102 -> 0 | K102: =(('Business Case'!E11*$C102*'Business Case'!E12*$B102)-'Business Case'!E11*$C102*'Business Case'!E13*$D102-'Business Case'!E14*$E102)-MAX(0,(('Business Case'!E11*$C102*'Business Case'!E12*$B102)-'Business Case'!E11*$C102*'Business Case'!E13*$D102-'Business Case'!E14*$E102))*'Business Case'!$B$7-'Business Case'!$B$8*(('Business Case'!E11*$C102*'Business Case'!E12*$B102)-('Business Case'!D11*$C102*'Business Case'!D12*$B102))-'Business Case'!E15*$F102 -> 0 | L102: =(('Business Case'!F11*$C102*'Business Case'!F12*$B102)-'Business Case'!F11*$C102*'Business Case'!F13*$D102-'Business Case'!F14*$E102)-MAX(0,(('Business Case'!F11*$C102*'Business Case'!F12*$B102)-'Business Case'!F11*$C102*'Business Case'!F13*$D102-'Business Case'!F14*$E102))*'Business Case'!$B$7-'Business Case'!$B$8*(('Business Case'!F11*$C102*'Business Case'!F12*$B102)-('Business Case'!E11*$C102*'Business Case'!E12*$B102))-'Business Case'!F15*$F102 -> 0 | M102: =(('Business Case'!G11*$C102*'Business Case'!G12*$B102)-'Business Case'!G11*$C102*'Business Case'!G13*$D102-'Business Case'!G14*$E102)-MAX(0,(('Business Case'!G11*$C102*'Business Case'!G12*$B102)-'Business Case'!G11*$C102*'Business Case'!G13*$D102-'Business Case'!G14*$E102))*'Business Case'!$B$7-'Business Case'!$B$8*(('Business Case'!G11*$C102*'Business Case'!G12*$B102)-('Business Case'!F11*$C102*'Business Case'!F12*$B102))-'Business Case'!G15*$F102+'Business Case'!$B$8*('Business Case'!G11*$C102*'Business Case'!G12*$B102) -> 0 | N102: =IF(COUNT('Business Case'!B11:G11)=0,"",H102+NPV(G102,I102:M102)) | P102: =RAND() -> 0.23061845 | Q102: =RAND() -> 0.3746841 | R102: =RAND() -> 0.81333008 | S102: =RAND() -> 0.83166153 | T102: =RAND() -> 0.53303167 | U102: =RAND() -> 0.89889299
A103: 23 | B103: =1+IF($G$6=$E$6,$F$6,IF(P103<($F$6-$E$6)/($G$6-$E$6),$E$6+SQRT(P103*($G$6-$E$6)*($F$6-$E$6)),$G$6-SQRT((1-P103)*($G$6-$E$6)*($G$6-$F$6)))) -> 1 | C103: =1+IF($G$7=$E$7,$F$7,IF(Q103<($F$7-$E$7)/($G$7-$E$7),$E$7+SQRT(Q103*($G$7-$E$7)*($F$7-$E$7)),$G$7-SQRT((1-Q103)*($G$7-$E$7)*($G$7-$F$7)))) -> 1 | D103: =1+IF($G$8=$E$8,$F$8,IF(R103<($F$8-$E$8)/($G$8-$E$8),$E$8+SQRT(R103*($G$8-$E$8)*($F$8-$E$8)),$G$8-SQRT((1-R103)*($G$8-$E$8)*($G$8-$F$8)))) -> 1 | E103: =1+IF($G$9=$E$9,$F$9,IF(S103<($F$9-$E$9)/($G$9-$E$9),$E$9+SQRT(S103*($G$9-$E$9)*($F$9-$E$9)),$G$9-SQRT((1-S103)*($G$9-$E$9)*($G$9-$F$9)))) -> 1 | F103: =1+IF($G$10=$E$10,$F$10,IF(T103<($F$10-$E$10)/($G$10-$E$10),$E$10+SQRT(T103*($G$10-$E$10)*($F$10-$E$10)),$G$10-SQRT((1-T103)*($G$10-$E$10)*($G$10-$F$10)))) -> 1 | G103: =IF($G$11=$E$11,$F$11,IF(U103<($F$11-$E$11)/($G$11-$E$11),$E$11+SQRT(U103*($G$11-$E$11)*($F$11-$E$11)),$G$11-SQRT((1-U103)*($G$11-$E$11)*($G$11-$F$11)))) -> 0 | H103: =(('Business Case'!B11*$C103*'Business Case'!B12*$B103)-'Business Case'!B11*$C103*'Business Case'!B13*$D103-'Business Case'!B14*$E103)-MAX(0,(('Business Case'!B11*$C103*'Business Case'!B12*$B103)-'Business Case'!B11*$C103*'Business Case'!B13*$D103-'Business Case'!B14*$E103))*'Business Case'!$B$7-'Business Case'!$B$8*('Business Case'!B11*$C103*'Business Case'!B12*$B103)-'Business Case'!B15*$F103 -> 0 | I103: =(('Business Case'!C11*$C103*'Business Case'!C12*$B103)-'Business Case'!C11*$C103*'Business Case'!C13*$D103-'Business Case'!C14*$E103)-MAX(0,(('Business Case'!C11*$C103*'Business Case'!C12*$B103)-'Business Case'!C11*$C103*'Business Case'!C13*$D103-'Business Case'!C14*$E103))*'Business Case'!$B$7-'Business Case'!$B$8*(('Business Case'!C11*$C103*'Business Case'!C12*$B103)-('Business Case'!B11*$C103*'Business Case'!B12*$B103))-'Business Case'!C15*$F103 -> 0 | J103: =(('Business Case'!D11*$C103*'Business Case'!D12*$B103)-'Business Case'!D11*$C103*'Business Case'!D13*$D103-'Business Case'!D14*$E103)-MAX(0,(('Business Case'!D11*$C103*'Business Case'!D12*$B103)-'Business Case'!D11*$C103*'Business Case'!D13*$D103-'Business Case'!D14*$E103))*'Business Case'!$B$7-'Business Case'!$B$8*(('Business Case'!D11*$C103*'Business Case'!D12*$B103)-('Business Case'!C11*$C103*'Business Case'!C12*$B103))-'Business Case'!D15*$F103 -> 0 | K103: =(('Business Case'!E11*$C103*'Business Case'!E12*$B103)-'Business Case'!E11*$C103*'Business Case'!E13*$D103-'Business Case'!E14*$E103)-MAX(0,(('Business Case'!E11*$C103*'Business Case'!E12*$B103)-'Business Case'!E11*$C103*'Business Case'!E13*$D103-'Business Case'!E14*$E103))*'Business Case'!$B$7-'Business Case'!$B$8*(('Business Case'!E11*$C103*'Business Case'!E12*$B103)-('Business Case'!D11*$C103*'Business Case'!D12*$B103))-'Business Case'!E15*$F103 -> 0 | L103: =(('Business Case'!F11*$C103*'Business Case'!F12*$B103)-'Business Case'!F11*$C103*'Business Case'!F13*$D103-'Business Case'!F14*$E103)-MAX(0,(('Business Case'!F11*$C103*'Business Case'!F12*$B103)-'Business Case'!F11*$C103*'Business Case'!F13*$D103-'Business Case'!F14*$E103))*'Business Case'!$B$7-'Business Case'!$B$8*(('Business Case'!F11*$C103*'Business Case'!F12*$B103)-('Business Case'!E11*$C103*'Business Case'!E12*$B103))-'Business Case'!F15*$F103 -> 0 | M103: =(('Business Case'!G11*$C103*'Business Case'!G12*$B103)-'Business Case'!G11*$C103*'Business Case'!G13*$D103-'Business Case'!G14*$E103)-MAX(0,(('Business Case'!G11*$C103*'Business Case'!G12*$B103)-'Business Case'!G11*$C103*'Business Case'!G13*$D103-'Business Case'!G14*$E103))*'Business Case'!$B$7-'Business Case'!$B$8*(('Business Case'!G11*$C103*'Business Case'!G12*$B103)-('Business Case'!F11*$C103*'Business Case'!F12*$B103))-'Business Case'!G15*$F103+'Business Case'!$B$8*('Business Case'!G11*$C103*'Business Case'!G12*$B103) -> 0 | N103: =IF(COUNT('Business Case'!B11:G11)=0,"",H103+NPV(G103,I103:M103)) | P103: =RAND() -> 0.32356607 | Q103: =RAND() -> 0.06176264 | R103: =RAND() -> 0.89094798 | S103: =RAND() -> 0.21083752 | T103: =RAND() -> 0.019764458 | U103: =RAND() -> 0.35328831
A104: 24 | B104: =1+IF($G$6=$E$6,$F$6,IF(P104<($F$6-$E$6)/($G$6-$E$6),$E$6+SQRT(P104*($G$6-$E$6)*($F$6-$E$6)),$G$6-SQRT((1-P104)*($G$6-$E$6)*($G$6-$F$6)))) -> 1 | C104: =1+IF($G$7=$E$7,$F$7,IF(Q104<($F$7-$E$7)/($G$7-$E$7),$E$7+SQRT(Q104*($G$7-$E$7)*($F$7-$E$7)),$G$7-SQRT((1-Q104)*($G$7-$E$7)*($G$7-$F$7)))) -> 1 | D104: =1+IF($G$8=$E$8,$F$8,IF(R104<($F$8-$E$8)/($G$8-$E$8),$E$8+SQRT(R104*($G$8-$E$8)*($F$8-$E$8)),$G$8-SQRT((1-R104)*($G$8-$E$8)*($G$8-$F$8)))) -> 1 | E104: =1+IF($G$9=$E$9,$F$9,IF(S104<($F$9-$E$9)/($G$9-$E$9),$E$9+SQRT(S104*($G$9-$E$9)*($F$9-$E$9)),$G$9-SQRT((1-S104)*($G$9-$E$9)*($G$9-$F$9)))) -> 1 | F104: =1+IF($G$10=$E$10,$F$10,IF(T104<($F$10-$E$10)/($G$10-$E$10),$E$10+SQRT(T104*($G$10-$E$10)*($F$10-$E$10)),$G$10-SQRT((1-T104)*($G$10-$E$10)*($G$10-$F$10)))) -> 1 | G104: =IF($G$11=$E$11,$F$11,IF(U104<($F$11-$E$11)/($G$11-$E$11),$E$11+SQRT(U104*($G$11-$E$11)*($F$11-$E$11)),$G$11-SQRT((1-U104)*($G$11-$E$11)*($G$11-$F$11)))) -> 0 | H104: =(('Business Case'!B11*$C104*'Business Case'!B12*$B104)-'Business Case'!B11*$C104*'Business Case'!B13*$D104-'Business Case'!B14*$E104)-MAX(0,(('Business Case'!B11*$C104*'Business Case'!B12*$B104)-'Business Case'!B11*$C104*'Business Case'!B13*$D104-'Business Case'!B14*$E104))*'Business Case'!$B$7-'Business Case'!$B$8*('Business Case'!B11*$C104*'Business Case'!B12*$B104)-'Business Case'!B15*$F104 -> 0 | I104: =(('Business Case'!C11*$C104*'Business Case'!C12*$B104)-'Business Case'!C11*$C104*'Business Case'!C13*$D104-'Business Case'!C14*$E104)-MAX(0,(('Business Case'!C11*$C104*'Business Case'!C12*$B104)-'Business Case'!C11*$C104*'Business Case'!C13*$D104-'Business Case'!C14*$E104))*'Business Case'!$B$7-'Business Case'!$B$8*(('Business Case'!C11*$C104*'Business Case'!C12*$B104)-('Business Case'!B11*$C104*'Business Case'!B12*$B104))-'Business Case'!C15*$F104 -> 0 | J104: =(('Business Case'!D11*$C104*'Business Case'!D12*$B104)-'Business Case'!D11*$C104*'Business Case'!D13*$D104-'Business Case'!D14*$E104)-MAX(0,(('Business Case'!D11*$C104*'Business Case'!D12*$B104)-'Business Case'!D11*$C104*'Business Case'!D13*$D104-'Business Case'!D14*$E104))*'Business Case'!$B$7-'Business Case'!$B$8*(('Business Case'!D11*$C104*'Business Case'!D12*$B104)-('Business Case'!C11*$C104*'Business Case'!C12*$B104))-'Business Case'!D15*$F104 -> 0 | K104: =(('Business Case'!E11*$C104*'Business Case'!E12*$B104)-'Business Case'!E11*$C104*'Business Case'!E13*$D104-'Business Case'!E14*$E104)-MAX(0,(('Business Case'!E11*$C104*'Business Case'!E12*$B104)-'Business Case'!E11*$C104*'Business Case'!E13*$D104-'Business Case'!E14*$E104))*'Business Case'!$B$7-'Business Case'!$B$8*(('Business Case'!E11*$C104*'Business Case'!E12*$B104)-('Business Case'!D11*$C104*'Business Case'!D12*$B104))-'Business Case'!E15*$F104 -> 0 | L104: =(('Business Case'!F11*$C104*'Business Case'!F12*$B104)-'Business Case'!F11*$C104*'Business Case'!F13*$D104-'Business Case'!F14*$E104)-MAX(0,(('Business Case'!F11*$C104*'Business Case'!F12*$B104)-'Business Case'!F11*$C104*'Business Case'!F13*$D104-'Business Case'!F14*$E104))*'Business Case'!$B$7-'Business Case'!$B$8*(('Business Case'!F11*$C104*'Business Case'!F12*$B104)-('Business Case'!E11*$C104*'Business Case'!E12*$B104))-'Business Case'!F15*$F104 -> 0 | M104: =(('Business Case'!G11*$C104*'Business Case'!G12*$B104)-'Business Case'!G11*$C104*'Business Case'!G13*$D104-'Business Case'!G14*$E104)-MAX(0,(('Business Case'!G11*$C104*'Business Case'!G12*$B104)-'Business Case'!G11*$C104*'Business Case'!G13*$D104-'Business Case'!G14*$E104))*'Business Case'!$B$7-'Business Case'!$B$8*(('Business Case'!G11*$C104*'Business Case'!G12*$B104)-('Business Case'!F11*$C104*'Business Case'!F12*$B104))-'Business Case'!G15*$F104+'Business Case'!$B$8*('Business Case'!G11*$C104*'Business Case'!G12*$B104) -> 0 | N104: =IF(COUNT('Business Case'!B11:G11)=0,"",H104+NPV(G104,I104:M104)) | P104: =RAND() -> 0.13184955 | Q104: =RAND() -> 0.27808395 | R104: =RAND() -> 0.81799874 | S104: =RAND() -> 0.99570264 | T104: =RAND() -> 0.42801713 | U104: =RAND() -> 0.079788116
A105: 25 | B105: =1+IF($G$6=$E$6,$F$6,IF(P105<($F$6-$E$6)/($G$6-$E$6),$E$6+SQRT(P105*($G$6-$E$6)*($F$6-$E$6)),$G$6-SQRT((1-P105)*($G$6-$E$6)*($G$6-$F$6)))) -> 1 | C105: =1+IF($G$7=$E$7,$F$7,IF(Q105<($F$7-$E$7)/($G$7-$E$7),$E$7+SQRT(Q105*($G$7-$E$7)*($F$7-$E$7)),$G$7-SQRT((1-Q105)*($G$7-$E$7)*($G$7-$F$7)))) -> 1 | D105: =1+IF($G$8=$E$8,$F$8,IF(R105<($F$8-$E$8)/($G$8-$E$8),$E$8+SQRT(R105*($G$8-$E$8)*($F$8-$E$8)),$G$8-SQRT((1-R105)*($G$8-$E$8)*($G$8-$F$8)))) -> 1 | E105: =1+IF($G$9=$E$9,$F$9,IF(S105<($F$9-$E$9)/($G$9-$E$9),$E$9+SQRT(S105*($G$9-$E$9)*($F$9-$E$9)),$G$9-SQRT((1-S105)*($G$9-$E$9)*($G$9-$F$9)))) -> 1 | F105: =1+IF($G$10=$E$10,$F$10,IF(T105<($F$10-$E$10)/($G$10-$E$10),$E$10+SQRT(T105*($G$10-$E$10)*($F$10-$E$10)),$G$10-SQRT((1-T105)*($G$10-$E$10)*($G$10-$F$10)))) -> 1 | G105: =IF($G$11=$E$11,$F$11,IF(U105<($F$11-$E$11)/($G$11-$E$11),$E$11+SQRT(U105*($G$11-$E$11)*($F$11-$E$11)),$G$11-SQRT((1-U105)*($G$11-$E$11)*($G$11-$F$11)))) -> 0 | H105: =(('Business Case'!B11*$C105*'Business Case'!B12*$B105)-'Business Case'!B11*$C105*'Business Case'!B13*$D105-'Business Case'!B14*$E105)-MAX(0,(('Business Case'!B11*$C105*'Business Case'!B12*$B105)-'Business Case'!B11*$C105*'Business Case'!B13*$D105-'Business Case'!B14*$E105))*'Business Case'!$B$7-'Business Case'!$B$8*('Business Case'!B11*$C105*'Business Case'!B12*$B105)-'Business Case'!B15*$F105 -> 0 | I105: =(('Business Case'!C11*$C105*'Business Case'!C12*$B105)-'Business Case'!C11*$C105*'Business Case'!C13*$D105-'Business Case'!C14*$E105)-MAX(0,(('Business Case'!C11*$C105*'Business Case'!C12*$B105)-'Business Case'!C11*$C105*'Business Case'!C13*$D105-'Business Case'!C14*$E105))*'Business Case'!$B$7-'Business Case'!$B$8*(('Business Case'!C11*$C105*'Business Case'!C12*$B105)-('Business Case'!B11*$C105*'Business Case'!B12*$B105))-'Business Case'!C15*$F105 -> 0 | J105: =(('Business Case'!D11*$C105*'Business Case'!D12*$B105)-'Business Case'!D11*$C105*'Business Case'!D13*$D105-'Business Case'!D14*$E105)-MAX(0,(('Business Case'!D11*$C105*'Business Case'!D12*$B105)-'Business Case'!D11*$C105*'Business Case'!D13*$D105-'Business Case'!D14*$E105))*'Business Case'!$B$7-'Business Case'!$B$8*(('Business Case'!D11*$C105*'Business Case'!D12*$B105)-('Business Case'!C11*$C105*'Business Case'!C12*$B105))-'Business Case'!D15*$F105 -> 0 | K105: =(('Business Case'!E11*$C105*'Business Case'!E12*$B105)-'Business Case'!E11*$C105*'Business Case'!E13*$D105-'Business Case'!E14*$E105)-MAX(0,(('Business Case'!E11*$C105*'Business Case'!E12*$B105)-'Business Case'!E11*$C105*'Business Case'!E13*$D105-'Business Case'!E14*$E105))*'Business Case'!$B$7-'Business Case'!$B$8*(('Business Case'!E11*$C105*'Business Case'!E12*$B105)-('Business Case'!D11*$C105*'Business Case'!D12*$B105))-'Business Case'!E15*$F105 -> 0 | L105: =(('Business Case'!F11*$C105*'Business Case'!F12*$B105)-'Business Case'!F11*$C105*'Business Case'!F13*$D105-'Business Case'!F14*$E105)-MAX(0,(('Business Case'!F11*$C105*'Business Case'!F12*$B105)-'Business Case'!F11*$C105*'Business Case'!F13*$D105-'Business Case'!F14*$E105))*'Business Case'!$B$7-'Business Case'!$B$8*(('Business Case'!F11*$C105*'Business Case'!F12*$B105)-('Business Case'!E11*$C105*'Business Case'!E12*$B105))-'Business Case'!F15*$F105 -> 0 | M105: =(('Business Case'!G11*$C105*'Business Case'!G12*$B105)-'Business Case'!G11*$C105*'Business Case'!G13*$D105-'Business Case'!G14*$E105)-MAX(0,(('Business Case'!G11*$C105*'Business Case'!G12*$B105)-'Business Case'!G11*$C105*'Business Case'!G13*$D105-'Business Case'!G14*$E105))*'Business Case'!$B$7-'Business Case'!$B$8*(('Business Case'!G11*$C105*'Business Case'!G12*$B105)-('Business Case'!F11*$C105*'Business Case'!F12*$B105))-'Business Case'!G15*$F105+'Business Case'!$B$8*('Business Case'!G11*$C105*'Business Case'!G12*$B105) -> 0 | N105: =IF(COUNT('Business Case'!B11:G11)=0,"",H105+NPV(G105,I105:M105)) | P105: =RAND() -> 0.48428049 | Q105: =RAND() -> 0.91699852 | R105: =RAND() -> 0.036644723 | S105: =RAND() -> 0.35812098 | T105: =RAND() -> 0.42992742 | U105: =RAND() -> 0.53452588
A106: 26 | B106: =1+IF($G$6=$E$6,$F$6,IF(P106<($F$6-$E$6)/($G$6-$E$6),$E$6+SQRT(P106*($G$6-$E$6)*($F$6-$E$6)),$G$6-SQRT((1-P106)*($G$6-$E$6)*($G$6-$F$6)))) -> 1 | C106: =1+IF($G$7=$E$7,$F$7,IF(Q106<($F$7-$E$7)/($G$7-$E$7),$E$7+SQRT(Q106*($G$7-$E$7)*($F$7-$E$7)),$G$7-SQRT((1-Q106)*($G$7-$E$7)*($G$7-$F$7)))) -> 1 | D106: =1+IF($G$8=$E$8,$F$8,IF(R106<($F$8-$E$8)/($G$8-$E$8),$E$8+SQRT(R106*($G$8-$E$8)*($F$8-$E$8)),$G$8-SQRT((1-R106)*($G$8-$E$8)*($G$8-$F$8)))) -> 1 | E106: =1+IF($G$9=$E$9,$F$9,IF(S106<($F$9-$E$9)/($G$9-$E$9),$E$9+SQRT(S106*($G$9-$E$9)*($F$9-$E$9)),$G$9-SQRT((1-S106)*($G$9-$E$9)*($G$9-$F$9)))) -> 1 | F106: =1+IF($G$10=$E$10,$F$10,IF(T106<($F$10-$E$10)/($G$10-$E$10),$E$10+SQRT(T106*($G$10-$E$10)*($F$10-$E$10)),$G$10-SQRT((1-T106)*($G$10-$E$10)*($G$10-$F$10)))) -> 1 | G106: =IF($G$11=$E$11,$F$11,IF(U106<($F$11-$E$11)/($G$11-$E$11),$E$11+SQRT(U106*($G$11-$E$11)*($F$11-$E$11)),$G$11-SQRT((1-U106)*($G$11-$E$11)*($G$11-$F$11)))) -> 0 | H106: =(('Business Case'!B11*$C106*'Business Case'!B12*$B106)-'Business Case'!B11*$C106*'Business Case'!B13*$D106-'Business Case'!B14*$E106)-MAX(0,(('Business Case'!B11*$C106*'Business Case'!B12*$B106)-'Business Case'!B11*$C106*'Business Case'!B13*$D106-'Business Case'!B14*$E106))*'Business Case'!$B$7-'Business Case'!$B$8*('Business Case'!B11*$C106*'Business Case'!B12*$B106)-'Business Case'!B15*$F106 -> 0 | I106: =(('Business Case'!C11*$C106*'Business Case'!C12*$B106)-'Business Case'!C11*$C106*'Business Case'!C13*$D106-'Business Case'!C14*$E106)-MAX(0,(('Business Case'!C11*$C106*'Business Case'!C12*$B106)-'Business Case'!C11*$C106*'Business Case'!C13*$D106-'Business Case'!C14*$E106))*'Business Case'!$B$7-'Business Case'!$B$8*(('Business Case'!C11*$C106*'Business Case'!C12*$B106)-('Business Case'!B11*$C106*'Business Case'!B12*$B106))-'Business Case'!C15*$F106 -> 0 | J106: =(('Business Case'!D11*$C106*'Business Case'!D12*$B106)-'Business Case'!D11*$C106*'Business Case'!D13*$D106-'Business Case'!D14*$E106)-MAX(0,(('Business Case'!D11*$C106*'Business Case'!D12*$B106)-'Business Case'!D11*$C106*'Business Case'!D13*$D106-'Business Case'!D14*$E106))*'Business Case'!$B$7-'Business Case'!$B$8*(('Business Case'!D11*$C106*'Business Case'!D12*$B106)-('Business Case'!C11*$C106*'Business Case'!C12*$B106))-'Business Case'!D15*$F106 -> 0 | K106: =(('Business Case'!E11*$C106*'Business Case'!E12*$B106)-'Business Case'!E11*$C106*'Business Case'!E13*$D106-'Business Case'!E14*$E106)-MAX(0,(('Business Case'!E11*$C106*'Business Case'!E12*$B106)-'Business Case'!E11*$C106*'Business Case'!E13*$D106-'Business Case'!E14*$E106))*'Business Case'!$B$7-'Business Case'!$B$8*(('Business Case'!E11*$C106*'Business Case'!E12*$B106)-('Business Case'!D11*$C106*'Business Case'!D12*$B106))-'Business Case'!E15*$F106 -> 0 | L106: =(('Business Case'!F11*$C106*'Business Case'!F12*$B106)-'Business Case'!F11*$C106*'Business Case'!F13*$D106-'Business Case'!F14*$E106)-MAX(0,(('Business Case'!F11*$C106*'Business Case'!F12*$B106)-'Business Case'!F11*$C106*'Business Case'!F13*$D106-'Business Case'!F14*$E106))*'Business Case'!$B$7-'Business Case'!$B$8*(('Business Case'!F11*$C106*'Business Case'!F12*$B106)-('Business Case'!E11*$C106*'Business Case'!E12*$B106))-'Business Case'!F15*$F106 -> 0 | M106: =(('Business Case'!G11*$C106*'Business Case'!G12*$B106)-'Business Case'!G11*$C106*'Business Case'!G13*$D106-'Business Case'!G14*$E106)-MAX(0,(('Business Case'!G11*$C106*'Business Case'!G12*$B106)-'Business Case'!G11*$C106*'Business Case'!G13*$D106-'Business Case'!G14*$E106))*'Business Case'!$B$7-'Business Case'!$B$8*(('Business Case'!G11*$C106*'Business Case'!G12*$B106)-('Business Case'!F11*$C106*'Business Case'!F12*$B106))-'Business Case'!G15*$F106+'Business Case'!$B$8*('Business Case'!G11*$C106*'Business Case'!G12*$B106) -> 0 | N106: =IF(COUNT('Business Case'!B11:G11)=0,"",H106+NPV(G106,I106:M106)) | P106: =RAND() -> 0.40219127 | Q106: =RAND() -> 0.7576495 | R106: =RAND() -> 0.048132195 | S106: =RAND() -> 0.5725203 | T106: =RAND() -> 0.11015511 | U106: =RAND() -> 0.20643485
A107: 27 | B107: =1+IF($G$6=$E$6,$F$6,IF(P107<($F$6-$E$6)/($G$6-$E$6),$E$6+SQRT(P107*($G$6-$E$6)*($F$6-$E$6)),$G$6-SQRT((1-P107)*($G$6-$E$6)*($G$6-$F$6)))) -> 1 | C107: =1+IF($G$7=$E$7,$F$7,IF(Q107<($F$7-$E$7)/($G$7-$E$7),$E$7+SQRT(Q107*($G$7-$E$7)*($F$7-$E$7)),$G$7-SQRT((1-Q107)*($G$7-$E$7)*($G$7-$F$7)))) -> 1 | D107: =1+IF($G$8=$E$8,$F$8,IF(R107<($F$8-$E$8)/($G$8-$E$8),$E$8+SQRT(R107*($G$8-$E$8)*($F$8-$E$8)),$G$8-SQRT((1-R107)*($G$8-$E$8)*($G$8-$F$8)))) -> 1 | E107: =1+IF($G$9=$E$9,$F$9,IF(S107<($F$9-$E$9)/($G$9-$E$9),$E$9+SQRT(S107*($G$9-$E$9)*($F$9-$E$9)),$G$9-SQRT((1-S107)*($G$9-$E$9)*($G$9-$F$9)))) -> 1 | F107: =1+IF($G$10=$E$10,$F$10,IF(T107<($F$10-$E$10)/($G$10-$E$10),$E$10+SQRT(T107*($G$10-$E$10)*($F$10-$E$10)),$G$10-SQRT((1-T107)*($G$10-$E$10)*($G$10-$F$10)))) -> 1 | G107: =IF($G$11=$E$11,$F$11,IF(U107<($F$11-$E$11)/($G$11-$E$11),$E$11+SQRT(U107*($G$11-$E$11)*($F$11-$E$11)),$G$11-SQRT((1-U107)*($G$11-$E$11)*($G$11-$F$11)))) -> 0 | H107: =(('Business Case'!B11*$C107*'Business Case'!B12*$B107)-'Business Case'!B11*$C107*'Business Case'!B13*$D107-'Business Case'!B14*$E107)-MAX(0,(('Business Case'!B11*$C107*'Business Case'!B12*$B107)-'Business Case'!B11*$C107*'Business Case'!B13*$D107-'Business Case'!B14*$E107))*'Business Case'!$B$7-'Business Case'!$B$8*('Business Case'!B11*$C107*'Business Case'!B12*$B107)-'Business Case'!B15*$F107 -> 0 | I107: =(('Business Case'!C11*$C107*'Business Case'!C12*$B107)-'Business Case'!C11*$C107*'Business Case'!C13*$D107-'Business Case'!C14*$E107)-MAX(0,(('Business Case'!C11*$C107*'Business Case'!C12*$B107)-'Business Case'!C11*$C107*'Business Case'!C13*$D107-'Business Case'!C14*$E107))*'Business Case'!$B$7-'Business Case'!$B$8*(('Business Case'!C11*$C107*'Business Case'!C12*$B107)-('Business Case'!B11*$C107*'Business Case'!B12*$B107))-'Business Case'!C15*$F107 -> 0 | J107: =(('Business Case'!D11*$C107*'Business Case'!D12*$B107)-'Business Case'!D11*$C107*'Business Case'!D13*$D107-'Business Case'!D14*$E107)-MAX(0,(('Business Case'!D11*$C107*'Business Case'!D12*$B107)-'Business Case'!D11*$C107*'Business Case'!D13*$D107-'Business Case'!D14*$E107))*'Business Case'!$B$7-'Business Case'!$B$8*(('Business Case'!D11*$C107*'Business Case'!D12*$B107)-('Business Case'!C11*$C107*'Business Case'!C12*$B107))-'Business Case'!D15*$F107 -> 0 | K107: =(('Business Case'!E11*$C107*'Business Case'!E12*$B107)-'Business Case'!E11*$C107*'Business Case'!E13*$D107-'Business Case'!E14*$E107)-MAX(0,(('Business Case'!E11*$C107*'Business Case'!E12*$B107)-'Business Case'!E11*$C107*'Business Case'!E13*$D107-'Business Case'!E14*$E107))*'Business Case'!$B$7-'Business Case'!$B$8*(('Business Case'!E11*$C107*'Business Case'!E12*$B107)-('Business Case'!D11*$C107*'Business Case'!D12*$B107))-'Business Case'!E15*$F107 -> 0 | L107: =(('Business Case'!F11*$C107*'Business Case'!F12*$B107)-'Business Case'!F11*$C107*'Business Case'!F13*$D107-'Business Case'!F14*$E107)-MAX(0,(('Business Case'!F11*$C107*'Business Case'!F12*$B107)-'Business Case'!F11*$C107*'Business Case'!F13*$D107-'Business Case'!F14*$E107))*'Business Case'!$B$7-'Business Case'!$B$8*(('Business Case'!F11*$C107*'Business Case'!F12*$B107)-('Business Case'!E11*$C107*'Business Case'!E12*$B107))-'Business Case'!F15*$F107 -> 0 | M107: =(('Business Case'!G11*$C107*'Business Case'!G12*$B107)-'Business Case'!G11*$C107*'Business Case'!G13*$D107-'Business Case'!G14*$E107)-MAX(0,(('Business Case'!G11*$C107*'Business Case'!G12*$B107)-'Business Case'!G11*$C107*'Business Case'!G13*$D107-'Business Case'!G14*$E107))*'Business Case'!$B$7-'Business Case'!$B$8*(('Business Case'!G11*$C107*'Business Case'!G12*$B107)-('Business Case'!F11*$C107*'Business Case'!F12*$B107))-'Business Case'!G15*$F107+'Business Case'!$B$8*('Business Case'!G11*$C107*'Business Case'!G12*$B107) -> 0 | N107: =IF(COUNT('Business Case'!B11:G11)=0,"",H107+NPV(G107,I107:M107)) | P107: =RAND() -> 0.76924457 | Q107: =RAND() -> 0.11316714 | R107: =RAND() -> 0.036588078 | S107: =RAND() -> 0.68086469 | T107: =RAND() -> 0.066510772 | U107: =RAND() -> 0.33074207
A108: 28 | B108: =1+IF($G$6=$E$6,$F$6,IF(P108<($F$6-$E$6)/($G$6-$E$6),$E$6+SQRT(P108*($G$6-$E$6)*($F$6-$E$6)),$G$6-SQRT((1-P108)*($G$6-$E$6)*($G$6-$F$6)))) -> 1 | C108: =1+IF($G$7=$E$7,$F$7,IF(Q108<($F$7-$E$7)/($G$7-$E$7),$E$7+SQRT(Q108*($G$7-$E$7)*($F$7-$E$7)),$G$7-SQRT((1-Q108)*($G$7-$E$7)*($G$7-$F$7)))) -> 1 | D108: =1+IF($G$8=$E$8,$F$8,IF(R108<($F$8-$E$8)/($G$8-$E$8),$E$8+SQRT(R108*($G$8-$E$8)*($F$8-$E$8)),$G$8-SQRT((1-R108)*($G$8-$E$8)*($G$8-$F$8)))) -> 1 | E108: =1+IF($G$9=$E$9,$F$9,IF(S108<($F$9-$E$9)/($G$9-$E$9),$E$9+SQRT(S108*($G$9-$E$9)*($F$9-$E$9)),$G$9-SQRT((1-S108)*($G$9-$E$9)*($G$9-$F$9)))) -> 1 | F108: =1+IF($G$10=$E$10,$F$10,IF(T108<($F$10-$E$10)/($G$10-$E$10),$E$10+SQRT(T108*($G$10-$E$10)*($F$10-$E$10)),$G$10-SQRT((1-T108)*($G$10-$E$10)*($G$10-$F$10)))) -> 1 | G108: =IF($G$11=$E$11,$F$11,IF(U108<($F$11-$E$11)/($G$11-$E$11),$E$11+SQRT(U108*($G$11-$E$11)*($F$11-$E$11)),$G$11-SQRT((1-U108)*($G$11-$E$11)*($G$11-$F$11)))) -> 0 | H108: =(('Business Case'!B11*$C108*'Business Case'!B12*$B108)-'Business Case'!B11*$C108*'Business Case'!B13*$D108-'Business Case'!B14*$E108)-MAX(0,(('Business Case'!B11*$C108*'Business Case'!B12*$B108)-'Business Case'!B11*$C108*'Business Case'!B13*$D108-'Business Case'!B14*$E108))*'Business Case'!$B$7-'Business Case'!$B$8*('Business Case'!B11*$C108*'Business Case'!B12*$B108)-'Business Case'!B15*$F108 -> 0 | I108: =(('Business Case'!C11*$C108*'Business Case'!C12*$B108)-'Business Case'!C11*$C108*'Business Case'!C13*$D108-'Business Case'!C14*$E108)-MAX(0,(('Business Case'!C11*$C108*'Business Case'!C12*$B108)-'Business Case'!C11*$C108*'Business Case'!C13*$D108-'Business Case'!C14*$E108))*'Business Case'!$B$7-'Business Case'!$B$8*(('Business Case'!C11*$C108*'Business Case'!C12*$B108)-('Business Case'!B11*$C108*'Business Case'!B12*$B108))-'Business Case'!C15*$F108 -> 0 | J108: =(('Business Case'!D11*$C108*'Business Case'!D12*$B108)-'Business Case'!D11*$C108*'Business Case'!D13*$D108-'Business Case'!D14*$E108)-MAX(0,(('Business Case'!D11*$C108*'Business Case'!D12*$B108)-'Business Case'!D11*$C108*'Business Case'!D13*$D108-'Business Case'!D14*$E108))*'Business Case'!$B$7-'Business Case'!$B$8*(('Business Case'!D11*$C108*'Business Case'!D12*$B108)-('Business Case'!C11*$C108*'Business Case'!C12*$B108))-'Business Case'!D15*$F108 -> 0 | K108: =(('Business Case'!E11*$C108*'Business Case'!E12*$B108)-'Business Case'!E11*$C108*'Business Case'!E13*$D108-'Business Case'!E14*$E108)-MAX(0,(('Business Case'!E11*$C108*'Business Case'!E12*$B108)-'Business Case'!E11*$C108*'Business Case'!E13*$D108-'Business Case'!E14*$E108))*'Business Case'!$B$7-'Business Case'!$B$8*(('Business Case'!E11*$C108*'Business Case'!E12*$B108)-('Business Case'!D11*$C108*'Business Case'!D12*$B108))-'Business Case'!E15*$F108 -> 0 | L108: =(('Business Case'!F11*$C108*'Business Case'!F12*$B108)-'Business Case'!F11*$C108*'Business Case'!F13*$D108-'Business Case'!F14*$E108)-MAX(0,(('Business Case'!F11*$C108*'Business Case'!F12*$B108)-'Business Case'!F11*$C108*'Business Case'!F13*$D108-'Business Case'!F14*$E108))*'Business Case'!$B$7-'Business Case'!$B$8*(('Business Case'!F11*$C108*'Business Case'!F12*$B108)-('Business Case'!E11*$C108*'Business Case'!E12*$B108))-'Business Case'!F15*$F108 -> 0 | M108: =(('Business Case'!G11*$C108*'Business Case'!G12*$B108)-'Business Case'!G11*$C108*'Business Case'!G13*$D108-'Business Case'!G14*$E108)-MAX(0,(('Business Case'!G11*$C108*'Business Case'!G12*$B108)-'Business Case'!G11*$C108*'Business Case'!G13*$D108-'Business Case'!G14*$E108))*'Business Case'!$B$7-'Business Case'!$B$8*(('Business Case'!G11*$C108*'Business Case'!G12*$B108)-('Business Case'!F11*$C108*'Business Case'!F12*$B108))-'Business Case'!G15*$F108+'Business Case'!$B$8*('Business Case'!G11*$C108*'Business Case'!G12*$B108) -> 0 | N108: =IF(COUNT('Business Case'!B11:G11)=0,"",H108+NPV(G108,I108:M108)) | P108: =RAND() -> 0.29233701 | Q108: =RAND() -> 0.13122578 | R108: =RAND() -> 0.075043545 | S108: =RAND() -> 0.83435438 | T108: =RAND() -> 0.73083822 | U108: =RAND() -> 0.33003367
...

Sheet Balanced Scorecard
A1: Balanced Scorecard
A2: 1-2 measures per objective, 8-16 in all. Status: on target ≥100% of target, caution 90-99%, below plan <90% (inverted when lower is better).
A3: Blue text on cream = your inputs. Black on grey = formulas (do not type over them).
A5: Perspective | B5: Objective | C5: Measure | D5: Leading / lagging | E5: Better when | F5: Target | G5: Actual | H5: % of target | I5: Status | J5: Owner | K5: Initiative | L5: Traces to
H6: =IF(AND(ISNUMBER(F6),ISNUMBER(G6),F6<>0,G6<>0),IF(E6="Lower",F6/G6,G6/F6),"") | I6: =IF(H6="",IF(C6="","","No actual yet"),IF(H6>=1,"On target",IF(H6>=0.9,"Caution","Below plan")))
H7: =IF(AND(ISNUMBER(F7),ISNUMBER(G7),F7<>0,G7<>0),IF(E7="Lower",F7/G7,G7/F7),"") | I7: =IF(H7="",IF(C7="","","No actual yet"),IF(H7>=1,"On target",IF(H7>=0.9,"Caution","Below plan")))
H8: =IF(AND(ISNUMBER(F8),ISNUMBER(G8),F8<>0,G8<>0),IF(E8="Lower",F8/G8,G8/F8),"") | I8: =IF(H8="",IF(C8="","","No actual yet"),IF(H8>=1,"On target",IF(H8>=0.9,"Caution","Below plan")))
H9: =IF(AND(ISNUMBER(F9),ISNUMBER(G9),F9<>0,G9<>0),IF(E9="Lower",F9/G9,G9/F9),"") | I9: =IF(H9="",IF(C9="","","No actual yet"),IF(H9>=1,"On target",IF(H9>=0.9,"Caution","Below plan")))
H10: =IF(AND(ISNUMBER(F10),ISNUMBER(G10),F10<>0,G10<>0),IF(E10="Lower",F10/G10,G10/F10),"") | I10: =IF(H10="",IF(C10="","","No actual yet"),IF(H10>=1,"On target",IF(H10>=0.9,"Caution","Below plan")))
H11: =IF(AND(ISNUMBER(F11),ISNUMBER(G11),F11<>0,G11<>0),IF(E11="Lower",F11/G11,G11/F11),"") | I11: =IF(H11="",IF(C11="","","No actual yet"),IF(H11>=1,"On target",IF(H11>=0.9,"Caution","Below plan")))
H12: =IF(AND(ISNUMBER(F12),ISNUMBER(G12),F12<>0,G12<>0),IF(E12="Lower",F12/G12,G12/F12),"") | I12: =IF(H12="",IF(C12="","","No actual yet"),IF(H12>=1,"On target",IF(H12>=0.9,"Caution","Below plan")))
H13: =IF(AND(ISNUMBER(F13),ISNUMBER(G13),F13<>0,G13<>0),IF(E13="Lower",F13/G13,G13/F13),"") | I13: =IF(H13="",IF(C13="","","No actual yet"),IF(H13>=1,"On target",IF(H13>=0.9,"Caution","Below plan")))
H14: =IF(AND(ISNUMBER(F14),ISNUMBER(G14),F14<>0,G14<>0),IF(E14="Lower",F14/G14,G14/F14),"") | I14: =IF(H14="",IF(C14="","","No actual yet"),IF(H14>=1,"On target",IF(H14>=0.9,"Caution","Below plan")))
H15: =IF(AND(ISNUMBER(F15),ISNUMBER(G15),F15<>0,G15<>0),IF(E15="Lower",F15/G15,G15/F15),"") | I15: =IF(H15="",IF(C15="","","No actual yet"),IF(H15>=1,"On target",IF(H15>=0.9,"Caution","Below plan")))
H16: =IF(AND(ISNUMBER(F16),ISNUMBER(G16),F16<>0,G16<>0),IF(E16="Lower",F16/G16,G16/F16),"") | I16: =IF(H16="",IF(C16="","","No actual yet"),IF(H16>=1,"On target",IF(H16>=0.9,"Caution","Below plan")))
H17: =IF(AND(ISNUMBER(F17),ISNUMBER(G17),F17<>0,G17<>0),IF(E17="Lower",F17/G17,G17/F17),"") | I17: =IF(H17="",IF(C17="","","No actual yet"),IF(H17>=1,"On target",IF(H17>=0.9,"Caution","Below plan")))
... H21: =IF(AND(ISNUMBER(F21),ISNUMBER(G21),F21<>0,G21<>0),IF(E21="Lower",F21/G21,G21/F21),"") | I21: =IF(H21="",IF(C21="","","No actual yet"),IF(H21>=1,"On target",IF(H21>=0.9,"Caution","Below plan")))
A23: Balance check
B24: Financial | C24: =COUNTIFS($A$6:$A$21,B24,$C$6:$C$21,"<>") -> 0 | D24: =IF(C24=0,"Add a measure","OK") -> Add a measure
B25: Customer | C25: =COUNTIFS($A$6:$A$21,B25,$C$6:$C$21,"<>") -> 0 | D25: =IF(C25=0,"Add a measure","OK") -> Add a measure
B26: Internal process | C26: =COUNTIFS($A$6:$A$21,B26,$C$6:$C$21,"<>") -> 0 | D26: =IF(C26=0,"Add a measure","OK") -> Add a measure
B27: Learning and growth | C27: =COUNTIFS($A$6:$A$21,B27,$C$6:$C$21,"<>") -> 0 | D27: =IF(C27=0,"Add a measure","OK") -> Add a measure
B29: Measures | C29: =COUNTA(C6:C21) -> 0
B30: Share that are leading | C30: =IF(C29=0,"",COUNTIFS(D6:D21,"Leading",C6:C21,"<>")/C29) | D30: =IF(C30="","",IF(C30>=1/3,"OK","Add leading measures"))
B31: Measures with no owner | C31: =SUMPRODUCT((C6:C21<>"")*(J6:J21="")) -> 0

Sheet Strategy Map
A1: Strategy Map
A2: Objectives by perspective, bottom to top. 'Drives' lists the IDs of the objectives each one leads to in the level above.
A3: Blue text on cream = your inputs. Black on grey = formulas (do not type over them).
A5: ID | B5: Perspective | C5: Objective | D5: Drives (IDs, ; separated) | E5: Check
E6: =IF(A6="","",IF(AND(B6<>"Financial",D6=""),"Drives nothing",IF(AND(B6<>"Learning and growth",COUNTIF($D$6:$D$21,"*"&A6&"*")=0),"Nothing drives it","OK")))
E7: =IF(A7="","",IF(AND(B7<>"Financial",D7=""),"Drives nothing",IF(AND(B7<>"Learning and growth",COUNTIF($D$6:$D$21,"*"&A7&"*")=0),"Nothing drives it","OK")))
E8: =IF(A8="","",IF(AND(B8<>"Financial",D8=""),"Drives nothing",IF(AND(B8<>"Learning and growth",COUNTIF($D$6:$D$21,"*"&A8&"*")=0),"Nothing drives it","OK")))
E9: =IF(A9="","",IF(AND(B9<>"Financial",D9=""),"Drives nothing",IF(AND(B9<>"Learning and growth",COUNTIF($D$6:$D$21,"*"&A9&"*")=0),"Nothing drives it","OK")))
E10: =IF(A10="","",IF(AND(B10<>"Financial",D10=""),"Drives nothing",IF(AND(B10<>"Learning and growth",COUNTIF($D$6:$D$21,"*"&A10&"*")=0),"Nothing drives it","OK")))
E11: =IF(A11="","",IF(AND(B11<>"Financial",D11=""),"Drives nothing",IF(AND(B11<>"Learning and growth",COUNTIF($D$6:$D$21,"*"&A11&"*")=0),"Nothing drives it","OK")))
E12: =IF(A12="","",IF(AND(B12<>"Financial",D12=""),"Drives nothing",IF(AND(B12<>"Learning and growth",COUNTIF($D$6:$D$21,"*"&A12&"*")=0),"Nothing drives it","OK")))
E13: =IF(A13="","",IF(AND(B13<>"Financial",D13=""),"Drives nothing",IF(AND(B13<>"Learning and growth",COUNTIF($D$6:$D$21,"*"&A13&"*")=0),"Nothing drives it","OK")))
E14: =IF(A14="","",IF(AND(B14<>"Financial",D14=""),"Drives nothing",IF(AND(B14<>"Learning and growth",COUNTIF($D$6:$D$21,"*"&A14&"*")=0),"Nothing drives it","OK")))
E15: =IF(A15="","",IF(AND(B15<>"Financial",D15=""),"Drives nothing",IF(AND(B15<>"Learning and growth",COUNTIF($D$6:$D$21,"*"&A15&"*")=0),"Nothing drives it","OK")))
E16: =IF(A16="","",IF(AND(B16<>"Financial",D16=""),"Drives nothing",IF(AND(B16<>"Learning and growth",COUNTIF($D$6:$D$21,"*"&A16&"*")=0),"Nothing drives it","OK")))
E17: =IF(A17="","",IF(AND(B17<>"Financial",D17=""),"Drives nothing",IF(AND(B17<>"Learning and growth",COUNTIF($D$6:$D$21,"*"&A17&"*")=0),"Nothing drives it","OK")))
... E21: =IF(A21="","",IF(AND(B21<>"Financial",D21=""),"Drives nothing",IF(AND(B21<>"Learning and growth",COUNTIF($D$6:$D$21,"*"&A21&"*")=0),"Nothing drives it","OK")))

Sheet GLO-BUS CIR
A1: GLO-BUS Competitive Intelligence Report
A2: One row per company and product. Groups are set against the share-weighted industry average for that product. Analogues, not answers: you decide.
A3: Blue text on cream = your inputs. Black on grey = formulas (do not type over them).
A5: Company | B5: Product | C5: Price ($) | D5: P/Q (stars) | E5: Share (%) | F5: Models | G5: Strategic group
G6: =IF(OR(A6="",B6="",C6="",D6="",E6=""),"",IFERROR(IF(C6>SUMPRODUCT(($B$6:$B$29=B6)*$C$6:$C$29*$E$6:$E$29)/SUMIF($B$6:$B$29,B6,$E$6:$E$29),IF(D6>=SUMPRODUCT(($B$6:$B$29=B6)*$D$6:$D$29*$E$6:$E$29)/SUMIF($B$6:$B$29,B6,$E$6:$E$29),"Premium differentiator","Stuck in the middle"),IF(D6>=SUMPRODUCT(($B$6:$B$29=B6)*$D$6:$D$29*$E$6:$E$29)/SUMIF($B$6:$B$29,B6,$E$6:$E$29),"Value leader","Low-cost / economy")),""))
G7: =IF(OR(A7="",B7="",C7="",D7="",E7=""),"",IFERROR(IF(C7>SUMPRODUCT(($B$6:$B$29=B7)*$C$6:$C$29*$E$6:$E$29)/SUMIF($B$6:$B$29,B7,$E$6:$E$29),IF(D7>=SUMPRODUCT(($B$6:$B$29=B7)*$D$6:$D$29*$E$6:$E$29)/SUMIF($B$6:$B$29,B7,$E$6:$E$29),"Premium differentiator","Stuck in the middle"),IF(D7>=SUMPRODUCT(($B$6:$B$29=B7)*$D$6:$D$29*$E$6:$E$29)/SUMIF($B$6:$B$29,B7,$E$6:$E$29),"Value leader","Low-cost / economy")),""))
G8: =IF(OR(A8="",B8="",C8="",D8="",E8=""),"",IFERROR(IF(C8>SUMPRODUCT(($B$6:$B$29=B8)*$C$6:$C$29*$E$6:$E$29)/SUMIF($B$6:$B$29,B8,$E$6:$E$29),IF(D8>=SUMPRODUCT(($B$6:$B$29=B8)*$D$6:$D$29*$E$6:$E$29)/SUMIF($B$6:$B$29,B8,$E$6:$E$29),"Premium differentiator","Stuck in the middle"),IF(D8>=SUMPRODUCT(($B$6:$B$29=B8)*$D$6:$D$29*$E$6:$E$29)/SUMIF($B$6:$B$29,B8,$E$6:$E$29),"Value leader","Low-cost / economy")),""))
G9: =IF(OR(A9="",B9="",C9="",D9="",E9=""),"",IFERROR(IF(C9>SUMPRODUCT(($B$6:$B$29=B9)*$C$6:$C$29*$E$6:$E$29)/SUMIF($B$6:$B$29,B9,$E$6:$E$29),IF(D9>=SUMPRODUCT(($B$6:$B$29=B9)*$D$6:$D$29*$E$6:$E$29)/SUMIF($B$6:$B$29,B9,$E$6:$E$29),"Premium differentiator","Stuck in the middle"),IF(D9>=SUMPRODUCT(($B$6:$B$29=B9)*$D$6:$D$29*$E$6:$E$29)/SUMIF($B$6:$B$29,B9,$E$6:$E$29),"Value leader","Low-cost / economy")),""))
G10: =IF(OR(A10="",B10="",C10="",D10="",E10=""),"",IFERROR(IF(C10>SUMPRODUCT(($B$6:$B$29=B10)*$C$6:$C$29*$E$6:$E$29)/SUMIF($B$6:$B$29,B10,$E$6:$E$29),IF(D10>=SUMPRODUCT(($B$6:$B$29=B10)*$D$6:$D$29*$E$6:$E$29)/SUMIF($B$6:$B$29,B10,$E$6:$E$29),"Premium differentiator","Stuck in the middle"),IF(D10>=SUMPRODUCT(($B$6:$B$29=B10)*$D$6:$D$29*$E$6:$E$29)/SUMIF($B$6:$B$29,B10,$E$6:$E$29),"Value leader","Low-cost / economy")),""))
G11: =IF(OR(A11="",B11="",C11="",D11="",E11=""),"",IFERROR(IF(C11>SUMPRODUCT(($B$6:$B$29=B11)*$C$6:$C$29*$E$6:$E$29)/SUMIF($B$6:$B$29,B11,$E$6:$E$29),IF(D11>=SUMPRODUCT(($B$6:$B$29=B11)*$D$6:$D$29*$E$6:$E$29)/SUMIF($B$6:$B$29,B11,$E$6:$E$29),"Premium differentiator","Stuck in the middle"),IF(D11>=SUMPRODUCT(($B$6:$B$29=B11)*$D$6:$D$29*$E$6:$E$29)/SUMIF($B$6:$B$29,B11,$E$6:$E$29),"Value leader","Low-cost / economy")),""))
G12: =IF(OR(A12="",B12="",C12="",D12="",E12=""),"",IFERROR(IF(C12>SUMPRODUCT(($B$6:$B$29=B12)*$C$6:$C$29*$E$6:$E$29)/SUMIF($B$6:$B$29,B12,$E$6:$E$29),IF(D12>=SUMPRODUCT(($B$6:$B$29=B12)*$D$6:$D$29*$E$6:$E$29)/SUMIF($B$6:$B$29,B12,$E$6:$E$29),"Premium differentiator","Stuck in the middle"),IF(D12>=SUMPRODUCT(($B$6:$B$29=B12)*$D$6:$D$29*$E$6:$E$29)/SUMIF($B$6:$B$29,B12,$E$6:$E$29),"Value leader","Low-cost / economy")),""))
G13: =IF(OR(A13="",B13="",C13="",D13="",E13=""),"",IFERROR(IF(C13>SUMPRODUCT(($B$6:$B$29=B13)*$C$6:$C$29*$E$6:$E$29)/SUMIF($B$6:$B$29,B13,$E$6:$E$29),IF(D13>=SUMPRODUCT(($B$6:$B$29=B13)*$D$6:$D$29*$E$6:$E$29)/SUMIF($B$6:$B$29,B13,$E$6:$E$29),"Premium differentiator","Stuck in the middle"),IF(D13>=SUMPRODUCT(($B$6:$B$29=B13)*$D$6:$D$29*$E$6:$E$29)/SUMIF($B$6:$B$29,B13,$E$6:$E$29),"Value leader","Low-cost / economy")),""))
G14: =IF(OR(A14="",B14="",C14="",D14="",E14=""),"",IFERROR(IF(C14>SUMPRODUCT(($B$6:$B$29=B14)*$C$6:$C$29*$E$6:$E$29)/SUMIF($B$6:$B$29,B14,$E$6:$E$29),IF(D14>=SUMPRODUCT(($B$6:$B$29=B14)*$D$6:$D$29*$E$6:$E$29)/SUMIF($B$6:$B$29,B14,$E$6:$E$29),"Premium differentiator","Stuck in the middle"),IF(D14>=SUMPRODUCT(($B$6:$B$29=B14)*$D$6:$D$29*$E$6:$E$29)/SUMIF($B$6:$B$29,B14,$E$6:$E$29),"Value leader","Low-cost / economy")),""))
G15: =IF(OR(A15="",B15="",C15="",D15="",E15=""),"",IFERROR(IF(C15>SUMPRODUCT(($B$6:$B$29=B15)*$C$6:$C$29*$E$6:$E$29)/SUMIF($B$6:$B$29,B15,$E$6:$E$29),IF(D15>=SUMPRODUCT(($B$6:$B$29=B15)*$D$6:$D$29*$E$6:$E$29)/SUMIF($B$6:$B$29,B15,$E$6:$E$29),"Premium differentiator","Stuck in the middle"),IF(D15>=SUMPRODUCT(($B$6:$B$29=B15)*$D$6:$D$29*$E$6:$E$29)/SUMIF($B$6:$B$29,B15,$E$6:$E$29),"Value leader","Low-cost / economy")),""))
G16: =IF(OR(A16="",B16="",C16="",D16="",E16=""),"",IFERROR(IF(C16>SUMPRODUCT(($B$6:$B$29=B16)*$C$6:$C$29*$E$6:$E$29)/SUMIF($B$6:$B$29,B16,$E$6:$E$29),IF(D16>=SUMPRODUCT(($B$6:$B$29=B16)*$D$6:$D$29*$E$6:$E$29)/SUMIF($B$6:$B$29,B16,$E$6:$E$29),"Premium differentiator","Stuck in the middle"),IF(D16>=SUMPRODUCT(($B$6:$B$29=B16)*$D$6:$D$29*$E$6:$E$29)/SUMIF($B$6:$B$29,B16,$E$6:$E$29),"Value leader","Low-cost / economy")),""))
G17: =IF(OR(A17="",B17="",C17="",D17="",E17=""),"",IFERROR(IF(C17>SUMPRODUCT(($B$6:$B$29=B17)*$C$6:$C$29*$E$6:$E$29)/SUMIF($B$6:$B$29,B17,$E$6:$E$29),IF(D17>=SUMPRODUCT(($B$6:$B$29=B17)*$D$6:$D$29*$E$6:$E$29)/SUMIF($B$6:$B$29,B17,$E$6:$E$29),"Premium differentiator","Stuck in the middle"),IF(D17>=SUMPRODUCT(($B$6:$B$29=B17)*$D$6:$D$29*$E$6:$E$29)/SUMIF($B$6:$B$29,B17,$E$6:$E$29),"Value leader","Low-cost / economy")),""))
... G29: =IF(OR(A29="",B29="",C29="",D29="",E29=""),"",IFERROR(IF(C29>SUMPRODUCT(($B$6:$B$29=B29)*$C$6:$C$29*$E$6:$E$29)/SUMIF($B$6:$B$29,B29,$E$6:$E$29),IF(D29>=SUMPRODUCT(($B$6:$B$29=B29)*$D$6:$D$29*$E$6:$E$29)/SUMIF($B$6:$B$29,B29,$E$6:$E$29),"Premium differentiator","Stuck in the middle"),IF(D29>=SUMPRODUCT(($B$6:$B$29=B29)*$D$6:$D$29*$E$6:$E$29)/SUMIF($B$6:$B$29,B29,$E$6:$E$29),"Value leader","Low-cost / economy")),""))
A31: Industry averages (share-weighted) | C31: Price | D31: P/Q
A32: Camera | C32: =IFERROR(SUMPRODUCT(($B$6:$B$29="Camera")*$C$6:$C$29*$E$6:$E$29)/SUMIF($B$6:$B$29,"Camera",$E$6:$E$29),"") | D32: =IFERROR(SUMPRODUCT(($B$6:$B$29="Camera")*$D$6:$D$29*$E$6:$E$29)/SUMIF($B$6:$B$29,"Camera",$E$6:$E$29),"")
A33: Drone | C33: =IFERROR(SUMPRODUCT(($B$6:$B$29="Drone")*$C$6:$C$29*$E$6:$E$29)/SUMIF($B$6:$B$29,"Drone",$E$6:$E$29),"") | D33: =IFERROR(SUMPRODUCT(($B$6:$B$29="Drone")*$D$6:$D$29*$E$6:$E$29)/SUMIF($B$6:$B$29,"Drone",$E$6:$E$29),"")

Sheet GLO-BUS Planner
A1: GLO-BUS Decision Planner
A2: Plan each year's decisions here, test them in the game's projections, then enter them in GLO-BUS screen by screen in this order. Your team makes and enters every decision.
A3: Blue text on cream = your inputs. Black on grey = formulas (do not type over them).
A4: Change threshold for the incremental-change check: | D4: 0.15
A5: Key (do not edit) | B5: Decision area | C5: Decision | D5: Unit | E5: Year 6 | F5: Year 7 | G5: Year 8 | H5: Year 9 | I5: Year 10 | J5: Year 11 | K5: Year 12 | L5: Year 13 | M5: Year 14 | N5: Year 15
A6: strategy.camera | B6: Strategy anchor | C6: Strategy (Cameras) | D6: text
A7: strategy.drone | C7: Strategy (Drones) | D7: text
A8: design.camera.pq | B8: Product design | C8: P/Q rating target (Cameras) | D8: stars
A9: design.drone.pq | C9: P/Q rating target (Drones) | D9: stars
A10: design.camera.models | C10: Number of models (Cameras) | D10: count
A11: design.drone.models | C11: Number of models (Drones) | D11: count
A12: design.camera.rd | C12: R&D / component quality spend (Cameras) | D12: $000s
A13: design.drone.rd | C13: R&D / component quality spend (Drones) | D13: $000s
A14: mkt.camera.na.price | B14: Marketing | C14: Price (Cameras, North America) | D14: $
A15: mkt.camera.ea.price | C15: Price (Cameras, Europe-Africa) | D15: $
A16: mkt.camera.ap.price | C16: Price (Cameras, Asia-Pacific) | D16: $
A17: mkt.camera.la.price | C17: Price (Cameras, Latin America) | D17: $
A18: mkt.drone.na.price | C18: Price (Drones, North America) | D18: $
A19: mkt.drone.ea.price | C19: Price (Drones, Europe-Africa) | D19: $
A20: mkt.drone.ap.price | C20: Price (Drones, Asia-Pacific) | D20: $
A21: mkt.drone.la.price | C21: Price (Drones, Latin America) | D21: $
A22: mkt.camera.na.ads | C22: Advertising (Cameras, North America) | D22: $000s
A23: mkt.camera.ea.ads | C23: Advertising (Cameras, Europe-Africa) | D23: $000s
A24: mkt.camera.ap.ads | C24: Advertising (Cameras, Asia-Pacific) | D24: $000s
A25: mkt.camera.la.ads | C25: Advertising (Cameras, Latin America) | D25: $000s
A26: mkt.drone.na.ads | C26: Advertising (Drones, North America) | D26: $000s
... A45: mkt.drone.la.warranty | C45: Warranty (Drones, Latin America) | D45: days
A46: ops.camera.workstations | B46: Assembly operations | C46: Workstations (Cameras) | D46: count
A47: ops.drone.workstations | C47: Workstations (Drones) | D47: count
A48: ops.camera.overtime | C48: Overtime (Cameras) | D48: %
A49: ops.drone.overtime | C49: Overtime (Drones) | D49: %
A50: ops.camera.training | C50: Best-practice training (Cameras) | D50: $ per worker
A51: ops.drone.training | C51: Best-practice training (Drones) | D51: $ per worker
A52: comp.base | B52: Compensation | C52: Base wage | D52: $ per worker
A53: comp.incentive | C53: Incentive pay | D53: $ per unit
A54: comp.fringe | C54: Fringe benefits | D54: $ per worker
A55: csr.budget | B55: Corporate citizenship | C55: CSR / citizenship spending | D55: $000s
A56: csr.programs | C56: Programs in place | D56: text
A57: fin.st_loan | B57: Finance | C57: Short-term loan | D57: $000s
A58: fin.lt_loan | C58: Long-term loan | D58: $000s
A59: fin.stock_issue | C59: Stock issue | D59: 000s shares
A60: fin.buyback | C60: Stock buyback | D60: 000s shares
A61: fin.dividend | C61: Dividend per share | D61: $
A62: kpi.eps | B62: Projected KPIs (from the game's projections) | C62: Projected EPS | D62: $
A63: kpi.roe | C63: Projected ROE | D63: %
A64: kpi.stock | C64: Projected stock price | D64: $
A65: kpi.credit | C65: Projected credit rating | D65: text
A66: kpi.image | C66: Projected image rating | D66: score
B68: Change vs the year before (numbers only); amber = bigger than the threshold
A69: Key | B69: Decision area | C69: Decision | D69: Unit | E69: Year 6 | F69: Year 7 | G69: Year 8 | H69: Year 9 | I69: Year 10 | J69: Year 11 | K69: Year 12 | L69: Year 13 | M69: Year 14 | N69: Year 15
A70: strategy.camera | C70: Strategy (Cameras) | F70: =IF(AND(ISNUMBER(F6),ISNUMBER(E6),E6<>0),F6/E6-1,"") | G70: =IF(AND(ISNUMBER(G6),ISNUMBER(F6),F6<>0),G6/F6-1,"") | H70: =IF(AND(ISNUMBER(H6),ISNUMBER(G6),G6<>0),H6/G6-1,"") | I70: =IF(AND(ISNUMBER(I6),ISNUMBER(H6),H6<>0),I6/H6-1,"") | J70: =IF(AND(ISNUMBER(J6),ISNUMBER(I6),I6<>0),J6/I6-1,"") | K70: =IF(AND(ISNUMBER(K6),ISNUMBER(J6),J6<>0),K6/J6-1,"") | L70: =IF(AND(ISNUMBER(L6),ISNUMBER(K6),K6<>0),L6/K6-1,"") | M70: =IF(AND(ISNUMBER(M6),ISNUMBER(L6),L6<>0),M6/L6-1,"") | N70: =IF(AND(ISNUMBER(N6),ISNUMBER(M6),M6<>0),N6/M6-1,"")
