Workbook

Sheet Start
B2: StratOS Workbook
B3: Global electric vehicles (passenger BEV and PHEV) · base company BYD
B4: Pre-filled from the StratOS ledger (global-ev-demo-2026, as of 2026-10-01).
B6: How to use | C6: Each sheet is one StratOS framework. Type only in the cream cells (blue text). Grey cells are formulas: they score, rank and flag automatically. Every finding should name its evidence in the Source column, the same rule StratOS follows.
B7: Colour key | C7: Blue on cream = input · black on grey = formula · green / amber / red = status.
B8: PESTEL | C8: Macro findings with impact × certainty priority and the P&L line each one hits.
B9: Five Forces | C9: Sub-factor scores roll up to each force and to an industry attractiveness score.
B10: KSF Scorecard | C10: Weighted KSFs, every competitor scored, totals and rank; weights must sum to 100%.
B11: VRIO | C11: Yes / No / ? for each test; the verdict and the KSF reality check are calculated.
B12: SWOT-TOWS | C12: Four traced lists and the TOWS options that pair them.
B13: Decision Matrix | C13: Criteria weights × option scores, with a weighted total and rank; do nothing included.
B14: Expected Value | C14: Scenario probabilities × NPVs, expected NPV, worst case, maximin, value of information, and a Bayes' rule pilot check (EVSI).
B15: Business Case | C15: Driver-based cash flows, NPV, IRR and cumulative cash.
B16: Risk Analysis | C16: Exhibit Q-3: a tornado chart (which driver moves NPV most) and a 1,000-run Monte Carlo simulation (median, P10-P90, chance NPV is below zero) over your low / likely / high ranges.
B17: Balanced Scorecard | C17: Objectives and measures in four perspectives, leading vs lagging, status vs target, balance check.
... B24: Your work stays yours | C24: In graded work, the inputs, choices and every Impact Summary are the student's. The workbook calculates; it never decides.
B26: © 2026 Brad Scheller · StratOS Strategy Lab · Apache-2.0

Sheet PESTEL
A1: PESTEL Analysis
A2: Macro findings, each tied to a P&L line. Priority = impact × certainty (1-25).
A3: Pre-filled from your StratOS ledger. Blue text on cream = inputs you can change. Black on grey = formulas (do not type over them).
A5: ID | B5: Dimension | C5: Finding | D5: Direction (+ / - / ±) | E5: Impact 1-5 | F5: Certainty 1-5 | G5: Priority | H5: P&L line | I5: Source / evidence
A6: P1 | B6: Economic | C6: Battery cell prices keep falling | D6: + | E6: 5 | F6: 3 | G6: =IF(AND(ISNUMBER(E6),ISNUMBER(F6)),E6*F6,"") -> 15 | H6: cogs.inputs | I6: E003
A7: P2 | B7: Political | C7: EU tariffs on China-built BEVs | D7: - | E7: 5 | F7: 5 | G7: =IF(AND(ISNUMBER(E7),ISNUMBER(F7)),E7*F7,"") -> 25 | H7: tax_and_levies | I7: E002
A8: P3 | B8: Technological | C8: Software-defined vehicles shift value to features | D8: + | E8: 5 | F8: 3 | G8: =IF(AND(ISNUMBER(E8),ISNUMBER(F8)),E8*F8,"") -> 15 | H8: revenue.mix | I8: E008
A9: P4 | B9: Social | C9: Range and charging anxiety slow mass-market adoption | D9: - | E9: 3 | F9: 3 | G9: =IF(AND(ISNUMBER(E9),ISNUMBER(F9)),E9*F9,"") -> 9 | H9: revenue.volume | I9: E007
A10: P5 | B10: Env | C10: Fleet CO2 targets push OEMs to sell more BEVs | D10: + | E10: 3 | F10: 5 | G10: =IF(AND(ISNUMBER(E10),ISNUMBER(F10)),E10*F10,"") -> 15 | H10: revenue.volume | I10: E005
A11: P6 | B11: Legal | C11: Local-content rules for EU incentives | D11: - | E11: 3 | F11: 3 | G11: =IF(AND(ISNUMBER(E11),ISNUMBER(F11)),E11*F11,"") -> 9 | H11: revenue.price | I11: E002
G12: =IF(AND(ISNUMBER(E12),ISNUMBER(F12)),E12*F12,"")
G13: =IF(AND(ISNUMBER(E13),ISNUMBER(F13)),E13*F13,"")
G14: =IF(AND(ISNUMBER(E14),ISNUMBER(F14)),E14*F14,"")
G15: =IF(AND(ISNUMBER(E15),ISNUMBER(F15)),E15*F15,"")
G16: =IF(AND(ISNUMBER(E16),ISNUMBER(F16)),E16*F16,"")
G17: =IF(AND(ISNUMBER(E17),ISNUMBER(F17)),E17*F17,"")
G18: =IF(AND(ISNUMBER(E18),ISNUMBER(F18)),E18*F18,"")
G19: =IF(AND(ISNUMBER(E19),ISNUMBER(F19)),E19*F19,"")
G20: =IF(AND(ISNUMBER(E20),ISNUMBER(F20)),E20*F20,"")
G21: =IF(AND(ISNUMBER(E21),ISNUMBER(F21)),E21*F21,"")
G22: =IF(AND(ISNUMBER(E22),ISNUMBER(F22)),E22*F22,"")
G23: =IF(AND(ISNUMBER(E23),ISNUMBER(F23)),E23*F23,"")
... G30: =IF(AND(ISNUMBER(E30),ISNUMBER(F30)),E30*F30,"")
B32: Findings | C32: =COUNTA(C6:C30) -> 6
B33: High priority (≥16) | C33: =COUNTIF(G6:G30,">=16") -> 1
B34: Missing a source | C34: =SUMPRODUCT((C6:C30<>"")*(I6:I30="")) -> 0

Sheet Five Forces
A1: Porter's Five Forces
A2: Score each sub-factor 1 (weak force, good for profit) to 5 (strong force). A force score you enter overrides the sub-factor average.
A3: Pre-filled from your StratOS ledger. Blue text on cream = inputs you can change. Black on grey = formulas (do not type over them).
A5: Force | B5: Sub-factor | C5: Score 1-5 | D5: Evidence / source
A6: Competitive rivalry | B6: Current competition
A7: Competitive rivalry | B7: Market growth
A8: Competitive rivalry | B8: Exit barriers
A9: Competitive rivalry | B9: Differentiation
A10: Supplier power | B10: Supplier concentration
A11: Supplier power | B11: Switching costs
A12: Supplier power | B12: Forward integration
A13: Supplier power | B13: Input uniqueness
A14: Buyer power | B14: Buyer concentration
A15: Buyer power | B15: Purchase volume
A16: Buyer power | B16: Switching costs
A17: Buyer power | B17: Price sensitivity
... A25: Threat of substitutes | B25: Buyer propensity
A27: Force | B27: Sub-factor average | C27: Your force score (optional) | D27: Score used | E27: Strength | F27: Horizon score (optional)
A28: Competitive rivalry | B28: =IFERROR(AVERAGEIF($A$6:$A$25,A28,$C$6:$C$25),"") | C28: 5 | D28: =IF(ISNUMBER(C28),C28,B28) -> 5 | E28: =IF(D28="","",IF(D28>=4,"Strong",IF(D28>=2.5,"Moderate","Weak"))) -> Strong | F28: 5
A29: Supplier power | B29: =IFERROR(AVERAGEIF($A$6:$A$25,A29,$C$6:$C$25),"") | C29: 4 | D29: =IF(ISNUMBER(C29),C29,B29) -> 4 | E29: =IF(D29="","",IF(D29>=4,"Strong",IF(D29>=2.5,"Moderate","Weak"))) -> Strong | F29: 3
A30: Buyer power | B30: =IFERROR(AVERAGEIF($A$6:$A$25,A30,$C$6:$C$25),"") | C30: 3 | D30: =IF(ISNUMBER(C30),C30,B30) -> 3 | E30: =IF(D30="","",IF(D30>=4,"Strong",IF(D30>=2.5,"Moderate","Weak"))) -> Moderate | F30: 4
A31: Threat of new entrants | B31: =IFERROR(AVERAGEIF($A$6:$A$25,A31,$C$6:$C$25),"") | C31: 4 | D31: =IF(ISNUMBER(C31),C31,B31) -> 4 | E31: =IF(D31="","",IF(D31>=4,"Strong",IF(D31>=2.5,"Moderate","Weak"))) -> Strong | F31: 4
A32: Threat of substitutes | B32: =IFERROR(AVERAGEIF($A$6:$A$25,A32,$C$6:$C$25),"") | C32: 2 | D32: =IF(ISNUMBER(C32),C32,B32) -> 2 | E32: =IF(D32="","",IF(D32>=4,"Strong",IF(D32>=2.5,"Moderate","Weak"))) -> Weak | F32: 2
A34: Industry attractiveness (1-5) | B34: =IFERROR(6-AVERAGE(D28:D32),"") -> 2.4
A35: At the horizon | B35: =IF(COUNT(F28:F32)=5,6-AVERAGE(F28:F32),"") -> 2.4
A37: Attractiveness = 6 minus the average force score (1-5; higher is more attractive).
A38: The horizon score appears once all five horizon scores are entered.

Sheet KSF Scorecard
A1: Key Success Factors Scorecard
A2: Weights are fractions that must sum to 100%. Score each competitor 1 (weak) to 5 (strong) on each KSF.
A3: Pre-filled from your StratOS ledger. Blue text on cream = inputs you can change. Black on grey = formulas (do not type over them).
A5: ID | B5: Key success factor | C5: Weight | D5: Traces to (force / driver) | E5: BYD | F5: Tesla | G5: Volkswagen Group | H5: Geely | I5: Xiaomi | J5: Stellantis
A6: K1 | B6: Battery cost and supply | C6: 0.3 | D6: suppliers, D1 | E6: 5 | F6: 4 | G6: 3 | H6: 4 | I6: 3 | J6: 2
A7: K2 | B7: Software and UX | C7: 0.25 | D7: rivalry, D3 | E7: 3 | F7: 5 | G7: 2 | H7: 3 | I7: 5 | J7: 2
A8: K3 | B8: Local production footprint | C8: 0.2 | D8: D2 | E8: 2 | F8: 4 | G8: 5 | H8: 3 | I8: 1 | J8: 5
A9: K4 | B9: Brand trust in Europe | C9: 0.15 | D9: buyers | E9: 2 | F9: 3 | G9: 5 | H9: 3 | I9: 2 | J9: 4
A10: K5 | B10: Charging and service network | C10: 0.1 | D10: D3 | E10: 3 | F10: 5 | G10: 4 | H10: 3 | I10: 2 | J10: 3
B16: Weight check (must be 100%) | C16: =SUM(C6:C15) -> 1 | D16: =IF(ABS(C16-1)<0.001,"OK","Weights must sum to 100%") -> OK
B17: Weighted score (out of 5) | E17: =IF(COUNT(E6:E15)=0,"",SUMPRODUCT($C$6:$C$15,E6:E15)) -> 3.25 | F17: =IF(COUNT(F6:F15)=0,"",SUMPRODUCT($C$6:$C$15,F6:F15)) -> 4.2 | G17: =IF(COUNT(G6:G15)=0,"",SUMPRODUCT($C$6:$C$15,G6:G15)) -> 3.55 | H17: =IF(COUNT(H6:H15)=0,"",SUMPRODUCT($C$6:$C$15,H6:H15)) -> 3.3 | I17: =IF(COUNT(I6:I15)=0,"",SUMPRODUCT($C$6:$C$15,I6:I15)) -> 2.85 | J17: =IF(COUNT(J6:J15)=0,"",SUMPRODUCT($C$6:$C$15,J6:J15)) -> 3
B18: Rank | E18: =IF(E17="","",RANK(E17,$E$17:$J$17)) -> 4 | F18: =IF(F17="","",RANK(F17,$E$17:$J$17)) -> 1 | G18: =IF(G17="","",RANK(G17,$E$17:$J$17)) -> 2 | H18: =IF(H17="","",RANK(H17,$E$17:$J$17)) -> 3 | I18: =IF(I17="","",RANK(I17,$E$17:$J$17)) -> 6 | J18: =IF(J17="","",RANK(J17,$E$17:$J$17)) -> 5

Sheet VRIO
A1: VRIO Analysis
A2: Answer the four tests in order with Yes / No / ?. The verdict stops at the first No or ?. KSF weight (a fraction) drives the reality check.
A3: Pre-filled from your StratOS ledger. Blue text on cream = inputs you can change. Black on grey = formulas (do not type over them).
A5: Resource or capability | B5: Type | C5: Valuable? | D5: Rare? | E5: Inimitable? | F5: Organized? | G5: Verdict | H5: KSF it delivers | I5: KSF weight | J5: Reality check | K5: Evidence
A6: Vertical battery integration | B6: capability | C6: Yes | D6: Yes | E6: Yes | F6: Yes | G6: =IF(A6="","",IF(C6<>"Yes",IF(C6="No","Competitive disadvantage","Undetermined"),IF(D6<>"Yes",IF(D6="No","Competitive parity","Undetermined beyond valuable"),IF(E6<>"Yes",IF(E6="No","Temporary advantage","Undetermined beyond rare"),IF(F6="Yes","Sustained advantage",IF(F6="No","Unexploited advantage","Undetermined beyond inimitable")))))) -> Sustained advantage | H6: K1 | I6: 0.3 | J6: =IF(A6="","",IF(AND(C6="Yes",D6="Yes",E6="Yes",N(I6)<0.1),"Competence trap",IF(AND(OR(G6="Temporary advantage",G6="Unexploited advantage",G6="Sustained advantage"),N(I6)>=0.1),"Supported",IF(AND(G6="Competitive parity",N(I6)>=0.1),"Table stakes","")))) -> Supported | K6: E010
A7: Fast model cadence | B7: capability | C7: Yes | D7: Yes | E7: No | F7: Yes | G7: =IF(A7="","",IF(C7<>"Yes",IF(C7="No","Competitive disadvantage","Undetermined"),IF(D7<>"Yes",IF(D7="No","Competitive parity","Undetermined beyond valuable"),IF(E7<>"Yes",IF(E7="No","Temporary advantage","Undetermined beyond rare"),IF(F7="Yes","Sustained advantage",IF(F7="No","Unexploited advantage","Undetermined beyond inimitable")))))) -> Temporary advantage | H7: K2 | I7: 0.25 | J7: =IF(A7="","",IF(AND(C7="Yes",D7="Yes",E7="Yes",N(I7)<0.1),"Competence trap",IF(AND(OR(G7="Temporary advantage",G7="Unexploited advantage",G7="Sustained advantage"),N(I7)>=0.1),"Supported",IF(AND(G7="Competitive parity",N(I7)>=0.1),"Table stakes","")))) -> Supported | K7: E001
A8: In-car software and OTA | B8: capability | C8: Yes | D8: No | E8: No | F8: ? | G8: =IF(A8="","",IF(C8<>"Yes",IF(C8="No","Competitive disadvantage","Undetermined"),IF(D8<>"Yes",IF(D8="No","Competitive parity","Undetermined beyond valuable"),IF(E8<>"Yes",IF(E8="No","Temporary advantage","Undetermined beyond rare"),IF(F8="Yes","Sustained advantage",IF(F8="No","Unexploited advantage","Undetermined beyond inimitable")))))) -> Competitive parity | H8: K2 | I8: 0.25 | J8: =IF(A8="","",IF(AND(C8="Yes",D8="Yes",E8="Yes",N(I8)<0.1),"Competence trap",IF(AND(OR(G8="Temporary advantage",G8="Unexploited advantage",G8="Sustained advantage"),N(I8)>=0.1),"Supported",IF(AND(G8="Competitive parity",N(I8)>=0.1),"Table stakes","")))) -> Table stakes | K8: E008
A9: Scale in China | B9: resource | C9: Yes | D9: Yes | E9: ? | F9: Yes | G9: =IF(A9="","",IF(C9<>"Yes",IF(C9="No","Competitive disadvantage","Undetermined"),IF(D9<>"Yes",IF(D9="No","Competitive parity","Undetermined beyond valuable"),IF(E9<>"Yes",IF(E9="No","Temporary advantage","Undetermined beyond rare"),IF(F9="Yes","Sustained advantage",IF(F9="No","Unexploited advantage","Undetermined beyond inimitable")))))) -> Undetermined beyond rare | H9: K1 | I9: 0.3 | J9: =IF(A9="","",IF(AND(C9="Yes",D9="Yes",E9="Yes",N(I9)<0.1),"Competence trap",IF(AND(OR(G9="Temporary advantage",G9="Unexploited advantage",G9="Sustained advantage"),N(I9)>=0.1),"Supported",IF(AND(G9="Competitive parity",N(I9)>=0.1),"Table stakes","")))) | K9: E001
G10: =IF(A10="","",IF(C10<>"Yes",IF(C10="No","Competitive disadvantage","Undetermined"),IF(D10<>"Yes",IF(D10="No","Competitive parity","Undetermined beyond valuable"),IF(E10<>"Yes",IF(E10="No","Temporary advantage","Undetermined beyond rare"),IF(F10="Yes","Sustained advantage",IF(F10="No","Unexploited advantage","Undetermined beyond inimitable")))))) | J10: =IF(A10="","",IF(AND(C10="Yes",D10="Yes",E10="Yes",N(I10)<0.1),"Competence trap",IF(AND(OR(G10="Temporary advantage",G10="Unexploited advantage",G10="Sustained advantage"),N(I10)>=0.1),"Supported",IF(AND(G10="Competitive parity",N(I10)>=0.1),"Table stakes",""))))
G11: =IF(A11="","",IF(C11<>"Yes",IF(C11="No","Competitive disadvantage","Undetermined"),IF(D11<>"Yes",IF(D11="No","Competitive parity","Undetermined beyond valuable"),IF(E11<>"Yes",IF(E11="No","Temporary advantage","Undetermined beyond rare"),IF(F11="Yes","Sustained advantage",IF(F11="No","Unexploited advantage","Undetermined beyond inimitable")))))) | J11: =IF(A11="","",IF(AND(C11="Yes",D11="Yes",E11="Yes",N(I11)<0.1),"Competence trap",IF(AND(OR(G11="Temporary advantage",G11="Unexploited advantage",G11="Sustained advantage"),N(I11)>=0.1),"Supported",IF(AND(G11="Competitive parity",N(I11)>=0.1),"Table stakes",""))))
G12: =IF(A12="","",IF(C12<>"Yes",IF(C12="No","Competitive disadvantage","Undetermined"),IF(D12<>"Yes",IF(D12="No","Competitive parity","Undetermined beyond valuable"),IF(E12<>"Yes",IF(E12="No","Temporary advantage","Undetermined beyond rare"),IF(F12="Yes","Sustained advantage",IF(F12="No","Unexploited advantage","Undetermined beyond inimitable")))))) | J12: =IF(A12="","",IF(AND(C12="Yes",D12="Yes",E12="Yes",N(I12)<0.1),"Competence trap",IF(AND(OR(G12="Temporary advantage",G12="Unexploited advantage",G12="Sustained advantage"),N(I12)>=0.1),"Supported",IF(AND(G12="Competitive parity",N(I12)>=0.1),"Table stakes",""))))
G13: =IF(A13="","",IF(C13<>"Yes",IF(C13="No","Competitive disadvantage","Undetermined"),IF(D13<>"Yes",IF(D13="No","Competitive parity","Undetermined beyond valuable"),IF(E13<>"Yes",IF(E13="No","Temporary advantage","Undetermined beyond rare"),IF(F13="Yes","Sustained advantage",IF(F13="No","Unexploited advantage","Undetermined beyond inimitable")))))) | J13: =IF(A13="","",IF(AND(C13="Yes",D13="Yes",E13="Yes",N(I13)<0.1),"Competence trap",IF(AND(OR(G13="Temporary advantage",G13="Unexploited advantage",G13="Sustained advantage"),N(I13)>=0.1),"Supported",IF(AND(G13="Competitive parity",N(I13)>=0.1),"Table stakes",""))))
G14: =IF(A14="","",IF(C14<>"Yes",IF(C14="No","Competitive disadvantage","Undetermined"),IF(D14<>"Yes",IF(D14="No","Competitive parity","Undetermined beyond valuable"),IF(E14<>"Yes",IF(E14="No","Temporary advantage","Undetermined beyond rare"),IF(F14="Yes","Sustained advantage",IF(F14="No","Unexploited advantage","Undetermined beyond inimitable")))))) | J14: =IF(A14="","",IF(AND(C14="Yes",D14="Yes",E14="Yes",N(I14)<0.1),"Competence trap",IF(AND(OR(G14="Temporary advantage",G14="Unexploited advantage",G14="Sustained advantage"),N(I14)>=0.1),"Supported",IF(AND(G14="Competitive parity",N(I14)>=0.1),"Table stakes",""))))
G15: =IF(A15="","",IF(C15<>"Yes",IF(C15="No","Competitive disadvantage","Undetermined"),IF(D15<>"Yes",IF(D15="No","Competitive parity","Undetermined beyond valuable"),IF(E15<>"Yes",IF(E15="No","Temporary advantage","Undetermined beyond rare"),IF(F15="Yes","Sustained advantage",IF(F15="No","Unexploited advantage","Undetermined beyond inimitable")))))) | J15: =IF(A15="","",IF(AND(C15="Yes",D15="Yes",E15="Yes",N(I15)<0.1),"Competence trap",IF(AND(OR(G15="Temporary advantage",G15="Unexploited advantage",G15="Sustained advantage"),N(I15)>=0.1),"Supported",IF(AND(G15="Competitive parity",N(I15)>=0.1),"Table stakes",""))))
G16: =IF(A16="","",IF(C16<>"Yes",IF(C16="No","Competitive disadvantage","Undetermined"),IF(D16<>"Yes",IF(D16="No","Competitive parity","Undetermined beyond valuable"),IF(E16<>"Yes",IF(E16="No","Temporary advantage","Undetermined beyond rare"),IF(F16="Yes","Sustained advantage",IF(F16="No","Unexploited advantage","Undetermined beyond inimitable")))))) | J16: =IF(A16="","",IF(AND(C16="Yes",D16="Yes",E16="Yes",N(I16)<0.1),"Competence trap",IF(AND(OR(G16="Temporary advantage",G16="Unexploited advantage",G16="Sustained advantage"),N(I16)>=0.1),"Supported",IF(AND(G16="Competitive parity",N(I16)>=0.1),"Table stakes",""))))
G17: =IF(A17="","",IF(C17<>"Yes",IF(C17="No","Competitive disadvantage","Undetermined"),IF(D17<>"Yes",IF(D17="No","Competitive parity","Undetermined beyond valuable"),IF(E17<>"Yes",IF(E17="No","Temporary advantage","Undetermined beyond rare"),IF(F17="Yes","Sustained advantage",IF(F17="No","Unexploited advantage","Undetermined beyond inimitable")))))) | J17: =IF(A17="","",IF(AND(C17="Yes",D17="Yes",E17="Yes",N(I17)<0.1),"Competence trap",IF(AND(OR(G17="Temporary advantage",G17="Unexploited advantage",G17="Sustained advantage"),N(I17)>=0.1),"Supported",IF(AND(G17="Competitive parity",N(I17)>=0.1),"Table stakes",""))))
G18: =IF(A18="","",IF(C18<>"Yes",IF(C18="No","Competitive disadvantage","Undetermined"),IF(D18<>"Yes",IF(D18="No","Competitive parity","Undetermined beyond valuable"),IF(E18<>"Yes",IF(E18="No","Temporary advantage","Undetermined beyond rare"),IF(F18="Yes","Sustained advantage",IF(F18="No","Unexploited advantage","Undetermined beyond inimitable")))))) | J18: =IF(A18="","",IF(AND(C18="Yes",D18="Yes",E18="Yes",N(I18)<0.1),"Competence trap",IF(AND(OR(G18="Temporary advantage",G18="Unexploited advantage",G18="Sustained advantage"),N(I18)>=0.1),"Supported",IF(AND(G18="Competitive parity",N(I18)>=0.1),"Table stakes",""))))
G19: =IF(A19="","",IF(C19<>"Yes",IF(C19="No","Competitive disadvantage","Undetermined"),IF(D19<>"Yes",IF(D19="No","Competitive parity","Undetermined beyond valuable"),IF(E19<>"Yes",IF(E19="No","Temporary advantage","Undetermined beyond rare"),IF(F19="Yes","Sustained advantage",IF(F19="No","Unexploited advantage","Undetermined beyond inimitable")))))) | J19: =IF(A19="","",IF(AND(C19="Yes",D19="Yes",E19="Yes",N(I19)<0.1),"Competence trap",IF(AND(OR(G19="Temporary advantage",G19="Unexploited advantage",G19="Sustained advantage"),N(I19)>=0.1),"Supported",IF(AND(G19="Competitive parity",N(I19)>=0.1),"Table stakes",""))))
G20: =IF(A20="","",IF(C20<>"Yes",IF(C20="No","Competitive disadvantage","Undetermined"),IF(D20<>"Yes",IF(D20="No","Competitive parity","Undetermined beyond valuable"),IF(E20<>"Yes",IF(E20="No","Temporary advantage","Undetermined beyond rare"),IF(F20="Yes","Sustained advantage",IF(F20="No","Unexploited advantage","Undetermined beyond inimitable")))))) | J20: =IF(A20="","",IF(AND(C20="Yes",D20="Yes",E20="Yes",N(I20)<0.1),"Competence trap",IF(AND(OR(G20="Temporary advantage",G20="Unexploited advantage",G20="Sustained advantage"),N(I20)>=0.1),"Supported",IF(AND(G20="Competitive parity",N(I20)>=0.1),"Table stakes",""))))

Sheet SWOT-TOWS
A1: SWOT and TOWS
A2: Every item names the finding it came from. TOWS options pair the items by ID.
A3: Pre-filled from your StratOS ledger. Blue text on cream = inputs you can change. Black on grey = formulas (do not type over them).
A5: ID | B5: Strengths (internal, helpful) | C5: Source | E5: ID | F5: Weaknesses (internal, harmful) | G5: Source
A6: S1 | B6: Lowest cell cost in the industry | C6: C1 | E6: W1 | F6: Low brand trust in Europe | G6: K4
A7: S2 | B7: Fast model cadence | C7: C2 | E7: W2 | F7: Software lags the leaders | G7: C3
A8: S3 | E8: W3
A9: S4 | E9: W4
A10: S5 | E10: W5
A11: S6 | E11: W6
A14: ID | B14: Opportunities (external, helpful) | C14: Source | E14: ID | F14: Threats (external, harmful) | G14: Source
A15: O1 | B15: Affordable EU compact segment is under-served | C15: W1 | E15: T1 | F15: EU tariffs on China-built BEVs | G15: P2
A16: O2 | B16: Fleet CO2 targets lift BEV demand | C16: P5 | E16: T2 | F16: Local-content rules for incentives | G16: P6
A17: O3 | E17: T3
A18: O4 | E18: T4
A19: O5 | E19: T5
A20: O6 | E20: T6
A23: Cell | B23: TOWS strategic option | C23: Pairs (e.g. S1 × O1)
A24: ST | B24: Build an EU plant to avoid tariffs | C24: S1 × T1
A25: SO | B25: Launch a sub-EUR 25k compact | C25: S1 × O1
A26: WT | B26: Partner with a European OEM for local assembly and brand | C26: W1 × T2

Sheet Decision Matrix
A1: Decision Matrix
A2: Weight each criterion 1-5 and score each option 1-5. Include do nothing.
A3: Pre-filled from your StratOS ledger. Blue text on cream = inputs you can change. Black on grey = formulas (do not type over them).
A5: Criterion | B5: Weight 1-5 | C5: Tied to goal | D5: A. EU plant | E5: B. Partner | F5: 0. Do nothing | G5: Option 4 | H5: Option 5
A6: Profit by 2029 | B6: 5 | C6: B1 | D6: 4 | E6: 3 | F6: 1
A7: Avoids tariffs | B7: 4 | C7: B2 | D7: 5 | E7: 4 | F7: 1
A8: Capital at risk (low = good) | B8: 3 | C8: B1 | D8: 1 | E8: 4 | F8: 5
A9: Builds EU brand trust | B9: 3 | C9: B3 | D9: 3 | E9: 5 | F9: 1
A14: Weighted score (out of 5) | D14: =IF(COUNT(D6:D13)=0,"",SUMPRODUCT($B$6:$B$13,D6:D13)/SUMPRODUCT($B$6:$B$13*(D6:D13<>""))) -> 3.4666667 | E14: =IF(COUNT(E6:E13)=0,"",SUMPRODUCT($B$6:$B$13,E6:E13)/SUMPRODUCT($B$6:$B$13*(E6:E13<>""))) -> 3.8666667 | F14: =IF(COUNT(F6:F13)=0,"",SUMPRODUCT($B$6:$B$13,F6:F13)/SUMPRODUCT($B$6:$B$13*(F6:F13<>""))) -> 1.8 | G14: =IF(COUNT(G6:G13)=0,"",SUMPRODUCT($B$6:$B$13,G6:G13)/SUMPRODUCT($B$6:$B$13*(G6:G13<>""))) | H14: =IF(COUNT(H6:H13)=0,"",SUMPRODUCT($B$6:$B$13,H6:H13)/SUMPRODUCT($B$6:$B$13*(H6:H13<>"")))
A15: Rank | D15: =IF(D14="","",RANK(D14,$D$14:$H$14)) -> 2 | E15: =IF(E14="","",RANK(E14,$D$14:$H$14)) -> 1 | F15: =IF(F14="","",RANK(F14,$D$14:$H$14)) -> 3 | G15: =IF(G14="","",RANK(G14,$D$14:$H$14)) | H15: =IF(H14="","",RANK(H14,$D$14:$H$14))
A17: The matrix ranks; it does not choose. The recommendation is yours.

Sheet Expected Value
A1: Expected Value
A2: Probabilities as percentages that sum to 100% per option; NPV in $M. Follows the course handout 'Choosing Among Strategic Alternatives'.
A3: Pre-filled from your StratOS ledger. Blue text on cream = inputs you can change. Black on grey = formulas (do not type over them).
A5: Option | B5: P strong | C5: NPV strong ($M) | D5: P moderate | E5: NPV moderate ($M) | F5: P weak | G5: NPV weak ($M) | H5: Probability check | I5: Expected NPV ($M) | J5: Worst case | K5: Best case
A6: A. EU plant | B6: 0.3 | C6: 620 | D6: 0.5 | E6: -35 | F6: 0.2 | G6: -540 | H6: =IF(A6="","",IF(ABS(B6+D6+F6-1)<0.001,"OK","Must sum to 100%")) -> OK | I6: =IF(A6="","",B6*C6+D6*E6+F6*G6) -> 60.5 | J6: =IF(A6="","",MIN(C6,E6,G6)) -> -540 | K6: =IF(A6="","",MAX(C6,E6,G6)) -> 620
A7: B. Partner | B7: 0.3 | C7: 260 | D7: 0.5 | E7: 40 | F7: 0.2 | G7: -60 | H7: =IF(A7="","",IF(ABS(B7+D7+F7-1)<0.001,"OK","Must sum to 100%")) -> OK | I7: =IF(A7="","",B7*C7+D7*E7+F7*G7) -> 86 | J7: =IF(A7="","",MIN(C7,E7,G7)) -> -60 | K7: =IF(A7="","",MAX(C7,E7,G7)) -> 260
A8: 0. Do nothing | B8: 0.3 | C8: 0 | D8: 0.5 | E8: 0 | F8: 0.2 | G8: 0 | H8: =IF(A8="","",IF(ABS(B8+D8+F8-1)<0.001,"OK","Must sum to 100%")) -> OK | I8: =IF(A8="","",B8*C8+D8*E8+F8*G8) -> 0 | J8: =IF(A8="","",MIN(C8,E8,G8)) -> 0 | K8: =IF(A8="","",MAX(C8,E8,G8)) -> 0
H9: =IF(A9="","",IF(ABS(B9+D9+F9-1)<0.001,"OK","Must sum to 100%")) | I9: =IF(A9="","",B9*C9+D9*E9+F9*G9) | J9: =IF(A9="","",MIN(C9,E9,G9)) | K9: =IF(A9="","",MAX(C9,E9,G9))
H10: =IF(A10="","",IF(ABS(B10+D10+F10-1)<0.001,"OK","Must sum to 100%")) | I10: =IF(A10="","",B10*C10+D10*E10+F10*G10) | J10: =IF(A10="","",MIN(C10,E10,G10)) | K10: =IF(A10="","",MAX(C10,E10,G10))
H11: =IF(A11="","",IF(ABS(B11+D11+F11-1)<0.001,"OK","Must sum to 100%")) | I11: =IF(A11="","",B11*C11+D11*E11+F11*G11) | J11: =IF(A11="","",MIN(C11,E11,G11)) | K11: =IF(A11="","",MAX(C11,E11,G11))
A13: Leader on expected value | B13: =IFERROR(INDEX(A6:A11,MATCH(MAX(I6:I11),I6:I11,0)),"") -> B. Partner
A14: Maximin choice (best worst case) | B14: =IFERROR(INDEX(A6:A11,MATCH(MAX(J6:J11),J6:J11,0)),"") -> 0. Do nothing
A15: Value of perfect information ($M) | B15: =IFERROR(INDEX(B6:B11,MATCH(MAX(I6:I11),I6:I11,0))*MAX(C6:C11)+INDEX(D6:D11,MATCH(MAX(I6:I11),I6:I11,0))*MAX(E6:E11)+INDEX(F6:F11,MATCH(MAX(I6:I11),I6:I11,0))*MAX(G6:G11)-MAX(I6:I11),"") -> 120 | C15: The most worth paying for a pilot that reveals the scenario first (leader's probabilities).
A18: Is a pilot worth it? (Bayes' rule) | B18: How likely the pilot shows each result IF that scenario is real. Each row sums to 100%. Uses the first option's scenario probabilities as the prior.
A19: Scenario | B19: Prior | C19: P(positive | scenario) | D19: P(negative | scenario) | E19: Row check | F19: Posterior if positive | G19: Posterior if negative
A20: Strong | B20: =IF(B6="","",B6) -> 0.3 | C20: 0.8 | D20: 0.2 | E20: =IF(C20="","",IF(ABS(C20+D20-1)<0.001,"OK","Must sum to 100%")) -> OK | F20: =IFERROR(B20*C20/SUMPRODUCT($B$20:$B$22,$C$20:$C$22),"") -> 0.46153846 | G20: =IFERROR(B20*D20/SUMPRODUCT($B$20:$B$22,$D$20:$D$22),"") -> 0.125
A21: Moderate | B21: =IF(D6="","",D6) -> 0.5 | C21: 0.5 | D21: 0.5 | E21: =IF(C21="","",IF(ABS(C21+D21-1)<0.001,"OK","Must sum to 100%")) -> OK | F21: =IFERROR(B21*C21/SUMPRODUCT($B$20:$B$22,$C$20:$C$22),"") -> 0.48076923 | G21: =IFERROR(B21*D21/SUMPRODUCT($B$20:$B$22,$D$20:$D$22),"") -> 0.52083333
A22: Weak | B22: =IF(F6="","",F6) -> 0.2 | C22: 0.15 | D22: 0.85 | E22: =IF(C22="","",IF(ABS(C22+D22-1)<0.001,"OK","Must sum to 100%")) -> OK | F22: =IFERROR(B22*C22/SUMPRODUCT($B$20:$B$22,$C$20:$C$22),"") -> 0.057692308 | G22: =IFERROR(B22*D22/SUMPRODUCT($B$20:$B$22,$D$20:$D$22),"") -> 0.35416667
A23: P(result) | F23: =IFERROR(SUMPRODUCT(B20:B22,C20:C22),"") -> 0.52 | G23: =IFERROR(SUMPRODUCT(B20:B22,D20:D22),"") -> 0.48
A25: Option | B25: Expected NPV now | C25: If positive | D25: If negative
A26: =IF(A6="","",A6) -> A. EU plant | B26: =IF(A6="","",I6) -> 60.5 | C26: =IF(OR(A6="",F20=""),"",C6*F20+E6*F21+G6*F22) -> 238.17308 | D26: =IF(OR(A6="",G20=""),"",C6*G20+E6*G21+G6*G22) -> -131.97917
A27: =IF(A7="","",A7) -> B. Partner | B27: =IF(A7="","",I7) -> 86 | C27: =IF(OR(A7="",F20=""),"",C7*F20+E7*F21+G7*F22) -> 135.76923 | D27: =IF(OR(A7="",G20=""),"",C7*G20+E7*G21+G7*G22) -> 32.083333
A28: =IF(A8="","",A8) -> 0. Do nothing | B28: =IF(A8="","",I8) -> 0 | C28: =IF(OR(A8="",F20=""),"",C8*F20+E8*F21+G8*F22) -> 0 | D28: =IF(OR(A8="",G20=""),"",C8*G20+E8*G21+G8*G22) -> 0
A29: =IF(A9="","",A9) | B29: =IF(A9="","",I9) | C29: =IF(OR(A9="",F20=""),"",C9*F20+E9*F21+G9*F22) | D29: =IF(OR(A9="",G20=""),"",C9*G20+E9*G21+G9*G22)
A30: =IF(A10="","",A10) | B30: =IF(A10="","",I10) | C30: =IF(OR(A10="",F20=""),"",C10*F20+E10*F21+G10*F22) | D30: =IF(OR(A10="",G20=""),"",C10*G20+E10*G21+G10*G22)
A31: =IF(A11="","",A11) | B31: =IF(A11="","",I11) | C31: =IF(OR(A11="",F20=""),"",C11*F20+E11*F21+G11*F22) | D31: =IF(OR(A11="",G20=""),"",C11*G20+E11*G21+G11*G22)
A33: Best option if the pilot is positive | B33: =IFERROR(INDEX(A26:A31,MATCH(MAX(C26:C31),C26:C31,0)),"") -> A. EU plant | C33: If both results point to the same option, the pilot cannot change the choice and is worth nothing for this decision.
A34: Best option if the pilot is negative | B34: =IFERROR(INDEX(A26:A31,MATCH(MAX(D26:D31),D26:D31,0)),"") -> B. Partner
A35: Expected NPV with the pilot ($M) | B35: =IFERROR(F23*MAX(C26:C31)+G23*MAX(D26:D31),"") -> 139.25
A36: Value of the pilot, EVSI ($M) | B36: =IFERROR(B35-MAX(I6:I11),"") -> 53.25
A37: Pilot cost ($M) | B37: 25
A38: Net value of running the pilot ($M) | B38: =IFERROR(IF(B37="","",B36-B37),"") -> 28.25
A39: Share of perfect information | B39: =IFERROR(B36/B15,"") -> 0.44375

Sheet Business Case
A1: Business Case
A2: One option. Year 0 is the investment year. Working capital is released in the final year. Money in $.
A3: Pre-filled from your StratOS ledger. Blue text on cream = inputs you can change. Black on grey = formulas (do not type over them).
A4: Option: A. EU plant (from the ledger)
A5: Assumptions
A6: Discount rate | B6: 0.1
A7: Tax rate | B7: 0.21
A8: Working capital (% of revenue) | B8: 0.05
A10: $ | B10: Year 0 | C10: Year 1 | D10: Year 2 | E10: Year 3 | F10: Year 4 | G10: Year 5
A11: Units | B11: 0 | C11: 32400 | D11: 64800 | E11: 97200 | F11: 108000 | G11: 108000
A12: Price per unit | B12: 32000 | C12: 32000 | D12: 32000 | E12: 32000 | F12: 32000 | G12: 32000
A13: Variable cost per unit | B13: 20000 | C13: 20000 | D13: 20000 | E13: 20000 | F13: 20000 | G13: 20000
A14: Fixed costs | B14: 0 | C14: 180000000 | D14: 180000000 | E14: 180000000 | F14: 180000000 | G14: 180000000
A15: Capex | B15: 2000000000 | C15: 100000000 | D15: 100000000 | E15: 50000000 | F15: 50000000 | G15: 50000000
A16: Revenue | B16: =B11*B12 -> 0 | C16: =C11*C12 -> 1036800000 | D16: =D11*D12 -> 2073600000 | E16: =E11*E12 -> 3110400000 | F16: =F11*F12 -> 3456000000 | G16: =G11*G12 -> 3456000000
A17: Contribution | B17: =B11*(B12-B13) -> 0 | C17: =C11*(C12-C13) -> 388800000 | D17: =D11*(D12-D13) -> 777600000 | E17: =E11*(E12-E13) -> 1166400000 | F17: =F11*(F12-F13) -> 1296000000 | G17: =G11*(G12-G13) -> 1296000000
A18: Operating profit (EBIT) | B18: =B17-B14 -> 0 | C18: =C17-C14 -> 208800000 | D18: =D17-D14 -> 597600000 | E18: =E17-E14 -> 986400000 | F18: =F17-F14 -> 1116000000 | G18: =G17-G14 -> 1116000000
A19: Tax | B19: =MAX(0,B18)*$B$7 -> 0 | C19: =MAX(0,C18)*$B$7 -> 43848000 | D19: =MAX(0,D18)*$B$7 -> 125496000 | E19: =MAX(0,E18)*$B$7 -> 207144000 | F19: =MAX(0,F18)*$B$7 -> 234360000 | G19: =MAX(0,G18)*$B$7 -> 234360000
A20: Working capital | B20: =B16*$B$8 -> 0 | C20: =C16*$B$8 -> 51840000 | D20: =D16*$B$8 -> 103680000 | E20: =E16*$B$8 -> 155520000 | F20: =F16*$B$8 -> 172800000 | G20: =G16*$B$8 -> 172800000
A21: Change in working capital | B21: =B20 -> 0 | C21: =C20-B20 -> 51840000 | D21: =D20-C20 -> 51840000 | E21: =E20-D20 -> 51840000 | F21: =F20-E20 -> 17280000 | G21: =G20-F20 -> 0
A22: Cash flow | B22: =B18-B19-B21-B15 -> -2000000000 | C22: =C18-C19-C21-C15 -> 13112000 | D22: =D18-D19-D21-D15 -> 320264000 | E22: =E18-E19-E21-E15 -> 677416000 | F22: =F18-F19-F21-F15 -> 814360000 | G22: =G18-G19-G21-G15+G20 -> 1004440000
A23: Cumulative cash flow | B23: =B22 -> -2000000000 | C23: =B23+C22 -> -1986888000 | D23: =C23+D22 -> -1666624000 | E23: =D23+E22 -> -989208000 | F23: =E23+F22 -> -174848000 | G23: =F23+G22 -> 829592000
A25: NPV | B25: =IF(COUNT(B11:G11)=0,"",B22+NPV($B$6,C22:G22)) -> -34549290
A26: IRR | B26: =IFERROR(IRR(B22:G22),"n/a") -> 0.09493193
A27: Clears the hurdle? | B27: =IF(ISNUMBER(B26),IF(B26>=$B$6,"Yes","No"),"") -> No
A29: State the break-even in words in your exhibit (the Business Case skill computes it).

Sheet Risk Analysis
A1: Risk Analysis (Exhibit Q-3)
A2: Works on the Business Case sheet. Set a low / likely / high for each driver: % change from plan, except the discount rate (an absolute rate). Blank = no uncertainty.
A3: Pre-filled from your StratOS ledger. Blue text on cream = inputs you can change. Black on grey = formulas (do not type over them).
A5: Driver | B5: Low | C5: Likely | D5: High | E5: Eff. low | F5: Eff. likely | G5: Eff. high
A6: Price per unit | B6: -0.08 | C6: 0 | D6: 0.04 | E6: =IF(B6="",F6,B6) -> -0.08 | F6: =IF(C6="",0,C6) -> 0 | G6: =IF(D6="",F6,D6) -> 0.04
A7: Units | B7: -0.2 | C7: 0 | D7: 0.15 | E7: =IF(B7="",F7,B7) -> -0.2 | F7: =IF(C7="",0,C7) -> 0 | G7: =IF(D7="",F7,D7) -> 0.15
A8: Variable cost per unit | B8: -0.05 | C8: 0 | D8: 0.08 | E8: =IF(B8="",F8,B8) -> -0.05 | F8: =IF(C8="",0,C8) -> 0 | G8: =IF(D8="",F8,D8) -> 0.08
A9: Fixed costs | B9: -0.05 | C9: 0 | D9: 0.1 | E9: =IF(B9="",F9,B9) -> -0.05 | F9: =IF(C9="",0,C9) -> 0 | G9: =IF(D9="",F9,D9) -> 0.1
A10: Capex | B10: -0.05 | C10: 0 | D10: 0.2 | E10: =IF(B10="",F10,B10) -> -0.05 | F10: =IF(C10="",0,C10) -> 0 | G10: =IF(D10="",F10,D10) -> 0.2
A11: Discount rate (absolute) | B11: 0.09 | C11: 0.1 | D11: 0.12 | E11: =IF(B11="",F11,B11) -> 0.09 | F11: =IF(C11="",'Business Case'!$B$6,C11) -> 0.1 | G11: =IF(D11="",F11,D11) -> 0.12
A12: Range check | B12: =IF(SUMPRODUCT((E6:E11>F6:F11)+(F6:F11>G6:G11))=0,"OK","Need low <= likely <= high") -> OK
A14: Tornado: NPV with one driver at its low or high, the others at plan
A15: Scenario | B15: Price × | C15: Units × | D15: Var. cost × | E15: Fixed × | F15: Capex × | G15: Rate | H15: CF Y0 | I15: CF Y1 | J15: CF Y2 | K15: CF Y3 | L15: CF Y4 | M15: CF Y5 | N15: NPV
A16: Plan | B16: =1 -> 1 | C16: =1 -> 1 | D16: =1 -> 1 | E16: =1 -> 1 | F16: =1 -> 1 | G16: ='Business Case'!$B$6 -> 0.1 | H16: =(('Business Case'!B11*$C16*'Business Case'!B12*$B16)-'Business Case'!B11*$C16*'Business Case'!B13*$D16-'Business Case'!B14*$E16)-MAX(0,(('Business Case'!B11*$C16*'Business Case'!B12*$B16)-'Business Case'!B11*$C16*'Business Case'!B13*$D16-'Business Case'!B14*$E16))*'Business Case'!$B$7-'Business Case'!$B$8*('Business Case'!B11*$C16*'Business Case'!B12*$B16)-'Business Case'!B15*$F16 -> -2000000000 | I16: =(('Business Case'!C11*$C16*'Business Case'!C12*$B16)-'Business Case'!C11*$C16*'Business Case'!C13*$D16-'Business Case'!C14*$E16)-MAX(0,(('Business Case'!C11*$C16*'Business Case'!C12*$B16)-'Business Case'!C11*$C16*'Business Case'!C13*$D16-'Business Case'!C14*$E16))*'Business Case'!$B$7-'Business Case'!$B$8*(('Business Case'!C11*$C16*'Business Case'!C12*$B16)-('Business Case'!B11*$C16*'Business Case'!B12*$B16))-'Business Case'!C15*$F16 -> 13112000 | J16: =(('Business Case'!D11*$C16*'Business Case'!D12*$B16)-'Business Case'!D11*$C16*'Business Case'!D13*$D16-'Business Case'!D14*$E16)-MAX(0,(('Business Case'!D11*$C16*'Business Case'!D12*$B16)-'Business Case'!D11*$C16*'Business Case'!D13*$D16-'Business Case'!D14*$E16))*'Business Case'!$B$7-'Business Case'!$B$8*(('Business Case'!D11*$C16*'Business Case'!D12*$B16)-('Business Case'!C11*$C16*'Business Case'!C12*$B16))-'Business Case'!D15*$F16 -> 320264000 | K16: =(('Business Case'!E11*$C16*'Business Case'!E12*$B16)-'Business Case'!E11*$C16*'Business Case'!E13*$D16-'Business Case'!E14*$E16)-MAX(0,(('Business Case'!E11*$C16*'Business Case'!E12*$B16)-'Business Case'!E11*$C16*'Business Case'!E13*$D16-'Business Case'!E14*$E16))*'Business Case'!$B$7-'Business Case'!$B$8*(('Business Case'!E11*$C16*'Business Case'!E12*$B16)-('Business Case'!D11*$C16*'Business Case'!D12*$B16))-'Business Case'!E15*$F16 -> 677416000 | L16: =(('Business Case'!F11*$C16*'Business Case'!F12*$B16)-'Business Case'!F11*$C16*'Business Case'!F13*$D16-'Business Case'!F14*$E16)-MAX(0,(('Business Case'!F11*$C16*'Business Case'!F12*$B16)-'Business Case'!F11*$C16*'Business Case'!F13*$D16-'Business Case'!F14*$E16))*'Business Case'!$B$7-'Business Case'!$B$8*(('Business Case'!F11*$C16*'Business Case'!F12*$B16)-('Business Case'!E11*$C16*'Business Case'!E12*$B16))-'Business Case'!F15*$F16 -> 814360000 | M16: =(('Business Case'!G11*$C16*'Business Case'!G12*$B16)-'Business Case'!G11*$C16*'Business Case'!G13*$D16-'Business Case'!G14*$E16)-MAX(0,(('Business Case'!G11*$C16*'Business Case'!G12*$B16)-'Business Case'!G11*$C16*'Business Case'!G13*$D16-'Business Case'!G14*$E16))*'Business Case'!$B$7-'Business Case'!$B$8*(('Business Case'!G11*$C16*'Business Case'!G12*$B16)-('Business Case'!F11*$C16*'Business Case'!F12*$B16))-'Business Case'!G15*$F16+'Business Case'!$B$8*('Business Case'!G11*$C16*'Business Case'!G12*$B16) -> 1004440000 | N16: =IF(COUNT('Business Case'!B11:G11)=0,"",H16+NPV(G16,I16:M16)) -> -34549290
A17: Price per unit low | B17: =1+E6 -> 0.92 | C17: =1 -> 1 | D17: =1 -> 1 | E17: =1 -> 1 | F17: =1 -> 1 | G17: ='Business Case'!$B$6 -> 0.1 | H17: =(('Business Case'!B11*$C17*'Business Case'!B12*$B17)-'Business Case'!B11*$C17*'Business Case'!B13*$D17-'Business Case'!B14*$E17)-MAX(0,(('Business Case'!B11*$C17*'Business Case'!B12*$B17)-'Business Case'!B11*$C17*'Business Case'!B13*$D17-'Business Case'!B14*$E17))*'Business Case'!$B$7-'Business Case'!$B$8*('Business Case'!B11*$C17*'Business Case'!B12*$B17)-'Business Case'!B15*$F17 -> -2000000000 | I17: =(('Business Case'!C11*$C17*'Business Case'!C12*$B17)-'Business Case'!C11*$C17*'Business Case'!C13*$D17-'Business Case'!C14*$E17)-MAX(0,(('Business Case'!C11*$C17*'Business Case'!C12*$B17)-'Business Case'!C11*$C17*'Business Case'!C13*$D17-'Business Case'!C14*$E17))*'Business Case'!$B$7-'Business Case'!$B$8*(('Business Case'!C11*$C17*'Business Case'!C12*$B17)-('Business Case'!B11*$C17*'Business Case'!B12*$B17))-'Business Case'!C15*$F17 -> -48266560 | J17: =(('Business Case'!D11*$C17*'Business Case'!D12*$B17)-'Business Case'!D11*$C17*'Business Case'!D13*$D17-'Business Case'!D14*$E17)-MAX(0,(('Business Case'!D11*$C17*'Business Case'!D12*$B17)-'Business Case'!D11*$C17*'Business Case'!D13*$D17-'Business Case'!D14*$E17))*'Business Case'!$B$7-'Business Case'!$B$8*(('Business Case'!D11*$C17*'Business Case'!D12*$B17)-('Business Case'!C11*$C17*'Business Case'!C12*$B17))-'Business Case'!D15*$F17 -> 193359680 | K17: =(('Business Case'!E11*$C17*'Business Case'!E12*$B17)-'Business Case'!E11*$C17*'Business Case'!E13*$D17-'Business Case'!E14*$E17)-MAX(0,(('Business Case'!E11*$C17*'Business Case'!E12*$B17)-'Business Case'!E11*$C17*'Business Case'!E13*$D17-'Business Case'!E14*$E17))*'Business Case'!$B$7-'Business Case'!$B$8*(('Business Case'!E11*$C17*'Business Case'!E12*$B17)-('Business Case'!D11*$C17*'Business Case'!D12*$B17))-'Business Case'!E15*$F17 -> 484985920 | L17: =(('Business Case'!F11*$C17*'Business Case'!F12*$B17)-'Business Case'!F11*$C17*'Business Case'!F13*$D17-'Business Case'!F14*$E17)-MAX(0,(('Business Case'!F11*$C17*'Business Case'!F12*$B17)-'Business Case'!F11*$C17*'Business Case'!F13*$D17-'Business Case'!F14*$E17))*'Business Case'!$B$7-'Business Case'!$B$8*(('Business Case'!F11*$C17*'Business Case'!F12*$B17)-('Business Case'!E11*$C17*'Business Case'!E12*$B17))-'Business Case'!F15*$F17 -> 597323200 | M17: =(('Business Case'!G11*$C17*'Business Case'!G12*$B17)-'Business Case'!G11*$C17*'Business Case'!G13*$D17-'Business Case'!G14*$E17)-MAX(0,(('Business Case'!G11*$C17*'Business Case'!G12*$B17)-'Business Case'!G11*$C17*'Business Case'!G13*$D17-'Business Case'!G14*$E17))*'Business Case'!$B$7-'Business Case'!$B$8*(('Business Case'!G11*$C17*'Business Case'!G12*$B17)-('Business Case'!F11*$C17*'Business Case'!F12*$B17))-'Business Case'!G15*$F17+'Business Case'!$B$8*('Business Case'!G11*$C17*'Business Case'!G12*$B17) -> 772196800 | N17: =IF(COUNT('Business Case'!B11:G11)=0,"",H17+NPV(G17,I17:M17)) -> -6.3224696e+08
A18: Price per unit high | B18: =1+G6 -> 1.04 | C18: =1 -> 1 | D18: =1 -> 1 | E18: =1 -> 1 | F18: =1 -> 1 | G18: ='Business Case'!$B$6 -> 0.1 | H18: =(('Business Case'!B11*$C18*'Business Case'!B12*$B18)-'Business Case'!B11*$C18*'Business Case'!B13*$D18-'Business Case'!B14*$E18)-MAX(0,(('Business Case'!B11*$C18*'Business Case'!B12*$B18)-'Business Case'!B11*$C18*'Business Case'!B13*$D18-'Business Case'!B14*$E18))*'Business Case'!$B$7-'Business Case'!$B$8*('Business Case'!B11*$C18*'Business Case'!B12*$B18)-'Business Case'!B15*$F18 -> -2000000000 | I18: =(('Business Case'!C11*$C18*'Business Case'!C12*$B18)-'Business Case'!C11*$C18*'Business Case'!C13*$D18-'Business Case'!C14*$E18)-MAX(0,(('Business Case'!C11*$C18*'Business Case'!C12*$B18)-'Business Case'!C11*$C18*'Business Case'!C13*$D18-'Business Case'!C14*$E18))*'Business Case'!$B$7-'Business Case'!$B$8*(('Business Case'!C11*$C18*'Business Case'!C12*$B18)-('Business Case'!B11*$C18*'Business Case'!B12*$B18))-'Business Case'!C15*$F18 -> 43801280 | J18: =(('Business Case'!D11*$C18*'Business Case'!D12*$B18)-'Business Case'!D11*$C18*'Business Case'!D13*$D18-'Business Case'!D14*$E18)-MAX(0,(('Business Case'!D11*$C18*'Business Case'!D12*$B18)-'Business Case'!D11*$C18*'Business Case'!D13*$D18-'Business Case'!D14*$E18))*'Business Case'!$B$7-'Business Case'!$B$8*(('Business Case'!D11*$C18*'Business Case'!D12*$B18)-('Business Case'!C11*$C18*'Business Case'!C12*$B18))-'Business Case'!D15*$F18 -> 383716160 | K18: =(('Business Case'!E11*$C18*'Business Case'!E12*$B18)-'Business Case'!E11*$C18*'Business Case'!E13*$D18-'Business Case'!E14*$E18)-MAX(0,(('Business Case'!E11*$C18*'Business Case'!E12*$B18)-'Business Case'!E11*$C18*'Business Case'!E13*$D18-'Business Case'!E14*$E18))*'Business Case'!$B$7-'Business Case'!$B$8*(('Business Case'!E11*$C18*'Business Case'!E12*$B18)-('Business Case'!D11*$C18*'Business Case'!D12*$B18))-'Business Case'!E15*$F18 -> 773631040 | L18: =(('Business Case'!F11*$C18*'Business Case'!F12*$B18)-'Business Case'!F11*$C18*'Business Case'!F13*$D18-'Business Case'!F14*$E18)-MAX(0,(('Business Case'!F11*$C18*'Business Case'!F12*$B18)-'Business Case'!F11*$C18*'Business Case'!F13*$D18-'Business Case'!F14*$E18))*'Business Case'!$B$7-'Business Case'!$B$8*(('Business Case'!F11*$C18*'Business Case'!F12*$B18)-('Business Case'!E11*$C18*'Business Case'!E12*$B18))-'Business Case'!F15*$F18 -> 922878400 | M18: =(('Business Case'!G11*$C18*'Business Case'!G12*$B18)-'Business Case'!G11*$C18*'Business Case'!G13*$D18-'Business Case'!G14*$E18)-MAX(0,(('Business Case'!G11*$C18*'Business Case'!G12*$B18)-'Business Case'!G11*$C18*'Business Case'!G13*$D18-'Business Case'!G14*$E18))*'Business Case'!$B$7-'Business Case'!$B$8*(('Business Case'!G11*$C18*'Business Case'!G12*$B18)-('Business Case'!F11*$C18*'Business Case'!F12*$B18))-'Business Case'!G15*$F18+'Business Case'!$B$8*('Business Case'!G11*$C18*'Business Case'!G12*$B18) -> 1120561600 | N18: =IF(COUNT('Business Case'!B11:G11)=0,"",H18+NPV(G18,I18:M18)) -> 2.6429955e+08
A19: Units low | B19: =1 -> 1 | C19: =1+E7 -> 0.8 | D19: =1 -> 1 | E19: =1 -> 1 | F19: =1 -> 1 | G19: ='Business Case'!$B$6 -> 0.1 | H19: =(('Business Case'!B11*$C19*'Business Case'!B12*$B19)-'Business Case'!B11*$C19*'Business Case'!B13*$D19-'Business Case'!B14*$E19)-MAX(0,(('Business Case'!B11*$C19*'Business Case'!B12*$B19)-'Business Case'!B11*$C19*'Business Case'!B13*$D19-'Business Case'!B14*$E19))*'Business Case'!$B$7-'Business Case'!$B$8*('Business Case'!B11*$C19*'Business Case'!B12*$B19)-'Business Case'!B15*$F19 -> -2000000000 | I19: =(('Business Case'!C11*$C19*'Business Case'!C12*$B19)-'Business Case'!C11*$C19*'Business Case'!C13*$D19-'Business Case'!C14*$E19)-MAX(0,(('Business Case'!C11*$C19*'Business Case'!C12*$B19)-'Business Case'!C11*$C19*'Business Case'!C13*$D19-'Business Case'!C14*$E19))*'Business Case'!$B$7-'Business Case'!$B$8*(('Business Case'!C11*$C19*'Business Case'!C12*$B19)-('Business Case'!B11*$C19*'Business Case'!B12*$B19))-'Business Case'!C15*$F19 -> -37950400 | J19: =(('Business Case'!D11*$C19*'Business Case'!D12*$B19)-'Business Case'!D11*$C19*'Business Case'!D13*$D19-'Business Case'!D14*$E19)-MAX(0,(('Business Case'!D11*$C19*'Business Case'!D12*$B19)-'Business Case'!D11*$C19*'Business Case'!D13*$D19-'Business Case'!D14*$E19))*'Business Case'!$B$7-'Business Case'!$B$8*(('Business Case'!D11*$C19*'Business Case'!D12*$B19)-('Business Case'!C11*$C19*'Business Case'!C12*$B19))-'Business Case'!D15*$F19 -> 207771200 | K19: =(('Business Case'!E11*$C19*'Business Case'!E12*$B19)-'Business Case'!E11*$C19*'Business Case'!E13*$D19-'Business Case'!E14*$E19)-MAX(0,(('Business Case'!E11*$C19*'Business Case'!E12*$B19)-'Business Case'!E11*$C19*'Business Case'!E13*$D19-'Business Case'!E14*$E19))*'Business Case'!$B$7-'Business Case'!$B$8*(('Business Case'!E11*$C19*'Business Case'!E12*$B19)-('Business Case'!D11*$C19*'Business Case'!D12*$B19))-'Business Case'!E15*$F19 -> 503492800 | L19: =(('Business Case'!F11*$C19*'Business Case'!F12*$B19)-'Business Case'!F11*$C19*'Business Case'!F13*$D19-'Business Case'!F14*$E19)-MAX(0,(('Business Case'!F11*$C19*'Business Case'!F12*$B19)-'Business Case'!F11*$C19*'Business Case'!F13*$D19-'Business Case'!F14*$E19))*'Business Case'!$B$7-'Business Case'!$B$8*(('Business Case'!F11*$C19*'Business Case'!F12*$B19)-('Business Case'!E11*$C19*'Business Case'!E12*$B19))-'Business Case'!F15*$F19 -> 613048000 | M19: =(('Business Case'!G11*$C19*'Business Case'!G12*$B19)-'Business Case'!G11*$C19*'Business Case'!G13*$D19-'Business Case'!G14*$E19)-MAX(0,(('Business Case'!G11*$C19*'Business Case'!G12*$B19)-'Business Case'!G11*$C19*'Business Case'!G13*$D19-'Business Case'!G14*$E19))*'Business Case'!$B$7-'Business Case'!$B$8*(('Business Case'!G11*$C19*'Business Case'!G12*$B19)-('Business Case'!F11*$C19*'Business Case'!F12*$B19))-'Business Case'!G15*$F19+'Business Case'!$B$8*('Business Case'!G11*$C19*'Business Case'!G12*$B19) -> 765112000 | N19: =IF(COUNT('Business Case'!B11:G11)=0,"",H19+NPV(G19,I19:M19)) -> -5.9071265e+08
A20: Units high | B20: =1 -> 1 | C20: =1+G7 -> 1.15 | D20: =1 -> 1 | E20: =1 -> 1 | F20: =1 -> 1 | G20: ='Business Case'!$B$6 -> 0.1 | H20: =(('Business Case'!B11*$C20*'Business Case'!B12*$B20)-'Business Case'!B11*$C20*'Business Case'!B13*$D20-'Business Case'!B14*$E20)-MAX(0,(('Business Case'!B11*$C20*'Business Case'!B12*$B20)-'Business Case'!B11*$C20*'Business Case'!B13*$D20-'Business Case'!B14*$E20))*'Business Case'!$B$7-'Business Case'!$B$8*('Business Case'!B11*$C20*'Business Case'!B12*$B20)-'Business Case'!B15*$F20 -> -2000000000 | I20: =(('Business Case'!C11*$C20*'Business Case'!C12*$B20)-'Business Case'!C11*$C20*'Business Case'!C13*$D20-'Business Case'!C14*$E20)-MAX(0,(('Business Case'!C11*$C20*'Business Case'!C12*$B20)-'Business Case'!C11*$C20*'Business Case'!C13*$D20-'Business Case'!C14*$E20))*'Business Case'!$B$7-'Business Case'!$B$8*(('Business Case'!C11*$C20*'Business Case'!C12*$B20)-('Business Case'!B11*$C20*'Business Case'!B12*$B20))-'Business Case'!C15*$F20 -> 51408800 | J20: =(('Business Case'!D11*$C20*'Business Case'!D12*$B20)-'Business Case'!D11*$C20*'Business Case'!D13*$D20-'Business Case'!D14*$E20)-MAX(0,(('Business Case'!D11*$C20*'Business Case'!D12*$B20)-'Business Case'!D11*$C20*'Business Case'!D13*$D20-'Business Case'!D14*$E20))*'Business Case'!$B$7-'Business Case'!$B$8*(('Business Case'!D11*$C20*'Business Case'!D12*$B20)-('Business Case'!C11*$C20*'Business Case'!C12*$B20))-'Business Case'!D15*$F20 -> 404633600 | K20: =(('Business Case'!E11*$C20*'Business Case'!E12*$B20)-'Business Case'!E11*$C20*'Business Case'!E13*$D20-'Business Case'!E14*$E20)-MAX(0,(('Business Case'!E11*$C20*'Business Case'!E12*$B20)-'Business Case'!E11*$C20*'Business Case'!E13*$D20-'Business Case'!E14*$E20))*'Business Case'!$B$7-'Business Case'!$B$8*(('Business Case'!E11*$C20*'Business Case'!E12*$B20)-('Business Case'!D11*$C20*'Business Case'!D12*$B20))-'Business Case'!E15*$F20 -> 807858400 | L20: =(('Business Case'!F11*$C20*'Business Case'!F12*$B20)-'Business Case'!F11*$C20*'Business Case'!F13*$D20-'Business Case'!F14*$E20)-MAX(0,(('Business Case'!F11*$C20*'Business Case'!F12*$B20)-'Business Case'!F11*$C20*'Business Case'!F13*$D20-'Business Case'!F14*$E20))*'Business Case'!$B$7-'Business Case'!$B$8*(('Business Case'!F11*$C20*'Business Case'!F12*$B20)-('Business Case'!E11*$C20*'Business Case'!E12*$B20))-'Business Case'!F15*$F20 -> 965344000 | M20: =(('Business Case'!G11*$C20*'Business Case'!G12*$B20)-'Business Case'!G11*$C20*'Business Case'!G13*$D20-'Business Case'!G14*$E20)-MAX(0,(('Business Case'!G11*$C20*'Business Case'!G12*$B20)-'Business Case'!G11*$C20*'Business Case'!G13*$D20-'Business Case'!G14*$E20))*'Business Case'!$B$7-'Business Case'!$B$8*(('Business Case'!G11*$C20*'Business Case'!G12*$B20)-('Business Case'!F11*$C20*'Business Case'!F12*$B20))-'Business Case'!G15*$F20+'Business Case'!$B$8*('Business Case'!G11*$C20*'Business Case'!G12*$B20) -> 1183936000 | N20: =IF(COUNT('Business Case'!B11:G11)=0,"",H20+NPV(G20,I20:M20)) -> 3.8257323e+08
A21: Variable cost per unit low | B21: =1 -> 1 | C21: =1 -> 1 | D21: =1+E8 -> 0.95 | E21: =1 -> 1 | F21: =1 -> 1 | G21: ='Business Case'!$B$6 -> 0.1 | H21: =(('Business Case'!B11*$C21*'Business Case'!B12*$B21)-'Business Case'!B11*$C21*'Business Case'!B13*$D21-'Business Case'!B14*$E21)-MAX(0,(('Business Case'!B11*$C21*'Business Case'!B12*$B21)-'Business Case'!B11*$C21*'Business Case'!B13*$D21-'Business Case'!B14*$E21))*'Business Case'!$B$7-'Business Case'!$B$8*('Business Case'!B11*$C21*'Business Case'!B12*$B21)-'Business Case'!B15*$F21 -> -2000000000 | I21: =(('Business Case'!C11*$C21*'Business Case'!C12*$B21)-'Business Case'!C11*$C21*'Business Case'!C13*$D21-'Business Case'!C14*$E21)-MAX(0,(('Business Case'!C11*$C21*'Business Case'!C12*$B21)-'Business Case'!C11*$C21*'Business Case'!C13*$D21-'Business Case'!C14*$E21))*'Business Case'!$B$7-'Business Case'!$B$8*(('Business Case'!C11*$C21*'Business Case'!C12*$B21)-('Business Case'!B11*$C21*'Business Case'!B12*$B21))-'Business Case'!C15*$F21 -> 38708000 | J21: =(('Business Case'!D11*$C21*'Business Case'!D12*$B21)-'Business Case'!D11*$C21*'Business Case'!D13*$D21-'Business Case'!D14*$E21)-MAX(0,(('Business Case'!D11*$C21*'Business Case'!D12*$B21)-'Business Case'!D11*$C21*'Business Case'!D13*$D21-'Business Case'!D14*$E21))*'Business Case'!$B$7-'Business Case'!$B$8*(('Business Case'!D11*$C21*'Business Case'!D12*$B21)-('Business Case'!C11*$C21*'Business Case'!C12*$B21))-'Business Case'!D15*$F21 -> 371456000 | K21: =(('Business Case'!E11*$C21*'Business Case'!E12*$B21)-'Business Case'!E11*$C21*'Business Case'!E13*$D21-'Business Case'!E14*$E21)-MAX(0,(('Business Case'!E11*$C21*'Business Case'!E12*$B21)-'Business Case'!E11*$C21*'Business Case'!E13*$D21-'Business Case'!E14*$E21))*'Business Case'!$B$7-'Business Case'!$B$8*(('Business Case'!E11*$C21*'Business Case'!E12*$B21)-('Business Case'!D11*$C21*'Business Case'!D12*$B21))-'Business Case'!E15*$F21 -> 754204000 | L21: =(('Business Case'!F11*$C21*'Business Case'!F12*$B21)-'Business Case'!F11*$C21*'Business Case'!F13*$D21-'Business Case'!F14*$E21)-MAX(0,(('Business Case'!F11*$C21*'Business Case'!F12*$B21)-'Business Case'!F11*$C21*'Business Case'!F13*$D21-'Business Case'!F14*$E21))*'Business Case'!$B$7-'Business Case'!$B$8*(('Business Case'!F11*$C21*'Business Case'!F12*$B21)-('Business Case'!E11*$C21*'Business Case'!E12*$B21))-'Business Case'!F15*$F21 -> 899680000 | M21: =(('Business Case'!G11*$C21*'Business Case'!G12*$B21)-'Business Case'!G11*$C21*'Business Case'!G13*$D21-'Business Case'!G14*$E21)-MAX(0,(('Business Case'!G11*$C21*'Business Case'!G12*$B21)-'Business Case'!G11*$C21*'Business Case'!G13*$D21-'Business Case'!G14*$E21))*'Business Case'!$B$7-'Business Case'!$B$8*(('Business Case'!G11*$C21*'Business Case'!G12*$B21)-('Business Case'!F11*$C21*'Business Case'!F12*$B21))-'Business Case'!G15*$F21+'Business Case'!$B$8*('Business Case'!G11*$C21*'Business Case'!G12*$B21) -> 1089760000 | N21: =IF(COUNT('Business Case'!B11:G11)=0,"",H21+NPV(G21,I21:M21)) -> 1.9997092e+08
A22: Variable cost per unit high | B22: =1 -> 1 | C22: =1 -> 1 | D22: =1+G8 -> 1.08 | E22: =1 -> 1 | F22: =1 -> 1 | G22: ='Business Case'!$B$6 -> 0.1 | H22: =(('Business Case'!B11*$C22*'Business Case'!B12*$B22)-'Business Case'!B11*$C22*'Business Case'!B13*$D22-'Business Case'!B14*$E22)-MAX(0,(('Business Case'!B11*$C22*'Business Case'!B12*$B22)-'Business Case'!B11*$C22*'Business Case'!B13*$D22-'Business Case'!B14*$E22))*'Business Case'!$B$7-'Business Case'!$B$8*('Business Case'!B11*$C22*'Business Case'!B12*$B22)-'Business Case'!B15*$F22 -> -2000000000 | I22: =(('Business Case'!C11*$C22*'Business Case'!C12*$B22)-'Business Case'!C11*$C22*'Business Case'!C13*$D22-'Business Case'!C14*$E22)-MAX(0,(('Business Case'!C11*$C22*'Business Case'!C12*$B22)-'Business Case'!C11*$C22*'Business Case'!C13*$D22-'Business Case'!C14*$E22))*'Business Case'!$B$7-'Business Case'!$B$8*(('Business Case'!C11*$C22*'Business Case'!C12*$B22)-('Business Case'!B11*$C22*'Business Case'!B12*$B22))-'Business Case'!C15*$F22 -> -27841600 | J22: =(('Business Case'!D11*$C22*'Business Case'!D12*$B22)-'Business Case'!D11*$C22*'Business Case'!D13*$D22-'Business Case'!D14*$E22)-MAX(0,(('Business Case'!D11*$C22*'Business Case'!D12*$B22)-'Business Case'!D11*$C22*'Business Case'!D13*$D22-'Business Case'!D14*$E22))*'Business Case'!$B$7-'Business Case'!$B$8*(('Business Case'!D11*$C22*'Business Case'!D12*$B22)-('Business Case'!C11*$C22*'Business Case'!C12*$B22))-'Business Case'!D15*$F22 -> 238356800 | K22: =(('Business Case'!E11*$C22*'Business Case'!E12*$B22)-'Business Case'!E11*$C22*'Business Case'!E13*$D22-'Business Case'!E14*$E22)-MAX(0,(('Business Case'!E11*$C22*'Business Case'!E12*$B22)-'Business Case'!E11*$C22*'Business Case'!E13*$D22-'Business Case'!E14*$E22))*'Business Case'!$B$7-'Business Case'!$B$8*(('Business Case'!E11*$C22*'Business Case'!E12*$B22)-('Business Case'!D11*$C22*'Business Case'!D12*$B22))-'Business Case'!E15*$F22 -> 554555200 | L22: =(('Business Case'!F11*$C22*'Business Case'!F12*$B22)-'Business Case'!F11*$C22*'Business Case'!F13*$D22-'Business Case'!F14*$E22)-MAX(0,(('Business Case'!F11*$C22*'Business Case'!F12*$B22)-'Business Case'!F11*$C22*'Business Case'!F13*$D22-'Business Case'!F14*$E22))*'Business Case'!$B$7-'Business Case'!$B$8*(('Business Case'!F11*$C22*'Business Case'!F12*$B22)-('Business Case'!E11*$C22*'Business Case'!E12*$B22))-'Business Case'!F15*$F22 -> 677848000 | M22: =(('Business Case'!G11*$C22*'Business Case'!G12*$B22)-'Business Case'!G11*$C22*'Business Case'!G13*$D22-'Business Case'!G14*$E22)-MAX(0,(('Business Case'!G11*$C22*'Business Case'!G12*$B22)-'Business Case'!G11*$C22*'Business Case'!G13*$D22-'Business Case'!G14*$E22))*'Business Case'!$B$7-'Business Case'!$B$8*(('Business Case'!G11*$C22*'Business Case'!G12*$B22)-('Business Case'!F11*$C22*'Business Case'!F12*$B22))-'Business Case'!G15*$F22+'Business Case'!$B$8*('Business Case'!G11*$C22*'Business Case'!G12*$B22) -> 867928000 | N22: =IF(COUNT('Business Case'!B11:G11)=0,"",H22+NPV(G22,I22:M22)) -> -4.0978162e+08
A23: Fixed costs low | B23: =1 -> 1 | C23: =1 -> 1 | D23: =1 -> 1 | E23: =1+E9 -> 0.95 | F23: =1 -> 1 | G23: ='Business Case'!$B$6 -> 0.1 | H23: =(('Business Case'!B11*$C23*'Business Case'!B12*$B23)-'Business Case'!B11*$C23*'Business Case'!B13*$D23-'Business Case'!B14*$E23)-MAX(0,(('Business Case'!B11*$C23*'Business Case'!B12*$B23)-'Business Case'!B11*$C23*'Business Case'!B13*$D23-'Business Case'!B14*$E23))*'Business Case'!$B$7-'Business Case'!$B$8*('Business Case'!B11*$C23*'Business Case'!B12*$B23)-'Business Case'!B15*$F23 -> -2000000000 | I23: =(('Business Case'!C11*$C23*'Business Case'!C12*$B23)-'Business Case'!C11*$C23*'Business Case'!C13*$D23-'Business Case'!C14*$E23)-MAX(0,(('Business Case'!C11*$C23*'Business Case'!C12*$B23)-'Business Case'!C11*$C23*'Business Case'!C13*$D23-'Business Case'!C14*$E23))*'Business Case'!$B$7-'Business Case'!$B$8*(('Business Case'!C11*$C23*'Business Case'!C12*$B23)-('Business Case'!B11*$C23*'Business Case'!B12*$B23))-'Business Case'!C15*$F23 -> 20222000 | J23: =(('Business Case'!D11*$C23*'Business Case'!D12*$B23)-'Business Case'!D11*$C23*'Business Case'!D13*$D23-'Business Case'!D14*$E23)-MAX(0,(('Business Case'!D11*$C23*'Business Case'!D12*$B23)-'Business Case'!D11*$C23*'Business Case'!D13*$D23-'Business Case'!D14*$E23))*'Business Case'!$B$7-'Business Case'!$B$8*(('Business Case'!D11*$C23*'Business Case'!D12*$B23)-('Business Case'!C11*$C23*'Business Case'!C12*$B23))-'Business Case'!D15*$F23 -> 327374000 | K23: =(('Business Case'!E11*$C23*'Business Case'!E12*$B23)-'Business Case'!E11*$C23*'Business Case'!E13*$D23-'Business Case'!E14*$E23)-MAX(0,(('Business Case'!E11*$C23*'Business Case'!E12*$B23)-'Business Case'!E11*$C23*'Business Case'!E13*$D23-'Business Case'!E14*$E23))*'Business Case'!$B$7-'Business Case'!$B$8*(('Business Case'!E11*$C23*'Business Case'!E12*$B23)-('Business Case'!D11*$C23*'Business Case'!D12*$B23))-'Business Case'!E15*$F23 -> 684526000 | L23: =(('Business Case'!F11*$C23*'Business Case'!F12*$B23)-'Business Case'!F11*$C23*'Business Case'!F13*$D23-'Business Case'!F14*$E23)-MAX(0,(('Business Case'!F11*$C23*'Business Case'!F12*$B23)-'Business Case'!F11*$C23*'Business Case'!F13*$D23-'Business Case'!F14*$E23))*'Business Case'!$B$7-'Business Case'!$B$8*(('Business Case'!F11*$C23*'Business Case'!F12*$B23)-('Business Case'!E11*$C23*'Business Case'!E12*$B23))-'Business Case'!F15*$F23 -> 821470000 | M23: =(('Business Case'!G11*$C23*'Business Case'!G12*$B23)-'Business Case'!G11*$C23*'Business Case'!G13*$D23-'Business Case'!G14*$E23)-MAX(0,(('Business Case'!G11*$C23*'Business Case'!G12*$B23)-'Business Case'!G11*$C23*'Business Case'!G13*$D23-'Business Case'!G14*$E23))*'Business Case'!$B$7-'Business Case'!$B$8*(('Business Case'!G11*$C23*'Business Case'!G12*$B23)-('Business Case'!F11*$C23*'Business Case'!F12*$B23))-'Business Case'!G15*$F23+'Business Case'!$B$8*('Business Case'!G11*$C23*'Business Case'!G12*$B23) -> 1011550000 | N23: =IF(COUNT('Business Case'!B11:G11)=0,"",H23+NPV(G23,I23:M23)) -> -7596795.9
A24: Fixed costs high | B24: =1 -> 1 | C24: =1 -> 1 | D24: =1 -> 1 | E24: =1+G9 -> 1.1 | F24: =1 -> 1 | G24: ='Business Case'!$B$6 -> 0.1 | H24: =(('Business Case'!B11*$C24*'Business Case'!B12*$B24)-'Business Case'!B11*$C24*'Business Case'!B13*$D24-'Business Case'!B14*$E24)-MAX(0,(('Business Case'!B11*$C24*'Business Case'!B12*$B24)-'Business Case'!B11*$C24*'Business Case'!B13*$D24-'Business Case'!B14*$E24))*'Business Case'!$B$7-'Business Case'!$B$8*('Business Case'!B11*$C24*'Business Case'!B12*$B24)-'Business Case'!B15*$F24 -> -2000000000 | I24: =(('Business Case'!C11*$C24*'Business Case'!C12*$B24)-'Business Case'!C11*$C24*'Business Case'!C13*$D24-'Business Case'!C14*$E24)-MAX(0,(('Business Case'!C11*$C24*'Business Case'!C12*$B24)-'Business Case'!C11*$C24*'Business Case'!C13*$D24-'Business Case'!C14*$E24))*'Business Case'!$B$7-'Business Case'!$B$8*(('Business Case'!C11*$C24*'Business Case'!C12*$B24)-('Business Case'!B11*$C24*'Business Case'!B12*$B24))-'Business Case'!C15*$F24 -> -1108000 | J24: =(('Business Case'!D11*$C24*'Business Case'!D12*$B24)-'Business Case'!D11*$C24*'Business Case'!D13*$D24-'Business Case'!D14*$E24)-MAX(0,(('Business Case'!D11*$C24*'Business Case'!D12*$B24)-'Business Case'!D11*$C24*'Business Case'!D13*$D24-'Business Case'!D14*$E24))*'Business Case'!$B$7-'Business Case'!$B$8*(('Business Case'!D11*$C24*'Business Case'!D12*$B24)-('Business Case'!C11*$C24*'Business Case'!C12*$B24))-'Business Case'!D15*$F24 -> 306044000 | K24: =(('Business Case'!E11*$C24*'Business Case'!E12*$B24)-'Business Case'!E11*$C24*'Business Case'!E13*$D24-'Business Case'!E14*$E24)-MAX(0,(('Business Case'!E11*$C24*'Business Case'!E12*$B24)-'Business Case'!E11*$C24*'Business Case'!E13*$D24-'Business Case'!E14*$E24))*'Business Case'!$B$7-'Business Case'!$B$8*(('Business Case'!E11*$C24*'Business Case'!E12*$B24)-('Business Case'!D11*$C24*'Business Case'!D12*$B24))-'Business Case'!E15*$F24 -> 663196000 | L24: =(('Business Case'!F11*$C24*'Business Case'!F12*$B24)-'Business Case'!F11*$C24*'Business Case'!F13*$D24-'Business Case'!F14*$E24)-MAX(0,(('Business Case'!F11*$C24*'Business Case'!F12*$B24)-'Business Case'!F11*$C24*'Business Case'!F13*$D24-'Business Case'!F14*$E24))*'Business Case'!$B$7-'Business Case'!$B$8*(('Business Case'!F11*$C24*'Business Case'!F12*$B24)-('Business Case'!E11*$C24*'Business Case'!E12*$B24))-'Business Case'!F15*$F24 -> 800140000 | M24: =(('Business Case'!G11*$C24*'Business Case'!G12*$B24)-'Business Case'!G11*$C24*'Business Case'!G13*$D24-'Business Case'!G14*$E24)-MAX(0,(('Business Case'!G11*$C24*'Business Case'!G12*$B24)-'Business Case'!G11*$C24*'Business Case'!G13*$D24-'Business Case'!G14*$E24))*'Business Case'!$B$7-'Business Case'!$B$8*(('Business Case'!G11*$C24*'Business Case'!G12*$B24)-('Business Case'!F11*$C24*'Business Case'!F12*$B24))-'Business Case'!G15*$F24+'Business Case'!$B$8*('Business Case'!G11*$C24*'Business Case'!G12*$B24) -> 990220000 | N24: =IF(COUNT('Business Case'!B11:G11)=0,"",H24+NPV(G24,I24:M24)) -> -88454278
A25: Capex low | B25: =1 -> 1 | C25: =1 -> 1 | D25: =1 -> 1 | E25: =1 -> 1 | F25: =1+E10 -> 0.95 | G25: ='Business Case'!$B$6 -> 0.1 | H25: =(('Business Case'!B11*$C25*'Business Case'!B12*$B25)-'Business Case'!B11*$C25*'Business Case'!B13*$D25-'Business Case'!B14*$E25)-MAX(0,(('Business Case'!B11*$C25*'Business Case'!B12*$B25)-'Business Case'!B11*$C25*'Business Case'!B13*$D25-'Business Case'!B14*$E25))*'Business Case'!$B$7-'Business Case'!$B$8*('Business Case'!B11*$C25*'Business Case'!B12*$B25)-'Business Case'!B15*$F25 -> -1900000000 | I25: =(('Business Case'!C11*$C25*'Business Case'!C12*$B25)-'Business Case'!C11*$C25*'Business Case'!C13*$D25-'Business Case'!C14*$E25)-MAX(0,(('Business Case'!C11*$C25*'Business Case'!C12*$B25)-'Business Case'!C11*$C25*'Business Case'!C13*$D25-'Business Case'!C14*$E25))*'Business Case'!$B$7-'Business Case'!$B$8*(('Business Case'!C11*$C25*'Business Case'!C12*$B25)-('Business Case'!B11*$C25*'Business Case'!B12*$B25))-'Business Case'!C15*$F25 -> 18112000 | J25: =(('Business Case'!D11*$C25*'Business Case'!D12*$B25)-'Business Case'!D11*$C25*'Business Case'!D13*$D25-'Business Case'!D14*$E25)-MAX(0,(('Business Case'!D11*$C25*'Business Case'!D12*$B25)-'Business Case'!D11*$C25*'Business Case'!D13*$D25-'Business Case'!D14*$E25))*'Business Case'!$B$7-'Business Case'!$B$8*(('Business Case'!D11*$C25*'Business Case'!D12*$B25)-('Business Case'!C11*$C25*'Business Case'!C12*$B25))-'Business Case'!D15*$F25 -> 325264000 | K25: =(('Business Case'!E11*$C25*'Business Case'!E12*$B25)-'Business Case'!E11*$C25*'Business Case'!E13*$D25-'Business Case'!E14*$E25)-MAX(0,(('Business Case'!E11*$C25*'Business Case'!E12*$B25)-'Business Case'!E11*$C25*'Business Case'!E13*$D25-'Business Case'!E14*$E25))*'Business Case'!$B$7-'Business Case'!$B$8*(('Business Case'!E11*$C25*'Business Case'!E12*$B25)-('Business Case'!D11*$C25*'Business Case'!D12*$B25))-'Business Case'!E15*$F25 -> 679916000 | L25: =(('Business Case'!F11*$C25*'Business Case'!F12*$B25)-'Business Case'!F11*$C25*'Business Case'!F13*$D25-'Business Case'!F14*$E25)-MAX(0,(('Business Case'!F11*$C25*'Business Case'!F12*$B25)-'Business Case'!F11*$C25*'Business Case'!F13*$D25-'Business Case'!F14*$E25))*'Business Case'!$B$7-'Business Case'!$B$8*(('Business Case'!F11*$C25*'Business Case'!F12*$B25)-('Business Case'!E11*$C25*'Business Case'!E12*$B25))-'Business Case'!F15*$F25 -> 816860000 | M25: =(('Business Case'!G11*$C25*'Business Case'!G12*$B25)-'Business Case'!G11*$C25*'Business Case'!G13*$D25-'Business Case'!G14*$E25)-MAX(0,(('Business Case'!G11*$C25*'Business Case'!G12*$B25)-'Business Case'!G11*$C25*'Business Case'!G13*$D25-'Business Case'!G14*$E25))*'Business Case'!$B$7-'Business Case'!$B$8*(('Business Case'!G11*$C25*'Business Case'!G12*$B25)-('Business Case'!F11*$C25*'Business Case'!F12*$B25))-'Business Case'!G15*$F25+'Business Case'!$B$8*('Business Case'!G11*$C25*'Business Case'!G12*$B25) -> 1006940000 | N25: =IF(COUNT('Business Case'!B11:G11)=0,"",H25+NPV(G25,I25:M25)) -> 79266520
A26: Capex high | B26: =1 -> 1 | C26: =1 -> 1 | D26: =1 -> 1 | E26: =1 -> 1 | F26: =1+G10 -> 1.2 | G26: ='Business Case'!$B$6 -> 0.1 | H26: =(('Business Case'!B11*$C26*'Business Case'!B12*$B26)-'Business Case'!B11*$C26*'Business Case'!B13*$D26-'Business Case'!B14*$E26)-MAX(0,(('Business Case'!B11*$C26*'Business Case'!B12*$B26)-'Business Case'!B11*$C26*'Business Case'!B13*$D26-'Business Case'!B14*$E26))*'Business Case'!$B$7-'Business Case'!$B$8*('Business Case'!B11*$C26*'Business Case'!B12*$B26)-'Business Case'!B15*$F26 -> -2400000000 | I26: =(('Business Case'!C11*$C26*'Business Case'!C12*$B26)-'Business Case'!C11*$C26*'Business Case'!C13*$D26-'Business Case'!C14*$E26)-MAX(0,(('Business Case'!C11*$C26*'Business Case'!C12*$B26)-'Business Case'!C11*$C26*'Business Case'!C13*$D26-'Business Case'!C14*$E26))*'Business Case'!$B$7-'Business Case'!$B$8*(('Business Case'!C11*$C26*'Business Case'!C12*$B26)-('Business Case'!B11*$C26*'Business Case'!B12*$B26))-'Business Case'!C15*$F26 -> -6888000 | J26: =(('Business Case'!D11*$C26*'Business Case'!D12*$B26)-'Business Case'!D11*$C26*'Business Case'!D13*$D26-'Business Case'!D14*$E26)-MAX(0,(('Business Case'!D11*$C26*'Business Case'!D12*$B26)-'Business Case'!D11*$C26*'Business Case'!D13*$D26-'Business Case'!D14*$E26))*'Business Case'!$B$7-'Business Case'!$B$8*(('Business Case'!D11*$C26*'Business Case'!D12*$B26)-('Business Case'!C11*$C26*'Business Case'!C12*$B26))-'Business Case'!D15*$F26 -> 300264000 | K26: =(('Business Case'!E11*$C26*'Business Case'!E12*$B26)-'Business Case'!E11*$C26*'Business Case'!E13*$D26-'Business Case'!E14*$E26)-MAX(0,(('Business Case'!E11*$C26*'Business Case'!E12*$B26)-'Business Case'!E11*$C26*'Business Case'!E13*$D26-'Business Case'!E14*$E26))*'Business Case'!$B$7-'Business Case'!$B$8*(('Business Case'!E11*$C26*'Business Case'!E12*$B26)-('Business Case'!D11*$C26*'Business Case'!D12*$B26))-'Business Case'!E15*$F26 -> 667416000 | L26: =(('Business Case'!F11*$C26*'Business Case'!F12*$B26)-'Business Case'!F11*$C26*'Business Case'!F13*$D26-'Business Case'!F14*$E26)-MAX(0,(('Business Case'!F11*$C26*'Business Case'!F12*$B26)-'Business Case'!F11*$C26*'Business Case'!F13*$D26-'Business Case'!F14*$E26))*'Business Case'!$B$7-'Business Case'!$B$8*(('Business Case'!F11*$C26*'Business Case'!F12*$B26)-('Business Case'!E11*$C26*'Business Case'!E12*$B26))-'Business Case'!F15*$F26 -> 804360000 | M26: =(('Business Case'!G11*$C26*'Business Case'!G12*$B26)-'Business Case'!G11*$C26*'Business Case'!G13*$D26-'Business Case'!G14*$E26)-MAX(0,(('Business Case'!G11*$C26*'Business Case'!G12*$B26)-'Business Case'!G11*$C26*'Business Case'!G13*$D26-'Business Case'!G14*$E26))*'Business Case'!$B$7-'Business Case'!$B$8*(('Business Case'!G11*$C26*'Business Case'!G12*$B26)-('Business Case'!F11*$C26*'Business Case'!F12*$B26))-'Business Case'!G15*$F26+'Business Case'!$B$8*('Business Case'!G11*$C26*'Business Case'!G12*$B26) -> 994440000 | N26: =IF(COUNT('Business Case'!B11:G11)=0,"",H26+NPV(G26,I26:M26)) -> -4.8981253e+08
A27: Discount rate (absolute) low | B27: =1 -> 1 | C27: =1 -> 1 | D27: =1 -> 1 | E27: =1 -> 1 | F27: =1 -> 1 | G27: =E11 -> 0.09 | H27: =(('Business Case'!B11*$C27*'Business Case'!B12*$B27)-'Business Case'!B11*$C27*'Business Case'!B13*$D27-'Business Case'!B14*$E27)-MAX(0,(('Business Case'!B11*$C27*'Business Case'!B12*$B27)-'Business Case'!B11*$C27*'Business Case'!B13*$D27-'Business Case'!B14*$E27))*'Business Case'!$B$7-'Business Case'!$B$8*('Business Case'!B11*$C27*'Business Case'!B12*$B27)-'Business Case'!B15*$F27 -> -2000000000 | I27: =(('Business Case'!C11*$C27*'Business Case'!C12*$B27)-'Business Case'!C11*$C27*'Business Case'!C13*$D27-'Business Case'!C14*$E27)-MAX(0,(('Business Case'!C11*$C27*'Business Case'!C12*$B27)-'Business Case'!C11*$C27*'Business Case'!C13*$D27-'Business Case'!C14*$E27))*'Business Case'!$B$7-'Business Case'!$B$8*(('Business Case'!C11*$C27*'Business Case'!C12*$B27)-('Business Case'!B11*$C27*'Business Case'!B12*$B27))-'Business Case'!C15*$F27 -> 13112000 | J27: =(('Business Case'!D11*$C27*'Business Case'!D12*$B27)-'Business Case'!D11*$C27*'Business Case'!D13*$D27-'Business Case'!D14*$E27)-MAX(0,(('Business Case'!D11*$C27*'Business Case'!D12*$B27)-'Business Case'!D11*$C27*'Business Case'!D13*$D27-'Business Case'!D14*$E27))*'Business Case'!$B$7-'Business Case'!$B$8*(('Business Case'!D11*$C27*'Business Case'!D12*$B27)-('Business Case'!C11*$C27*'Business Case'!C12*$B27))-'Business Case'!D15*$F27 -> 320264000 | K27: =(('Business Case'!E11*$C27*'Business Case'!E12*$B27)-'Business Case'!E11*$C27*'Business Case'!E13*$D27-'Business Case'!E14*$E27)-MAX(0,(('Business Case'!E11*$C27*'Business Case'!E12*$B27)-'Business Case'!E11*$C27*'Business Case'!E13*$D27-'Business Case'!E14*$E27))*'Business Case'!$B$7-'Business Case'!$B$8*(('Business Case'!E11*$C27*'Business Case'!E12*$B27)-('Business Case'!D11*$C27*'Business Case'!D12*$B27))-'Business Case'!E15*$F27 -> 677416000 | L27: =(('Business Case'!F11*$C27*'Business Case'!F12*$B27)-'Business Case'!F11*$C27*'Business Case'!F13*$D27-'Business Case'!F14*$E27)-MAX(0,(('Business Case'!F11*$C27*'Business Case'!F12*$B27)-'Business Case'!F11*$C27*'Business Case'!F13*$D27-'Business Case'!F14*$E27))*'Business Case'!$B$7-'Business Case'!$B$8*(('Business Case'!F11*$C27*'Business Case'!F12*$B27)-('Business Case'!E11*$C27*'Business Case'!E12*$B27))-'Business Case'!F15*$F27 -> 814360000 | M27: =(('Business Case'!G11*$C27*'Business Case'!G12*$B27)-'Business Case'!G11*$C27*'Business Case'!G13*$D27-'Business Case'!G14*$E27)-MAX(0,(('Business Case'!G11*$C27*'Business Case'!G12*$B27)-'Business Case'!G11*$C27*'Business Case'!G13*$D27-'Business Case'!G14*$E27))*'Business Case'!$B$7-'Business Case'!$B$8*(('Business Case'!G11*$C27*'Business Case'!G12*$B27)-('Business Case'!F11*$C27*'Business Case'!F12*$B27))-'Business Case'!G15*$F27+'Business Case'!$B$8*('Business Case'!G11*$C27*'Business Case'!G12*$B27) -> 1004440000 | N27: =IF(COUNT('Business Case'!B11:G11)=0,"",H27+NPV(G27,I27:M27)) -> 34408840
A28: Discount rate (absolute) high | B28: =1 -> 1 | C28: =1 -> 1 | D28: =1 -> 1 | E28: =1 -> 1 | F28: =1 -> 1 | G28: =G11 -> 0.12 | H28: =(('Business Case'!B11*$C28*'Business Case'!B12*$B28)-'Business Case'!B11*$C28*'Business Case'!B13*$D28-'Business Case'!B14*$E28)-MAX(0,(('Business Case'!B11*$C28*'Business Case'!B12*$B28)-'Business Case'!B11*$C28*'Business Case'!B13*$D28-'Business Case'!B14*$E28))*'Business Case'!$B$7-'Business Case'!$B$8*('Business Case'!B11*$C28*'Business Case'!B12*$B28)-'Business Case'!B15*$F28 -> -2000000000 | I28: =(('Business Case'!C11*$C28*'Business Case'!C12*$B28)-'Business Case'!C11*$C28*'Business Case'!C13*$D28-'Business Case'!C14*$E28)-MAX(0,(('Business Case'!C11*$C28*'Business Case'!C12*$B28)-'Business Case'!C11*$C28*'Business Case'!C13*$D28-'Business Case'!C14*$E28))*'Business Case'!$B$7-'Business Case'!$B$8*(('Business Case'!C11*$C28*'Business Case'!C12*$B28)-('Business Case'!B11*$C28*'Business Case'!B12*$B28))-'Business Case'!C15*$F28 -> 13112000 | J28: =(('Business Case'!D11*$C28*'Business Case'!D12*$B28)-'Business Case'!D11*$C28*'Business Case'!D13*$D28-'Business Case'!D14*$E28)-MAX(0,(('Business Case'!D11*$C28*'Business Case'!D12*$B28)-'Business Case'!D11*$C28*'Business Case'!D13*$D28-'Business Case'!D14*$E28))*'Business Case'!$B$7-'Business Case'!$B$8*(('Business Case'!D11*$C28*'Business Case'!D12*$B28)-('Business Case'!C11*$C28*'Business Case'!C12*$B28))-'Business Case'!D15*$F28 -> 320264000 | K28: =(('Business Case'!E11*$C28*'Business Case'!E12*$B28)-'Business Case'!E11*$C28*'Business Case'!E13*$D28-'Business Case'!E14*$E28)-MAX(0,(('Business Case'!E11*$C28*'Business Case'!E12*$B28)-'Business Case'!E11*$C28*'Business Case'!E13*$D28-'Business Case'!E14*$E28))*'Business Case'!$B$7-'Business Case'!$B$8*(('Business Case'!E11*$C28*'Business Case'!E12*$B28)-('Business Case'!D11*$C28*'Business Case'!D12*$B28))-'Business Case'!E15*$F28 -> 677416000 | L28: =(('Business Case'!F11*$C28*'Business Case'!F12*$B28)-'Business Case'!F11*$C28*'Business Case'!F13*$D28-'Business Case'!F14*$E28)-MAX(0,(('Business Case'!F11*$C28*'Business Case'!F12*$B28)-'Business Case'!F11*$C28*'Business Case'!F13*$D28-'Business Case'!F14*$E28))*'Business Case'!$B$7-'Business Case'!$B$8*(('Business Case'!F11*$C28*'Business Case'!F12*$B28)-('Business Case'!E11*$C28*'Business Case'!E12*$B28))-'Business Case'!F15*$F28 -> 814360000 | M28: =(('Business Case'!G11*$C28*'Business Case'!G12*$B28)-'Business Case'!G11*$C28*'Business Case'!G13*$D28-'Business Case'!G14*$E28)-MAX(0,(('Business Case'!G11*$C28*'Business Case'!G12*$B28)-'Business Case'!G11*$C28*'Business Case'!G13*$D28-'Business Case'!G14*$E28))*'Business Case'!$B$7-'Business Case'!$B$8*(('Business Case'!G11*$C28*'Business Case'!G12*$B28)-('Business Case'!F11*$C28*'Business Case'!F12*$B28))-'Business Case'!G15*$F28+'Business Case'!$B$8*('Business Case'!G11*$C28*'Business Case'!G12*$B28) -> 1004440000 | N28: =IF(COUNT('Business Case'!B11:G11)=0,"",H28+NPV(G28,I28:M28)) -> -1.633223e+08
A30: Tornado table (sorted by swing; the chart reads this)
A31: Driver | B31: NPV at low | C31: NPV at high | D31: Swing | E31: Low − plan | F31: High − plan | G31: Crosses zero? | H31: Rank key
A32: =INDEX($A$40:$A$45,MATCH(LARGE($D$40:$D$45,1),$D$40:$D$45,0)) -> Units | B32: =INDEX($B$40:$B$45,MATCH(LARGE($D$40:$D$45,1),$D$40:$D$45,0)) -> -5.9071265e+08 | C32: =INDEX($C$40:$C$45,MATCH(LARGE($D$40:$D$45,1),$D$40:$D$45,0)) -> 3.8257323e+08 | D32: =IFERROR(ABS(C32-B32),"") -> 9.7328588e+08 | E32: =IFERROR(B32-$N$16,"") -> -5.5616336e+08 | F32: =IFERROR(C32-$N$16,"") -> 4.1712252e+08 | G32: =IF(B32="","",IF(MIN(B32,C32)<0,IF(MAX(B32,C32)>0,"Yes","Below zero"),"No")) -> Yes | H32: =1 -> 1
A33: =INDEX($A$40:$A$45,MATCH(LARGE($D$40:$D$45,2),$D$40:$D$45,0)) -> Price per unit | B33: =INDEX($B$40:$B$45,MATCH(LARGE($D$40:$D$45,2),$D$40:$D$45,0)) -> -6.3224696e+08 | C33: =INDEX($C$40:$C$45,MATCH(LARGE($D$40:$D$45,2),$D$40:$D$45,0)) -> 2.6429955e+08 | D33: =IFERROR(ABS(C33-B33),"") -> 8.9654651e+08 | E33: =IFERROR(B33-$N$16,"") -> -5.9769767e+08 | F33: =IFERROR(C33-$N$16,"") -> 2.9884884e+08 | G33: =IF(B33="","",IF(MIN(B33,C33)<0,IF(MAX(B33,C33)>0,"Yes","Below zero"),"No")) -> Yes | H33: =2 -> 2
A34: =INDEX($A$40:$A$45,MATCH(LARGE($D$40:$D$45,3),$D$40:$D$45,0)) -> Variable cost per unit | B34: =INDEX($B$40:$B$45,MATCH(LARGE($D$40:$D$45,3),$D$40:$D$45,0)) -> 1.9997092e+08 | C34: =INDEX($C$40:$C$45,MATCH(LARGE($D$40:$D$45,3),$D$40:$D$45,0)) -> -4.0978162e+08 | D34: =IFERROR(ABS(C34-B34),"") -> 6.0975253e+08 | E34: =IFERROR(B34-$N$16,"") -> 2.3452021e+08 | F34: =IFERROR(C34-$N$16,"") -> -3.7523233e+08 | G34: =IF(B34="","",IF(MIN(B34,C34)<0,IF(MAX(B34,C34)>0,"Yes","Below zero"),"No")) -> Yes | H34: =3 -> 3
A35: =INDEX($A$40:$A$45,MATCH(LARGE($D$40:$D$45,4),$D$40:$D$45,0)) -> Capex | B35: =INDEX($B$40:$B$45,MATCH(LARGE($D$40:$D$45,4),$D$40:$D$45,0)) -> 79266520 | C35: =INDEX($C$40:$C$45,MATCH(LARGE($D$40:$D$45,4),$D$40:$D$45,0)) -> -4.8981253e+08 | D35: =IFERROR(ABS(C35-B35),"") -> 5.6907905e+08 | E35: =IFERROR(B35-$N$16,"") -> 1.1381581e+08 | F35: =IFERROR(C35-$N$16,"") -> -4.5526324e+08 | G35: =IF(B35="","",IF(MIN(B35,C35)<0,IF(MAX(B35,C35)>0,"Yes","Below zero"),"No")) -> Yes | H35: =4 -> 4
A36: =INDEX($A$40:$A$45,MATCH(LARGE($D$40:$D$45,5),$D$40:$D$45,0)) -> Discount rate (absolute) | B36: =INDEX($B$40:$B$45,MATCH(LARGE($D$40:$D$45,5),$D$40:$D$45,0)) -> 34408840 | C36: =INDEX($C$40:$C$45,MATCH(LARGE($D$40:$D$45,5),$D$40:$D$45,0)) -> -1.633223e+08 | D36: =IFERROR(ABS(C36-B36),"") -> 1.9773114e+08 | E36: =IFERROR(B36-$N$16,"") -> 68958130 | F36: =IFERROR(C36-$N$16,"") -> -1.2877301e+08 | G36: =IF(B36="","",IF(MIN(B36,C36)<0,IF(MAX(B36,C36)>0,"Yes","Below zero"),"No")) -> Yes | H36: =5 -> 5
A37: =INDEX($A$40:$A$45,MATCH(LARGE($D$40:$D$45,6),$D$40:$D$45,0)) -> Fixed costs | B37: =INDEX($B$40:$B$45,MATCH(LARGE($D$40:$D$45,6),$D$40:$D$45,0)) -> -7596795.9 | C37: =INDEX($C$40:$C$45,MATCH(LARGE($D$40:$D$45,6),$D$40:$D$45,0)) -> -88454278 | D37: =IFERROR(ABS(C37-B37),"") -> 80857482 | E37: =IFERROR(B37-$N$16,"") -> 26952494 | F37: =IFERROR(C37-$N$16,"") -> -53904988 | G37: =IF(B37="","",IF(MIN(B37,C37)<0,IF(MAX(B37,C37)>0,"Yes","Below zero"),"No")) -> Below zero | H37: =6 -> 6
A39: Helper (unsorted)
A40: Price per unit | B40: =N17 -> -6.3224696e+08 | C40: =N18 -> 2.6429955e+08 | D40: =IFERROR(ABS(C40-B40)+ROW()/1000000000,0) -> 8.9654651e+08
A41: Units | B41: =N19 -> -5.9071265e+08 | C41: =N20 -> 3.8257323e+08 | D41: =IFERROR(ABS(C41-B41)+ROW()/1000000000,0) -> 9.7328588e+08
A42: Variable cost per unit | B42: =N21 -> 1.9997092e+08 | C42: =N22 -> -4.0978162e+08 | D42: =IFERROR(ABS(C42-B42)+ROW()/1000000000,0) -> 6.0975253e+08
A43: Fixed costs | B43: =N23 -> -7596795.9 | C43: =N24 -> -88454278 | D43: =IFERROR(ABS(C43-B43)+ROW()/1000000000,0) -> 80857482
A44: Capex | B44: =N25 -> 79266520 | C44: =N26 -> -4.8981253e+08 | D44: =IFERROR(ABS(C44-B44)+ROW()/1000000000,0) -> 5.6907905e+08
A45: Discount rate (absolute) | B45: =N27 -> 34408840 | C45: =N28 -> -1.633223e+08 | D45: =IFERROR(ABS(C45-B45)+ROW()/1000000000,0) -> 1.9773114e+08
A48: Monte Carlo simulation: 1,000 futures, each driver drawn from a triangular (low, likely, high) distribution. Press F9 to draw again; results move slightly each time.
A49: Mean NPV | B49: =IFERROR(AVERAGE($N$81:$N$1080),"") -> -3.8025053e+08
A50: Median NPV | B50: =IFERROR(MEDIAN($N$81:$N$1080),"") -> -3.8818029e+08
A51: P10 (1 in 10 worse than this) | B51: =IFERROR(PERCENTILE($N$81:$N$1080,0.1),"") -> -7.734384e+08
A52: P90 (1 in 10 better than this) | B52: =IFERROR(PERCENTILE($N$81:$N$1080,0.9),"") -> 23459282
A53: Standard deviation | B53: =IFERROR(STDEV($N$81:$N$1080),"") -> 3.0583602e+08
A54: Probability NPV < 0 | B54: =IFERROR(COUNTIF($N$81:$N$1080,"<0")/COUNT($N$81:$N$1080),"") -> 0.886
A55: NPV at plan (for comparison) | B55: =IFERROR(N16,"") -> -34549290
A56: Drivers are drawn independently. If two move together (e.g. a price cut that lifts volume), the real spread differs. For exact, repeatable figures use the Business Case skill's risk_analysis.py.
A58: Bin from | B58: Bin to | C58: Count
A59: =MIN($N$81:$N$1080)+(MAX($N$81:$N$1080)-MIN($N$81:$N$1080))*0/20 -> -1.2932566e+09 | B59: =MIN($N$81:$N$1080)+(MAX($N$81:$N$1080)-MIN($N$81:$N$1080))*1/20 -> -1.2009066e+09 | C59: =COUNTIFS($N$81:$N$1080,">="&A59,$N$81:$N$1080,"<"&B59) -> 4
A60: =MIN($N$81:$N$1080)+(MAX($N$81:$N$1080)-MIN($N$81:$N$1080))*1/20 -> -1.2009066e+09 | B60: =MIN($N$81:$N$1080)+(MAX($N$81:$N$1080)-MIN($N$81:$N$1080))*2/20 -> -1.1085566e+09 | C60: =COUNTIFS($N$81:$N$1080,">="&A60,$N$81:$N$1080,"<"&B60) -> 3
A61: =MIN($N$81:$N$1080)+(MAX($N$81:$N$1080)-MIN($N$81:$N$1080))*2/20 -> -1.1085566e+09 | B61: =MIN($N$81:$N$1080)+(MAX($N$81:$N$1080)-MIN($N$81:$N$1080))*3/20 -> -1.0162066e+09 | C61: =COUNTIFS($N$81:$N$1080,">="&A61,$N$81:$N$1080,"<"&B61) -> 10
A62: =MIN($N$81:$N$1080)+(MAX($N$81:$N$1080)-MIN($N$81:$N$1080))*3/20 -> -1.0162066e+09 | B62: =MIN($N$81:$N$1080)+(MAX($N$81:$N$1080)-MIN($N$81:$N$1080))*4/20 -> -9.2385662e+08 | C62: =COUNTIFS($N$81:$N$1080,">="&A62,$N$81:$N$1080,"<"&B62) -> 21
A63: =MIN($N$81:$N$1080)+(MAX($N$81:$N$1080)-MIN($N$81:$N$1080))*4/20 -> -9.2385662e+08 | B63: =MIN($N$81:$N$1080)+(MAX($N$81:$N$1080)-MIN($N$81:$N$1080))*5/20 -> -8.3150661e+08 | C63: =COUNTIFS($N$81:$N$1080,">="&A63,$N$81:$N$1080,"<"&B63) -> 29
A64: =MIN($N$81:$N$1080)+(MAX($N$81:$N$1080)-MIN($N$81:$N$1080))*5/20 -> -8.3150661e+08 | B64: =MIN($N$81:$N$1080)+(MAX($N$81:$N$1080)-MIN($N$81:$N$1080))*6/20 -> -7.3915661e+08 | C64: =COUNTIFS($N$81:$N$1080,">="&A64,$N$81:$N$1080,"<"&B64) -> 52
A65: =MIN($N$81:$N$1080)+(MAX($N$81:$N$1080)-MIN($N$81:$N$1080))*6/20 -> -7.3915661e+08 | B65: =MIN($N$81:$N$1080)+(MAX($N$81:$N$1080)-MIN($N$81:$N$1080))*7/20 -> -6.4680661e+08 | C65: =COUNTIFS($N$81:$N$1080,">="&A65,$N$81:$N$1080,"<"&B65) -> 84
A66: =MIN($N$81:$N$1080)+(MAX($N$81:$N$1080)-MIN($N$81:$N$1080))*7/20 -> -6.4680661e+08 | B66: =MIN($N$81:$N$1080)+(MAX($N$81:$N$1080)-MIN($N$81:$N$1080))*8/20 -> -5.544566e+08 | C66: =COUNTIFS($N$81:$N$1080,">="&A66,$N$81:$N$1080,"<"&B66) -> 97
A67: =MIN($N$81:$N$1080)+(MAX($N$81:$N$1080)-MIN($N$81:$N$1080))*8/20 -> -5.544566e+08 | B67: =MIN($N$81:$N$1080)+(MAX($N$81:$N$1080)-MIN($N$81:$N$1080))*9/20 -> -4.621066e+08 | C67: =COUNTIFS($N$81:$N$1080,">="&A67,$N$81:$N$1080,"<"&B67) -> 100
A68: =MIN($N$81:$N$1080)+(MAX($N$81:$N$1080)-MIN($N$81:$N$1080))*9/20 -> -4.621066e+08 | B68: =MIN($N$81:$N$1080)+(MAX($N$81:$N$1080)-MIN($N$81:$N$1080))*10/20 -> -3.6975659e+08 | C68: =COUNTIFS($N$81:$N$1080,">="&A68,$N$81:$N$1080,"<"&B68) -> 121
A69: =MIN($N$81:$N$1080)+(MAX($N$81:$N$1080)-MIN($N$81:$N$1080))*10/20 -> -3.6975659e+08 | B69: =MIN($N$81:$N$1080)+(MAX($N$81:$N$1080)-MIN($N$81:$N$1080))*11/20 -> -2.7740659e+08 | C69: =COUNTIFS($N$81:$N$1080,">="&A69,$N$81:$N$1080,"<"&B69) -> 94
A70: =MIN($N$81:$N$1080)+(MAX($N$81:$N$1080)-MIN($N$81:$N$1080))*11/20 -> -2.7740659e+08 | B70: =MIN($N$81:$N$1080)+(MAX($N$81:$N$1080)-MIN($N$81:$N$1080))*12/20 -> -1.8505658e+08 | C70: =COUNTIFS($N$81:$N$1080,">="&A70,$N$81:$N$1080,"<"&B70) -> 116
A71: =MIN($N$81:$N$1080)+(MAX($N$81:$N$1080)-MIN($N$81:$N$1080))*12/20 -> -1.8505658e+08 | B71: =MIN($N$81:$N$1080)+(MAX($N$81:$N$1080)-MIN($N$81:$N$1080))*13/20 -> -92706580 | C71: =COUNTIFS($N$81:$N$1080,">="&A71,$N$81:$N$1080,"<"&B71) -> 90
A72: =MIN($N$81:$N$1080)+(MAX($N$81:$N$1080)-MIN($N$81:$N$1080))*13/20 -> -92706580 | B72: =MIN($N$81:$N$1080)+(MAX($N$81:$N$1080)-MIN($N$81:$N$1080))*14/20 -> -356575.98 | C72: =COUNTIFS($N$81:$N$1080,">="&A72,$N$81:$N$1080,"<"&B72) -> 65
A73: =MIN($N$81:$N$1080)+(MAX($N$81:$N$1080)-MIN($N$81:$N$1080))*14/20 -> -356575.98 | B73: =MIN($N$81:$N$1080)+(MAX($N$81:$N$1080)-MIN($N$81:$N$1080))*15/20 -> 91993428 | C73: =COUNTIFS($N$81:$N$1080,">="&A73,$N$81:$N$1080,"<"&B73) -> 55
A74: =MIN($N$81:$N$1080)+(MAX($N$81:$N$1080)-MIN($N$81:$N$1080))*15/20 -> 91993428 | B74: =MIN($N$81:$N$1080)+(MAX($N$81:$N$1080)-MIN($N$81:$N$1080))*16/20 -> 1.8434343e+08 | C74: =COUNTIFS($N$81:$N$1080,">="&A74,$N$81:$N$1080,"<"&B74) -> 23
A75: =MIN($N$81:$N$1080)+(MAX($N$81:$N$1080)-MIN($N$81:$N$1080))*16/20 -> 1.8434343e+08 | B75: =MIN($N$81:$N$1080)+(MAX($N$81:$N$1080)-MIN($N$81:$N$1080))*17/20 -> 2.7669344e+08 | C75: =COUNTIFS($N$81:$N$1080,">="&A75,$N$81:$N$1080,"<"&B75) -> 25
A76: =MIN($N$81:$N$1080)+(MAX($N$81:$N$1080)-MIN($N$81:$N$1080))*17/20 -> 2.7669344e+08 | B76: =MIN($N$81:$N$1080)+(MAX($N$81:$N$1080)-MIN($N$81:$N$1080))*18/20 -> 3.6904344e+08 | C76: =COUNTIFS($N$81:$N$1080,">="&A76,$N$81:$N$1080,"<"&B76) -> 6
A77: =MIN($N$81:$N$1080)+(MAX($N$81:$N$1080)-MIN($N$81:$N$1080))*18/20 -> 3.6904344e+08 | B77: =MIN($N$81:$N$1080)+(MAX($N$81:$N$1080)-MIN($N$81:$N$1080))*19/20 -> 4.6139345e+08 | C77: =COUNTIFS($N$81:$N$1080,">="&A77,$N$81:$N$1080,"<"&B77) -> 3
A78: =MIN($N$81:$N$1080)+(MAX($N$81:$N$1080)-MIN($N$81:$N$1080))*19/20 -> 4.6139345e+08 | B78: =MIN($N$81:$N$1080)+(MAX($N$81:$N$1080)-MIN($N$81:$N$1080))*20/20 -> 5.5374345e+08 | C78: =COUNTIFS($N$81:$N$1080,">="&A78,$N$81:$N$1080,"<="&B78) -> 2
A80: Run | B80: Price × | C80: Units × | D80: Var. cost × | E80: Fixed × | F80: Capex × | G80: Rate | H80: CF Y0 | I80: CF Y1 | J80: CF Y2 | K80: CF Y3 | L80: CF Y4 | M80: CF Y5 | N80: NPV | P80: Random 1 | Q80: Random 2 | R80: Random 3 | S80: Random 4 | T80: Random 5 | U80: Random 6
A81: 1 | B81: =1+IF($G$6=$E$6,$F$6,IF(P81<($F$6-$E$6)/($G$6-$E$6),$E$6+SQRT(P81*($G$6-$E$6)*($F$6-$E$6)),$G$6-SQRT((1-P81)*($G$6-$E$6)*($G$6-$F$6)))) -> 1.0236513 | C81: =1+IF($G$7=$E$7,$F$7,IF(Q81<($F$7-$E$7)/($G$7-$E$7),$E$7+SQRT(Q81*($G$7-$E$7)*($F$7-$E$7)),$G$7-SQRT((1-Q81)*($G$7-$E$7)*($G$7-$F$7)))) -> 0.97273784 | D81: =1+IF($G$8=$E$8,$F$8,IF(R81<($F$8-$E$8)/($G$8-$E$8),$E$8+SQRT(R81*($G$8-$E$8)*($F$8-$E$8)),$G$8-SQRT((1-R81)*($G$8-$E$8)*($G$8-$F$8)))) -> 1.0111531 | E81: =1+IF($G$9=$E$9,$F$9,IF(S81<($F$9-$E$9)/($G$9-$E$9),$E$9+SQRT(S81*($G$9-$E$9)*($F$9-$E$9)),$G$9-SQRT((1-S81)*($G$9-$E$9)*($G$9-$F$9)))) -> 1.0532608 | F81: =1+IF($G$10=$E$10,$F$10,IF(T81<($F$10-$E$10)/($G$10-$E$10),$E$10+SQRT(T81*($G$10-$E$10)*($F$10-$E$10)),$G$10-SQRT((1-T81)*($G$10-$E$10)*($G$10-$F$10)))) -> 0.96659429 | G81: =IF($G$11=$E$11,$F$11,IF(U81<($F$11-$E$11)/($G$11-$E$11),$E$11+SQRT(U81*($G$11-$E$11)*($F$11-$E$11)),$G$11-SQRT((1-U81)*($G$11-$E$11)*($G$11-$F$11)))) -> 0.10035827 | H81: =(('Business Case'!B11*$C81*'Business Case'!B12*$B81)-'Business Case'!B11*$C81*'Business Case'!B13*$D81-'Business Case'!B14*$E81)-MAX(0,(('Business Case'!B11*$C81*'Business Case'!B12*$B81)-'Business Case'!B11*$C81*'Business Case'!B13*$D81-'Business Case'!B14*$E81))*'Business Case'!$B$7-'Business Case'!$B$8*('Business Case'!B11*$C81*'Business Case'!B12*$B81)-'Business Case'!B15*$F81 -> -1.9331886e+09 | I81: =(('Business Case'!C11*$C81*'Business Case'!C12*$B81)-'Business Case'!C11*$C81*'Business Case'!C13*$D81-'Business Case'!C14*$E81)-MAX(0,(('Business Case'!C11*$C81*'Business Case'!C12*$B81)-'Business Case'!C11*$C81*'Business Case'!C13*$D81-'Business Case'!C14*$E81))*'Business Case'!$B$7-'Business Case'!$B$8*(('Business Case'!C11*$C81*'Business Case'!C12*$B81)-('Business Case'!B11*$C81*'Business Case'!B12*$B81))-'Business Case'!C15*$F81 -> 14015992 | J81: =(('Business Case'!D11*$C81*'Business Case'!D12*$B81)-'Business Case'!D11*$C81*'Business Case'!D13*$D81-'Business Case'!D14*$E81)-MAX(0,(('Business Case'!D11*$C81*'Business Case'!D12*$B81)-'Business Case'!D11*$C81*'Business Case'!D13*$D81-'Business Case'!D14*$E81))*'Business Case'!$B$7-'Business Case'!$B$8*(('Business Case'!D11*$C81*'Business Case'!D12*$B81)-('Business Case'!C11*$C81*'Business Case'!C12*$B81))-'Business Case'!D15*$F81 -> 3.2608449e+08 | K81: =(('Business Case'!E11*$C81*'Business Case'!E12*$B81)-'Business Case'!E11*$C81*'Business Case'!E13*$D81-'Business Case'!E14*$E81)-MAX(0,(('Business Case'!E11*$C81*'Business Case'!E12*$B81)-'Business Case'!E11*$C81*'Business Case'!E13*$D81-'Business Case'!E14*$E81))*'Business Case'!$B$7-'Business Case'!$B$8*(('Business Case'!E11*$C81*'Business Case'!E12*$B81)-('Business Case'!D11*$C81*'Business Case'!D12*$B81))-'Business Case'!E15*$F81 -> 6.864827e+08 | L81: =(('Business Case'!F11*$C81*'Business Case'!F12*$B81)-'Business Case'!F11*$C81*'Business Case'!F13*$D81-'Business Case'!F14*$E81)-MAX(0,(('Business Case'!F11*$C81*'Business Case'!F12*$B81)-'Business Case'!F11*$C81*'Business Case'!F13*$D81-'Business Case'!F14*$E81))*'Business Case'!$B$7-'Business Case'!$B$8*(('Business Case'!F11*$C81*'Business Case'!F12*$B81)-('Business Case'!E11*$C81*'Business Case'!E12*$B81))-'Business Case'!F15*$F81 -> 8.2491846e+08 | M81: =(('Business Case'!G11*$C81*'Business Case'!G12*$B81)-'Business Case'!G11*$C81*'Business Case'!G13*$D81-'Business Case'!G14*$E81)-MAX(0,(('Business Case'!G11*$C81*'Business Case'!G12*$B81)-'Business Case'!G11*$C81*'Business Case'!G13*$D81-'Business Case'!G14*$E81))*'Business Case'!$B$7-'Business Case'!$B$8*(('Business Case'!G11*$C81*'Business Case'!G12*$B81)-('Business Case'!F11*$C81*'Business Case'!F12*$B81))-'Business Case'!G15*$F81+'Business Case'!$B$8*('Business Case'!G11*$C81*'Business Case'!G12*$B81) -> 1.0141895e+09 | N81: =IF(COUNT('Business Case'!B11:G11)=0,"",H81+NPV(G81,I81:M81)) -> 55530251 | P81: =RAND() -> 0.94431648 | Q81: =RAND() -> 0.42626232 | R81: =RAND() -> 0.54424091 | S81: =RAND() -> 0.85436332 | T81: =RAND() -> 0.022029642 | U81: =RAND() -> 0.35700436
A82: 2 | B82: =1+IF($G$6=$E$6,$F$6,IF(P82<($F$6-$E$6)/($G$6-$E$6),$E$6+SQRT(P82*($G$6-$E$6)*($F$6-$E$6)),$G$6-SQRT((1-P82)*($G$6-$E$6)*($G$6-$F$6)))) -> 0.93794295 | C82: =1+IF($G$7=$E$7,$F$7,IF(Q82<($F$7-$E$7)/($G$7-$E$7),$E$7+SQRT(Q82*($G$7-$E$7)*($F$7-$E$7)),$G$7-SQRT((1-Q82)*($G$7-$E$7)*($G$7-$F$7)))) -> 0.95786614 | D82: =1+IF($G$8=$E$8,$F$8,IF(R82<($F$8-$E$8)/($G$8-$E$8),$E$8+SQRT(R82*($G$8-$E$8)*($F$8-$E$8)),$G$8-SQRT((1-R82)*($G$8-$E$8)*($G$8-$F$8)))) -> 1.0087522 | E82: =1+IF($G$9=$E$9,$F$9,IF(S82<($F$9-$E$9)/($G$9-$E$9),$E$9+SQRT(S82*($G$9-$E$9)*($F$9-$E$9)),$G$9-SQRT((1-S82)*($G$9-$E$9)*($G$9-$F$9)))) -> 0.98876086 | F82: =1+IF($G$10=$E$10,$F$10,IF(T82<($F$10-$E$10)/($G$10-$E$10),$E$10+SQRT(T82*($G$10-$E$10)*($F$10-$E$10)),$G$10-SQRT((1-T82)*($G$10-$E$10)*($G$10-$F$10)))) -> 1.0693973 | G82: =IF($G$11=$E$11,$F$11,IF(U82<($F$11-$E$11)/($G$11-$E$11),$E$11+SQRT(U82*($G$11-$E$11)*($F$11-$E$11)),$G$11-SQRT((1-U82)*($G$11-$E$11)*($G$11-$F$11)))) -> 0.098327213 | H82: =(('Business Case'!B11*$C82*'Business Case'!B12*$B82)-'Business Case'!B11*$C82*'Business Case'!B13*$D82-'Business Case'!B14*$E82)-MAX(0,(('Business Case'!B11*$C82*'Business Case'!B12*$B82)-'Business Case'!B11*$C82*'Business Case'!B13*$D82-'Business Case'!B14*$E82))*'Business Case'!$B$7-'Business Case'!$B$8*('Business Case'!B11*$C82*'Business Case'!B12*$B82)-'Business Case'!B15*$F82 -> -2.1387946e+09 | I82: =(('Business Case'!C11*$C82*'Business Case'!C12*$B82)-'Business Case'!C11*$C82*'Business Case'!C13*$D82-'Business Case'!C14*$E82)-MAX(0,(('Business Case'!C11*$C82*'Business Case'!C12*$B82)-'Business Case'!C11*$C82*'Business Case'!C13*$D82-'Business Case'!C14*$E82))*'Business Case'!$B$7-'Business Case'!$B$8*(('Business Case'!C11*$C82*'Business Case'!C12*$B82)-('Business Case'!B11*$C82*'Business Case'!B12*$B82))-'Business Case'!C15*$F82 -> -52884530 | J82: =(('Business Case'!D11*$C82*'Business Case'!D12*$B82)-'Business Case'!D11*$C82*'Business Case'!D13*$D82-'Business Case'!D14*$E82)-MAX(0,(('Business Case'!D11*$C82*'Business Case'!D12*$B82)-'Business Case'!D11*$C82*'Business Case'!D13*$D82-'Business Case'!D14*$E82))*'Business Case'!$B$7-'Business Case'!$B$8*(('Business Case'!D11*$C82*'Business Case'!D12*$B82)-('Business Case'!C11*$C82*'Business Case'!C12*$B82))-'Business Case'!D15*$F82 -> 1.8834675e+08 | K82: =(('Business Case'!E11*$C82*'Business Case'!E12*$B82)-'Business Case'!E11*$C82*'Business Case'!E13*$D82-'Business Case'!E14*$E82)-MAX(0,(('Business Case'!E11*$C82*'Business Case'!E12*$B82)-'Business Case'!E11*$C82*'Business Case'!E13*$D82-'Business Case'!E14*$E82))*'Business Case'!$B$7-'Business Case'!$B$8*(('Business Case'!E11*$C82*'Business Case'!E12*$B82)-('Business Case'!D11*$C82*'Business Case'!D12*$B82))-'Business Case'!E15*$F82 -> 4.830479e+08 | L82: =(('Business Case'!F11*$C82*'Business Case'!F12*$B82)-'Business Case'!F11*$C82*'Business Case'!F13*$D82-'Business Case'!F14*$E82)-MAX(0,(('Business Case'!F11*$C82*'Business Case'!F12*$B82)-'Business Case'!F11*$C82*'Business Case'!F13*$D82-'Business Case'!F14*$E82))*'Business Case'!$B$7-'Business Case'!$B$8*(('Business Case'!F11*$C82*'Business Case'!F12*$B82)-('Business Case'!E11*$C82*'Business Case'!E12*$B82))-'Business Case'!F15*$F82 -> 5.9450785e+08 | M82: =(('Business Case'!G11*$C82*'Business Case'!G12*$B82)-'Business Case'!G11*$C82*'Business Case'!G13*$D82-'Business Case'!G14*$E82)-MAX(0,(('Business Case'!G11*$C82*'Business Case'!G12*$B82)-'Business Case'!G11*$C82*'Business Case'!G13*$D82-'Business Case'!G14*$E82))*'Business Case'!$B$7-'Business Case'!$B$8*(('Business Case'!G11*$C82*'Business Case'!G12*$B82)-('Business Case'!F11*$C82*'Business Case'!F12*$B82))-'Business Case'!G15*$F82+'Business Case'!$B$8*('Business Case'!G11*$C82*'Business Case'!G12*$B82) -> 7.6528025e+08 | N82: =IF(COUNT('Business Case'!B11:G11)=0,"",H82+NPV(G82,I82:M82)) -> -7.7888517e+08 | P82: =RAND() -> 0.033536416 | Q82: =RAND() -> 0.35602455 | R82: =RAND() -> 0.51189945 | S82: =RAND() -> 0.20032056 | T82: =RAND() -> 0.65885859 | U82: =RAND() -> 0.23114158
A83: 3 | B83: =1+IF($G$6=$E$6,$F$6,IF(P83<($F$6-$E$6)/($G$6-$E$6),$E$6+SQRT(P83*($G$6-$E$6)*($F$6-$E$6)),$G$6-SQRT((1-P83)*($G$6-$E$6)*($G$6-$F$6)))) -> 0.997962 | C83: =1+IF($G$7=$E$7,$F$7,IF(Q83<($F$7-$E$7)/($G$7-$E$7),$E$7+SQRT(Q83*($G$7-$E$7)*($F$7-$E$7)),$G$7-SQRT((1-Q83)*($G$7-$E$7)*($G$7-$F$7)))) -> 0.9983274 | D83: =1+IF($G$8=$E$8,$F$8,IF(R83<($F$8-$E$8)/($G$8-$E$8),$E$8+SQRT(R83*($G$8-$E$8)*($F$8-$E$8)),$G$8-SQRT((1-R83)*($G$8-$E$8)*($G$8-$F$8)))) -> 1.0190313 | E83: =1+IF($G$9=$E$9,$F$9,IF(S83<($F$9-$E$9)/($G$9-$E$9),$E$9+SQRT(S83*($G$9-$E$9)*($F$9-$E$9)),$G$9-SQRT((1-S83)*($G$9-$E$9)*($G$9-$F$9)))) -> 1.0604562 | F83: =1+IF($G$10=$E$10,$F$10,IF(T83<($F$10-$E$10)/($G$10-$E$10),$E$10+SQRT(T83*($G$10-$E$10)*($F$10-$E$10)),$G$10-SQRT((1-T83)*($G$10-$E$10)*($G$10-$F$10)))) -> 0.97464083 | G83: =IF($G$11=$E$11,$F$11,IF(U83<($F$11-$E$11)/($G$11-$E$11),$E$11+SQRT(U83*($G$11-$E$11)*($F$11-$E$11)),$G$11-SQRT((1-U83)*($G$11-$E$11)*($G$11-$F$11)))) -> 0.10500435 | H83: =(('Business Case'!B11*$C83*'Business Case'!B12*$B83)-'Business Case'!B11*$C83*'Business Case'!B13*$D83-'Business Case'!B14*$E83)-MAX(0,(('Business Case'!B11*$C83*'Business Case'!B12*$B83)-'Business Case'!B11*$C83*'Business Case'!B13*$D83-'Business Case'!B14*$E83))*'Business Case'!$B$7-'Business Case'!$B$8*('Business Case'!B11*$C83*'Business Case'!B12*$B83)-'Business Case'!B15*$F83 -> -1.9492817e+09 | I83: =(('Business Case'!C11*$C83*'Business Case'!C12*$B83)-'Business Case'!C11*$C83*'Business Case'!C13*$D83-'Business Case'!C14*$E83)-MAX(0,(('Business Case'!C11*$C83*'Business Case'!C12*$B83)-'Business Case'!C11*$C83*'Business Case'!C13*$D83-'Business Case'!C14*$E83))*'Business Case'!$B$7-'Business Case'!$B$8*(('Business Case'!C11*$C83*'Business Case'!C12*$B83)-('Business Case'!B11*$C83*'Business Case'!B12*$B83))-'Business Case'!C15*$F83 -> -4663181.2 | J83: =(('Business Case'!D11*$C83*'Business Case'!D12*$B83)-'Business Case'!D11*$C83*'Business Case'!D13*$D83-'Business Case'!D14*$E83)-MAX(0,(('Business Case'!D11*$C83*'Business Case'!D12*$B83)-'Business Case'!D11*$C83*'Business Case'!D13*$D83-'Business Case'!D14*$E83))*'Business Case'!$B$7-'Business Case'!$B$8*(('Business Case'!D11*$C83*'Business Case'!D12*$B83)-('Business Case'!C11*$C83*'Business Case'!C12*$B83))-'Business Case'!D15*$F83 -> 2.9058242e+08 | K83: =(('Business Case'!E11*$C83*'Business Case'!E12*$B83)-'Business Case'!E11*$C83*'Business Case'!E13*$D83-'Business Case'!E14*$E83)-MAX(0,(('Business Case'!E11*$C83*'Business Case'!E12*$B83)-'Business Case'!E11*$C83*'Business Case'!E13*$D83-'Business Case'!E14*$E83))*'Business Case'!$B$7-'Business Case'!$B$8*(('Business Case'!E11*$C83*'Business Case'!E12*$B83)-('Business Case'!D11*$C83*'Business Case'!D12*$B83))-'Business Case'!E15*$F83 -> 6.3456006e+08 | L83: =(('Business Case'!F11*$C83*'Business Case'!F12*$B83)-'Business Case'!F11*$C83*'Business Case'!F13*$D83-'Business Case'!F14*$E83)-MAX(0,(('Business Case'!F11*$C83*'Business Case'!F12*$B83)-'Business Case'!F11*$C83*'Business Case'!F13*$D83-'Business Case'!F14*$E83))*'Business Case'!$B$7-'Business Case'!$B$8*(('Business Case'!F11*$C83*'Business Case'!F12*$B83)-('Business Case'!E11*$C83*'Business Case'!E12*$B83))-'Business Case'!F15*$F83 -> 7.6740713e+08 | M83: =(('Business Case'!G11*$C83*'Business Case'!G12*$B83)-'Business Case'!G11*$C83*'Business Case'!G13*$D83-'Business Case'!G14*$E83)-MAX(0,(('Business Case'!G11*$C83*'Business Case'!G12*$B83)-'Business Case'!G11*$C83*'Business Case'!G13*$D83-'Business Case'!G14*$E83))*'Business Case'!$B$7-'Business Case'!$B$8*(('Business Case'!G11*$C83*'Business Case'!G12*$B83)-('Business Case'!F11*$C83*'Business Case'!F12*$B83))-'Business Case'!G15*$F83+'Business Case'!$B$8*('Business Case'!G11*$C83*'Business Case'!G12*$B83) -> 9.5678247e+08 | N83: =IF(COUNT('Business Case'!B11:G11)=0,"",H83+NPV(G83,I83:M83)) -> -1.4974092e+08 | P83: =RAND() -> 0.63313267 | Q83: =RAND() -> 0.56191084 | R83: =RAND() -> 0.6425781 | S83: =RAND() -> 0.89575271 | T83: =RAND() -> 0.048573625 | U83: =RAND() -> 0.62521757
A84: 4 | B84: =1+IF($G$6=$E$6,$F$6,IF(P84<($F$6-$E$6)/($G$6-$E$6),$E$6+SQRT(P84*($G$6-$E$6)*($F$6-$E$6)),$G$6-SQRT((1-P84)*($G$6-$E$6)*($G$6-$F$6)))) -> 0.99877794 | C84: =1+IF($G$7=$E$7,$F$7,IF(Q84<($F$7-$E$7)/($G$7-$E$7),$E$7+SQRT(Q84*($G$7-$E$7)*($F$7-$E$7)),$G$7-SQRT((1-Q84)*($G$7-$E$7)*($G$7-$F$7)))) -> 0.92571039 | D84: =1+IF($G$8=$E$8,$F$8,IF(R84<($F$8-$E$8)/($G$8-$E$8),$E$8+SQRT(R84*($G$8-$E$8)*($F$8-$E$8)),$G$8-SQRT((1-R84)*($G$8-$E$8)*($G$8-$F$8)))) -> 1.0558938 | E84: =1+IF($G$9=$E$9,$F$9,IF(S84<($F$9-$E$9)/($G$9-$E$9),$E$9+SQRT(S84*($G$9-$E$9)*($F$9-$E$9)),$G$9-SQRT((1-S84)*($G$9-$E$9)*($G$9-$F$9)))) -> 0.97476683 | F84: =1+IF($G$10=$E$10,$F$10,IF(T84<($F$10-$E$10)/($G$10-$E$10),$E$10+SQRT(T84*($G$10-$E$10)*($F$10-$E$10)),$G$10-SQRT((1-T84)*($G$10-$E$10)*($G$10-$F$10)))) -> 1.0037174 | G84: =IF($G$11=$E$11,$F$11,IF(U84<($F$11-$E$11)/($G$11-$E$11),$E$11+SQRT(U84*($G$11-$E$11)*($F$11-$E$11)),$G$11-SQRT((1-U84)*($G$11-$E$11)*($G$11-$F$11)))) -> 0.099136926 | H84: =(('Business Case'!B11*$C84*'Business Case'!B12*$B84)-'Business Case'!B11*$C84*'Business Case'!B13*$D84-'Business Case'!B14*$E84)-MAX(0,(('Business Case'!B11*$C84*'Business Case'!B12*$B84)-'Business Case'!B11*$C84*'Business Case'!B13*$D84-'Business Case'!B14*$E84))*'Business Case'!$B$7-'Business Case'!$B$8*('Business Case'!B11*$C84*'Business Case'!B12*$B84)-'Business Case'!B15*$F84 -> -2.0074349e+09 | I84: =(('Business Case'!C11*$C84*'Business Case'!C12*$B84)-'Business Case'!C11*$C84*'Business Case'!C13*$D84-'Business Case'!C14*$E84)-MAX(0,(('Business Case'!C11*$C84*'Business Case'!C12*$B84)-'Business Case'!C11*$C84*'Business Case'!C13*$D84-'Business Case'!C14*$E84))*'Business Case'!$B$7-'Business Case'!$B$8*(('Business Case'!C11*$C84*'Business Case'!C12*$B84)-('Business Case'!B11*$C84*'Business Case'!B12*$B84))-'Business Case'!C15*$F84 -> -29994072 | J84: =(('Business Case'!D11*$C84*'Business Case'!D12*$B84)-'Business Case'!D11*$C84*'Business Case'!D13*$D84-'Business Case'!D14*$E84)-MAX(0,(('Business Case'!D11*$C84*'Business Case'!D12*$B84)-'Business Case'!D11*$C84*'Business Case'!D13*$D84-'Business Case'!D14*$E84))*'Business Case'!$B$7-'Business Case'!$B$8*(('Business Case'!D11*$C84*'Business Case'!D12*$B84)-('Business Case'!C11*$C84*'Business Case'!C12*$B84))-'Business Case'!D15*$F84 -> 2.2692563e+08 | K84: =(('Business Case'!E11*$C84*'Business Case'!E12*$B84)-'Business Case'!E11*$C84*'Business Case'!E13*$D84-'Business Case'!E14*$E84)-MAX(0,(('Business Case'!E11*$C84*'Business Case'!E12*$B84)-'Business Case'!E11*$C84*'Business Case'!E13*$D84-'Business Case'!E14*$E84))*'Business Case'!$B$7-'Business Case'!$B$8*(('Business Case'!E11*$C84*'Business Case'!E12*$B84)-('Business Case'!D11*$C84*'Business Case'!D12*$B84))-'Business Case'!E15*$F84 -> 5.340312e+08 | L84: =(('Business Case'!F11*$C84*'Business Case'!F12*$B84)-'Business Case'!F11*$C84*'Business Case'!F13*$D84-'Business Case'!F14*$E84)-MAX(0,(('Business Case'!F11*$C84*'Business Case'!F12*$B84)-'Business Case'!F11*$C84*'Business Case'!F13*$D84-'Business Case'!F14*$E84))*'Business Case'!$B$7-'Business Case'!$B$8*(('Business Case'!F11*$C84*'Business Case'!F12*$B84)-('Business Case'!E11*$C84*'Business Case'!E12*$B84))-'Business Case'!F15*$F84 -> 6.5162455e+08 | M84: =(('Business Case'!G11*$C84*'Business Case'!G12*$B84)-'Business Case'!G11*$C84*'Business Case'!G13*$D84-'Business Case'!G14*$E84)-MAX(0,(('Business Case'!G11*$C84*'Business Case'!G12*$B84)-'Business Case'!G11*$C84*'Business Case'!G13*$D84-'Business Case'!G14*$E84))*'Business Case'!$B$7-'Business Case'!$B$8*(('Business Case'!G11*$C84*'Business Case'!G12*$B84)-('Business Case'!F11*$C84*'Business Case'!F12*$B84))-'Business Case'!G15*$F84+'Business Case'!$B$8*('Business Case'!G11*$C84*'Business Case'!G12*$B84) -> 8.2736855e+08 | N84: =IF(COUNT('Business Case'!B11:G11)=0,"",H84+NPV(G84,I84:M84)) -> -4.8249689e+08 | P84: =RAND() -> 0.64645458 | Q84: =RAND() -> 0.22575861 | R84: =RAND() -> 0.94412427 | S84: =RAND() -> 0.081786134 | T84: =RAND() -> 0.22946319 | U84: =RAND() -> 0.27827805
A85: 5 | B85: =1+IF($G$6=$E$6,$F$6,IF(P85<($F$6-$E$6)/($G$6-$E$6),$E$6+SQRT(P85*($G$6-$E$6)*($F$6-$E$6)),$G$6-SQRT((1-P85)*($G$6-$E$6)*($G$6-$F$6)))) -> 0.98671556 | C85: =1+IF($G$7=$E$7,$F$7,IF(Q85<($F$7-$E$7)/($G$7-$E$7),$E$7+SQRT(Q85*($G$7-$E$7)*($F$7-$E$7)),$G$7-SQRT((1-Q85)*($G$7-$E$7)*($G$7-$F$7)))) -> 1.105809 | D85: =1+IF($G$8=$E$8,$F$8,IF(R85<($F$8-$E$8)/($G$8-$E$8),$E$8+SQRT(R85*($G$8-$E$8)*($F$8-$E$8)),$G$8-SQRT((1-R85)*($G$8-$E$8)*($G$8-$F$8)))) -> 1.0213914 | E85: =1+IF($G$9=$E$9,$F$9,IF(S85<($F$9-$E$9)/($G$9-$E$9),$E$9+SQRT(S85*($G$9-$E$9)*($F$9-$E$9)),$G$9-SQRT((1-S85)*($G$9-$E$9)*($G$9-$F$9)))) -> 1.0133652 | F85: =1+IF($G$10=$E$10,$F$10,IF(T85<($F$10-$E$10)/($G$10-$E$10),$E$10+SQRT(T85*($G$10-$E$10)*($F$10-$E$10)),$G$10-SQRT((1-T85)*($G$10-$E$10)*($G$10-$F$10)))) -> 1.08471 | G85: =IF($G$11=$E$11,$F$11,IF(U85<($F$11-$E$11)/($G$11-$E$11),$E$11+SQRT(U85*($G$11-$E$11)*($F$11-$E$11)),$G$11-SQRT((1-U85)*($G$11-$E$11)*($G$11-$F$11)))) -> 0.10986885 | H85: =(('Business Case'!B11*$C85*'Business Case'!B12*$B85)-'Business Case'!B11*$C85*'Business Case'!B13*$D85-'Business Case'!B14*$E85)-MAX(0,(('Business Case'!B11*$C85*'Business Case'!B12*$B85)-'Business Case'!B11*$C85*'Business Case'!B13*$D85-'Business Case'!B14*$E85))*'Business Case'!$B$7-'Business Case'!$B$8*('Business Case'!B11*$C85*'Business Case'!B12*$B85)-'Business Case'!B15*$F85 -> -2.1694199e+09 | I85: =(('Business Case'!C11*$C85*'Business Case'!C12*$B85)-'Business Case'!C11*$C85*'Business Case'!C13*$D85-'Business Case'!C14*$E85)-MAX(0,(('Business Case'!C11*$C85*'Business Case'!C12*$B85)-'Business Case'!C11*$C85*'Business Case'!C13*$D85-'Business Case'!C14*$E85))*'Business Case'!$B$7-'Business Case'!$B$8*(('Business Case'!C11*$C85*'Business Case'!C12*$B85)-('Business Case'!B11*$C85*'Business Case'!B12*$B85))-'Business Case'!C15*$F85 -> 6374719.5 | J85: =(('Business Case'!D11*$C85*'Business Case'!D12*$B85)-'Business Case'!D11*$C85*'Business Case'!D13*$D85-'Business Case'!D14*$E85)-MAX(0,(('Business Case'!D11*$C85*'Business Case'!D12*$B85)-'Business Case'!D11*$C85*'Business Case'!D13*$D85-'Business Case'!D14*$E85))*'Business Case'!$B$7-'Business Case'!$B$8*(('Business Case'!D11*$C85*'Business Case'!D12*$B85)-('Business Case'!C11*$C85*'Business Case'!C12*$B85))-'Business Case'!D15*$F85 -> 3.2188457e+08 | K85: =(('Business Case'!E11*$C85*'Business Case'!E12*$B85)-'Business Case'!E11*$C85*'Business Case'!E13*$D85-'Business Case'!E14*$E85)-MAX(0,(('Business Case'!E11*$C85*'Business Case'!E12*$B85)-'Business Case'!E11*$C85*'Business Case'!E13*$D85-'Business Case'!E14*$E85))*'Business Case'!$B$7-'Business Case'!$B$8*(('Business Case'!E11*$C85*'Business Case'!E12*$B85)-('Business Case'!D11*$C85*'Business Case'!D12*$B85))-'Business Case'!E15*$F85 -> 6.9162991e+08 | L85: =(('Business Case'!F11*$C85*'Business Case'!F12*$B85)-'Business Case'!F11*$C85*'Business Case'!F13*$D85-'Business Case'!F14*$E85)-MAX(0,(('Business Case'!F11*$C85*'Business Case'!F12*$B85)-'Business Case'!F11*$C85*'Business Case'!F13*$D85-'Business Case'!F14*$E85))*'Business Case'!$B$7-'Business Case'!$B$8*(('Business Case'!F11*$C85*'Business Case'!F12*$B85)-('Business Case'!E11*$C85*'Business Case'!E12*$B85))-'Business Case'!F15*$F85 -> 8.3450893e+08 | M85: =(('Business Case'!G11*$C85*'Business Case'!G12*$B85)-'Business Case'!G11*$C85*'Business Case'!G13*$D85-'Business Case'!G14*$E85)-MAX(0,(('Business Case'!G11*$C85*'Business Case'!G12*$B85)-'Business Case'!G11*$C85*'Business Case'!G13*$D85-'Business Case'!G14*$E85))*'Business Case'!$B$7-'Business Case'!$B$8*(('Business Case'!G11*$C85*'Business Case'!G12*$B85)-('Business Case'!F11*$C85*'Business Case'!F12*$B85))-'Business Case'!G15*$F85+'Business Case'!$B$8*('Business Case'!G11*$C85*'Business Case'!G12*$B85) -> 1.0419088e+09 | N85: =IF(COUNT('Business Case'!B11:G11)=0,"",H85+NPV(G85,I85:M85)) -> -2.278083e+08 | P85: =RAND() -> 0.46364224 | Q85: =RAND() -> 0.96280299 | R85: =RAND() -> 0.66971506 | S85: =RAND() -> 0.49962687 | T85: =RAND() -> 0.73416415 | U85: =RAND() -> 0.82893299
A86: 6 | B86: =1+IF($G$6=$E$6,$F$6,IF(P86<($F$6-$E$6)/($G$6-$E$6),$E$6+SQRT(P86*($G$6-$E$6)*($F$6-$E$6)),$G$6-SQRT((1-P86)*($G$6-$E$6)*($G$6-$F$6)))) -> 0.94277802 | C86: =1+IF($G$7=$E$7,$F$7,IF(Q86<($F$7-$E$7)/($G$7-$E$7),$E$7+SQRT(Q86*($G$7-$E$7)*($F$7-$E$7)),$G$7-SQRT((1-Q86)*($G$7-$E$7)*($G$7-$F$7)))) -> 1.0549048 | D86: =1+IF($G$8=$E$8,$F$8,IF(R86<($F$8-$E$8)/($G$8-$E$8),$E$8+SQRT(R86*($G$8-$E$8)*($F$8-$E$8)),$G$8-SQRT((1-R86)*($G$8-$E$8)*($G$8-$F$8)))) -> 1.0057447 | E86: =1+IF($G$9=$E$9,$F$9,IF(S86<($F$9-$E$9)/($G$9-$E$9),$E$9+SQRT(S86*($G$9-$E$9)*($F$9-$E$9)),$G$9-SQRT((1-S86)*($G$9-$E$9)*($G$9-$F$9)))) -> 1.0408078 | F86: =1+IF($G$10=$E$10,$F$10,IF(T86<($F$10-$E$10)/($G$10-$E$10),$E$10+SQRT(T86*($G$10-$E$10)*($F$10-$E$10)),$G$10-SQRT((1-T86)*($G$10-$E$10)*($G$10-$F$10)))) -> 1.0124839 | G86: =IF($G$11=$E$11,$F$11,IF(U86<($F$11-$E$11)/($G$11-$E$11),$E$11+SQRT(U86*($G$11-$E$11)*($F$11-$E$11)),$G$11-SQRT((1-U86)*($G$11-$E$11)*($G$11-$F$11)))) -> 0.10328394 | H86: =(('Business Case'!B11*$C86*'Business Case'!B12*$B86)-'Business Case'!B11*$C86*'Business Case'!B13*$D86-'Business Case'!B14*$E86)-MAX(0,(('Business Case'!B11*$C86*'Business Case'!B12*$B86)-'Business Case'!B11*$C86*'Business Case'!B13*$D86-'Business Case'!B14*$E86))*'Business Case'!$B$7-'Business Case'!$B$8*('Business Case'!B11*$C86*'Business Case'!B12*$B86)-'Business Case'!B15*$F86 -> -2.0249678e+09 | I86: =(('Business Case'!C11*$C86*'Business Case'!C12*$B86)-'Business Case'!C11*$C86*'Business Case'!C13*$D86-'Business Case'!C14*$E86)-MAX(0,(('Business Case'!C11*$C86*'Business Case'!C12*$B86)-'Business Case'!C11*$C86*'Business Case'!C13*$D86-'Business Case'!C14*$E86))*'Business Case'!$B$7-'Business Case'!$B$8*(('Business Case'!C11*$C86*'Business Case'!C12*$B86)-('Business Case'!B11*$C86*'Business Case'!B12*$B86))-'Business Case'!C15*$F86 -> -29336714 | J86: =(('Business Case'!D11*$C86*'Business Case'!D12*$B86)-'Business Case'!D11*$C86*'Business Case'!D13*$D86-'Business Case'!D14*$E86)-MAX(0,(('Business Case'!D11*$C86*'Business Case'!D12*$B86)-'Business Case'!D11*$C86*'Business Case'!D13*$D86-'Business Case'!D14*$E86))*'Business Case'!$B$7-'Business Case'!$B$8*(('Business Case'!D11*$C86*'Business Case'!D12*$B86)-('Business Case'!C11*$C86*'Business Case'!C12*$B86))-'Business Case'!D15*$F86 -> 2.4213484e+08 | K86: =(('Business Case'!E11*$C86*'Business Case'!E12*$B86)-'Business Case'!E11*$C86*'Business Case'!E13*$D86-'Business Case'!E14*$E86)-MAX(0,(('Business Case'!E11*$C86*'Business Case'!E12*$B86)-'Business Case'!E11*$C86*'Business Case'!E13*$D86-'Business Case'!E14*$E86))*'Business Case'!$B$7-'Business Case'!$B$8*(('Business Case'!E11*$C86*'Business Case'!E12*$B86)-('Business Case'!D11*$C86*'Business Case'!D12*$B86))-'Business Case'!E15*$F86 -> 5.642306e+08 | L86: =(('Business Case'!F11*$C86*'Business Case'!F12*$B86)-'Business Case'!F11*$C86*'Business Case'!F13*$D86-'Business Case'!F14*$E86)-MAX(0,(('Business Case'!F11*$C86*'Business Case'!F12*$B86)-'Business Case'!F11*$C86*'Business Case'!F13*$D86-'Business Case'!F14*$E86))*'Business Case'!$B$7-'Business Case'!$B$8*(('Business Case'!F11*$C86*'Business Case'!F12*$B86)-('Business Case'!E11*$C86*'Business Case'!E12*$B86))-'Business Case'!F15*$F86 -> 6.8909246e+08 | M86: =(('Business Case'!G11*$C86*'Business Case'!G12*$B86)-'Business Case'!G11*$C86*'Business Case'!G13*$D86-'Business Case'!G14*$E86)-MAX(0,(('Business Case'!G11*$C86*'Business Case'!G12*$B86)-'Business Case'!G11*$C86*'Business Case'!G13*$D86-'Business Case'!G14*$E86))*'Business Case'!$B$7-'Business Case'!$B$8*(('Business Case'!G11*$C86*'Business Case'!G12*$B86)-('Business Case'!F11*$C86*'Business Case'!F12*$B86))-'Business Case'!G15*$F86+'Business Case'!$B$8*('Business Case'!G11*$C86*'Business Case'!G12*$B86) -> 8.7813482e+08 | N86: =IF(COUNT('Business Case'!B11:G11)=0,"",H86+NPV(G86,I86:M86)) -> -4.3022882e+08 | P86: =RAND() -> 0.054045664 | Q86: =RAND() -> 0.82775053 | R86: =RAND() -> 0.46982272 | S86: =RAND() -> 0.76641908 | T86: =RAND() -> 0.29675437 | U86: =RAND() -> 0.53428887
A87: 7 | B87: =1+IF($G$6=$E$6,$F$6,IF(P87<($F$6-$E$6)/($G$6-$E$6),$E$6+SQRT(P87*($G$6-$E$6)*($F$6-$E$6)),$G$6-SQRT((1-P87)*($G$6-$E$6)*($G$6-$F$6)))) -> 1.0193218 | C87: =1+IF($G$7=$E$7,$F$7,IF(Q87<($F$7-$E$7)/($G$7-$E$7),$E$7+SQRT(Q87*($G$7-$E$7)*($F$7-$E$7)),$G$7-SQRT((1-Q87)*($G$7-$E$7)*($G$7-$F$7)))) -> 0.92310016 | D87: =1+IF($G$8=$E$8,$F$8,IF(R87<($F$8-$E$8)/($G$8-$E$8),$E$8+SQRT(R87*($G$8-$E$8)*($F$8-$E$8)),$G$8-SQRT((1-R87)*($G$8-$E$8)*($G$8-$F$8)))) -> 1.0457949 | E87: =1+IF($G$9=$E$9,$F$9,IF(S87<($F$9-$E$9)/($G$9-$E$9),$E$9+SQRT(S87*($G$9-$E$9)*($F$9-$E$9)),$G$9-SQRT((1-S87)*($G$9-$E$9)*($G$9-$F$9)))) -> 0.96784063 | F87: =1+IF($G$10=$E$10,$F$10,IF(T87<($F$10-$E$10)/($G$10-$E$10),$E$10+SQRT(T87*($G$10-$E$10)*($F$10-$E$10)),$G$10-SQRT((1-T87)*($G$10-$E$10)*($G$10-$F$10)))) -> 0.99086353 | G87: =IF($G$11=$E$11,$F$11,IF(U87<($F$11-$E$11)/($G$11-$E$11),$E$11+SQRT(U87*($G$11-$E$11)*($F$11-$E$11)),$G$11-SQRT((1-U87)*($G$11-$E$11)*($G$11-$F$11)))) -> 0.09370184 | H87: =(('Business Case'!B11*$C87*'Business Case'!B12*$B87)-'Business Case'!B11*$C87*'Business Case'!B13*$D87-'Business Case'!B14*$E87)-MAX(0,(('Business Case'!B11*$C87*'Business Case'!B12*$B87)-'Business Case'!B11*$C87*'Business Case'!B13*$D87-'Business Case'!B14*$E87))*'Business Case'!$B$7-'Business Case'!$B$8*('Business Case'!B11*$C87*'Business Case'!B12*$B87)-'Business Case'!B15*$F87 -> -1.9817271e+09 | I87: =(('Business Case'!C11*$C87*'Business Case'!C12*$B87)-'Business Case'!C11*$C87*'Business Case'!C13*$D87-'Business Case'!C14*$E87)-MAX(0,(('Business Case'!C11*$C87*'Business Case'!C12*$B87)-'Business Case'!C11*$C87*'Business Case'!C13*$D87-'Business Case'!C14*$E87))*'Business Case'!$B$7-'Business Case'!$B$8*(('Business Case'!C11*$C87*'Business Case'!C12*$B87)-('Business Case'!B11*$C87*'Business Case'!B12*$B87))-'Business Case'!C15*$F87 -> -8990971 | J87: =(('Business Case'!D11*$C87*'Business Case'!D12*$B87)-'Business Case'!D11*$C87*'Business Case'!D13*$D87-'Business Case'!D14*$E87)-MAX(0,(('Business Case'!D11*$C87*'Business Case'!D12*$B87)-'Business Case'!D11*$C87*'Business Case'!D13*$D87-'Business Case'!D14*$E87))*'Business Case'!$B$7-'Business Case'!$B$8*(('Business Case'!D11*$C87*'Business Case'!D12*$B87)-('Business Case'!C11*$C87*'Business Case'!C12*$B87))-'Business Case'!D15*$F87 -> 2.6750948e+08 | K87: =(('Business Case'!E11*$C87*'Business Case'!E12*$B87)-'Business Case'!E11*$C87*'Business Case'!E13*$D87-'Business Case'!E14*$E87)-MAX(0,(('Business Case'!E11*$C87*'Business Case'!E12*$B87)-'Business Case'!E11*$C87*'Business Case'!E13*$D87-'Business Case'!E14*$E87))*'Business Case'!$B$7-'Business Case'!$B$8*(('Business Case'!E11*$C87*'Business Case'!E12*$B87)-('Business Case'!D11*$C87*'Business Case'!D12*$B87))-'Business Case'!E15*$F87 -> 5.935531e+08 | L87: =(('Business Case'!F11*$C87*'Business Case'!F12*$B87)-'Business Case'!F11*$C87*'Business Case'!F13*$D87-'Business Case'!F14*$E87)-MAX(0,(('Business Case'!F11*$C87*'Business Case'!F12*$B87)-'Business Case'!F11*$C87*'Business Case'!F13*$D87-'Business Case'!F14*$E87))*'Business Case'!$B$7-'Business Case'!$B$8*(('Business Case'!F11*$C87*'Business Case'!F12*$B87)-('Business Case'!E11*$C87*'Business Case'!E12*$B87))-'Business Case'!F15*$F87 -> 7.1823867e+08 | M87: =(('Business Case'!G11*$C87*'Business Case'!G12*$B87)-'Business Case'!G11*$C87*'Business Case'!G13*$D87-'Business Case'!G14*$E87)-MAX(0,(('Business Case'!G11*$C87*'Business Case'!G12*$B87)-'Business Case'!G11*$C87*'Business Case'!G13*$D87-'Business Case'!G14*$E87))*'Business Case'!$B$7-'Business Case'!$B$8*(('Business Case'!G11*$C87*'Business Case'!G12*$B87)-('Business Case'!F11*$C87*'Business Case'!F12*$B87))-'Business Case'!G15*$F87+'Business Case'!$B$8*('Business Case'!G11*$C87*'Business Case'!G12*$B87) -> 8.9709181e+08 | N87: =IF(COUNT('Business Case'!B11:G11)=0,"",H87+NPV(G87,I87:M87)) -> -2.3740623e+08 | P87: =RAND() -> 0.91091933 | Q87: =RAND() -> 0.2164807 | R87: =RAND() -> 0.88750135 | S87: =RAND() -> 0.042438414 | T87: =RAND() -> 0.13358622 | U87: =RAND() -> 0.045678743
A88: 8 | B88: =1+IF($G$6=$E$6,$F$6,IF(P88<($F$6-$E$6)/($G$6-$E$6),$E$6+SQRT(P88*($G$6-$E$6)*($F$6-$E$6)),$G$6-SQRT((1-P88)*($G$6-$E$6)*($G$6-$F$6)))) -> 0.99235414 | C88: =1+IF($G$7=$E$7,$F$7,IF(Q88<($F$7-$E$7)/($G$7-$E$7),$E$7+SQRT(Q88*($G$7-$E$7)*($F$7-$E$7)),$G$7-SQRT((1-Q88)*($G$7-$E$7)*($G$7-$F$7)))) -> 0.89610019 | D88: =1+IF($G$8=$E$8,$F$8,IF(R88<($F$8-$E$8)/($G$8-$E$8),$E$8+SQRT(R88*($G$8-$E$8)*($F$8-$E$8)),$G$8-SQRT((1-R88)*($G$8-$E$8)*($G$8-$F$8)))) -> 0.96654102 | E88: =1+IF($G$9=$E$9,$F$9,IF(S88<($F$9-$E$9)/($G$9-$E$9),$E$9+SQRT(S88*($G$9-$E$9)*($F$9-$E$9)),$G$9-SQRT((1-S88)*($G$9-$E$9)*($G$9-$F$9)))) -> 1.0268073 | F88: =1+IF($G$10=$E$10,$F$10,IF(T88<($F$10-$E$10)/($G$10-$E$10),$E$10+SQRT(T88*($G$10-$E$10)*($F$10-$E$10)),$G$10-SQRT((1-T88)*($G$10-$E$10)*($G$10-$F$10)))) -> 1.0654899 | G88: =IF($G$11=$E$11,$F$11,IF(U88<($F$11-$E$11)/($G$11-$E$11),$E$11+SQRT(U88*($G$11-$E$11)*($F$11-$E$11)),$G$11-SQRT((1-U88)*($G$11-$E$11)*($G$11-$F$11)))) -> 0.099837564 | H88: =(('Business Case'!B11*$C88*'Business Case'!B12*$B88)-'Business Case'!B11*$C88*'Business Case'!B13*$D88-'Business Case'!B14*$E88)-MAX(0,(('Business Case'!B11*$C88*'Business Case'!B12*$B88)-'Business Case'!B11*$C88*'Business Case'!B13*$D88-'Business Case'!B14*$E88))*'Business Case'!$B$7-'Business Case'!$B$8*('Business Case'!B11*$C88*'Business Case'!B12*$B88)-'Business Case'!B15*$F88 -> -2.1309797e+09 | I88: =(('Business Case'!C11*$C88*'Business Case'!C12*$B88)-'Business Case'!C11*$C88*'Business Case'!C13*$D88-'Business Case'!C14*$E88)-MAX(0,(('Business Case'!C11*$C88*'Business Case'!C12*$B88)-'Business Case'!C11*$C88*'Business Case'!C13*$D88-'Business Case'!C14*$E88))*'Business Case'!$B$7-'Business Case'!$B$8*(('Business Case'!C11*$C88*'Business Case'!C12*$B88)-('Business Case'!B11*$C88*'Business Case'!B12*$B88))-'Business Case'!C15*$F88 -> -13683822 | J88: =(('Business Case'!D11*$C88*'Business Case'!D12*$B88)-'Business Case'!D11*$C88*'Business Case'!D13*$D88-'Business Case'!D14*$E88)-MAX(0,(('Business Case'!D11*$C88*'Business Case'!D12*$B88)-'Business Case'!D11*$C88*'Business Case'!D13*$D88-'Business Case'!D14*$E88))*'Business Case'!$B$7-'Business Case'!$B$8*(('Business Case'!D11*$C88*'Business Case'!D12*$B88)-('Business Case'!C11*$C88*'Business Case'!C12*$B88))-'Business Case'!D15*$F88 -> 2.71292e+08 | K88: =(('Business Case'!E11*$C88*'Business Case'!E12*$B88)-'Business Case'!E11*$C88*'Business Case'!E13*$D88-'Business Case'!E14*$E88)-MAX(0,(('Business Case'!E11*$C88*'Business Case'!E12*$B88)-'Business Case'!E11*$C88*'Business Case'!E13*$D88-'Business Case'!E14*$E88))*'Business Case'!$B$7-'Business Case'!$B$8*(('Business Case'!E11*$C88*'Business Case'!E12*$B88)-('Business Case'!D11*$C88*'Business Case'!D12*$B88))-'Business Case'!E15*$F88 -> 6.0954231e+08 | L88: =(('Business Case'!F11*$C88*'Business Case'!F12*$B88)-'Business Case'!F11*$C88*'Business Case'!F13*$D88-'Business Case'!F14*$E88)-MAX(0,(('Business Case'!F11*$C88*'Business Case'!F12*$B88)-'Business Case'!F11*$C88*'Business Case'!F13*$D88-'Business Case'!F14*$E88))*'Business Case'!$B$7-'Business Case'!$B$8*(('Business Case'!F11*$C88*'Business Case'!F12*$B88)-('Business Case'!E11*$C88*'Business Case'!E12*$B88))-'Business Case'!F15*$F88 -> 7.3526669e+08 | M88: =(('Business Case'!G11*$C88*'Business Case'!G12*$B88)-'Business Case'!G11*$C88*'Business Case'!G13*$D88-'Business Case'!G14*$E88)-MAX(0,(('Business Case'!G11*$C88*'Business Case'!G12*$B88)-'Business Case'!G11*$C88*'Business Case'!G13*$D88-'Business Case'!G14*$E88))*'Business Case'!$B$7-'Business Case'!$B$8*(('Business Case'!G11*$C88*'Business Case'!G12*$B88)-('Business Case'!F11*$C88*'Business Case'!F12*$B88))-'Business Case'!G15*$F88+'Business Case'!$B$8*('Business Case'!G11*$C88*'Business Case'!G12*$B88) -> 9.0429509e+08 | N88: =IF(COUNT('Business Case'!B11:G11)=0,"",H88+NPV(G88,I88:M88)) -> -3.9658117e+08 | P88: =RAND() -> 0.54532514 | Q88: =RAND() -> 0.13193209 | R88: =RAND() -> 0.042093134 | S88: =RAND() -> 0.64285542 | T88: =RAND() -> 0.63814049 | U88: =RAND() -> 0.32259222
A89: 9 | B89: =1+IF($G$6=$E$6,$F$6,IF(P89<($F$6-$E$6)/($G$6-$E$6),$E$6+SQRT(P89*($G$6-$E$6)*($F$6-$E$6)),$G$6-SQRT((1-P89)*($G$6-$E$6)*($G$6-$F$6)))) -> 0.95381703 | C89: =1+IF($G$7=$E$7,$F$7,IF(Q89<($F$7-$E$7)/($G$7-$E$7),$E$7+SQRT(Q89*($G$7-$E$7)*($F$7-$E$7)),$G$7-SQRT((1-Q89)*($G$7-$E$7)*($G$7-$F$7)))) -> 0.93668721 | D89: =1+IF($G$8=$E$8,$F$8,IF(R89<($F$8-$E$8)/($G$8-$E$8),$E$8+SQRT(R89*($G$8-$E$8)*($F$8-$E$8)),$G$8-SQRT((1-R89)*($G$8-$E$8)*($G$8-$F$8)))) -> 1.0594746 | E89: =1+IF($G$9=$E$9,$F$9,IF(S89<($F$9-$E$9)/($G$9-$E$9),$E$9+SQRT(S89*($G$9-$E$9)*($F$9-$E$9)),$G$9-SQRT((1-S89)*($G$9-$E$9)*($G$9-$F$9)))) -> 1.0032942 | F89: =1+IF($G$10=$E$10,$F$10,IF(T89<($F$10-$E$10)/($G$10-$E$10),$E$10+SQRT(T89*($G$10-$E$10)*($F$10-$E$10)),$G$10-SQRT((1-T89)*($G$10-$E$10)*($G$10-$F$10)))) -> 1.0790297 | G89: =IF($G$11=$E$11,$F$11,IF(U89<($F$11-$E$11)/($G$11-$E$11),$E$11+SQRT(U89*($G$11-$E$11)*($F$11-$E$11)),$G$11-SQRT((1-U89)*($G$11-$E$11)*($G$11-$F$11)))) -> 0.10113063 | H89: =(('Business Case'!B11*$C89*'Business Case'!B12*$B89)-'Business Case'!B11*$C89*'Business Case'!B13*$D89-'Business Case'!B14*$E89)-MAX(0,(('Business Case'!B11*$C89*'Business Case'!B12*$B89)-'Business Case'!B11*$C89*'Business Case'!B13*$D89-'Business Case'!B14*$E89))*'Business Case'!$B$7-'Business Case'!$B$8*('Business Case'!B11*$C89*'Business Case'!B12*$B89)-'Business Case'!B15*$F89 -> -2.1580594e+09 | I89: =(('Business Case'!C11*$C89*'Business Case'!C12*$B89)-'Business Case'!C11*$C89*'Business Case'!C13*$D89-'Business Case'!C14*$E89)-MAX(0,(('Business Case'!C11*$C89*'Business Case'!C12*$B89)-'Business Case'!C11*$C89*'Business Case'!C13*$D89-'Business Case'!C14*$E89))*'Business Case'!$B$7-'Business Case'!$B$8*(('Business Case'!C11*$C89*'Business Case'!C12*$B89)-('Business Case'!B11*$C89*'Business Case'!B12*$B89))-'Business Case'!C15*$F89 -> -73132205 | J89: =(('Business Case'!D11*$C89*'Business Case'!D12*$B89)-'Business Case'!D11*$C89*'Business Case'!D13*$D89-'Business Case'!D14*$E89)-MAX(0,(('Business Case'!D11*$C89*'Business Case'!D12*$B89)-'Business Case'!D11*$C89*'Business Case'!D13*$D89-'Business Case'!D14*$E89))*'Business Case'!$B$7-'Business Case'!$B$8*(('Business Case'!D11*$C89*'Business Case'!D12*$B89)-('Business Case'!C11*$C89*'Business Case'!C12*$B89))-'Business Case'!D15*$F89 -> 1.5062231e+08 | K89: =(('Business Case'!E11*$C89*'Business Case'!E12*$B89)-'Business Case'!E11*$C89*'Business Case'!E13*$D89-'Business Case'!E14*$E89)-MAX(0,(('Business Case'!E11*$C89*'Business Case'!E12*$B89)-'Business Case'!E11*$C89*'Business Case'!E13*$D89-'Business Case'!E14*$E89))*'Business Case'!$B$7-'Business Case'!$B$8*(('Business Case'!E11*$C89*'Business Case'!E12*$B89)-('Business Case'!D11*$C89*'Business Case'!D12*$B89))-'Business Case'!E15*$F89 -> 4.2832831e+08 | L89: =(('Business Case'!F11*$C89*'Business Case'!F12*$B89)-'Business Case'!F11*$C89*'Business Case'!F13*$D89-'Business Case'!F14*$E89)-MAX(0,(('Business Case'!F11*$C89*'Business Case'!F12*$B89)-'Business Case'!F11*$C89*'Business Case'!F13*$D89-'Business Case'!F14*$E89))*'Business Case'!$B$7-'Business Case'!$B$8*(('Business Case'!F11*$C89*'Business Case'!F12*$B89)-('Business Case'!E11*$C89*'Business Case'!E12*$B89))-'Business Case'!F15*$F89 -> 5.3379003e+08 | M89: =(('Business Case'!G11*$C89*'Business Case'!G12*$B89)-'Business Case'!G11*$C89*'Business Case'!G13*$D89-'Business Case'!G14*$E89)-MAX(0,(('Business Case'!G11*$C89*'Business Case'!G12*$B89)-'Business Case'!G11*$C89*'Business Case'!G13*$D89-'Business Case'!G14*$E89))*'Business Case'!$B$7-'Business Case'!$B$8*(('Business Case'!G11*$C89*'Business Case'!G12*$B89)-('Business Case'!F11*$C89*'Business Case'!F12*$B89))-'Business Case'!G15*$F89+'Business Case'!$B$8*('Business Case'!G11*$C89*'Business Case'!G12*$B89) -> 7.0361287e+08 | N89: =IF(COUNT('Business Case'!B11:G11)=0,"",H89+NPV(G89,I89:M89)) -> -9.8168953e+08 | P89: =RAND() -> 0.1191241 | Q89: =RAND() -> 0.26690561 | R89: =RAND() -> 0.95949112 | S89: =RAND() -> 0.37653245 | T89: =RAND() -> 0.70732372 | U89: =RAND() -> 0.40657799
A90: 10 | B90: =1+IF($G$6=$E$6,$F$6,IF(P90<($F$6-$E$6)/($G$6-$E$6),$E$6+SQRT(P90*($G$6-$E$6)*($F$6-$E$6)),$G$6-SQRT((1-P90)*($G$6-$E$6)*($G$6-$F$6)))) -> 0.99657346 | C90: =1+IF($G$7=$E$7,$F$7,IF(Q90<($F$7-$E$7)/($G$7-$E$7),$E$7+SQRT(Q90*($G$7-$E$7)*($F$7-$E$7)),$G$7-SQRT((1-Q90)*($G$7-$E$7)*($G$7-$F$7)))) -> 0.99900085 | D90: =1+IF($G$8=$E$8,$F$8,IF(R90<($F$8-$E$8)/($G$8-$E$8),$E$8+SQRT(R90*($G$8-$E$8)*($F$8-$E$8)),$G$8-SQRT((1-R90)*($G$8-$E$8)*($G$8-$F$8)))) -> 1.0234157 | E90: =1+IF($G$9=$E$9,$F$9,IF(S90<($F$9-$E$9)/($G$9-$E$9),$E$9+SQRT(S90*($G$9-$E$9)*($F$9-$E$9)),$G$9-SQRT((1-S90)*($G$9-$E$9)*($G$9-$F$9)))) -> 0.98315997 | F90: =1+IF($G$10=$E$10,$F$10,IF(T90<($F$10-$E$10)/($G$10-$E$10),$E$10+SQRT(T90*($G$10-$E$10)*($F$10-$E$10)),$G$10-SQRT((1-T90)*($G$10-$E$10)*($G$10-$F$10)))) -> 1.0408494 | G90: =IF($G$11=$E$11,$F$11,IF(U90<($F$11-$E$11)/($G$11-$E$11),$E$11+SQRT(U90*($G$11-$E$11)*($F$11-$E$11)),$G$11-SQRT((1-U90)*($G$11-$E$11)*($G$11-$F$11)))) -> 0.096874147 | H90: =(('Business Case'!B11*$C90*'Business Case'!B12*$B90)-'Business Case'!B11*$C90*'Business Case'!B13*$D90-'Business Case'!B14*$E90)-MAX(0,(('Business Case'!B11*$C90*'Business Case'!B12*$B90)-'Business Case'!B11*$C90*'Business Case'!B13*$D90-'Business Case'!B14*$E90))*'Business Case'!$B$7-'Business Case'!$B$8*('Business Case'!B11*$C90*'Business Case'!B12*$B90)-'Business Case'!B15*$F90 -> -2.0816987e+09 | I90: =(('Business Case'!C11*$C90*'Business Case'!C12*$B90)-'Business Case'!C11*$C90*'Business Case'!C13*$D90-'Business Case'!C14*$E90)-MAX(0,(('Business Case'!C11*$C90*'Business Case'!C12*$B90)-'Business Case'!C11*$C90*'Business Case'!C13*$D90-'Business Case'!C14*$E90))*'Business Case'!$B$7-'Business Case'!$B$8*(('Business Case'!C11*$C90*'Business Case'!C12*$B90)-('Business Case'!B11*$C90*'Business Case'!B12*$B90))-'Business Case'!C15*$F90 -> -3434671.8 | J90: =(('Business Case'!D11*$C90*'Business Case'!D12*$B90)-'Business Case'!D11*$C90*'Business Case'!D13*$D90-'Business Case'!D14*$E90)-MAX(0,(('Business Case'!D11*$C90*'Business Case'!D12*$B90)-'Business Case'!D11*$C90*'Business Case'!D13*$D90-'Business Case'!D14*$E90))*'Business Case'!$B$7-'Business Case'!$B$8*(('Business Case'!D11*$C90*'Business Case'!D12*$B90)-('Business Case'!C11*$C90*'Business Case'!C12*$B90))-'Business Case'!D15*$F90 -> 2.8863169e+08 | K90: =(('Business Case'!E11*$C90*'Business Case'!E12*$B90)-'Business Case'!E11*$C90*'Business Case'!E13*$D90-'Business Case'!E14*$E90)-MAX(0,(('Business Case'!E11*$C90*'Business Case'!E12*$B90)-'Business Case'!E11*$C90*'Business Case'!E13*$D90-'Business Case'!E14*$E90))*'Business Case'!$B$7-'Business Case'!$B$8*(('Business Case'!E11*$C90*'Business Case'!E12*$B90)-('Business Case'!D11*$C90*'Business Case'!D12*$B90))-'Business Case'!E15*$F90 -> 6.3274052e+08 | L90: =(('Business Case'!F11*$C90*'Business Case'!F12*$B90)-'Business Case'!F11*$C90*'Business Case'!F13*$D90-'Business Case'!F14*$E90)-MAX(0,(('Business Case'!F11*$C90*'Business Case'!F12*$B90)-'Business Case'!F11*$C90*'Business Case'!F13*$D90-'Business Case'!F14*$E90))*'Business Case'!$B$7-'Business Case'!$B$8*(('Business Case'!F11*$C90*'Business Case'!F12*$B90)-('Business Case'!E11*$C90*'Business Case'!E12*$B90))-'Business Case'!F15*$F90 -> 7.6450314e+08 | M90: =(('Business Case'!G11*$C90*'Business Case'!G12*$B90)-'Business Case'!G11*$C90*'Business Case'!G13*$D90-'Business Case'!G14*$E90)-MAX(0,(('Business Case'!G11*$C90*'Business Case'!G12*$B90)-'Business Case'!G11*$C90*'Business Case'!G13*$D90-'Business Case'!G14*$E90))*'Business Case'!$B$7-'Business Case'!$B$8*(('Business Case'!G11*$C90*'Business Case'!G12*$B90)-('Business Case'!F11*$C90*'Business Case'!F12*$B90))-'Business Case'!G15*$F90+'Business Case'!$B$8*('Business Case'!G11*$C90*'Business Case'!G12*$B90) -> 9.5374255e+08 | N90: =IF(COUNT('Business Case'!B11:G11)=0,"",H90+NPV(G90,I90:M90)) -> -2.3663761e+08 | P90: =RAND() -> 0.61078074 | Q90: =RAND() -> 0.56573339 | R90: =RAND() -> 0.69213586 | S90: =RAND() -> 0.14661119 | T90: =RAND() -> 0.49342141 | U90: =RAND() -> 0.15751301
A91: 11 | B91: =1+IF($G$6=$E$6,$F$6,IF(P91<($F$6-$E$6)/($G$6-$E$6),$E$6+SQRT(P91*($G$6-$E$6)*($F$6-$E$6)),$G$6-SQRT((1-P91)*($G$6-$E$6)*($G$6-$F$6)))) -> 1.0066026 | C91: =1+IF($G$7=$E$7,$F$7,IF(Q91<($F$7-$E$7)/($G$7-$E$7),$E$7+SQRT(Q91*($G$7-$E$7)*($F$7-$E$7)),$G$7-SQRT((1-Q91)*($G$7-$E$7)*($G$7-$F$7)))) -> 0.98632425 | D91: =1+IF($G$8=$E$8,$F$8,IF(R91<($F$8-$E$8)/($G$8-$E$8),$E$8+SQRT(R91*($G$8-$E$8)*($F$8-$E$8)),$G$8-SQRT((1-R91)*($G$8-$E$8)*($G$8-$F$8)))) -> 1.0424129 | E91: =1+IF($G$9=$E$9,$F$9,IF(S91<($F$9-$E$9)/($G$9-$E$9),$E$9+SQRT(S91*($G$9-$E$9)*($F$9-$E$9)),$G$9-SQRT((1-S91)*($G$9-$E$9)*($G$9-$F$9)))) -> 0.98309824 | F91: =1+IF($G$10=$E$10,$F$10,IF(T91<($F$10-$E$10)/($G$10-$E$10),$E$10+SQRT(T91*($G$10-$E$10)*($F$10-$E$10)),$G$10-SQRT((1-T91)*($G$10-$E$10)*($G$10-$F$10)))) -> 1.1394678 | G91: =IF($G$11=$E$11,$F$11,IF(U91<($F$11-$E$11)/($G$11-$E$11),$E$11+SQRT(U91*($G$11-$E$11)*($F$11-$E$11)),$G$11-SQRT((1-U91)*($G$11-$E$11)*($G$11-$F$11)))) -> 0.114148 | H91: =(('Business Case'!B11*$C91*'Business Case'!B12*$B91)-'Business Case'!B11*$C91*'Business Case'!B13*$D91-'Business Case'!B14*$E91)-MAX(0,(('Business Case'!B11*$C91*'Business Case'!B12*$B91)-'Business Case'!B11*$C91*'Business Case'!B13*$D91-'Business Case'!B14*$E91))*'Business Case'!$B$7-'Business Case'!$B$8*('Business Case'!B11*$C91*'Business Case'!B12*$B91)-'Business Case'!B15*$F91 -> -2.2789355e+09 | I91: =(('Business Case'!C11*$C91*'Business Case'!C12*$B91)-'Business Case'!C11*$C91*'Business Case'!C13*$D91-'Business Case'!C14*$E91)-MAX(0,(('Business Case'!C11*$C91*'Business Case'!C12*$B91)-'Business Case'!C11*$C91*'Business Case'!C13*$D91-'Business Case'!C14*$E91))*'Business Case'!$B$7-'Business Case'!$B$8*(('Business Case'!C11*$C91*'Business Case'!C12*$B91)-('Business Case'!B11*$C91*'Business Case'!B12*$B91))-'Business Case'!C15*$F91 -> -18341608 | J91: =(('Business Case'!D11*$C91*'Business Case'!D12*$B91)-'Business Case'!D11*$C91*'Business Case'!D13*$D91-'Business Case'!D14*$E91)-MAX(0,(('Business Case'!D11*$C91*'Business Case'!D12*$B91)-'Business Case'!D11*$C91*'Business Case'!D13*$D91-'Business Case'!D14*$E91))*'Business Case'!$B$7-'Business Case'!$B$8*(('Business Case'!D11*$C91*'Business Case'!D12*$B91)-('Business Case'!C11*$C91*'Business Case'!C12*$B91))-'Business Case'!D15*$F91 -> 2.6852878e+08 | K91: =(('Business Case'!E11*$C91*'Business Case'!E12*$B91)-'Business Case'!E11*$C91*'Business Case'!E13*$D91-'Business Case'!E14*$E91)-MAX(0,(('Business Case'!E11*$C91*'Business Case'!E12*$B91)-'Business Case'!E11*$C91*'Business Case'!E13*$D91-'Business Case'!E14*$E91))*'Business Case'!$B$7-'Business Case'!$B$8*(('Business Case'!E11*$C91*'Business Case'!E12*$B91)-('Business Case'!D11*$C91*'Business Case'!D12*$B91))-'Business Case'!E15*$F91 -> 6.1237255e+08 | L91: =(('Business Case'!F11*$C91*'Business Case'!F12*$B91)-'Business Case'!F11*$C91*'Business Case'!F13*$D91-'Business Case'!F14*$E91)-MAX(0,(('Business Case'!F11*$C91*'Business Case'!F12*$B91)-'Business Case'!F11*$C91*'Business Case'!F13*$D91-'Business Case'!F14*$E91))*'Business Case'!$B$7-'Business Case'!$B$8*(('Business Case'!F11*$C91*'Business Case'!F12*$B91)-('Business Case'!E11*$C91*'Business Case'!E12*$B91))-'Business Case'!F15*$F91 -> 7.4230844e+08 | M91: =(('Business Case'!G11*$C91*'Business Case'!G12*$B91)-'Business Case'!G11*$C91*'Business Case'!G13*$D91-'Business Case'!G14*$E91)-MAX(0,(('Business Case'!G11*$C91*'Business Case'!G12*$B91)-'Business Case'!G11*$C91*'Business Case'!G13*$D91-'Business Case'!G14*$E91))*'Business Case'!$B$7-'Business Case'!$B$8*(('Business Case'!G11*$C91*'Business Case'!G12*$B91)-('Business Case'!F11*$C91*'Business Case'!F12*$B91))-'Business Case'!G15*$F91+'Business Case'!$B$8*('Business Case'!G11*$C91*'Business Case'!G12*$B91) -> 9.3102681e+08 | N91: =IF(COUNT('Business Case'!B11:G11)=0,"",H91+NPV(G91,I91:M91)) -> -6.122444e+08 | P91: =RAND() -> 0.76762742 | Q91: =RAND() -> 0.49595325 | R91: =RAND() -> 0.8641551 | S91: =RAND() -> 0.14606577 | T91: =RAND() -> 0.92671698 | U91: =RAND() -> 0.94292344
A92: 12 | B92: =1+IF($G$6=$E$6,$F$6,IF(P92<($F$6-$E$6)/($G$6-$E$6),$E$6+SQRT(P92*($G$6-$E$6)*($F$6-$E$6)),$G$6-SQRT((1-P92)*($G$6-$E$6)*($G$6-$F$6)))) -> 0.98716928 | C92: =1+IF($G$7=$E$7,$F$7,IF(Q92<($F$7-$E$7)/($G$7-$E$7),$E$7+SQRT(Q92*($G$7-$E$7)*($F$7-$E$7)),$G$7-SQRT((1-Q92)*($G$7-$E$7)*($G$7-$F$7)))) -> 0.93112231 | D92: =1+IF($G$8=$E$8,$F$8,IF(R92<($F$8-$E$8)/($G$8-$E$8),$E$8+SQRT(R92*($G$8-$E$8)*($F$8-$E$8)),$G$8-SQRT((1-R92)*($G$8-$E$8)*($G$8-$F$8)))) -> 1.0059286 | E92: =1+IF($G$9=$E$9,$F$9,IF(S92<($F$9-$E$9)/($G$9-$E$9),$E$9+SQRT(S92*($G$9-$E$9)*($F$9-$E$9)),$G$9-SQRT((1-S92)*($G$9-$E$9)*($G$9-$F$9)))) -> 0.97672867 | F92: =1+IF($G$10=$E$10,$F$10,IF(T92<($F$10-$E$10)/($G$10-$E$10),$E$10+SQRT(T92*($G$10-$E$10)*($F$10-$E$10)),$G$10-SQRT((1-T92)*($G$10-$E$10)*($G$10-$F$10)))) -> 1.0684136 | G92: =IF($G$11=$E$11,$F$11,IF(U92<($F$11-$E$11)/($G$11-$E$11),$E$11+SQRT(U92*($G$11-$E$11)*($F$11-$E$11)),$G$11-SQRT((1-U92)*($G$11-$E$11)*($G$11-$F$11)))) -> 0.10785274 | H92: =(('Business Case'!B11*$C92*'Business Case'!B12*$B92)-'Business Case'!B11*$C92*'Business Case'!B13*$D92-'Business Case'!B14*$E92)-MAX(0,(('Business Case'!B11*$C92*'Business Case'!B12*$B92)-'Business Case'!B11*$C92*'Business Case'!B13*$D92-'Business Case'!B14*$E92))*'Business Case'!$B$7-'Business Case'!$B$8*('Business Case'!B11*$C92*'Business Case'!B12*$B92)-'Business Case'!B15*$F92 -> -2.1368272e+09 | I92: =(('Business Case'!C11*$C92*'Business Case'!C12*$B92)-'Business Case'!C11*$C92*'Business Case'!C13*$D92-'Business Case'!C14*$E92)-MAX(0,(('Business Case'!C11*$C92*'Business Case'!C12*$B92)-'Business Case'!C11*$C92*'Business Case'!C13*$D92-'Business Case'!C14*$E92))*'Business Case'!$B$7-'Business Case'!$B$8*(('Business Case'!C11*$C92*'Business Case'!C12*$B92)-('Business Case'!B11*$C92*'Business Case'!B12*$B92))-'Business Case'!C15*$F92 -> -19997513 | J92: =(('Business Case'!D11*$C92*'Business Case'!D12*$B92)-'Business Case'!D11*$C92*'Business Case'!D13*$D92-'Business Case'!D14*$E92)-MAX(0,(('Business Case'!D11*$C92*'Business Case'!D12*$B92)-'Business Case'!D11*$C92*'Business Case'!D13*$D92-'Business Case'!D14*$E92))*'Business Case'!$B$7-'Business Case'!$B$8*(('Business Case'!D11*$C92*'Business Case'!D12*$B92)-('Business Case'!C11*$C92*'Business Case'!C12*$B92))-'Business Case'!D15*$F92 -> 2.533872e+08 | K92: =(('Business Case'!E11*$C92*'Business Case'!E12*$B92)-'Business Case'!E11*$C92*'Business Case'!E13*$D92-'Business Case'!E14*$E92)-MAX(0,(('Business Case'!E11*$C92*'Business Case'!E12*$B92)-'Business Case'!E11*$C92*'Business Case'!E13*$D92-'Business Case'!E14*$E92))*'Business Case'!$B$7-'Business Case'!$B$8*(('Business Case'!E11*$C92*'Business Case'!E12*$B92)-('Business Case'!D11*$C92*'Business Case'!D12*$B92))-'Business Case'!E15*$F92 -> 5.8019259e+08 | L92: =(('Business Case'!F11*$C92*'Business Case'!F12*$B92)-'Business Case'!F11*$C92*'Business Case'!F13*$D92-'Business Case'!F14*$E92)-MAX(0,(('Business Case'!F11*$C92*'Business Case'!F12*$B92)-'Business Case'!F11*$C92*'Business Case'!F13*$D92-'Business Case'!F14*$E92))*'Business Case'!$B$7-'Business Case'!$B$8*(('Business Case'!F11*$C92*'Business Case'!F12*$B92)-('Business Case'!E11*$C92*'Business Case'!E12*$B92))-'Business Case'!F15*$F92 -> 7.0308753e+08 | M92: =(('Business Case'!G11*$C92*'Business Case'!G12*$B92)-'Business Case'!G11*$C92*'Business Case'!G13*$D92-'Business Case'!G14*$E92)-MAX(0,(('Business Case'!G11*$C92*'Business Case'!G12*$B92)-'Business Case'!G11*$C92*'Business Case'!G13*$D92-'Business Case'!G14*$E92))*'Business Case'!$B$7-'Business Case'!$B$8*(('Business Case'!G11*$C92*'Business Case'!G12*$B92)-('Business Case'!F11*$C92*'Business Case'!F12*$B92))-'Business Case'!G15*$F92+'Business Case'!$B$8*('Business Case'!G11*$C92*'Business Case'!G12*$B92) -> 8.7780437e+08 | N92: =IF(COUNT('Business Case'!B11:G11)=0,"",H92+NPV(G92,I92:M92)) -> -5.2897287e+08 | P92: =RAND() -> 0.46997009 | Q92: =RAND() -> 0.24561513 | R92: =RAND() -> 0.47244543 | S92: =RAND() -> 0.09525621 | T92: =RAND() -> 0.65370032 | U92: =RAND() -> 0.75407329
A93: 13 | B93: =1+IF($G$6=$E$6,$F$6,IF(P93<($F$6-$E$6)/($G$6-$E$6),$E$6+SQRT(P93*($G$6-$E$6)*($F$6-$E$6)),$G$6-SQRT((1-P93)*($G$6-$E$6)*($G$6-$F$6)))) -> 0.97156477 | C93: =1+IF($G$7=$E$7,$F$7,IF(Q93<($F$7-$E$7)/($G$7-$E$7),$E$7+SQRT(Q93*($G$7-$E$7)*($F$7-$E$7)),$G$7-SQRT((1-Q93)*($G$7-$E$7)*($G$7-$F$7)))) -> 0.94283838 | D93: =1+IF($G$8=$E$8,$F$8,IF(R93<($F$8-$E$8)/($G$8-$E$8),$E$8+SQRT(R93*($G$8-$E$8)*($F$8-$E$8)),$G$8-SQRT((1-R93)*($G$8-$E$8)*($G$8-$F$8)))) -> 0.9879188 | E93: =1+IF($G$9=$E$9,$F$9,IF(S93<($F$9-$E$9)/($G$9-$E$9),$E$9+SQRT(S93*($G$9-$E$9)*($F$9-$E$9)),$G$9-SQRT((1-S93)*($G$9-$E$9)*($G$9-$F$9)))) -> 1.0038383 | F93: =1+IF($G$10=$E$10,$F$10,IF(T93<($F$10-$E$10)/($G$10-$E$10),$E$10+SQRT(T93*($G$10-$E$10)*($F$10-$E$10)),$G$10-SQRT((1-T93)*($G$10-$E$10)*($G$10-$F$10)))) -> 1.0226706 | G93: =IF($G$11=$E$11,$F$11,IF(U93<($F$11-$E$11)/($G$11-$E$11),$E$11+SQRT(U93*($G$11-$E$11)*($F$11-$E$11)),$G$11-SQRT((1-U93)*($G$11-$E$11)*($G$11-$F$11)))) -> 0.1014342 | H93: =(('Business Case'!B11*$C93*'Business Case'!B12*$B93)-'Business Case'!B11*$C93*'Business Case'!B13*$D93-'Business Case'!B14*$E93)-MAX(0,(('Business Case'!B11*$C93*'Business Case'!B12*$B93)-'Business Case'!B11*$C93*'Business Case'!B13*$D93-'Business Case'!B14*$E93))*'Business Case'!$B$7-'Business Case'!$B$8*('Business Case'!B11*$C93*'Business Case'!B12*$B93)-'Business Case'!B15*$F93 -> -2.0453411e+09 | I93: =(('Business Case'!C11*$C93*'Business Case'!C12*$B93)-'Business Case'!C11*$C93*'Business Case'!C13*$D93-'Business Case'!C14*$E93)-MAX(0,(('Business Case'!C11*$C93*'Business Case'!C12*$B93)-'Business Case'!C11*$C93*'Business Case'!C13*$D93-'Business Case'!C14*$E93))*'Business Case'!$B$7-'Business Case'!$B$8*(('Business Case'!C11*$C93*'Business Case'!C12*$B93)-('Business Case'!B11*$C93*'Business Case'!B12*$B93))-'Business Case'!C15*$F93 -> -19033180 | J93: =(('Business Case'!D11*$C93*'Business Case'!D12*$B93)-'Business Case'!D11*$C93*'Business Case'!D13*$D93-'Business Case'!D14*$E93)-MAX(0,(('Business Case'!D11*$C93*'Business Case'!D12*$B93)-'Business Case'!D11*$C93*'Business Case'!D13*$D93-'Business Case'!D14*$E93))*'Business Case'!$B$7-'Business Case'!$B$8*(('Business Case'!D11*$C93*'Business Case'!D12*$B93)-('Business Case'!C11*$C93*'Business Case'!C12*$B93))-'Business Case'!D15*$F93 -> 2.5443342e+08 | K93: =(('Business Case'!E11*$C93*'Business Case'!E12*$B93)-'Business Case'!E11*$C93*'Business Case'!E13*$D93-'Business Case'!E14*$E93)-MAX(0,(('Business Case'!E11*$C93*'Business Case'!E12*$B93)-'Business Case'!E11*$C93*'Business Case'!E13*$D93-'Business Case'!E14*$E93))*'Business Case'!$B$7-'Business Case'!$B$8*(('Business Case'!E11*$C93*'Business Case'!E12*$B93)-('Business Case'!D11*$C93*'Business Case'!D12*$B93))-'Business Case'!E15*$F93 -> 5.7903355e+08 | L93: =(('Business Case'!F11*$C93*'Business Case'!F12*$B93)-'Business Case'!F11*$C93*'Business Case'!F13*$D93-'Business Case'!F14*$E93)-MAX(0,(('Business Case'!F11*$C93*'Business Case'!F12*$B93)-'Business Case'!F11*$C93*'Business Case'!F13*$D93-'Business Case'!F14*$E93))*'Business Case'!$B$7-'Business Case'!$B$8*(('Business Case'!F11*$C93*'Business Case'!F12*$B93)-('Business Case'!E11*$C93*'Business Case'!E12*$B93))-'Business Case'!F15*$F93 -> 7.0184703e+08 | M93: =(('Business Case'!G11*$C93*'Business Case'!G12*$B93)-'Business Case'!G11*$C93*'Business Case'!G13*$D93-'Business Case'!G14*$E93)-MAX(0,(('Business Case'!G11*$C93*'Business Case'!G12*$B93)-'Business Case'!G11*$C93*'Business Case'!G13*$D93-'Business Case'!G14*$E93))*'Business Case'!$B$7-'Business Case'!$B$8*(('Business Case'!G11*$C93*'Business Case'!G12*$B93)-('Business Case'!F11*$C93*'Business Case'!F12*$B93))-'Business Case'!G15*$F93+'Business Case'!$B$8*('Business Case'!G11*$C93*'Business Case'!G12*$B93) -> 8.7596574e+08 | N93: =IF(COUNT('Business Case'!B11:G11)=0,"",H93+NPV(G93,I93:M93)) -> -4.0230098e+08 | P93: =RAND() -> 0.27697141 | Q93: =RAND() -> 0.29146861 | R93: =RAND() -> 0.22120541 | S93: =RAND() -> 0.38352854 | T93: =RAND() -> 0.37108534 | U93: =RAND() -> 0.42551853
A94: 14 | B94: =1+IF($G$6=$E$6,$F$6,IF(P94<($F$6-$E$6)/($G$6-$E$6),$E$6+SQRT(P94*($G$6-$E$6)*($F$6-$E$6)),$G$6-SQRT((1-P94)*($G$6-$E$6)*($G$6-$F$6)))) -> 0.98432112 | C94: =1+IF($G$7=$E$7,$F$7,IF(Q94<($F$7-$E$7)/($G$7-$E$7),$E$7+SQRT(Q94*($G$7-$E$7)*($F$7-$E$7)),$G$7-SQRT((1-Q94)*($G$7-$E$7)*($G$7-$F$7)))) -> 0.88430684 | D94: =1+IF($G$8=$E$8,$F$8,IF(R94<($F$8-$E$8)/($G$8-$E$8),$E$8+SQRT(R94*($G$8-$E$8)*($F$8-$E$8)),$G$8-SQRT((1-R94)*($G$8-$E$8)*($G$8-$F$8)))) -> 1.0640525 | E94: =1+IF($G$9=$E$9,$F$9,IF(S94<($F$9-$E$9)/($G$9-$E$9),$E$9+SQRT(S94*($G$9-$E$9)*($F$9-$E$9)),$G$9-SQRT((1-S94)*($G$9-$E$9)*($G$9-$F$9)))) -> 1.0450469 | F94: =1+IF($G$10=$E$10,$F$10,IF(T94<($F$10-$E$10)/($G$10-$E$10),$E$10+SQRT(T94*($G$10-$E$10)*($F$10-$E$10)),$G$10-SQRT((1-T94)*($G$10-$E$10)*($G$10-$F$10)))) -> 1.101981 | G94: =IF($G$11=$E$11,$F$11,IF(U94<($F$11-$E$11)/($G$11-$E$11),$E$11+SQRT(U94*($G$11-$E$11)*($F$11-$E$11)),$G$11-SQRT((1-U94)*($G$11-$E$11)*($G$11-$F$11)))) -> 0.10115041 | H94: =(('Business Case'!B11*$C94*'Business Case'!B12*$B94)-'Business Case'!B11*$C94*'Business Case'!B13*$D94-'Business Case'!B14*$E94)-MAX(0,(('Business Case'!B11*$C94*'Business Case'!B12*$B94)-'Business Case'!B11*$C94*'Business Case'!B13*$D94-'Business Case'!B14*$E94))*'Business Case'!$B$7-'Business Case'!$B$8*('Business Case'!B11*$C94*'Business Case'!B12*$B94)-'Business Case'!B15*$F94 -> -2.203962e+09 | I94: =(('Business Case'!C11*$C94*'Business Case'!C12*$B94)-'Business Case'!C11*$C94*'Business Case'!C13*$D94-'Business Case'!C14*$E94)-MAX(0,(('Business Case'!C11*$C94*'Business Case'!C12*$B94)-'Business Case'!C11*$C94*'Business Case'!C13*$D94-'Business Case'!C14*$E94))*'Business Case'!$B$7-'Business Case'!$B$8*(('Business Case'!C11*$C94*'Business Case'!C12*$B94)-('Business Case'!B11*$C94*'Business Case'!B12*$B94))-'Business Case'!C15*$F94 -> -72663475 | J94: =(('Business Case'!D11*$C94*'Business Case'!D12*$B94)-'Business Case'!D11*$C94*'Business Case'!D13*$D94-'Business Case'!D14*$E94)-MAX(0,(('Business Case'!D11*$C94*'Business Case'!D12*$B94)-'Business Case'!D11*$C94*'Business Case'!D13*$D94-'Business Case'!D14*$E94))*'Business Case'!$B$7-'Business Case'!$B$8*(('Business Case'!D11*$C94*'Business Case'!D12*$B94)-('Business Case'!C11*$C94*'Business Case'!C12*$B94))-'Business Case'!D15*$F94 -> 1.5860053e+08 | K94: =(('Business Case'!E11*$C94*'Business Case'!E12*$B94)-'Business Case'!E11*$C94*'Business Case'!E13*$D94-'Business Case'!E14*$E94)-MAX(0,(('Business Case'!E11*$C94*'Business Case'!E12*$B94)-'Business Case'!E11*$C94*'Business Case'!E13*$D94-'Business Case'!E14*$E94))*'Business Case'!$B$7-'Business Case'!$B$8*(('Business Case'!E11*$C94*'Business Case'!E12*$B94)-('Business Case'!D11*$C94*'Business Case'!D12*$B94))-'Business Case'!E15*$F94 -> 4.4496358e+08 | L94: =(('Business Case'!F11*$C94*'Business Case'!F12*$B94)-'Business Case'!F11*$C94*'Business Case'!F13*$D94-'Business Case'!F14*$E94)-MAX(0,(('Business Case'!F11*$C94*'Business Case'!F12*$B94)-'Business Case'!F11*$C94*'Business Case'!F13*$D94-'Business Case'!F14*$E94))*'Business Case'!$B$7-'Business Case'!$B$8*(('Business Case'!F11*$C94*'Business Case'!F12*$B94)-('Business Case'!E11*$C94*'Business Case'!E12*$B94))-'Business Case'!F15*$F94 -> 5.5213406e+08 | M94: =(('Business Case'!G11*$C94*'Business Case'!G12*$B94)-'Business Case'!G11*$C94*'Business Case'!G13*$D94-'Business Case'!G14*$E94)-MAX(0,(('Business Case'!G11*$C94*'Business Case'!G12*$B94)-'Business Case'!G11*$C94*'Business Case'!G13*$D94-'Business Case'!G14*$E94))*'Business Case'!$B$7-'Business Case'!$B$8*(('Business Case'!G11*$C94*'Business Case'!G12*$B94)-('Business Case'!F11*$C94*'Business Case'!F12*$B94))-'Business Case'!G15*$F94+'Business Case'!$B$8*('Business Case'!G11*$C94*'Business Case'!G12*$B94) -> 7.1758766e+08 | N94: =IF(COUNT('Business Case'!B11:G11)=0,"",H94+NPV(G94,I94:M94)) -> -9.8710426e+08 | P94: =RAND() -> 0.43095901 | Q94: =RAND() -> 0.10153777 | R94: =RAND() -> 0.97554603 | S94: =RAND() -> 0.79867715 | T94: =RAND() -> 0.80784558 | U94: =RAND() -> 0.4078219
A95: 15 | B95: =1+IF($G$6=$E$6,$F$6,IF(P95<($F$6-$E$6)/($G$6-$E$6),$E$6+SQRT(P95*($G$6-$E$6)*($F$6-$E$6)),$G$6-SQRT((1-P95)*($G$6-$E$6)*($G$6-$F$6)))) -> 0.95259267 | C95: =1+IF($G$7=$E$7,$F$7,IF(Q95<($F$7-$E$7)/($G$7-$E$7),$E$7+SQRT(Q95*($G$7-$E$7)*($F$7-$E$7)),$G$7-SQRT((1-Q95)*($G$7-$E$7)*($G$7-$F$7)))) -> 1.0354647 | D95: =1+IF($G$8=$E$8,$F$8,IF(R95<($F$8-$E$8)/($G$8-$E$8),$E$8+SQRT(R95*($G$8-$E$8)*($F$8-$E$8)),$G$8-SQRT((1-R95)*($G$8-$E$8)*($G$8-$F$8)))) -> 0.98763977 | E95: =1+IF($G$9=$E$9,$F$9,IF(S95<($F$9-$E$9)/($G$9-$E$9),$E$9+SQRT(S95*($G$9-$E$9)*($F$9-$E$9)),$G$9-SQRT((1-S95)*($G$9-$E$9)*($G$9-$F$9)))) -> 1.007333 | F95: =1+IF($G$10=$E$10,$F$10,IF(T95<($F$10-$E$10)/($G$10-$E$10),$E$10+SQRT(T95*($G$10-$E$10)*($F$10-$E$10)),$G$10-SQRT((1-T95)*($G$10-$E$10)*($G$10-$F$10)))) -> 0.99594307 | G95: =IF($G$11=$E$11,$F$11,IF(U95<($F$11-$E$11)/($G$11-$E$11),$E$11+SQRT(U95*($G$11-$E$11)*($F$11-$E$11)),$G$11-SQRT((1-U95)*($G$11-$E$11)*($G$11-$F$11)))) -> 0.10653745 | H95: =(('Business Case'!B11*$C95*'Business Case'!B12*$B95)-'Business Case'!B11*$C95*'Business Case'!B13*$D95-'Business Case'!B14*$E95)-MAX(0,(('Business Case'!B11*$C95*'Business Case'!B12*$B95)-'Business Case'!B11*$C95*'Business Case'!B13*$D95-'Business Case'!B14*$E95))*'Business Case'!$B$7-'Business Case'!$B$8*('Business Case'!B11*$C95*'Business Case'!B12*$B95)-'Business Case'!B15*$F95 -> -1.9918861e+09 | I95: =(('Business Case'!C11*$C95*'Business Case'!C12*$B95)-'Business Case'!C11*$C95*'Business Case'!C13*$D95-'Business Case'!C14*$E95)-MAX(0,(('Business Case'!C11*$C95*'Business Case'!C12*$B95)-'Business Case'!C11*$C95*'Business Case'!C13*$D95-'Business Case'!C14*$E95))*'Business Case'!$B$7-'Business Case'!$B$8*(('Business Case'!C11*$C95*'Business Case'!C12*$B95)-('Business Case'!B11*$C95*'Business Case'!B12*$B95))-'Business Case'!C15*$F95 -> -9580999.6 | J95: =(('Business Case'!D11*$C95*'Business Case'!D12*$B95)-'Business Case'!D11*$C95*'Business Case'!D13*$D95-'Business Case'!D14*$E95)-MAX(0,(('Business Case'!D11*$C95*'Business Case'!D12*$B95)-'Business Case'!D11*$C95*'Business Case'!D13*$D95-'Business Case'!D14*$E95))*'Business Case'!$B$7-'Business Case'!$B$8*(('Business Case'!D11*$C95*'Business Case'!D12*$B95)-('Business Case'!C11*$C95*'Business Case'!C12*$B95))-'Business Case'!D15*$F95 -> 2.7480879e+08 | K95: =(('Business Case'!E11*$C95*'Business Case'!E12*$B95)-'Business Case'!E11*$C95*'Business Case'!E13*$D95-'Business Case'!E14*$E95)-MAX(0,(('Business Case'!E11*$C95*'Business Case'!E12*$B95)-'Business Case'!E11*$C95*'Business Case'!E13*$D95-'Business Case'!E14*$E95))*'Business Case'!$B$7-'Business Case'!$B$8*(('Business Case'!E11*$C95*'Business Case'!E12*$B95)-('Business Case'!D11*$C95*'Business Case'!D12*$B95))-'Business Case'!E15*$F95 -> 6.0899573e+08 | L95: =(('Business Case'!F11*$C95*'Business Case'!F12*$B95)-'Business Case'!F11*$C95*'Business Case'!F13*$D95-'Business Case'!F14*$E95)-MAX(0,(('Business Case'!F11*$C95*'Business Case'!F12*$B95)-'Business Case'!F11*$C95*'Business Case'!F13*$D95-'Business Case'!F14*$E95))*'Business Case'!$B$7-'Business Case'!$B$8*(('Business Case'!F11*$C95*'Business Case'!F12*$B95)-('Business Case'!E11*$C95*'Business Case'!E12*$B95))-'Business Case'!F15*$F95 -> 7.3788149e+08 | M95: =(('Business Case'!G11*$C95*'Business Case'!G12*$B95)-'Business Case'!G11*$C95*'Business Case'!G13*$D95-'Business Case'!G14*$E95)-MAX(0,(('Business Case'!G11*$C95*'Business Case'!G12*$B95)-'Business Case'!G11*$C95*'Business Case'!G13*$D95-'Business Case'!G14*$E95))*'Business Case'!$B$7-'Business Case'!$B$8*(('Business Case'!G11*$C95*'Business Case'!G12*$B95)-('Business Case'!F11*$C95*'Business Case'!F12*$B95))-'Business Case'!G15*$F95+'Business Case'!$B$8*('Business Case'!G11*$C95*'Business Case'!G12*$B95) -> 9.2537185e+08 | N95: =IF(COUNT('Business Case'!B11:G11)=0,"",H95+NPV(G95,I95:M95)) -> -2.7663277e+08 | P95: =RAND() -> 0.11065437 | Q95: =RAND() -> 0.75012698 | R95: =RAND() -> 0.21796193 | S95: =RAND() -> 0.42752121 | T95: =RAND() -> 0.16886127 | U95: =RAND() -> 0.69793306
A96: 16 | B96: =1+IF($G$6=$E$6,$F$6,IF(P96<($F$6-$E$6)/($G$6-$E$6),$E$6+SQRT(P96*($G$6-$E$6)*($F$6-$E$6)),$G$6-SQRT((1-P96)*($G$6-$E$6)*($G$6-$F$6)))) -> 0.97087488 | C96: =1+IF($G$7=$E$7,$F$7,IF(Q96<($F$7-$E$7)/($G$7-$E$7),$E$7+SQRT(Q96*($G$7-$E$7)*($F$7-$E$7)),$G$7-SQRT((1-Q96)*($G$7-$E$7)*($G$7-$F$7)))) -> 0.90814534 | D96: =1+IF($G$8=$E$8,$F$8,IF(R96<($F$8-$E$8)/($G$8-$E$8),$E$8+SQRT(R96*($G$8-$E$8)*($F$8-$E$8)),$G$8-SQRT((1-R96)*($G$8-$E$8)*($G$8-$F$8)))) -> 1.0095828 | E96: =1+IF($G$9=$E$9,$F$9,IF(S96<($F$9-$E$9)/($G$9-$E$9),$E$9+SQRT(S96*($G$9-$E$9)*($F$9-$E$9)),$G$9-SQRT((1-S96)*($G$9-$E$9)*($G$9-$F$9)))) -> 1.0256852 | F96: =1+IF($G$10=$E$10,$F$10,IF(T96<($F$10-$E$10)/($G$10-$E$10),$E$10+SQRT(T96*($G$10-$E$10)*($F$10-$E$10)),$G$10-SQRT((1-T96)*($G$10-$E$10)*($G$10-$F$10)))) -> 1.1618743 | G96: =IF($G$11=$E$11,$F$11,IF(U96<($F$11-$E$11)/($G$11-$E$11),$E$11+SQRT(U96*($G$11-$E$11)*($F$11-$E$11)),$G$11-SQRT((1-U96)*($G$11-$E$11)*($G$11-$F$11)))) -> 0.097408962 | H96: =(('Business Case'!B11*$C96*'Business Case'!B12*$B96)-'Business Case'!B11*$C96*'Business Case'!B13*$D96-'Business Case'!B14*$E96)-MAX(0,(('Business Case'!B11*$C96*'Business Case'!B12*$B96)-'Business Case'!B11*$C96*'Business Case'!B13*$D96-'Business Case'!B14*$E96))*'Business Case'!$B$7-'Business Case'!$B$8*('Business Case'!B11*$C96*'Business Case'!B12*$B96)-'Business Case'!B15*$F96 -> -2.3237486e+09 | I96: =(('Business Case'!C11*$C96*'Business Case'!C12*$B96)-'Business Case'!C11*$C96*'Business Case'!C13*$D96-'Business Case'!C14*$E96)-MAX(0,(('Business Case'!C11*$C96*'Business Case'!C12*$B96)-'Business Case'!C11*$C96*'Business Case'!C13*$D96-'Business Case'!C14*$E96))*'Business Case'!$B$7-'Business Case'!$B$8*(('Business Case'!C11*$C96*'Business Case'!C12*$B96)-('Business Case'!B11*$C96*'Business Case'!B12*$B96))-'Business Case'!C15*$F96 -> -54927633 | J96: =(('Business Case'!D11*$C96*'Business Case'!D12*$B96)-'Business Case'!D11*$C96*'Business Case'!D13*$D96-'Business Case'!D14*$E96)-MAX(0,(('Business Case'!D11*$C96*'Business Case'!D12*$B96)-'Business Case'!D11*$C96*'Business Case'!D13*$D96-'Business Case'!D14*$E96))*'Business Case'!$B$7-'Business Case'!$B$8*(('Business Case'!D11*$C96*'Business Case'!D12*$B96)-('Business Case'!C11*$C96*'Business Case'!C12*$B96))-'Business Case'!D15*$F96 -> 1.9789169e+08 | K96: =(('Business Case'!E11*$C96*'Business Case'!E12*$B96)-'Business Case'!E11*$C96*'Business Case'!E13*$D96-'Business Case'!E14*$E96)-MAX(0,(('Business Case'!E11*$C96*'Business Case'!E12*$B96)-'Business Case'!E11*$C96*'Business Case'!E13*$D96-'Business Case'!E14*$E96))*'Business Case'!$B$7-'Business Case'!$B$8*(('Business Case'!E11*$C96*'Business Case'!E12*$B96)-('Business Case'!D11*$C96*'Business Case'!D12*$B96))-'Business Case'!E15*$F96 -> 5.0880472e+08 | L96: =(('Business Case'!F11*$C96*'Business Case'!F12*$B96)-'Business Case'!F11*$C96*'Business Case'!F13*$D96-'Business Case'!F14*$E96)-MAX(0,(('Business Case'!F11*$C96*'Business Case'!F12*$B96)-'Business Case'!F11*$C96*'Business Case'!F13*$D96-'Business Case'!F14*$E96))*'Business Case'!$B$7-'Business Case'!$B$8*(('Business Case'!F11*$C96*'Business Case'!F12*$B96)-('Business Case'!E11*$C96*'Business Case'!E12*$B96))-'Business Case'!F15*$F96 -> 6.2354922e+08 | M96: =(('Business Case'!G11*$C96*'Business Case'!G12*$B96)-'Business Case'!G11*$C96*'Business Case'!G13*$D96-'Business Case'!G14*$E96)-MAX(0,(('Business Case'!G11*$C96*'Business Case'!G12*$B96)-'Business Case'!G11*$C96*'Business Case'!G13*$D96-'Business Case'!G14*$E96))*'Business Case'!$B$7-'Business Case'!$B$8*(('Business Case'!G11*$C96*'Business Case'!G12*$B96)-('Business Case'!F11*$C96*'Business Case'!F12*$B96))-'Business Case'!G15*$F96+'Business Case'!$B$8*('Business Case'!G11*$C96*'Business Case'!G12*$B96) -> 7.911419e+08 | N96: =IF(COUNT('Business Case'!B11:G11)=0,"",H96+NPV(G96,I96:M96)) -> -8.9750152e+08 | P96: =RAND() -> 0.26960974 | Q96: =RAND() -> 0.16707734 | R96: =RAND() -> 0.52321299 | S96: =RAND() -> 0.63182029 | T96: =RAND() -> 0.97092859 | U96: =RAND() -> 0.18297574
A97: 17 | B97: =1+IF($G$6=$E$6,$F$6,IF(P97<($F$6-$E$6)/($G$6-$E$6),$E$6+SQRT(P97*($G$6-$E$6)*($F$6-$E$6)),$G$6-SQRT((1-P97)*($G$6-$E$6)*($G$6-$F$6)))) -> 0.98939824 | C97: =1+IF($G$7=$E$7,$F$7,IF(Q97<($F$7-$E$7)/($G$7-$E$7),$E$7+SQRT(Q97*($G$7-$E$7)*($F$7-$E$7)),$G$7-SQRT((1-Q97)*($G$7-$E$7)*($G$7-$F$7)))) -> 0.95351572 | D97: =1+IF($G$8=$E$8,$F$8,IF(R97<($F$8-$E$8)/($G$8-$E$8),$E$8+SQRT(R97*($G$8-$E$8)*($F$8-$E$8)),$G$8-SQRT((1-R97)*($G$8-$E$8)*($G$8-$F$8)))) -> 1.0160636 | E97: =1+IF($G$9=$E$9,$F$9,IF(S97<($F$9-$E$9)/($G$9-$E$9),$E$9+SQRT(S97*($G$9-$E$9)*($F$9-$E$9)),$G$9-SQRT((1-S97)*($G$9-$E$9)*($G$9-$F$9)))) -> 1.0347518 | F97: =1+IF($G$10=$E$10,$F$10,IF(T97<($F$10-$E$10)/($G$10-$E$10),$E$10+SQRT(T97*($G$10-$E$10)*($F$10-$E$10)),$G$10-SQRT((1-T97)*($G$10-$E$10)*($G$10-$F$10)))) -> 1.0956696 | G97: =IF($G$11=$E$11,$F$11,IF(U97<($F$11-$E$11)/($G$11-$E$11),$E$11+SQRT(U97*($G$11-$E$11)*($F$11-$E$11)),$G$11-SQRT((1-U97)*($G$11-$E$11)*($G$11-$F$11)))) -> 0.1064988 | H97: =(('Business Case'!B11*$C97*'Business Case'!B12*$B97)-'Business Case'!B11*$C97*'Business Case'!B13*$D97-'Business Case'!B14*$E97)-MAX(0,(('Business Case'!B11*$C97*'Business Case'!B12*$B97)-'Business Case'!B11*$C97*'Business Case'!B13*$D97-'Business Case'!B14*$E97))*'Business Case'!$B$7-'Business Case'!$B$8*('Business Case'!B11*$C97*'Business Case'!B12*$B97)-'Business Case'!B15*$F97 -> -2.1913393e+09 | I97: =(('Business Case'!C11*$C97*'Business Case'!C12*$B97)-'Business Case'!C11*$C97*'Business Case'!C13*$D97-'Business Case'!C14*$E97)-MAX(0,(('Business Case'!C11*$C97*'Business Case'!C12*$B97)-'Business Case'!C11*$C97*'Business Case'!C13*$D97-'Business Case'!C14*$E97))*'Business Case'!$B$7-'Business Case'!$B$8*(('Business Case'!C11*$C97*'Business Case'!C12*$B97)-('Business Case'!B11*$C97*'Business Case'!B12*$B97))-'Business Case'!C15*$F97 -> -28861605 | J97: =(('Business Case'!D11*$C97*'Business Case'!D12*$B97)-'Business Case'!D11*$C97*'Business Case'!D13*$D97-'Business Case'!D14*$E97)-MAX(0,(('Business Case'!D11*$C97*'Business Case'!D12*$B97)-'Business Case'!D11*$C97*'Business Case'!D13*$D97-'Business Case'!D14*$E97))*'Business Case'!$B$7-'Business Case'!$B$8*(('Business Case'!D11*$C97*'Business Case'!D12*$B97)-('Business Case'!C11*$C97*'Business Case'!C12*$B97))-'Business Case'!D15*$F97 -> 2.4789166e+08 | K97: =(('Business Case'!E11*$C97*'Business Case'!E12*$B97)-'Business Case'!E11*$C97*'Business Case'!E13*$D97-'Business Case'!E14*$E97)-MAX(0,(('Business Case'!E11*$C97*'Business Case'!E12*$B97)-'Business Case'!E11*$C97*'Business Case'!E13*$D97-'Business Case'!E14*$E97))*'Business Case'!$B$7-'Business Case'!$B$8*(('Business Case'!E11*$C97*'Business Case'!E12*$B97)-('Business Case'!D11*$C97*'Business Case'!D12*$B97))-'Business Case'!E15*$F97 -> 5.7942841e+08 | L97: =(('Business Case'!F11*$C97*'Business Case'!F12*$B97)-'Business Case'!F11*$C97*'Business Case'!F13*$D97-'Business Case'!F14*$E97)-MAX(0,(('Business Case'!F11*$C97*'Business Case'!F12*$B97)-'Business Case'!F11*$C97*'Business Case'!F13*$D97-'Business Case'!F14*$E97))*'Business Case'!$B$7-'Business Case'!$B$8*(('Business Case'!F11*$C97*'Business Case'!F12*$B97)-('Business Case'!E11*$C97*'Business Case'!E12*$B97))-'Business Case'!F15*$F97 -> 7.0428364e+08 | M97: =(('Business Case'!G11*$C97*'Business Case'!G12*$B97)-'Business Case'!G11*$C97*'Business Case'!G13*$D97-'Business Case'!G14*$E97)-MAX(0,(('Business Case'!G11*$C97*'Business Case'!G12*$B97)-'Business Case'!G11*$C97*'Business Case'!G13*$D97-'Business Case'!G14*$E97))*'Business Case'!$B$7-'Business Case'!$B$8*(('Business Case'!G11*$C97*'Business Case'!G12*$B97)-('Business Case'!F11*$C97*'Business Case'!F12*$B97))-'Business Case'!G15*$F97+'Business Case'!$B$8*('Business Case'!G11*$C97*'Business Case'!G12*$B97) -> 8.836064e+08 | N97: =IF(COUNT('Business Case'!B11:G11)=0,"",H97+NPV(G97,I97:M97)) -> -5.8468613e+08 | P97: =RAND() -> 0.50167875 | Q97: =RAND() -> 0.33667254 | R97: =RAND() -> 0.60693669 | S97: =RAND() -> 0.71617776 | T97: =RAND() -> 0.78230354 | U97: =RAND() -> 0.69619578
A98: 18 | B98: =1+IF($G$6=$E$6,$F$6,IF(P98<($F$6-$E$6)/($G$6-$E$6),$E$6+SQRT(P98*($G$6-$E$6)*($F$6-$E$6)),$G$6-SQRT((1-P98)*($G$6-$E$6)*($G$6-$F$6)))) -> 1.0240896 | C98: =1+IF($G$7=$E$7,$F$7,IF(Q98<($F$7-$E$7)/($G$7-$E$7),$E$7+SQRT(Q98*($G$7-$E$7)*($F$7-$E$7)),$G$7-SQRT((1-Q98)*($G$7-$E$7)*($G$7-$F$7)))) -> 0.91314103 | D98: =1+IF($G$8=$E$8,$F$8,IF(R98<($F$8-$E$8)/($G$8-$E$8),$E$8+SQRT(R98*($G$8-$E$8)*($F$8-$E$8)),$G$8-SQRT((1-R98)*($G$8-$E$8)*($G$8-$F$8)))) -> 0.97158839 | E98: =1+IF($G$9=$E$9,$F$9,IF(S98<($F$9-$E$9)/($G$9-$E$9),$E$9+SQRT(S98*($G$9-$E$9)*($F$9-$E$9)),$G$9-SQRT((1-S98)*($G$9-$E$9)*($G$9-$F$9)))) -> 1.0656751 | F98: =1+IF($G$10=$E$10,$F$10,IF(T98<($F$10-$E$10)/($G$10-$E$10),$E$10+SQRT(T98*($G$10-$E$10)*($F$10-$E$10)),$G$10-SQRT((1-T98)*($G$10-$E$10)*($G$10-$F$10)))) -> 0.98643 | G98: =IF($G$11=$E$11,$F$11,IF(U98<($F$11-$E$11)/($G$11-$E$11),$E$11+SQRT(U98*($G$11-$E$11)*($F$11-$E$11)),$G$11-SQRT((1-U98)*($G$11-$E$11)*($G$11-$F$11)))) -> 0.1089874 | H98: =(('Business Case'!B11*$C98*'Business Case'!B12*$B98)-'Business Case'!B11*$C98*'Business Case'!B13*$D98-'Business Case'!B14*$E98)-MAX(0,(('Business Case'!B11*$C98*'Business Case'!B12*$B98)-'Business Case'!B11*$C98*'Business Case'!B13*$D98-'Business Case'!B14*$E98))*'Business Case'!$B$7-'Business Case'!$B$8*('Business Case'!B11*$C98*'Business Case'!B12*$B98)-'Business Case'!B15*$F98 -> -1.97286e+09 | I98: =(('Business Case'!C11*$C98*'Business Case'!C12*$B98)-'Business Case'!C11*$C98*'Business Case'!C13*$D98-'Business Case'!C14*$E98)-MAX(0,(('Business Case'!C11*$C98*'Business Case'!C12*$B98)-'Business Case'!C11*$C98*'Business Case'!C13*$D98-'Business Case'!C14*$E98))*'Business Case'!$B$7-'Business Case'!$B$8*(('Business Case'!C11*$C98*'Business Case'!C12*$B98)-('Business Case'!B11*$C98*'Business Case'!B12*$B98))-'Business Case'!C15*$F98 -> 13111950 | J98: =(('Business Case'!D11*$C98*'Business Case'!D12*$B98)-'Business Case'!D11*$C98*'Business Case'!D13*$D98-'Business Case'!D14*$E98)-MAX(0,(('Business Case'!D11*$C98*'Business Case'!D12*$B98)-'Business Case'!D11*$C98*'Business Case'!D13*$D98-'Business Case'!D14*$E98))*'Business Case'!$B$7-'Business Case'!$B$8*(('Business Case'!D11*$C98*'Business Case'!D12*$B98)-('Business Case'!C11*$C98*'Business Case'!C12*$B98))-'Business Case'!D15*$F98 -> 3.2488346e+08 | K98: =(('Business Case'!E11*$C98*'Business Case'!E12*$B98)-'Business Case'!E11*$C98*'Business Case'!E13*$D98-'Business Case'!E14*$E98)-MAX(0,(('Business Case'!E11*$C98*'Business Case'!E12*$B98)-'Business Case'!E11*$C98*'Business Case'!E13*$D98-'Business Case'!E14*$E98))*'Business Case'!$B$7-'Business Case'!$B$8*(('Business Case'!E11*$C98*'Business Case'!E12*$B98)-('Business Case'!D11*$C98*'Business Case'!D12*$B98))-'Business Case'!E15*$F98 -> 6.8597648e+08 | L98: =(('Business Case'!F11*$C98*'Business Case'!F12*$B98)-'Business Case'!F11*$C98*'Business Case'!F13*$D98-'Business Case'!F14*$E98)-MAX(0,(('Business Case'!F11*$C98*'Business Case'!F12*$B98)-'Business Case'!F11*$C98*'Business Case'!F13*$D98-'Business Case'!F14*$E98))*'Business Case'!$B$7-'Business Case'!$B$8*(('Business Case'!F11*$C98*'Business Case'!F12*$B98)-('Business Case'!E11*$C98*'Business Case'!E12*$B98))-'Business Case'!F15*$F98 -> 8.2221869e+08 | M98: =(('Business Case'!G11*$C98*'Business Case'!G12*$B98)-'Business Case'!G11*$C98*'Business Case'!G13*$D98-'Business Case'!G14*$E98)-MAX(0,(('Business Case'!G11*$C98*'Business Case'!G12*$B98)-'Business Case'!G11*$C98*'Business Case'!G13*$D98-'Business Case'!G14*$E98))*'Business Case'!$B$7-'Business Case'!$B$8*(('Business Case'!G11*$C98*'Business Case'!G12*$B98)-('Business Case'!F11*$C98*'Business Case'!F12*$B98))-'Business Case'!G15*$F98+'Business Case'!$B$8*('Business Case'!G11*$C98*'Business Case'!G12*$B98) -> 9.9996976e+08 | N98: =IF(COUNT('Business Case'!B11:G11)=0,"",H98+NPV(G98,I98:M98)) -> -54167473 | P98: =RAND() -> 0.9472621 | Q98: =RAND() -> 0.18286989 | R98: =RAND() -> 0.071701296 | S98: =RAND() -> 0.92145347 | T98: =RAND() -> 0.10617156 | U98: =RAND() -> 0.79787119
A99: 19 | B99: =1+IF($G$6=$E$6,$F$6,IF(P99<($F$6-$E$6)/($G$6-$E$6),$E$6+SQRT(P99*($G$6-$E$6)*($F$6-$E$6)),$G$6-SQRT((1-P99)*($G$6-$E$6)*($G$6-$F$6)))) -> 0.97428048 | C99: =1+IF($G$7=$E$7,$F$7,IF(Q99<($F$7-$E$7)/($G$7-$E$7),$E$7+SQRT(Q99*($G$7-$E$7)*($F$7-$E$7)),$G$7-SQRT((1-Q99)*($G$7-$E$7)*($G$7-$F$7)))) -> 0.949513 | D99: =1+IF($G$8=$E$8,$F$8,IF(R99<($F$8-$E$8)/($G$8-$E$8),$E$8+SQRT(R99*($G$8-$E$8)*($F$8-$E$8)),$G$8-SQRT((1-R99)*($G$8-$E$8)*($G$8-$F$8)))) -> 1.0120805 | E99: =1+IF($G$9=$E$9,$F$9,IF(S99<($F$9-$E$9)/($G$9-$E$9),$E$9+SQRT(S99*($G$9-$E$9)*($F$9-$E$9)),$G$9-SQRT((1-S99)*($G$9-$E$9)*($G$9-$F$9)))) -> 1.0506698 | F99: =1+IF($G$10=$E$10,$F$10,IF(T99<($F$10-$E$10)/($G$10-$E$10),$E$10+SQRT(T99*($G$10-$E$10)*($F$10-$E$10)),$G$10-SQRT((1-T99)*($G$10-$E$10)*($G$10-$F$10)))) -> 1.0487235 | G99: =IF($G$11=$E$11,$F$11,IF(U99<($F$11-$E$11)/($G$11-$E$11),$E$11+SQRT(U99*($G$11-$E$11)*($F$11-$E$11)),$G$11-SQRT((1-U99)*($G$11-$E$11)*($G$11-$F$11)))) -> 0.10118254 | H99: =(('Business Case'!B11*$C99*'Business Case'!B12*$B99)-'Business Case'!B11*$C99*'Business Case'!B13*$D99-'Business Case'!B14*$E99)-MAX(0,(('Business Case'!B11*$C99*'Business Case'!B12*$B99)-'Business Case'!B11*$C99*'Business Case'!B13*$D99-'Business Case'!B14*$E99))*'Business Case'!$B$7-'Business Case'!$B$8*('Business Case'!B11*$C99*'Business Case'!B12*$B99)-'Business Case'!B15*$F99 -> -2.0974471e+09 | I99: =(('Business Case'!C11*$C99*'Business Case'!C12*$B99)-'Business Case'!C11*$C99*'Business Case'!C13*$D99-'Business Case'!C14*$E99)-MAX(0,(('Business Case'!C11*$C99*'Business Case'!C12*$B99)-'Business Case'!C11*$C99*'Business Case'!C13*$D99-'Business Case'!C14*$E99))*'Business Case'!$B$7-'Business Case'!$B$8*(('Business Case'!C11*$C99*'Business Case'!C12*$B99)-('Business Case'!B11*$C99*'Business Case'!B12*$B99))-'Business Case'!C15*$F99 -> -36464163 | J99: =(('Business Case'!D11*$C99*'Business Case'!D12*$B99)-'Business Case'!D11*$C99*'Business Case'!D13*$D99-'Business Case'!D14*$E99)-MAX(0,(('Business Case'!D11*$C99*'Business Case'!D12*$B99)-'Business Case'!D11*$C99*'Business Case'!D13*$D99-'Business Case'!D14*$E99))*'Business Case'!$B$7-'Business Case'!$B$8*(('Business Case'!D11*$C99*'Business Case'!D12*$B99)-('Business Case'!C11*$C99*'Business Case'!C12*$B99))-'Business Case'!D15*$F99 -> 2.2930604e+08 | K99: =(('Business Case'!E11*$C99*'Business Case'!E12*$B99)-'Business Case'!E11*$C99*'Business Case'!E13*$D99-'Business Case'!E14*$E99)-MAX(0,(('Business Case'!E11*$C99*'Business Case'!E12*$B99)-'Business Case'!E11*$C99*'Business Case'!E13*$D99-'Business Case'!E14*$E99))*'Business Case'!$B$7-'Business Case'!$B$8*(('Business Case'!E11*$C99*'Business Case'!E12*$B99)-('Business Case'!D11*$C99*'Business Case'!D12*$B99))-'Business Case'!E15*$F99 -> 5.4751241e+08 | L99: =(('Business Case'!F11*$C99*'Business Case'!F12*$B99)-'Business Case'!F11*$C99*'Business Case'!F13*$D99-'Business Case'!F14*$E99)-MAX(0,(('Business Case'!F11*$C99*'Business Case'!F12*$B99)-'Business Case'!F11*$C99*'Business Case'!F13*$D99-'Business Case'!F14*$E99))*'Business Case'!$B$7-'Business Case'!$B$8*(('Business Case'!F11*$C99*'Business Case'!F12*$B99)-('Business Case'!E11*$C99*'Business Case'!E12*$B99))-'Business Case'!F15*$F99 -> 6.6807366e+08 | M99: =(('Business Case'!G11*$C99*'Business Case'!G12*$B99)-'Business Case'!G11*$C99*'Business Case'!G13*$D99-'Business Case'!G14*$E99)-MAX(0,(('Business Case'!G11*$C99*'Business Case'!G12*$B99)-'Business Case'!G11*$C99*'Business Case'!G13*$D99-'Business Case'!G14*$E99))*'Business Case'!$B$7-'Business Case'!$B$8*(('Business Case'!G11*$C99*'Business Case'!G12*$B99)-('Business Case'!F11*$C99*'Business Case'!F12*$B99))-'Business Case'!G15*$F99+'Business Case'!$B$8*('Business Case'!G11*$C99*'Business Case'!G12*$B99) -> 8.4391514e+08 | N99: =IF(COUNT('Business Case'!B11:G11)=0,"",H99+NPV(G99,I99:M99)) -> -5.5588431e+08 | P99: =RAND() -> 0.30691355 | Q99: =RAND() -> 0.3193448 | R99: =RAND() -> 0.55643714 | S99: =RAND() -> 0.83776847 | T99: =RAND() -> 0.54230862 | U99: =RAND() -> 0.40983882
A100: 20 | B100: =1+IF($G$6=$E$6,$F$6,IF(P100<($F$6-$E$6)/($G$6-$E$6),$E$6+SQRT(P100*($G$6-$E$6)*($F$6-$E$6)),$G$6-SQRT((1-P100)*($G$6-$E$6)*($G$6-$F$6)))) -> 1.0019808 | C100: =1+IF($G$7=$E$7,$F$7,IF(Q100<($F$7-$E$7)/($G$7-$E$7),$E$7+SQRT(Q100*($G$7-$E$7)*($F$7-$E$7)),$G$7-SQRT((1-Q100)*($G$7-$E$7)*($G$7-$F$7)))) -> 0.9612904 | D100: =1+IF($G$8=$E$8,$F$8,IF(R100<($F$8-$E$8)/($G$8-$E$8),$E$8+SQRT(R100*($G$8-$E$8)*($F$8-$E$8)),$G$8-SQRT((1-R100)*($G$8-$E$8)*($G$8-$F$8)))) -> 1.0488718 | E100: =1+IF($G$9=$E$9,$F$9,IF(S100<($F$9-$E$9)/($G$9-$E$9),$E$9+SQRT(S100*($G$9-$E$9)*($F$9-$E$9)),$G$9-SQRT((1-S100)*($G$9-$E$9)*($G$9-$F$9)))) -> 1.0286424 | F100: =1+IF($G$10=$E$10,$F$10,IF(T100<($F$10-$E$10)/($G$10-$E$10),$E$10+SQRT(T100*($G$10-$E$10)*($F$10-$E$10)),$G$10-SQRT((1-T100)*($G$10-$E$10)*($G$10-$F$10)))) -> 0.99870225 | G100: =IF($G$11=$E$11,$F$11,IF(U100<($F$11-$E$11)/($G$11-$E$11),$E$11+SQRT(U100*($G$11-$E$11)*($F$11-$E$11)),$G$11-SQRT((1-U100)*($G$11-$E$11)*($G$11-$F$11)))) -> 0.097773455 | H100: =(('Business Case'!B11*$C100*'Business Case'!B12*$B100)-'Business Case'!B11*$C100*'Business Case'!B13*$D100-'Business Case'!B14*$E100)-MAX(0,(('Business Case'!B11*$C100*'Business Case'!B12*$B100)-'Business Case'!B11*$C100*'Business Case'!B13*$D100-'Business Case'!B14*$E100))*'Business Case'!$B$7-'Business Case'!$B$8*('Business Case'!B11*$C100*'Business Case'!B12*$B100)-'Business Case'!B15*$F100 -> -1.9974045e+09 | I100: =(('Business Case'!C11*$C100*'Business Case'!C12*$B100)-'Business Case'!C11*$C100*'Business Case'!C13*$D100-'Business Case'!C14*$E100)-MAX(0,(('Business Case'!C11*$C100*'Business Case'!C12*$B100)-'Business Case'!C11*$C100*'Business Case'!C13*$D100-'Business Case'!C14*$E100))*'Business Case'!$B$7-'Business Case'!$B$8*(('Business Case'!C11*$C100*'Business Case'!C12*$B100)-('Business Case'!B11*$C100*'Business Case'!B12*$B100))-'Business Case'!C15*$F100 -> -23303326 | J100: =(('Business Case'!D11*$C100*'Business Case'!D12*$B100)-'Business Case'!D11*$C100*'Business Case'!D13*$D100-'Business Case'!D14*$E100)-MAX(0,(('Business Case'!D11*$C100*'Business Case'!D12*$B100)-'Business Case'!D11*$C100*'Business Case'!D13*$D100-'Business Case'!D14*$E100))*'Business Case'!$B$7-'Business Case'!$B$8*(('Business Case'!D11*$C100*'Business Case'!D12*$B100)-('Business Case'!C11*$C100*'Business Case'!C12*$B100))-'Business Case'!D15*$F100 -> 2.4946852e+08 | K100: =(('Business Case'!E11*$C100*'Business Case'!E12*$B100)-'Business Case'!E11*$C100*'Business Case'!E13*$D100-'Business Case'!E14*$E100)-MAX(0,(('Business Case'!E11*$C100*'Business Case'!E12*$B100)-'Business Case'!E11*$C100*'Business Case'!E13*$D100-'Business Case'!E14*$E100))*'Business Case'!$B$7-'Business Case'!$B$8*(('Business Case'!E11*$C100*'Business Case'!E12*$B100)-('Business Case'!D11*$C100*'Business Case'!D12*$B100))-'Business Case'!E15*$F100 -> 5.7217548e+08 | L100: =(('Business Case'!F11*$C100*'Business Case'!F12*$B100)-'Business Case'!F11*$C100*'Business Case'!F13*$D100-'Business Case'!F14*$E100)-MAX(0,(('Business Case'!F11*$C100*'Business Case'!F12*$B100)-'Business Case'!F11*$C100*'Business Case'!F13*$D100-'Business Case'!F14*$E100))*'Business Case'!$B$7-'Business Case'!$B$8*(('Business Case'!F11*$C100*'Business Case'!F12*$B100)-('Business Case'!E11*$C100*'Business Case'!E12*$B100))-'Business Case'!F15*$F100 -> 6.9638743e+08 | M100: =(('Business Case'!G11*$C100*'Business Case'!G12*$B100)-'Business Case'!G11*$C100*'Business Case'!G13*$D100-'Business Case'!G14*$E100)-MAX(0,(('Business Case'!G11*$C100*'Business Case'!G12*$B100)-'Business Case'!G11*$C100*'Business Case'!G13*$D100-'Business Case'!G14*$E100))*'Business Case'!$B$7-'Business Case'!$B$8*(('Business Case'!G11*$C100*'Business Case'!G12*$B100)-('Business Case'!F11*$C100*'Business Case'!F12*$B100))-'Business Case'!G15*$F100+'Business Case'!$B$8*('Business Case'!G11*$C100*'Business Case'!G12*$B100) -> 8.7947144e+08 | N100: =IF(COUNT('Business Case'!B11:G11)=0,"",H100+NPV(G100,I100:M100)) -> -3.4796224e+08 | P100: =RAND() -> 0.69886199 | Q100: =RAND() -> 0.37163704 | R100: =RAND() -> 0.9068304 | S100: =RAND() -> 0.6605394 | T100: =RAND() -> 0.1897527 | U100: =RAND() -> 0.201422
A101: 21 | B101: =1+IF($G$6=$E$6,$F$6,IF(P101<($F$6-$E$6)/($G$6-$E$6),$E$6+SQRT(P101*($G$6-$E$6)*($F$6-$E$6)),$G$6-SQRT((1-P101)*($G$6-$E$6)*($G$6-$F$6)))) -> 0.9748575 | C101: =1+IF($G$7=$E$7,$F$7,IF(Q101<($F$7-$E$7)/($G$7-$E$7),$E$7+SQRT(Q101*($G$7-$E$7)*($F$7-$E$7)),$G$7-SQRT((1-Q101)*($G$7-$E$7)*($G$7-$F$7)))) -> 0.91620994 | D101: =1+IF($G$8=$E$8,$F$8,IF(R101<($F$8-$E$8)/($G$8-$E$8),$E$8+SQRT(R101*($G$8-$E$8)*($F$8-$E$8)),$G$8-SQRT((1-R101)*($G$8-$E$8)*($G$8-$F$8)))) -> 1.0085143 | E101: =1+IF($G$9=$E$9,$F$9,IF(S101<($F$9-$E$9)/($G$9-$E$9),$E$9+SQRT(S101*($G$9-$E$9)*($F$9-$E$9)),$G$9-SQRT((1-S101)*($G$9-$E$9)*($G$9-$F$9)))) -> 1.0520741 | F101: =1+IF($G$10=$E$10,$F$10,IF(T101<($F$10-$E$10)/($G$10-$E$10),$E$10+SQRT(T101*($G$10-$E$10)*($F$10-$E$10)),$G$10-SQRT((1-T101)*($G$10-$E$10)*($G$10-$F$10)))) -> 1.0295244 | G101: =IF($G$11=$E$11,$F$11,IF(U101<($F$11-$E$11)/($G$11-$E$11),$E$11+SQRT(U101*($G$11-$E$11)*($F$11-$E$11)),$G$11-SQRT((1-U101)*($G$11-$E$11)*($G$11-$F$11)))) -> 0.09771337 | H101: =(('Business Case'!B11*$C101*'Business Case'!B12*$B101)-'Business Case'!B11*$C101*'Business Case'!B13*$D101-'Business Case'!B14*$E101)-MAX(0,(('Business Case'!B11*$C101*'Business Case'!B12*$B101)-'Business Case'!B11*$C101*'Business Case'!B13*$D101-'Business Case'!B14*$E101))*'Business Case'!$B$7-'Business Case'!$B$8*('Business Case'!B11*$C101*'Business Case'!B12*$B101)-'Business Case'!B15*$F101 -> -2.0590488e+09 | I101: =(('Business Case'!C11*$C101*'Business Case'!C12*$B101)-'Business Case'!C11*$C101*'Business Case'!C13*$D101-'Business Case'!C14*$E101)-MAX(0,(('Business Case'!C11*$C101*'Business Case'!C12*$B101)-'Business Case'!C11*$C101*'Business Case'!C13*$D101-'Business Case'!C14*$E101))*'Business Case'!$B$7-'Business Case'!$B$8*(('Business Case'!C11*$C101*'Business Case'!C12*$B101)-('Business Case'!B11*$C101*'Business Case'!B12*$B101))-'Business Case'!C15*$F101 -> -40305213 | J101: =(('Business Case'!D11*$C101*'Business Case'!D12*$B101)-'Business Case'!D11*$C101*'Business Case'!D13*$D101-'Business Case'!D14*$E101)-MAX(0,(('Business Case'!D11*$C101*'Business Case'!D12*$B101)-'Business Case'!D11*$C101*'Business Case'!D13*$D101-'Business Case'!D14*$E101))*'Business Case'!$B$7-'Business Case'!$B$8*(('Business Case'!D11*$C101*'Business Case'!D12*$B101)-('Business Case'!C11*$C101*'Business Case'!C12*$B101))-'Business Case'!D15*$F101 -> 2.182491e+08 | K101: =(('Business Case'!E11*$C101*'Business Case'!E12*$B101)-'Business Case'!E11*$C101*'Business Case'!E13*$D101-'Business Case'!E14*$E101)-MAX(0,(('Business Case'!E11*$C101*'Business Case'!E12*$B101)-'Business Case'!E11*$C101*'Business Case'!E13*$D101-'Business Case'!E14*$E101))*'Business Case'!$B$7-'Business Case'!$B$8*(('Business Case'!E11*$C101*'Business Case'!E12*$B101)-('Business Case'!D11*$C101*'Business Case'!D12*$B101))-'Business Case'!E15*$F101 -> 5.2827963e+08 | L101: =(('Business Case'!F11*$C101*'Business Case'!F12*$B101)-'Business Case'!F11*$C101*'Business Case'!F13*$D101-'Business Case'!F14*$E101)-MAX(0,(('Business Case'!F11*$C101*'Business Case'!F12*$B101)-'Business Case'!F11*$C101*'Business Case'!F13*$D101-'Business Case'!F14*$E101))*'Business Case'!$B$7-'Business Case'!$B$8*(('Business Case'!F11*$C101*'Business Case'!F12*$B101)-('Business Case'!E11*$C101*'Business Case'!E12*$B101))-'Business Case'!F15*$F101 -> 6.453325e+08 | M101: =(('Business Case'!G11*$C101*'Business Case'!G12*$B101)-'Business Case'!G11*$C101*'Business Case'!G13*$D101-'Business Case'!G14*$E101)-MAX(0,(('Business Case'!G11*$C101*'Business Case'!G12*$B101)-'Business Case'!G11*$C101*'Business Case'!G13*$D101-'Business Case'!G14*$E101))*'Business Case'!$B$7-'Business Case'!$B$8*(('Business Case'!G11*$C101*'Business Case'!G12*$B101)-('Business Case'!F11*$C101*'Business Case'!F12*$B101))-'Business Case'!G15*$F101+'Business Case'!$B$8*('Business Case'!G11*$C101*'Business Case'!G12*$B101) -> 8.1510704e+08 | N101: =IF(COUNT('Business Case'!B11:G11)=0,"",H101+NPV(G101,I101:M101)) -> -5.593873e+08 | P101: =RAND() -> 0.3134735 | Q101: =RAND() -> 0.19292501 | R101: =RAND() -> 0.5086338 | S101: =RAND() -> 0.84687397 | T101: =RAND() -> 0.4187614 | U101: =RAND() -> 0.19832026
A102: 22 | B102: =1+IF($G$6=$E$6,$F$6,IF(P102<($F$6-$E$6)/($G$6-$E$6),$E$6+SQRT(P102*($G$6-$E$6)*($F$6-$E$6)),$G$6-SQRT((1-P102)*($G$6-$E$6)*($G$6-$F$6)))) -> 0.99410964 | C102: =1+IF($G$7=$E$7,$F$7,IF(Q102<($F$7-$E$7)/($G$7-$E$7),$E$7+SQRT(Q102*($G$7-$E$7)*($F$7-$E$7)),$G$7-SQRT((1-Q102)*($G$7-$E$7)*($G$7-$F$7)))) -> 0.93106014 | D102: =1+IF($G$8=$E$8,$F$8,IF(R102<($F$8-$E$8)/($G$8-$E$8),$E$8+SQRT(R102*($G$8-$E$8)*($F$8-$E$8)),$G$8-SQRT((1-R102)*($G$8-$E$8)*($G$8-$F$8)))) -> 1.0195205 | E102: =1+IF($G$9=$E$9,$F$9,IF(S102<($F$9-$E$9)/($G$9-$E$9),$E$9+SQRT(S102*($G$9-$E$9)*($F$9-$E$9)),$G$9-SQRT((1-S102)*($G$9-$E$9)*($G$9-$F$9)))) -> 1.0612783 | F102: =1+IF($G$10=$E$10,$F$10,IF(T102<($F$10-$E$10)/($G$10-$E$10),$E$10+SQRT(T102*($G$10-$E$10)*($F$10-$E$10)),$G$10-SQRT((1-T102)*($G$10-$E$10)*($G$10-$F$10)))) -> 1.1045406 | G102: =IF($G$11=$E$11,$F$11,IF(U102<($F$11-$E$11)/($G$11-$E$11),$E$11+SQRT(U102*($G$11-$E$11)*($F$11-$E$11)),$G$11-SQRT((1-U102)*($G$11-$E$11)*($G$11-$F$11)))) -> 0.10257514 | H102: =(('Business Case'!B11*$C102*'Business Case'!B12*$B102)-'Business Case'!B11*$C102*'Business Case'!B13*$D102-'Business Case'!B14*$E102)-MAX(0,(('Business Case'!B11*$C102*'Business Case'!B12*$B102)-'Business Case'!B11*$C102*'Business Case'!B13*$D102-'Business Case'!B14*$E102))*'Business Case'!$B$7-'Business Case'!$B$8*('Business Case'!B11*$C102*'Business Case'!B12*$B102)-'Business Case'!B15*$F102 -> -2.2090813e+09 | I102: =(('Business Case'!C11*$C102*'Business Case'!C12*$B102)-'Business Case'!C11*$C102*'Business Case'!C13*$D102-'Business Case'!C14*$E102)-MAX(0,(('Business Case'!C11*$C102*'Business Case'!C12*$B102)-'Business Case'!C11*$C102*'Business Case'!C13*$D102-'Business Case'!C14*$E102))*'Business Case'!$B$7-'Business Case'!$B$8*(('Business Case'!C11*$C102*'Business Case'!C12*$B102)-('Business Case'!B11*$C102*'Business Case'!B12*$B102))-'Business Case'!C15*$F102 -> -37168740 | J102: =(('Business Case'!D11*$C102*'Business Case'!D12*$B102)-'Business Case'!D11*$C102*'Business Case'!D13*$D102-'Business Case'!D14*$E102)-MAX(0,(('Business Case'!D11*$C102*'Business Case'!D12*$B102)-'Business Case'!D11*$C102*'Business Case'!D13*$D102-'Business Case'!D14*$E102))*'Business Case'!$B$7-'Business Case'!$B$8*(('Business Case'!D11*$C102*'Business Case'!D12*$B102)-('Business Case'!C11*$C102*'Business Case'!C12*$B102))-'Business Case'!D15*$F102 -> 2.350122e+08 | K102: =(('Business Case'!E11*$C102*'Business Case'!E12*$B102)-'Business Case'!E11*$C102*'Business Case'!E13*$D102-'Business Case'!E14*$E102)-MAX(0,(('Business Case'!E11*$C102*'Business Case'!E12*$B102)-'Business Case'!E11*$C102*'Business Case'!E13*$D102-'Business Case'!E14*$E102))*'Business Case'!$B$7-'Business Case'!$B$8*(('Business Case'!E11*$C102*'Business Case'!E12*$B102)-('Business Case'!D11*$C102*'Business Case'!D12*$B102))-'Business Case'!E15*$F102 -> 5.6242018e+08 | L102: =(('Business Case'!F11*$C102*'Business Case'!F12*$B102)-'Business Case'!F11*$C102*'Business Case'!F13*$D102-'Business Case'!F14*$E102)-MAX(0,(('Business Case'!F11*$C102*'Business Case'!F12*$B102)-'Business Case'!F11*$C102*'Business Case'!F13*$D102-'Business Case'!F14*$E102))*'Business Case'!$B$7-'Business Case'!$B$8*(('Business Case'!F11*$C102*'Business Case'!F12*$B102)-('Business Case'!E11*$C102*'Business Case'!E12*$B102))-'Business Case'!F15*$F102 -> 6.8513506e+08 | M102: =(('Business Case'!G11*$C102*'Business Case'!G12*$B102)-'Business Case'!G11*$C102*'Business Case'!G13*$D102-'Business Case'!G14*$E102)-MAX(0,(('Business Case'!G11*$C102*'Business Case'!G12*$B102)-'Business Case'!G11*$C102*'Business Case'!G13*$D102-'Business Case'!G14*$E102))*'Business Case'!$B$7-'Business Case'!$B$8*(('Business Case'!G11*$C102*'Business Case'!G12*$B102)-('Business Case'!F11*$C102*'Business Case'!F12*$B102))-'Business Case'!G15*$F102+'Business Case'!$B$8*('Business Case'!G11*$C102*'Business Case'!G12*$B102) -> 8.6106852e+08 | N102: =IF(COUNT('Business Case'!B11:G11)=0,"",H102+NPV(G102,I102:M102)) -> -6.3783125e+08 | P102: =RAND() -> 0.57210824 | Q102: =RAND() -> 0.24538227 | R102: =RAND() -> 0.6482913 | S102: =RAND() -> 0.90004182 | T102: =RAND() -> 0.81775016 | U102: =RAND() -> 0.49395692
A103: 23 | B103: =1+IF($G$6=$E$6,$F$6,IF(P103<($F$6-$E$6)/($G$6-$E$6),$E$6+SQRT(P103*($G$6-$E$6)*($F$6-$E$6)),$G$6-SQRT((1-P103)*($G$6-$E$6)*($G$6-$F$6)))) -> 0.95481699 | C103: =1+IF($G$7=$E$7,$F$7,IF(Q103<($F$7-$E$7)/($G$7-$E$7),$E$7+SQRT(Q103*($G$7-$E$7)*($F$7-$E$7)),$G$7-SQRT((1-Q103)*($G$7-$E$7)*($G$7-$F$7)))) -> 1.0751223 | D103: =1+IF($G$8=$E$8,$F$8,IF(R103<($F$8-$E$8)/($G$8-$E$8),$E$8+SQRT(R103*($G$8-$E$8)*($F$8-$E$8)),$G$8-SQRT((1-R103)*($G$8-$E$8)*($G$8-$F$8)))) -> 0.9787525 | E103: =1+IF($G$9=$E$9,$F$9,IF(S103<($F$9-$E$9)/($G$9-$E$9),$E$9+SQRT(S103*($G$9-$E$9)*($F$9-$E$9)),$G$9-SQRT((1-S103)*($G$9-$E$9)*($G$9-$F$9)))) -> 1.0409158 | F103: =1+IF($G$10=$E$10,$F$10,IF(T103<($F$10-$E$10)/($G$10-$E$10),$E$10+SQRT(T103*($G$10-$E$10)*($F$10-$E$10)),$G$10-SQRT((1-T103)*($G$10-$E$10)*($G$10-$F$10)))) -> 1.0412216 | G103: =IF($G$11=$E$11,$F$11,IF(U103<($F$11-$E$11)/($G$11-$E$11),$E$11+SQRT(U103*($G$11-$E$11)*($F$11-$E$11)),$G$11-SQRT((1-U103)*($G$11-$E$11)*($G$11-$F$11)))) -> 0.10292996 | H103: =(('Business Case'!B11*$C103*'Business Case'!B12*$B103)-'Business Case'!B11*$C103*'Business Case'!B13*$D103-'Business Case'!B14*$E103)-MAX(0,(('Business Case'!B11*$C103*'Business Case'!B12*$B103)-'Business Case'!B11*$C103*'Business Case'!B13*$D103-'Business Case'!B14*$E103))*'Business Case'!$B$7-'Business Case'!$B$8*('Business Case'!B11*$C103*'Business Case'!B12*$B103)-'Business Case'!B15*$F103 -> -2.0824432e+09 | I103: =(('Business Case'!C11*$C103*'Business Case'!C12*$B103)-'Business Case'!C11*$C103*'Business Case'!C13*$D103-'Business Case'!C14*$E103)-MAX(0,(('Business Case'!C11*$C103*'Business Case'!C12*$B103)-'Business Case'!C11*$C103*'Business Case'!C13*$D103-'Business Case'!C14*$E103))*'Business Case'!$B$7-'Business Case'!$B$8*(('Business Case'!C11*$C103*'Business Case'!C12*$B103)-('Business Case'!B11*$C103*'Business Case'!B12*$B103))-'Business Case'!C15*$F103 -> -3224665.6 | J103: =(('Business Case'!D11*$C103*'Business Case'!D12*$B103)-'Business Case'!D11*$C103*'Business Case'!D13*$D103-'Business Case'!D14*$E103)-MAX(0,(('Business Case'!D11*$C103*'Business Case'!D12*$B103)-'Business Case'!D11*$C103*'Business Case'!D13*$D103-'Business Case'!D14*$E103))*'Business Case'!$B$7-'Business Case'!$B$8*(('Business Case'!D11*$C103*'Business Case'!D12*$B103)-('Business Case'!C11*$C103*'Business Case'!C12*$B103))-'Business Case'!D15*$F103 -> 2.9890715e+08 | K103: =(('Business Case'!E11*$C103*'Business Case'!E12*$B103)-'Business Case'!E11*$C103*'Business Case'!E13*$D103-'Business Case'!E14*$E103)-MAX(0,(('Business Case'!E11*$C103*'Business Case'!E12*$B103)-'Business Case'!E11*$C103*'Business Case'!E13*$D103-'Business Case'!E14*$E103))*'Business Case'!$B$7-'Business Case'!$B$8*(('Business Case'!E11*$C103*'Business Case'!E12*$B103)-('Business Case'!D11*$C103*'Business Case'!D12*$B103))-'Business Case'!E15*$F103 -> 6.5310004e+08 | L103: =(('Business Case'!F11*$C103*'Business Case'!F12*$B103)-'Business Case'!F11*$C103*'Business Case'!F13*$D103-'Business Case'!F14*$E103)-MAX(0,(('Business Case'!F11*$C103*'Business Case'!F12*$B103)-'Business Case'!F11*$C103*'Business Case'!F13*$D103-'Business Case'!F14*$E103))*'Business Case'!$B$7-'Business Case'!$B$8*(('Business Case'!F11*$C103*'Business Case'!F12*$B103)-('Business Case'!E11*$C103*'Business Case'!E12*$B103))-'Business Case'!F15*$F103 -> 7.8928803e+08 | M103: =(('Business Case'!G11*$C103*'Business Case'!G12*$B103)-'Business Case'!G11*$C103*'Business Case'!G13*$D103-'Business Case'!G14*$E103)-MAX(0,(('Business Case'!G11*$C103*'Business Case'!G12*$B103)-'Business Case'!G11*$C103*'Business Case'!G13*$D103-'Business Case'!G14*$E103))*'Business Case'!$B$7-'Business Case'!$B$8*(('Business Case'!G11*$C103*'Business Case'!G12*$B103)-('Business Case'!F11*$C103*'Business Case'!F12*$B103))-'Business Case'!G15*$F103+'Business Case'!$B$8*('Business Case'!G11*$C103*'Business Case'!G12*$B103) -> 9.8441371e+08 | N103: =IF(COUNT('Business Case'!B11:G11)=0,"",H103+NPV(G103,I103:M103)) -> -2.1630711e+08 | P103: =RAND() -> 0.12627321 | Q103: =RAND() -> 0.89320623 | R103: =RAND() -> 0.1271856 | S103: =RAND() -> 0.7672704 | T103: =RAND() -> 0.49578824 | U103: =RAND() -> 0.51435615
A104: 24 | B104: =1+IF($G$6=$E$6,$F$6,IF(P104<($F$6-$E$6)/($G$6-$E$6),$E$6+SQRT(P104*($G$6-$E$6)*($F$6-$E$6)),$G$6-SQRT((1-P104)*($G$6-$E$6)*($G$6-$F$6)))) -> 1.004078 | C104: =1+IF($G$7=$E$7,$F$7,IF(Q104<($F$7-$E$7)/($G$7-$E$7),$E$7+SQRT(Q104*($G$7-$E$7)*($F$7-$E$7)),$G$7-SQRT((1-Q104)*($G$7-$E$7)*($G$7-$F$7)))) -> 0.90718128 | D104: =1+IF($G$8=$E$8,$F$8,IF(R104<($F$8-$E$8)/($G$8-$E$8),$E$8+SQRT(R104*($G$8-$E$8)*($F$8-$E$8)),$G$8-SQRT((1-R104)*($G$8-$E$8)*($G$8-$F$8)))) -> 1.0425007 | E104: =1+IF($G$9=$E$9,$F$9,IF(S104<($F$9-$E$9)/($G$9-$E$9),$E$9+SQRT(S104*($G$9-$E$9)*($F$9-$E$9)),$G$9-SQRT((1-S104)*($G$9-$E$9)*($G$9-$F$9)))) -> 1.000026 | F104: =1+IF($G$10=$E$10,$F$10,IF(T104<($F$10-$E$10)/($G$10-$E$10),$E$10+SQRT(T104*($G$10-$E$10)*($F$10-$E$10)),$G$10-SQRT((1-T104)*($G$10-$E$10)*($G$10-$F$10)))) -> 1.0594236 | G104: =IF($G$11=$E$11,$F$11,IF(U104<($F$11-$E$11)/($G$11-$E$11),$E$11+SQRT(U104*($G$11-$E$11)*($F$11-$E$11)),$G$11-SQRT((1-U104)*($G$11-$E$11)*($G$11-$F$11)))) -> 0.095532173 | H104: =(('Business Case'!B11*$C104*'Business Case'!B12*$B104)-'Business Case'!B11*$C104*'Business Case'!B13*$D104-'Business Case'!B14*$E104)-MAX(0,(('Business Case'!B11*$C104*'Business Case'!B12*$B104)-'Business Case'!B11*$C104*'Business Case'!B13*$D104-'Business Case'!B14*$E104))*'Business Case'!$B$7-'Business Case'!$B$8*('Business Case'!B11*$C104*'Business Case'!B12*$B104)-'Business Case'!B15*$F104 -> -2.1188471e+09 | I104: =(('Business Case'!C11*$C104*'Business Case'!C12*$B104)-'Business Case'!C11*$C104*'Business Case'!C13*$D104-'Business Case'!C14*$E104)-MAX(0,(('Business Case'!C11*$C104*'Business Case'!C12*$B104)-'Business Case'!C11*$C104*'Business Case'!C13*$D104-'Business Case'!C14*$E104))*'Business Case'!$B$7-'Business Case'!$B$8*(('Business Case'!C11*$C104*'Business Case'!C12*$B104)-('Business Case'!B11*$C104*'Business Case'!B12*$B104))-'Business Case'!C15*$F104 -> -33430955 | J104: =(('Business Case'!D11*$C104*'Business Case'!D12*$B104)-'Business Case'!D11*$C104*'Business Case'!D13*$D104-'Business Case'!D14*$E104)-MAX(0,(('Business Case'!D11*$C104*'Business Case'!D12*$B104)-'Business Case'!D11*$C104*'Business Case'!D13*$D104-'Business Case'!D14*$E104))*'Business Case'!$B$7-'Business Case'!$B$8*(('Business Case'!D11*$C104*'Business Case'!D12*$B104)-('Business Case'!C11*$C104*'Business Case'!C12*$B104))-'Business Case'!D15*$F104 -> 2.2850421e+08 | K104: =(('Business Case'!E11*$C104*'Business Case'!E12*$B104)-'Business Case'!E11*$C104*'Business Case'!E13*$D104-'Business Case'!E14*$E104)-MAX(0,(('Business Case'!E11*$C104*'Business Case'!E12*$B104)-'Business Case'!E11*$C104*'Business Case'!E13*$D104-'Business Case'!E14*$E104))*'Business Case'!$B$7-'Business Case'!$B$8*(('Business Case'!E11*$C104*'Business Case'!E12*$B104)-('Business Case'!D11*$C104*'Business Case'!D12*$B104))-'Business Case'!E15*$F104 -> 5.4341054e+08 | L104: =(('Business Case'!F11*$C104*'Business Case'!F12*$B104)-'Business Case'!F11*$C104*'Business Case'!F13*$D104-'Business Case'!F14*$E104)-MAX(0,(('Business Case'!F11*$C104*'Business Case'!F12*$B104)-'Business Case'!F11*$C104*'Business Case'!F13*$D104-'Business Case'!F14*$E104))*'Business Case'!$B$7-'Business Case'!$B$8*(('Business Case'!F11*$C104*'Business Case'!F12*$B104)-('Business Case'!E11*$C104*'Business Case'!E12*$B104))-'Business Case'!F15*$F104 -> 6.622023e+08 | M104: =(('Business Case'!G11*$C104*'Business Case'!G12*$B104)-'Business Case'!G11*$C104*'Business Case'!G13*$D104-'Business Case'!G14*$E104)-MAX(0,(('Business Case'!G11*$C104*'Business Case'!G12*$B104)-'Business Case'!G11*$C104*'Business Case'!G13*$D104-'Business Case'!G14*$E104))*'Business Case'!$B$7-'Business Case'!$B$8*(('Business Case'!G11*$C104*'Business Case'!G12*$B104)-('Business Case'!F11*$C104*'Business Case'!F12*$B104))-'Business Case'!G15*$F104+'Business Case'!$B$8*('Business Case'!G11*$C104*'Business Case'!G12*$B104) -> 8.3534251e+08 | N104: =IF(COUNT('Business Case'!B11:G11)=0,"",H104+NPV(G104,I104:M104)) -> -5.5662343e+08 | P104: =RAND() -> 0.73116831 | Q104: =RAND() -> 0.16411181 | R104: =RAND() -> 0.86478874 | S104: =RAND() -> 0.33368029 | T104: =RAND() -> 0.60476534 | U104: =RAND() -> 0.10201646
A105: 25 | B105: =1+IF($G$6=$E$6,$F$6,IF(P105<($F$6-$E$6)/($G$6-$E$6),$E$6+SQRT(P105*($G$6-$E$6)*($F$6-$E$6)),$G$6-SQRT((1-P105)*($G$6-$E$6)*($G$6-$F$6)))) -> 0.98401949 | C105: =1+IF($G$7=$E$7,$F$7,IF(Q105<($F$7-$E$7)/($G$7-$E$7),$E$7+SQRT(Q105*($G$7-$E$7)*($F$7-$E$7)),$G$7-SQRT((1-Q105)*($G$7-$E$7)*($G$7-$F$7)))) -> 1.0907431 | D105: =1+IF($G$8=$E$8,$F$8,IF(R105<($F$8-$E$8)/($G$8-$E$8),$E$8+SQRT(R105*($G$8-$E$8)*($F$8-$E$8)),$G$8-SQRT((1-R105)*($G$8-$E$8)*($G$8-$F$8)))) -> 0.9808361 | E105: =1+IF($G$9=$E$9,$F$9,IF(S105<($F$9-$E$9)/($G$9-$E$9),$E$9+SQRT(S105*($G$9-$E$9)*($F$9-$E$9)),$G$9-SQRT((1-S105)*($G$9-$E$9)*($G$9-$F$9)))) -> 0.97115067 | F105: =1+IF($G$10=$E$10,$F$10,IF(T105<($F$10-$E$10)/($G$10-$E$10),$E$10+SQRT(T105*($G$10-$E$10)*($F$10-$E$10)),$G$10-SQRT((1-T105)*($G$10-$E$10)*($G$10-$F$10)))) -> 1.1148661 | G105: =IF($G$11=$E$11,$F$11,IF(U105<($F$11-$E$11)/($G$11-$E$11),$E$11+SQRT(U105*($G$11-$E$11)*($F$11-$E$11)),$G$11-SQRT((1-U105)*($G$11-$E$11)*($G$11-$F$11)))) -> 0.094282653 | H105: =(('Business Case'!B11*$C105*'Business Case'!B12*$B105)-'Business Case'!B11*$C105*'Business Case'!B13*$D105-'Business Case'!B14*$E105)-MAX(0,(('Business Case'!B11*$C105*'Business Case'!B12*$B105)-'Business Case'!B11*$C105*'Business Case'!B13*$D105-'Business Case'!B14*$E105))*'Business Case'!$B$7-'Business Case'!$B$8*('Business Case'!B11*$C105*'Business Case'!B12*$B105)-'Business Case'!B15*$F105 -> -2.2297322e+09 | I105: =(('Business Case'!C11*$C105*'Business Case'!C12*$B105)-'Business Case'!C11*$C105*'Business Case'!C13*$D105-'Business Case'!C14*$E105)-MAX(0,(('Business Case'!C11*$C105*'Business Case'!C12*$B105)-'Business Case'!C11*$C105*'Business Case'!C13*$D105-'Business Case'!C14*$E105))*'Business Case'!$B$7-'Business Case'!$B$8*(('Business Case'!C11*$C105*'Business Case'!C12*$B105)-('Business Case'!B11*$C105*'Business Case'!B12*$B105))-'Business Case'!C15*$F105 -> 26222828 | J105: =(('Business Case'!D11*$C105*'Business Case'!D12*$B105)-'Business Case'!D11*$C105*'Business Case'!D13*$D105-'Business Case'!D14*$E105)-MAX(0,(('Business Case'!D11*$C105*'Business Case'!D12*$B105)-'Business Case'!D11*$C105*'Business Case'!D13*$D105-'Business Case'!D14*$E105))*'Business Case'!$B$7-'Business Case'!$B$8*(('Business Case'!D11*$C105*'Business Case'!D12*$B105)-('Business Case'!C11*$C105*'Business Case'!C12*$B105))-'Business Case'!D15*$F105 -> 3.5767041e+08 | K105: =(('Business Case'!E11*$C105*'Business Case'!E12*$B105)-'Business Case'!E11*$C105*'Business Case'!E13*$D105-'Business Case'!E14*$E105)-MAX(0,(('Business Case'!E11*$C105*'Business Case'!E12*$B105)-'Business Case'!E11*$C105*'Business Case'!E13*$D105-'Business Case'!E14*$E105))*'Business Case'!$B$7-'Business Case'!$B$8*(('Business Case'!E11*$C105*'Business Case'!E12*$B105)-('Business Case'!D11*$C105*'Business Case'!D12*$B105))-'Business Case'!E15*$F105 -> 7.4486129e+08 | L105: =(('Business Case'!F11*$C105*'Business Case'!F12*$B105)-'Business Case'!F11*$C105*'Business Case'!F13*$D105-'Business Case'!F14*$E105)-MAX(0,(('Business Case'!F11*$C105*'Business Case'!F12*$B105)-'Business Case'!F11*$C105*'Business Case'!F13*$D105-'Business Case'!F14*$E105))*'Business Case'!$B$7-'Business Case'!$B$8*(('Business Case'!F11*$C105*'Business Case'!F12*$B105)-('Business Case'!E11*$C105*'Business Case'!E12*$B105))-'Business Case'!F15*$F105 -> 8.924375e+08 | M105: =(('Business Case'!G11*$C105*'Business Case'!G12*$B105)-'Business Case'!G11*$C105*'Business Case'!G13*$D105-'Business Case'!G14*$E105)-MAX(0,(('Business Case'!G11*$C105*'Business Case'!G12*$B105)-'Business Case'!G11*$C105*'Business Case'!G13*$D105-'Business Case'!G14*$E105))*'Business Case'!$B$7-'Business Case'!$B$8*(('Business Case'!G11*$C105*'Business Case'!G12*$B105)-('Business Case'!F11*$C105*'Business Case'!F12*$B105))-'Business Case'!G15*$F105+'Business Case'!$B$8*('Business Case'!G11*$C105*'Business Case'!G12*$B105) -> 1.0964527e+09 | N105: =IF(COUNT('Business Case'!B11:G11)=0,"",H105+NPV(G105,I105:M105)) -> -17464617 | P105: =RAND() -> 0.42692658 | Q105: =RAND() -> 0.93311649 | R105: =RAND() -> 0.14628694 | S105: =RAND() -> 0.059646796 | T105: =RAND() -> 0.8550444 | U105: =RAND() -> 0.061137063
A106: 26 | B106: =1+IF($G$6=$E$6,$F$6,IF(P106<($F$6-$E$6)/($G$6-$E$6),$E$6+SQRT(P106*($G$6-$E$6)*($F$6-$E$6)),$G$6-SQRT((1-P106)*($G$6-$E$6)*($G$6-$F$6)))) -> 1.0089374 | C106: =1+IF($G$7=$E$7,$F$7,IF(Q106<($F$7-$E$7)/($G$7-$E$7),$E$7+SQRT(Q106*($G$7-$E$7)*($F$7-$E$7)),$G$7-SQRT((1-Q106)*($G$7-$E$7)*($G$7-$F$7)))) -> 0.95101251 | D106: =1+IF($G$8=$E$8,$F$8,IF(R106<($F$8-$E$8)/($G$8-$E$8),$E$8+SQRT(R106*($G$8-$E$8)*($F$8-$E$8)),$G$8-SQRT((1-R106)*($G$8-$E$8)*($G$8-$F$8)))) -> 1.0064511 | E106: =1+IF($G$9=$E$9,$F$9,IF(S106<($F$9-$E$9)/($G$9-$E$9),$E$9+SQRT(S106*($G$9-$E$9)*($F$9-$E$9)),$G$9-SQRT((1-S106)*($G$9-$E$9)*($G$9-$F$9)))) -> 0.97841887 | F106: =1+IF($G$10=$E$10,$F$10,IF(T106<($F$10-$E$10)/($G$10-$E$10),$E$10+SQRT(T106*($G$10-$E$10)*($F$10-$E$10)),$G$10-SQRT((1-T106)*($G$10-$E$10)*($G$10-$F$10)))) -> 0.96351781 | G106: =IF($G$11=$E$11,$F$11,IF(U106<($F$11-$E$11)/($G$11-$E$11),$E$11+SQRT(U106*($G$11-$E$11)*($F$11-$E$11)),$G$11-SQRT((1-U106)*($G$11-$E$11)*($G$11-$F$11)))) -> 0.10187548 | H106: =(('Business Case'!B11*$C106*'Business Case'!B12*$B106)-'Business Case'!B11*$C106*'Business Case'!B13*$D106-'Business Case'!B14*$E106)-MAX(0,(('Business Case'!B11*$C106*'Business Case'!B12*$B106)-'Business Case'!B11*$C106*'Business Case'!B13*$D106-'Business Case'!B14*$E106))*'Business Case'!$B$7-'Business Case'!$B$8*('Business Case'!B11*$C106*'Business Case'!B12*$B106)-'Business Case'!B15*$F106 -> -1.9270356e+09 | I106: =(('Business Case'!C11*$C106*'Business Case'!C12*$B106)-'Business Case'!C11*$C106*'Business Case'!C13*$D106-'Business Case'!C14*$E106)-MAX(0,(('Business Case'!C11*$C106*'Business Case'!C12*$B106)-'Business Case'!C11*$C106*'Business Case'!C13*$D106-'Business Case'!C14*$E106))*'Business Case'!$B$7-'Business Case'!$B$8*(('Business Case'!C11*$C106*'Business Case'!C12*$B106)-('Business Case'!B11*$C106*'Business Case'!B12*$B106))-'Business Case'!C15*$F106 -> 10702447 | J106: =(('Business Case'!D11*$C106*'Business Case'!D12*$B106)-'Business Case'!D11*$C106*'Business Case'!D13*$D106-'Business Case'!D14*$E106)-MAX(0,(('Business Case'!D11*$C106*'Business Case'!D12*$B106)-'Business Case'!D11*$C106*'Business Case'!D13*$D106-'Business Case'!D14*$E106))*'Business Case'!$B$7-'Business Case'!$B$8*(('Business Case'!D11*$C106*'Business Case'!D12*$B106)-('Business Case'!C11*$C106*'Business Case'!C12*$B106))-'Business Case'!D15*$F106 -> 3.0662895e+08 | K106: =(('Business Case'!E11*$C106*'Business Case'!E12*$B106)-'Business Case'!E11*$C106*'Business Case'!E13*$D106-'Business Case'!E14*$E106)-MAX(0,(('Business Case'!E11*$C106*'Business Case'!E12*$B106)-'Business Case'!E11*$C106*'Business Case'!E13*$D106-'Business Case'!E14*$E106))*'Business Case'!$B$7-'Business Case'!$B$8*(('Business Case'!E11*$C106*'Business Case'!E12*$B106)-('Business Case'!D11*$C106*'Business Case'!D12*$B106))-'Business Case'!E15*$F106 -> 6.5073133e+08 | L106: =(('Business Case'!F11*$C106*'Business Case'!F12*$B106)-'Business Case'!F11*$C106*'Business Case'!F13*$D106-'Business Case'!F14*$E106)-MAX(0,(('Business Case'!F11*$C106*'Business Case'!F12*$B106)-'Business Case'!F11*$C106*'Business Case'!F13*$D106-'Business Case'!F14*$E106))*'Business Case'!$B$7-'Business Case'!$B$8*(('Business Case'!F11*$C106*'Business Case'!F12*$B106)-('Business Case'!E11*$C106*'Business Case'!E12*$B106))-'Business Case'!F15*$F106 -> 7.8253424e+08 | M106: =(('Business Case'!G11*$C106*'Business Case'!G12*$B106)-'Business Case'!G11*$C106*'Business Case'!G13*$D106-'Business Case'!G14*$E106)-MAX(0,(('Business Case'!G11*$C106*'Business Case'!G12*$B106)-'Business Case'!G11*$C106*'Business Case'!G13*$D106-'Business Case'!G14*$E106))*'Business Case'!$B$7-'Business Case'!$B$8*(('Business Case'!G11*$C106*'Business Case'!G12*$B106)-('Business Case'!F11*$C106*'Business Case'!F12*$B106))-'Business Case'!G15*$F106+'Business Case'!$B$8*('Business Case'!G11*$C106*'Business Case'!G12*$B106) -> 9.6491829e+08 | N106: =IF(COUNT('Business Case'!B11:G11)=0,"",H106+NPV(G106,I106:M106)) -> -53451823 | P106: =RAND() -> 0.79898212 | Q106: =RAND() -> 0.32578253 | R106: =RAND() -> 0.47986104 | S106: =RAND() -> 0.10768429 | T106: =RAND() -> 0.014618501 | U106: =RAND() -> 0.45250268
A107: 27 | B107: =1+IF($G$6=$E$6,$F$6,IF(P107<($F$6-$E$6)/($G$6-$E$6),$E$6+SQRT(P107*($G$6-$E$6)*($F$6-$E$6)),$G$6-SQRT((1-P107)*($G$6-$E$6)*($G$6-$F$6)))) -> 0.97891376 | C107: =1+IF($G$7=$E$7,$F$7,IF(Q107<($F$7-$E$7)/($G$7-$E$7),$E$7+SQRT(Q107*($G$7-$E$7)*($F$7-$E$7)),$G$7-SQRT((1-Q107)*($G$7-$E$7)*($G$7-$F$7)))) -> 0.9849235 | D107: =1+IF($G$8=$E$8,$F$8,IF(R107<($F$8-$E$8)/($G$8-$E$8),$E$8+SQRT(R107*($G$8-$E$8)*($F$8-$E$8)),$G$8-SQRT((1-R107)*($G$8-$E$8)*($G$8-$F$8)))) -> 0.98479542 | E107: =1+IF($G$9=$E$9,$F$9,IF(S107<($F$9-$E$9)/($G$9-$E$9),$E$9+SQRT(S107*($G$9-$E$9)*($F$9-$E$9)),$G$9-SQRT((1-S107)*($G$9-$E$9)*($G$9-$F$9)))) -> 1.0149538 | F107: =1+IF($G$10=$E$10,$F$10,IF(T107<($F$10-$E$10)/($G$10-$E$10),$E$10+SQRT(T107*($G$10-$E$10)*($F$10-$E$10)),$G$10-SQRT((1-T107)*($G$10-$E$10)*($G$10-$F$10)))) -> 1.1299319 | G107: =IF($G$11=$E$11,$F$11,IF(U107<($F$11-$E$11)/($G$11-$E$11),$E$11+SQRT(U107*($G$11-$E$11)*($F$11-$E$11)),$G$11-SQRT((1-U107)*($G$11-$E$11)*($G$11-$F$11)))) -> 0.10151794 | H107: =(('Business Case'!B11*$C107*'Business Case'!B12*$B107)-'Business Case'!B11*$C107*'Business Case'!B13*$D107-'Business Case'!B14*$E107)-MAX(0,(('Business Case'!B11*$C107*'Business Case'!B12*$B107)-'Business Case'!B11*$C107*'Business Case'!B13*$D107-'Business Case'!B14*$E107))*'Business Case'!$B$7-'Business Case'!$B$8*('Business Case'!B11*$C107*'Business Case'!B12*$B107)-'Business Case'!B15*$F107 -> -2.2598639e+09 | I107: =(('Business Case'!C11*$C107*'Business Case'!C12*$B107)-'Business Case'!C11*$C107*'Business Case'!C13*$D107-'Business Case'!C14*$E107)-MAX(0,(('Business Case'!C11*$C107*'Business Case'!C12*$B107)-'Business Case'!C11*$C107*'Business Case'!C13*$D107-'Business Case'!C14*$E107))*'Business Case'!$B$7-'Business Case'!$B$8*(('Business Case'!C11*$C107*'Business Case'!C12*$B107)-('Business Case'!B11*$C107*'Business Case'!B12*$B107))-'Business Case'!C15*$F107 -> -14124781 | J107: =(('Business Case'!D11*$C107*'Business Case'!D12*$B107)-'Business Case'!D11*$C107*'Business Case'!D13*$D107-'Business Case'!D14*$E107)-MAX(0,(('Business Case'!D11*$C107*'Business Case'!D12*$B107)-'Business Case'!D11*$C107*'Business Case'!D13*$D107-'Business Case'!D14*$E107))*'Business Case'!$B$7-'Business Case'!$B$8*(('Business Case'!D11*$C107*'Business Case'!D12*$B107)-('Business Case'!C11*$C107*'Business Case'!C12*$B107))-'Business Case'!D15*$F107 -> 2.7905186e+08 | K107: =(('Business Case'!E11*$C107*'Business Case'!E12*$B107)-'Business Case'!E11*$C107*'Business Case'!E13*$D107-'Business Case'!E14*$E107)-MAX(0,(('Business Case'!E11*$C107*'Business Case'!E12*$B107)-'Business Case'!E11*$C107*'Business Case'!E13*$D107-'Business Case'!E14*$E107))*'Business Case'!$B$7-'Business Case'!$B$8*(('Business Case'!E11*$C107*'Business Case'!E12*$B107)-('Business Case'!D11*$C107*'Business Case'!D12*$B107))-'Business Case'!E15*$F107 -> 6.287251e+08 | L107: =(('Business Case'!F11*$C107*'Business Case'!F12*$B107)-'Business Case'!F11*$C107*'Business Case'!F13*$D107-'Business Case'!F14*$E107)-MAX(0,(('Business Case'!F11*$C107*'Business Case'!F12*$B107)-'Business Case'!F11*$C107*'Business Case'!F13*$D107-'Business Case'!F14*$E107))*'Business Case'!$B$7-'Business Case'!$B$8*(('Business Case'!F11*$C107*'Business Case'!F12*$B107)-('Business Case'!E11*$C107*'Business Case'!E12*$B107))-'Business Case'!F15*$F107 -> 7.5977185e+08 | M107: =(('Business Case'!G11*$C107*'Business Case'!G12*$B107)-'Business Case'!G11*$C107*'Business Case'!G13*$D107-'Business Case'!G14*$E107)-MAX(0,(('Business Case'!G11*$C107*'Business Case'!G12*$B107)-'Business Case'!G11*$C107*'Business Case'!G13*$D107-'Business Case'!G14*$E107))*'Business Case'!$B$7-'Business Case'!$B$8*(('Business Case'!G11*$C107*'Business Case'!G12*$B107)-('Business Case'!F11*$C107*'Business Case'!F12*$B107))-'Business Case'!G15*$F107+'Business Case'!$B$8*('Business Case'!G11*$C107*'Business Case'!G12*$B107) -> 9.4303847e+08 | N107: =IF(COUNT('Business Case'!B11:G11)=0,"",H107+NPV(G107,I107:M107)) -> -4.7467131e+08 | P107: =RAND() -> 0.36154493 | Q107: =RAND() -> 0.48852432 | R107: =RAND() -> 0.18626484 | S107: =RAND() -> 0.51780924 | T107: =RAND() -> 0.90180936 | U107: =RAND() -> 0.430689
A108: 28 | B108: =1+IF($G$6=$E$6,$F$6,IF(P108<($F$6-$E$6)/($G$6-$E$6),$E$6+SQRT(P108*($G$6-$E$6)*($F$6-$E$6)),$G$6-SQRT((1-P108)*($G$6-$E$6)*($G$6-$F$6)))) -> 0.99446749 | C108: =1+IF($G$7=$E$7,$F$7,IF(Q108<($F$7-$E$7)/($G$7-$E$7),$E$7+SQRT(Q108*($G$7-$E$7)*($F$7-$E$7)),$G$7-SQRT((1-Q108)*($G$7-$E$7)*($G$7-$F$7)))) -> 0.93749266 | D108: =1+IF($G$8=$E$8,$F$8,IF(R108<($F$8-$E$8)/($G$8-$E$8),$E$8+SQRT(R108*($G$8-$E$8)*($F$8-$E$8)),$G$8-SQRT((1-R108)*($G$8-$E$8)*($G$8-$F$8)))) -> 0.99079296 | E108: =1+IF($G$9=$E$9,$F$9,IF(S108<($F$9-$E$9)/($G$9-$E$9),$E$9+SQRT(S108*($G$9-$E$9)*($F$9-$E$9)),$G$9-SQRT((1-S108)*($G$9-$E$9)*($G$9-$F$9)))) -> 0.99777455 | F108: =1+IF($G$10=$E$10,$F$10,IF(T108<($F$10-$E$10)/($G$10-$E$10),$E$10+SQRT(T108*($G$10-$E$10)*($F$10-$E$10)),$G$10-SQRT((1-T108)*($G$10-$E$10)*($G$10-$F$10)))) -> 1.0848278 | G108: =IF($G$11=$E$11,$F$11,IF(U108<($F$11-$E$11)/($G$11-$E$11),$E$11+SQRT(U108*($G$11-$E$11)*($F$11-$E$11)),$G$11-SQRT((1-U108)*($G$11-$E$11)*($G$11-$F$11)))) -> 0.096966188 | H108: =(('Business Case'!B11*$C108*'Business Case'!B12*$B108)-'Business Case'!B11*$C108*'Business Case'!B13*$D108-'Business Case'!B14*$E108)-MAX(0,(('Business Case'!B11*$C108*'Business Case'!B12*$B108)-'Business Case'!B11*$C108*'Business Case'!B13*$D108-'Business Case'!B14*$E108))*'Business Case'!$B$7-'Business Case'!$B$8*('Business Case'!B11*$C108*'Business Case'!B12*$B108)-'Business Case'!B15*$F108 -> -2.1696557e+09 | I108: =(('Business Case'!C11*$C108*'Business Case'!C12*$B108)-'Business Case'!C11*$C108*'Business Case'!C13*$D108-'Business Case'!C14*$E108)-MAX(0,(('Business Case'!C11*$C108*'Business Case'!C12*$B108)-'Business Case'!C11*$C108*'Business Case'!C13*$D108-'Business Case'!C14*$E108))*'Business Case'!$B$7-'Business Case'!$B$8*(('Business Case'!C11*$C108*'Business Case'!C12*$B108)-('Business Case'!B11*$C108*'Business Case'!B12*$B108))-'Business Case'!C15*$F108 -> -10573939 | J108: =(('Business Case'!D11*$C108*'Business Case'!D12*$B108)-'Business Case'!D11*$C108*'Business Case'!D13*$D108-'Business Case'!D14*$E108)-MAX(0,(('Business Case'!D11*$C108*'Business Case'!D12*$B108)-'Business Case'!D11*$C108*'Business Case'!D13*$D108-'Business Case'!D14*$E108))*'Business Case'!$B$7-'Business Case'!$B$8*(('Business Case'!D11*$C108*'Business Case'!D12*$B108)-('Business Case'!C11*$C108*'Business Case'!C12*$B108))-'Business Case'!D15*$F108 -> 2.7754919e+08 | K108: =(('Business Case'!E11*$C108*'Business Case'!E12*$B108)-'Business Case'!E11*$C108*'Business Case'!E13*$D108-'Business Case'!E14*$E108)-MAX(0,(('Business Case'!E11*$C108*'Business Case'!E12*$B108)-'Business Case'!E11*$C108*'Business Case'!E13*$D108-'Business Case'!E14*$E108))*'Business Case'!$B$7-'Business Case'!$B$8*(('Business Case'!E11*$C108*'Business Case'!E12*$B108)-('Business Case'!D11*$C108*'Business Case'!D12*$B108))-'Business Case'!E15*$F108 -> 6.1991371e+08 | L108: =(('Business Case'!F11*$C108*'Business Case'!F12*$B108)-'Business Case'!F11*$C108*'Business Case'!F13*$D108-'Business Case'!F14*$E108)-MAX(0,(('Business Case'!F11*$C108*'Business Case'!F12*$B108)-'Business Case'!F11*$C108*'Business Case'!F13*$D108-'Business Case'!F14*$E108))*'Business Case'!$B$7-'Business Case'!$B$8*(('Business Case'!F11*$C108*'Business Case'!F12*$B108)-('Business Case'!E11*$C108*'Business Case'!E12*$B108))-'Business Case'!F15*$F108 -> 7.4817524e+08 | M108: =(('Business Case'!G11*$C108*'Business Case'!G12*$B108)-'Business Case'!G11*$C108*'Business Case'!G13*$D108-'Business Case'!G14*$E108)-MAX(0,(('Business Case'!G11*$C108*'Business Case'!G12*$B108)-'Business Case'!G11*$C108*'Business Case'!G13*$D108-'Business Case'!G14*$E108))*'Business Case'!$B$7-'Business Case'!$B$8*(('Business Case'!G11*$C108*'Business Case'!G12*$B108)-('Business Case'!F11*$C108*'Business Case'!F12*$B108))-'Business Case'!G15*$F108+'Business Case'!$B$8*('Business Case'!G11*$C108*'Business Case'!G12*$B108) -> 9.2538796e+08 | N108: =IF(COUNT('Business Case'!B11:G11)=0,"",H108+NPV(G108,I108:M108)) -> -3.7974643e+08 | P108: =RAND() -> 0.57764656 | Q108: =RAND() -> 0.27006045 | R108: =RAND() -> 0.25601013 | S108: =RAND() -> 0.30432104 | T108: =RAND() -> 0.73470743 | U108: =RAND() -> 0.16175925
...

Sheet Balanced Scorecard
A1: Balanced Scorecard
A2: 1-2 measures per objective, 8-16 in all. Status: on target ≥100% of target, caution 90-99%, below plan <90% (inverted when lower is better).
A3: Pre-filled from your StratOS ledger. Blue text on cream = inputs you can change. Black on grey = formulas (do not type over them).
A5: Perspective | B5: Objective | C5: Measure | D5: Leading / lagging | E5: Better when | F5: Target | G5: Actual | H5: % of target | I5: Status | J5: Owner | K5: Initiative | L5: Traces to
A6: Financial | B6: Profitable EU growth | C6: EU operating margin | D6: Lagging | E6: Higher | F6: 0.08 | G6: 0.06 | H6: =IF(AND(ISNUMBER(F6),ISNUMBER(G6),F6<>0,G6<>0),IF(E6="Lower",F6/G6,G6/F6),"") -> 0.75 | I6: =IF(H6="",IF(C6="","","No actual yet"),IF(H6>=1,"On target",IF(H6>=0.9,"Caution","Below plan"))) -> Below plan | J6: CFO
A7: Customer | B7: Value choice below EUR 30k | C7: EU registrations (000s) | D7: Lagging | E7: Higher | F7: 90 | G7: 74 | H7: =IF(AND(ISNUMBER(F7),ISNUMBER(G7),F7<>0,G7<>0),IF(E7="Lower",F7/G7,G7/F7),"") -> 0.82222222 | I7: =IF(H7="",IF(C7="","","No actual yet"),IF(H7>=1,"On target",IF(H7>=0.9,"Caution","Below plan"))) -> Below plan | J7: CMO
A8: Internal process | B8: Local cell supply | C8: Local cell share | D8: Leading | E8: Higher | F8: 0.5 | G8: 0.55 | H8: =IF(AND(ISNUMBER(F8),ISNUMBER(G8),F8<>0,G8<>0),IF(E8="Lower",F8/G8,G8/F8),"") -> 1.1 | I8: =IF(H8="",IF(C8="","","No actual yet"),IF(H8>=1,"On target",IF(H8>=0.9,"Caution","Below plan"))) -> On target | J8: COO
A9: Learning and growth | B9: EU plant workforce | C9: Trained line staff | D9: Leading | E9: Higher | F9: 1200 | G9: 900 | H9: =IF(AND(ISNUMBER(F9),ISNUMBER(G9),F9<>0,G9<>0),IF(E9="Lower",F9/G9,G9/F9),"") -> 0.75 | I9: =IF(H9="",IF(C9="","","No actual yet"),IF(H9>=1,"On target",IF(H9>=0.9,"Caution","Below plan"))) -> Below plan | J9: CHRO
H10: =IF(AND(ISNUMBER(F10),ISNUMBER(G10),F10<>0,G10<>0),IF(E10="Lower",F10/G10,G10/F10),"") | I10: =IF(H10="",IF(C10="","","No actual yet"),IF(H10>=1,"On target",IF(H10>=0.9,"Caution","Below plan")))
H11: =IF(AND(ISNUMBER(F11),ISNUMBER(G11),F11<>0,G11<>0),IF(E11="Lower",F11/G11,G11/F11),"") | I11: =IF(H11="",IF(C11="","","No actual yet"),IF(H11>=1,"On target",IF(H11>=0.9,"Caution","Below plan")))
H12: =IF(AND(ISNUMBER(F12),ISNUMBER(G12),F12<>0,G12<>0),IF(E12="Lower",F12/G12,G12/F12),"") | I12: =IF(H12="",IF(C12="","","No actual yet"),IF(H12>=1,"On target",IF(H12>=0.9,"Caution","Below plan")))
H13: =IF(AND(ISNUMBER(F13),ISNUMBER(G13),F13<>0,G13<>0),IF(E13="Lower",F13/G13,G13/F13),"") | I13: =IF(H13="",IF(C13="","","No actual yet"),IF(H13>=1,"On target",IF(H13>=0.9,"Caution","Below plan")))
H14: =IF(AND(ISNUMBER(F14),ISNUMBER(G14),F14<>0,G14<>0),IF(E14="Lower",F14/G14,G14/F14),"") | I14: =IF(H14="",IF(C14="","","No actual yet"),IF(H14>=1,"On target",IF(H14>=0.9,"Caution","Below plan")))
H15: =IF(AND(ISNUMBER(F15),ISNUMBER(G15),F15<>0,G15<>0),IF(E15="Lower",F15/G15,G15/F15),"") | I15: =IF(H15="",IF(C15="","","No actual yet"),IF(H15>=1,"On target",IF(H15>=0.9,"Caution","Below plan")))
H16: =IF(AND(ISNUMBER(F16),ISNUMBER(G16),F16<>0,G16<>0),IF(E16="Lower",F16/G16,G16/F16),"") | I16: =IF(H16="",IF(C16="","","No actual yet"),IF(H16>=1,"On target",IF(H16>=0.9,"Caution","Below plan")))
H17: =IF(AND(ISNUMBER(F17),ISNUMBER(G17),F17<>0,G17<>0),IF(E17="Lower",F17/G17,G17/F17),"") | I17: =IF(H17="",IF(C17="","","No actual yet"),IF(H17>=1,"On target",IF(H17>=0.9,"Caution","Below plan")))
H18: =IF(AND(ISNUMBER(F18),ISNUMBER(G18),F18<>0,G18<>0),IF(E18="Lower",F18/G18,G18/F18),"") | I18: =IF(H18="",IF(C18="","","No actual yet"),IF(H18>=1,"On target",IF(H18>=0.9,"Caution","Below plan")))
H19: =IF(AND(ISNUMBER(F19),ISNUMBER(G19),F19<>0,G19<>0),IF(E19="Lower",F19/G19,G19/F19),"") | I19: =IF(H19="",IF(C19="","","No actual yet"),IF(H19>=1,"On target",IF(H19>=0.9,"Caution","Below plan")))
H20: =IF(AND(ISNUMBER(F20),ISNUMBER(G20),F20<>0,G20<>0),IF(E20="Lower",F20/G20,G20/F20),"") | I20: =IF(H20="",IF(C20="","","No actual yet"),IF(H20>=1,"On target",IF(H20>=0.9,"Caution","Below plan")))
